Workbook
Name Stage_List: '02_Pipeline_Stages'!$B$5:$B$13

Sheet READ ME
B1: CHISON VETERINARY ULTRASOUND: DEALER & END-USER TARGET LIST v17
B2: Japan · South Korea · Taiwan · Singapore | Companion animal, exotics, equine and production animal | Casper Tan, Senior Regional Sales Manager, AstraMed Healthcare (a subsidiary of CHISON) | 27 Sep 2026
B4: WHAT CHANGED IN v11 (27 Sep 2026) | C4: 1. EMAIL CHECK: every email domain in the workbook was tested for a live mail server (DNS MX). 58 of 60 passed. Two Singapore clinic addresses bounce (Animal Infirmary, The Pet Doctors) and were removed. 2. CONTACTS RE-OPENED: company sites were re-opened for Japan, Korea and Taiwan rows missing email; 8 new confirmed emails added (Shine Kochi, OpenVet, GETECH, KogiPet, Pinyork, Yu Chiang, Hungan, Rayence phone) and MUNATEX upgraded from D to A. 3. NEW TARGETS: 16 Japan (mainly the regional opening support dealers on Mikasa X-ray's national dealer map, giving coverage in Tohoku, Hokkaido, Tokai, Kansai, Chugoku, Shikoku and Okinawa), 3 Korea, 2 Taiwan, and a NEW Singapore Dealers tab with 4 targets. 4. CORRECTIONS: Tokushima Iryoki carries Hitachi Aloka, Canon and Fujifilm, so moved to Tier 2; KogiPet and Pinyork moved to Tier 3 (see Corrections Log C-v11). 5. EMAILS: all 270 plus ready to send emails rewritten to your title and signature (casper@astramed.sg), em and en dashes removed, dealer pricing offer removed, and Singapore clinic emails no longer promise direct supply. 6. Former dealers AJJ, Medical Plus, AMF and Smitch Tech added to the Reference tab as DO NOT APPOINT.
B5: OUTREACH STATUS (29 Sep 2026) | C5: 45 prospects emailed on 28 Sep 2026 from casper@astramed.sg with the CHISON VET introduction attached, checked against the Winmail Sent folder on 29 Sep: Korea 5 dealers (POSKOM, JPI Healthcare, VSI, BlueVet, VETON), Taiwan 8 dealers (OpenVet, AHOSS, GETECH, Guojien, KogiPet, Hungan, Meijin, Pinyork), Singapore 3 dealers (Sage Healthcare, Vedmed Agri, Singapore Veterinary Imaging) and 29 Singapore end user clinics. 4 bounced, 1 real reply (AAVC), 3 auto replies. Every send is on the Outreach Log tab, with a new Channel column (Dealer or End user), and the new Outreach Summary tab counts them by market. Follow up date 5 Oct 2026. Japan: no emails yet. Still to email in Taiwan: Shine Kochi, Tengpon, Vet Supply, Vetnostrum, YoChung, YUMAX, Best Digital, ISVD. Korea: clear new contacts with Jerry first.
B6: WHAT v11 COULD NOT VERIFY | C6: a) The Korean government registry of 2,646 licensed veterinary device sellers (data.go.kr dataset 15045052) could not be downloaded from here; download it by hand, it is the best source for more Korean dealers. b) The QIA licensed importer list is blocked to automated readers. c) Singapore Vet show exhibitor list is not public; ask singaporevet@closerstillmedia.com. d) Several Japanese regional dealer sites (Nactol, Tech Mikasa, Goodwill Medical, Sanko, marukou11) would not load, so they are graded C. e) No named individual has been verified anywhere, except sales contacts published on a company's own page.
B7: WHAT THIS WORKBOOK IS | C7: One consolidated target list for CHISON veterinary ultrasound across four markets, built by merging four earlier workbooks (TargetList v5, Workbook v2.0, Market Development Target List v2 and the Top 10 Engagement List) and then re-checking every row for whether it can actually buy. There are no duplicates: two rows that turned out to be one company have been merged, and the collapse of every source row is logged on the Merge Log tab. Every organisation on an outreach tab has a subject line and an email body written for that specific company, ready to copy and send.
B8: HOW TO USE IT IN THE MORNING | C8: 1. Open the tab for the market you are working. 2. Filter the BUYING POTENTIAL column to HIGH. 3. Read the two background and fit-note columns: that is your thirty seconds of preparation. 4. Check the CONTACT CONFIDENCE column: A means the phone or email came off the company's own page; D means confirm the company exists first. 5. Copy the last two columns into your mail client and send. Nothing needs editing except your own signature block if you prefer a different one.
B9: WHAT CHANGED IN v9: RE-VERIFICATION OF THE MARKET DEVELOPMENT TARGET LIST v3 | C9: The whole of CHISON_Market_Development_Target_List_v3 was re-checked against this workbook, row by row. 1. THE FOUR VETERINARY TABS ARE ALREADY HERE. All 205 rows on the v3 VET Taiwan / VET Korea / VET Japan / VET Singapore tabs were traced into this workbook: every one is already present on a target tab, on Channel Resources, or on Reference: Do Not Contact. Nothing was missing and nothing new was added from them. The full row-by-row trace is on the new 'v9 Reconciliation (MDv3)' tab. 2. THE HUMAN-DIAGNOSTIC TABS WERE MINED FOR VETERINARY CROSSOVER: this is where the value was. The v3 file also carries ~245 HUMAN diagnostic dealer rows that had never been read for veterinary relevance. Six companies on them turned out to have a real veterinary business, and every one has been live-checked and added: JPI Healthcare and Mediana (Korea), Best Digital (Taiwan), Inter Medical (Japan), Sage Healthcare (Singapore), plus DK Medical Systems carried with a correction. One more, the ASUS handheld distributor, went to Reference. 3. THREE STRUCTURAL DEFECTS IN v8 WERE REPAIRED: see the row below. 4. Six new organisations, each with a bespoke ready-to-send email.
B10: DEFECTS IN v8 REPAIRED IN v9: READ THIS IF YOU USED THE v8 COUNTS | C10: a) EVERY TIER, PRIORITY, BUYING-POTENTIAL AND CONTACT-CONFIDENCE COUNT IN v8 WAS WRONG, and almost all of them read zero. When v8 inserted the four pipeline columns (Pipeline Stage, Owner, Next Action, Next Action Date) at column D, every column from D rightwards shifted four places: but the COUNTIF formulas under each table were not moved with them. They were still counting tiers in the contact-confidence column and priorities in the email column. All 66 of them have been repointed to the correct columns and now show real numbers. If you quoted any v8 count to anyone, re-check it here. b) COLUMN WIDTHS WERE STALE BY THE SAME FOUR COLUMNS. 'Email template', which holds a single letter, was 88 characters wide, while 'Email body': the column you actually copy from: was 13. Widths on all seven target tabs have been realigned to the headers they now sit under. c) FREEZE PANES WERE MISSING OR WRONG on three tabs. The v8 READ ME states that column D sits inside the frozen panes on every target tab; in fact Japan Dealers and Singapore End Users had no freeze at all, and Korea End Users & KOL was frozen at R21. All seven are now frozen at H5, so # / company / stage / owner / next action stay on screen while you scroll right.
B11: WHAT THE v9 PASS DID NOT DO | C11: It did not re-verify the rows already in v8: those still carry the confidence grades and source notes they were given in v6 and v7, and the open items on the 'WHAT IS STILL NOT VERIFIED' row below all still stand. It did not add the nine v3 rows that were research tasks rather than organisations (southern-Korea regional dealers, the Gyeonggi-North / Incheon veterinary associations, the 쿨펫/웰펫 franchise names, the Tokyo 24-hour cluster, 'ONE for Animals'-style consolidators, online CE platforms, prefectural veterinary associations and the Royal Canin / Hill's rep networks): they are listed on the reconciliation tab as open tasks, because a row with no confirmed entity behind it cannot carry an email. And no named individual has been verified at any company in this workbook: that is still true, and still the single biggest gap.
B12: WHAT CHANGED IN v7 | C12: 1. NEW COLUMN: 'Company / Organisation background': what each company actually does, its scale and history, and one explicit sentence on why it is relevant to CHISON. Column D on every outreach tab. 2. NEW COLUMN: 'BUYING / DISTRIBUTION POTENTIAL': a plain verdict (HIGH / MEDIUM / LOW) with the reason and the regulatory timing, so you can sort the list by who can actually transact. 3. NON-BUYERS REMOVED FROM THE OUTREACH TABS: 13 organisations that cannot buy (competitors, brand subsidiaries, competitor distribution channels, one wound-down operation and one research task) moved to a new 'Reference: Do Not Contact' tab. Every remaining row on every outreach tab is sendable. 4. NEW TAB: 'Why These Contacts': the relevance logic for each type of row, and what would disqualify it. 5. FOUR RESEARCH CORRECTIONS applied: see the row below. 6. READ ME rewritten.
B13: CORRECTIONS MADE DURING THE v7 RELEVANCE CHECK | C13: a) EASTECH (Taiwan) was carried as a Tier 3 dealer candidate. Opening eastech-medical.com showed it is 華鋒科技, the SOLE TAIWAN AGENT FOR ESAOTE, selling handheld, portable AND cart veterinary ultrasound plus veterinary MRI, majority-owned by BenQ Medical Technology within the Qisda group. It is a competitor channel, not a recruit. Moved to Reference. b) 'Animal Recovery Veterinary Referral Centre' and 'Pet Space Singapore' were TWO ROWS FOR ONE COMPANY: Animal Recovery Veterinary Centre Pte Ltd was formerly Pet Space (Singapore) Pte Ltd. Merged into one P1 row, and upgraded: the group runs 12 clinics across Hong Kong and Singapore and already offers both ultrasound and a HOUSE-CALL service, which is the strongest handheld argument there is. c) Singapore Turf Club Equine Hospital: horse racing in Singapore ended on 5 October 2024 and the Kranji site is being returned to the state. Not a realistic buyer. Moved to Reference. d) The AS-1 / ASCO duplicate flag raised in v6 is RESOLVED: ASCO Corporation is a Sala Group company in Toyohashi with 22 branches, so the two are different companies. ASCO was also upgraded: their own site states they sell instruments and machinery, not only drugs. e) SOAR Instrument-Tech (Taiwan) was downgraded from Tier 1 to Tier 2: uni-soar.com returned no content when fetched, so the 'no ultrasound in the catalogue' claim is unverified. It returns to Tier 1 the moment that is confirmed.
B14: CHANNEL MODEL PER MARKET: READ BEFORE ANY EMAIL | C14: v11 UPDATE: as agreed with Jerry, all four markets are developed primarily through dealers. SINGAPORE: dealer led, with AstraMed (CHISON's own subsidiary) supporting installation, training and service; veterinary health products sit outside the Health Products Act device regime, confirm with AVS. JAPAN: dealers may be approached freely; MAFF foreign manufacturer registration, a Japanese MAH and NVAL notification are needed before any order. SOUTH KOREA: discuss each distributor with Jerry first; a Korean entity must hold a QIA veterinary device import licence. TAIWAN: no animal only device registration identified; the open question is customs import permission for Chinese origin goods. Former dealers AJJ, Medical Plus, AMF and Smitch Tech will not be reappointed.
B15: WHY THESE CONTACTS ARE RELEVANT: THE SHORT VERSION | C15: Dealers were selected on one test: do they already sell into animal hospitals, and do they have NO competing ultrasound line? That produces four repeating profiles: the imaging dealer with X-ray or CT but no ultrasound, the clinic-opening trading house that writes the equipment list, the animal-drug wholesaler whose rep is in every clinic weekly, and the surgical dealer whose customer wants peri-operative imaging. Dealers who DO carry ultrasound are graded Tier 2 with one rule: pocket tier only, never a competing console. End users were selected on where a handheld actually gets used: emergency floors, house calls, feline and exotic practice, multi-site groups that decide once and repeat, and teaching hospitals that set habits for a decade. The full logic, profile by profile, is on the 'Why These Contacts' tab.
... B18: PRODUCT CONSTRAINT: DECISION D-2 | C18: Twelve veterinary SKUs exist at USD 5,299 to 21,200 US list, and there is NO veterinary-labelled cart. Referral hospitals and university teaching hospitals must be led with handheld and portable units. Do not promise a veterinary cart to any account before D-2 resolves.
B20: COVERAGE
B21: Japan: dealer targets | D21: =COUNTA('Japan Dealers'!B5:B48)
B22: South Korea: dealer targets | D22: =COUNTA('Korea Dealers'!B5:B36)
B23: Taiwan: dealer targets | D23: =COUNTA('Taiwan Dealers'!B5:B30)
B24: Singapore: dealer targets (new in v11) | D24: =COUNTA('Singapore Dealers'!B5:B8)
B25: Singapore: end-user clinic accounts | D25: =COUNTA('Singapore End Users'!B5:B78)
B26: Japan: end-user and KOL accounts | D26: =COUNTA('Japan End Users & KOL'!B5:B32)
B27: South Korea: end-user and KOL accounts | D27: =COUNTA('Korea End Users & KOL'!B5:B30)
B28: Taiwan: end-user and KOL accounts | D28: =COUNTA('Taiwan End Users & KOL'!B5:B51)
B29: TOTAL CONTACTABLE ORGANISATIONS, all with a ready to send email | D29: =SUM(D21:D28)
B30: Dealer rows with a confirmed email address in column N (all four dealer tabs) | D30: =COUNTIF('Japan Dealers'!N5:N48,"*@*")+COUNTIF('Korea Dealers'!N5:N36,"*@*")+COUNTIF('Taiwan Dealers'!N5:N30,"*@*")+COUNTIF('Singapore Dealers'!N5:N8,"*@*")
B31: Registries, associations and research tasks (Channel Resources) | D31: =COUNTA('Channel Resources'!B5:B29)
B32: Competitors, non-buyers and former dealers (Reference, no email) | D32: =COUNTA('Reference — Do Not Contact'!B5:B23)
B33: Search strings, registries and directories | D33: =COUNTA('Search Terms'!C5:C50)
B34: Master email frames | D34: =COUNTA('Email Templates'!A5:A18)
B36: TIER AND PRIORITY KEY
B37: TIER 1 / P1 | C37: Contact first: right segment, real capability, no competing ultrasound line.
B38: TIER 2 / P2 | C38: Qualify first: strong channel but a competing line, or fit unconfirmed.
B39: TIER 3 / P3 | C39: Long tail, niche or regional fill-in.
B40: MFR | C40: Manufacturer or supplier selling INTO dealers. Complementary-line or OEM talk only: never a distribution appointment.
B41: BUYING POTENTIAL: HIGH | C41: Real budget, right customer, and either can transact today (Singapore) or is appoint-grade the moment the market gate clears.
B42: BUYING POTENTIAL: MEDIUM | C42: A genuine buyer or partner, but something needs qualifying first: a competing line, an unconfirmed entity, or a slow cycle.
B43: BUYING POTENTIAL: LOW | C43: Long tail, niche, or a partnership rather than a purchase. Work only after everything above it.
B44: VERIFY FIRST | C44: Entity or operating status not confirmed. Check before spending time.
B46: TAB GUIDE
B47: Japan / Korea / Taiwan / Singapore Dealers | C47: Distributor and manufacturer targets. Relationship and evaluation now; no quotes until each market gate clears. Singapore Dealers is new in v11.
B48: Singapore End Users | C48: Clinic accounts: demand, KOL and evaluation targets. v11: channel is dealer led; Sage Healthcare is worked from the Singapore Dealers tab.
B49: Japan / Korea / Taiwan End Users & KOL | C49: Hospitals, chains and university teaching hospitals. Relationship, evaluation and KOL work: not distribution targets.
B50: Reference: Do Not Contact | C50: Competitors and non-buyers, kept as intelligence. No email on this tab, by design.
B51: Why These Contacts | C51: The relevance logic for every type of row, and what would disqualify it. Read once.
B52: Channel Resources | C52: Registries, regulators, associations, congresses and open research tasks, with an instruction for each.
B53: Search Terms / Email Templates | C53: Local-language search strings and the master email frames the per-row emails were built from.
B54: Top 10 Engage Now / Bench 11-20 | C54: The prioritised call list. NOTE: bench rank 12 (Animal Recovery) and rank 20 (Pet Space) are the same company: now merged on the Singapore tab.
B55: Engagement rules | C55: What you may and may not do in each market before the channel is in place. Read before the first call.
B56: Verification / Merge Log / Corrections Log | C56: Where every claim came from, how the four source workbooks were reconciled, and what was corrected.
B57: Product Registration / Reconciliation (v2.0) | C57: Preserved unchanged from Workbook v2.0.
B59: PIPELINE STAGE TRACKING: NEW IN v8 | C59: Column D of all seven target tabs is a 'Pipeline Stage' dropdown, pinned inside the frozen panes and colour-coded from grey (Not started) through amber (in conversation) to green (Won). Every existing row is pre-set to 'Not started'. The nine stages are the same nine that were already in use on the Top 10 Engage Now tab: nothing new to learn: and they are set out, with what each one means, on the 02_Pipeline_Stages tab. Click any cell in column D and the dropdown arrow appears on the right of the cell. Stage is part of each tab's AutoFilter, so you can work one stage at a time.
... B62: NAMED INDIVIDUALS: STILL NONE | C62: Unchanged in v9. No named contact at any company in this workbook has been verified, including the six new ones. Use the dealer-linkedin-outreach workflow to find real people before sending. The three names that appeared in the old Market Development list: 'Jane Cho', 'Jovi Peng', 'Yutaro Yasuda': remain do-not-use.
A64: v18 change: new tab 'Japan VET_additional' with 259 new Japan veterinary leads, tiered V1 to V5, scored out of 35, with regional quota tracking.
A65: The same list is also delivered as a standalone file Japan_Distributor_List_Vet_v2.xlsx (Master List, Distributor Shortlist, Hospital Groups, By Region, Summary, Sources).
A66: v19 change (10 Oct 2026): Email column filled from published company addresses (46 rows; 31 Verified on own site, 15 Likely from third party listings). No personal email was guessed. Rows with no published email show the inquiry form URL or 'phone only'; 70 V4 qualify first rows were not searched yet.
A67: v19 fixes: HQ prefecture corrected for 13 rows after recheck; Primo group operator corrected to 株式会社JPR. Closed, dissolved or acquired companies are flagged in Contact confidence (rows kept).
A68: NOT VERIFIED: websites were not opened directly (network policy blocked page fetches); contact details were read through search results. No named person contact was found.
A69: QUALIFY FIRST: 120 V4 rows are human medical dealers with no confirmed animal hospital business; the v9 Reconciliation tab had screened such dealers out. Use them only after a qualifying call.
A70: All other tabs are unchanged from v17.

Sheet 02_Pipeline_Stages
A1: PIPELINE STAGES — THE SINGLE SOURCE FOR EVERY STAGE DROPDOWN
A2: These nine stages are not new. They are the same nine already in use in the 'Response' dropdown on the Top 10 Engage Now tab, so the whole workbook tracks progress in one vocabulary. They now populate the 'Pipeline Stage' dropdown in column D of all seven target tabs — Japan / Korea / Taiwan Dealers, Singapore End Users, and the three End Users & KOL tabs. THIS SHEET IS THE REFERENCE: what each stage means and what colour it turns. The dropdowns themselves carry the nine names inline, the same way the Top 10 Engage Now dropdown always has, so they need nothing else in the workbook to resolve and work in any version of Excel. To change a stage name, edit it here and then update the validations: select column D, Data ▸ Data Validation, edit the Source line, and repeat on each tab — or ask Claude to regenerate the workbook, which is faster. Renaming a stage does not rewrite stages already chosen on the tabs; use Find & Replace across the workbook if you rename one mid-campaign.
A4: # | B4: Pipeline stage (this column IS the dropdown list) | C4: What it means — the test for moving a row into this stage | D4: Colour on the tabs
A5: 1 | B5: Not started | C5: On the list, no approach made yet. Every row starts here.
A6: 2 | B6: Contacted | C6: First approach sent — the ready-to-send email on this row, or an equivalent call or LinkedIn touch. No reply yet.
A7: 3 | B7: Meeting booked | C7: They came back and a call or a visit is in the diary.
A8: 4 | B8: Meeting held | C8: Call or visit done. Segment fit, decision route and budget understood.
A9: 5 | B9: Evaluation placed | C9: A unit is with the dealer or the account for hands-on trial, clinical evaluation or a seminar demo. Check the Engagement rules tab first — outside Singapore there are things you may not yet ship or quote.
A10: 6 | B10: Quoted | C10: Formal pricing issued — unit price, dealer terms or an opening package.
A11: 7 | B11: Won | C11: Dealer appointed, or end-user purchase order received. Hand over to account management.
A12: 8 | B12: Declined | C12: Ruled out — competitor lock-in, wrong segment, no budget, entity unverifiable, or they said no.
A13: 9 | B13: Parked | C13: A real target at the wrong moment. Held with a review date — not the same as Declined.
B15: HOW THE TABS USE THIS | C15: Column D on each target tab is a dropdown, pre-set to 'Not started' on every existing row and colour-coded to the swatches above. Column D sits inside the frozen panes, so the stage stays on screen while you scroll right through contact details and the ready-to-send email columns. Stage is included in each tab's AutoFilter — filter column D to work one stage at a time.
B16: BEFORE YOU MOVE ANYTHING TO 'QUOTED' | C16: Read the Engagement rules tab. Singapore is the only market where you may quote, invoice and install today. In Taiwan, South Korea and Japan there is a gating action outstanding, so 'Evaluation placed' and 'Quoted' carry conditions — do not move a row into them on autopilot.
B18: OWNER, NEXT ACTION AND NEXT ACTION DATE | C18: Added directly after Pipeline Stage on every target tab, so the whole working record lives in this one workbook. The funnel dashboard reads them: a row past 'Not started' with no next action, no owner, or a date in the past is flagged as needing attention. All three are optional — leave them blank and the dashboard simply omits those fields.

Sheet Outreach Summary
A1: EMAIL OUTREACH SUMMARY BY MARKET: VETERINARY
A2: Counts are live formulas on the Outreach Log and the target tabs. Source checked against the casper@astramed.sg Winmail Sent folder on 29 Sep 2026. Human diagnostics outreach is tracked in CHISON_Market_Development_Target_List_v6.xlsx.
A4: Market | B4: Channel | C4: Targets on list | D4: Emails sent | E4: Delivered | F4: Bounced | G4: Replied | H4: Auto reply / no reply yet | I4: Follow up due by | J4: Still to email | K4: % of list emailed | L4: Target tab
A5: Singapore | B5: Dealer | C5: =COUNTA('Singapore Dealers'!D5:D8) | D5: =COUNTIFS('Outreach Log'!C:C,A5,'Outreach Log'!N:N,B5) | E5: =D5-F5 | F5: =COUNTIFS('Outreach Log'!C:C,A5,'Outreach Log'!N:N,B5,'Outreach Log'!L:L,"Bounced") | G5: =COUNTIFS('Outreach Log'!C:C,A5,'Outreach Log'!N:N,B5,'Outreach Log'!L:L,"Yes") | H5: =COUNTIFS('Outreach Log'!C:C,A5,'Outreach Log'!N:N,B5,'Outreach Log'!L:L,"No")+COUNTIFS('Outreach Log'!C:C,A5,'Outreach Log'!N:N,B5,'Outreach Log'!L:L,"Out of office") | I5: =IF(H5=0,"",_xlfn.MINIFS('Outreach Log'!K:K,'Outreach Log'!C:C,A5,'Outreach Log'!N:N,B5,'Outreach Log'!L:L,"No")) | J5: =MAX(C5-D5,0) | K5: =IF(C5=0,0,D5/C5) | L5: Singapore Dealers
A6: Singapore | B6: End user | C6: =COUNTA('Singapore End Users'!D5:D78) | D6: =COUNTIFS('Outreach Log'!C:C,A6,'Outreach Log'!N:N,B6) | E6: =D6-F6 | F6: =COUNTIFS('Outreach Log'!C:C,A6,'Outreach Log'!N:N,B6,'Outreach Log'!L:L,"Bounced") | G6: =COUNTIFS('Outreach Log'!C:C,A6,'Outreach Log'!N:N,B6,'Outreach Log'!L:L,"Yes") | H6: =COUNTIFS('Outreach Log'!C:C,A6,'Outreach Log'!N:N,B6,'Outreach Log'!L:L,"No")+COUNTIFS('Outreach Log'!C:C,A6,'Outreach Log'!N:N,B6,'Outreach Log'!L:L,"Out of office") | I6: =IF(H6=0,"",_xlfn.MINIFS('Outreach Log'!K:K,'Outreach Log'!C:C,A6,'Outreach Log'!N:N,B6,'Outreach Log'!L:L,"No")) | J6: =MAX(C6-D6,0) | K6: =IF(C6=0,0,D6/C6) | L6: Singapore End Users
A7: Taiwan | B7: Dealer | C7: =COUNTA('Taiwan Dealers'!D5:D30) | D7: =COUNTIFS('Outreach Log'!C:C,A7,'Outreach Log'!N:N,B7) | E7: =D7-F7 | F7: =COUNTIFS('Outreach Log'!C:C,A7,'Outreach Log'!N:N,B7,'Outreach Log'!L:L,"Bounced") | G7: =COUNTIFS('Outreach Log'!C:C,A7,'Outreach Log'!N:N,B7,'Outreach Log'!L:L,"Yes") | H7: =COUNTIFS('Outreach Log'!C:C,A7,'Outreach Log'!N:N,B7,'Outreach Log'!L:L,"No")+COUNTIFS('Outreach Log'!C:C,A7,'Outreach Log'!N:N,B7,'Outreach Log'!L:L,"Out of office") | I7: =IF(H7=0,"",_xlfn.MINIFS('Outreach Log'!K:K,'Outreach Log'!C:C,A7,'Outreach Log'!N:N,B7,'Outreach Log'!L:L,"No")) | J7: =MAX(C7-D7,0) | K7: =IF(C7=0,0,D7/C7) | L7: Taiwan Dealers
A8: Taiwan | B8: End user | C8: =COUNTA('Taiwan End Users & KOL'!D5:D51) | D8: =COUNTIFS('Outreach Log'!C:C,A8,'Outreach Log'!N:N,B8) | E8: =D8-F8 | F8: =COUNTIFS('Outreach Log'!C:C,A8,'Outreach Log'!N:N,B8,'Outreach Log'!L:L,"Bounced") | G8: =COUNTIFS('Outreach Log'!C:C,A8,'Outreach Log'!N:N,B8,'Outreach Log'!L:L,"Yes") | H8: =COUNTIFS('Outreach Log'!C:C,A8,'Outreach Log'!N:N,B8,'Outreach Log'!L:L,"No")+COUNTIFS('Outreach Log'!C:C,A8,'Outreach Log'!N:N,B8,'Outreach Log'!L:L,"Out of office") | I8: =IF(H8=0,"",_xlfn.MINIFS('Outreach Log'!K:K,'Outreach Log'!C:C,A8,'Outreach Log'!N:N,B8,'Outreach Log'!L:L,"No")) | J8: =MAX(C8-D8,0) | K8: =IF(C8=0,0,D8/C8) | L8: Taiwan End Users & KOL
A9: South Korea | B9: Dealer | C9: =COUNTA('Korea Dealers'!D5:D36) | D9: =COUNTIFS('Outreach Log'!C:C,A9,'Outreach Log'!N:N,B9) | E9: =D9-F9 | F9: =COUNTIFS('Outreach Log'!C:C,A9,'Outreach Log'!N:N,B9,'Outreach Log'!L:L,"Bounced") | G9: =COUNTIFS('Outreach Log'!C:C,A9,'Outreach Log'!N:N,B9,'Outreach Log'!L:L,"Yes") | H9: =COUNTIFS('Outreach Log'!C:C,A9,'Outreach Log'!N:N,B9,'Outreach Log'!L:L,"No")+COUNTIFS('Outreach Log'!C:C,A9,'Outreach Log'!N:N,B9,'Outreach Log'!L:L,"Out of office") | I9: =IF(H9=0,"",_xlfn.MINIFS('Outreach Log'!K:K,'Outreach Log'!C:C,A9,'Outreach Log'!N:N,B9,'Outreach Log'!L:L,"No")) | J9: =MAX(C9-D9,0) | K9: =IF(C9=0,0,D9/C9) | L9: Korea Dealers
A10: South Korea | B10: End user | C10: =COUNTA('Korea End Users & KOL'!D5:D30) | D10: =COUNTIFS('Outreach Log'!C:C,A10,'Outreach Log'!N:N,B10) | E10: =D10-F10 | F10: =COUNTIFS('Outreach Log'!C:C,A10,'Outreach Log'!N:N,B10,'Outreach Log'!L:L,"Bounced") | G10: =COUNTIFS('Outreach Log'!C:C,A10,'Outreach Log'!N:N,B10,'Outreach Log'!L:L,"Yes") | H10: =COUNTIFS('Outreach Log'!C:C,A10,'Outreach Log'!N:N,B10,'Outreach Log'!L:L,"No")+COUNTIFS('Outreach Log'!C:C,A10,'Outreach Log'!N:N,B10,'Outreach Log'!L:L,"Out of office") | I10: =IF(H10=0,"",_xlfn.MINIFS('Outreach Log'!K:K,'Outreach Log'!C:C,A10,'Outreach Log'!N:N,B10,'Outreach Log'!L:L,"No")) | J10: =MAX(C10-D10,0) | K10: =IF(C10=0,0,D10/C10) | L10: Korea End Users & KOL
A11: Japan | B11: Dealer | C11: =COUNTA('Japan Dealers'!D5:D48) | D11: =COUNTIFS('Outreach Log'!C:C,A11,'Outreach Log'!N:N,B11) | E11: =D11-F11 | F11: =COUNTIFS('Outreach Log'!C:C,A11,'Outreach Log'!N:N,B11,'Outreach Log'!L:L,"Bounced") | G11: =COUNTIFS('Outreach Log'!C:C,A11,'Outreach Log'!N:N,B11,'Outreach Log'!L:L,"Yes") | H11: =COUNTIFS('Outreach Log'!C:C,A11,'Outreach Log'!N:N,B11,'Outreach Log'!L:L,"No")+COUNTIFS('Outreach Log'!C:C,A11,'Outreach Log'!N:N,B11,'Outreach Log'!L:L,"Out of office") | I11: =IF(H11=0,"",_xlfn.MINIFS('Outreach Log'!K:K,'Outreach Log'!C:C,A11,'Outreach Log'!N:N,B11,'Outreach Log'!L:L,"No")) | J11: =MAX(C11-D11,0) | K11: =IF(C11=0,0,D11/C11) | L11: Japan Dealers
A12: Japan | B12: End user | C12: =COUNTA('Japan End Users & KOL'!D5:D32) | D12: =COUNTIFS('Outreach Log'!C:C,A12,'Outreach Log'!N:N,B12) | E12: =D12-F12 | F12: =COUNTIFS('Outreach Log'!C:C,A12,'Outreach Log'!N:N,B12,'Outreach Log'!L:L,"Bounced") | G12: =COUNTIFS('Outreach Log'!C:C,A12,'Outreach Log'!N:N,B12,'Outreach Log'!L:L,"Yes") | H12: =COUNTIFS('Outreach Log'!C:C,A12,'Outreach Log'!N:N,B12,'Outreach Log'!L:L,"No")+COUNTIFS('Outreach Log'!C:C,A12,'Outreach Log'!N:N,B12,'Outreach Log'!L:L,"Out of office") | I12: =IF(H12=0,"",_xlfn.MINIFS('Outreach Log'!K:K,'Outreach Log'!C:C,A12,'Outreach Log'!N:N,B12,'Outreach Log'!L:L,"No")) | J12: =MAX(C12-D12,0) | K12: =IF(C12=0,0,D12/C12) | L12: Japan End Users & KOL
A13: TOTAL VET | C13: =SUM(C5:C12) | D13: =SUM(D5:D12) | E13: =SUM(E5:E12) | F13: =SUM(F5:F12) | G13: =SUM(G5:G12) | H13: =SUM(H5:H12) | I13: =MIN(I5:I12) | J13: =SUM(J5:J12) | K13: =IF(C13=0,0,D13/C13)
A15: BY MARKET, DEALERS AND END USERS COMBINED
A16: Market | B16: Emails sent | C16: Bounced | D16: Replied | E16: Still to email
A17: Singapore | B17: =SUMIF(A$5:A$12,A17,D$5:D$12) | C17: =SUMIF(A$5:A$12,A17,F$5:F$12) | D17: =SUMIF(A$5:A$12,A17,G$5:G$12) | E17: =SUMIF(A$5:A$12,A17,J$5:J$12)
A18: Taiwan | B18: =SUMIF(A$5:A$12,A18,D$5:D$12) | C18: =SUMIF(A$5:A$12,A18,F$5:F$12) | D18: =SUMIF(A$5:A$12,A18,G$5:G$12) | E18: =SUMIF(A$5:A$12,A18,J$5:J$12)
A19: South Korea | B19: =SUMIF(A$5:A$12,A19,D$5:D$12) | C19: =SUMIF(A$5:A$12,A19,F$5:F$12) | D19: =SUMIF(A$5:A$12,A19,G$5:G$12) | E19: =SUMIF(A$5:A$12,A19,J$5:J$12)
A20: Japan | B20: =SUMIF(A$5:A$12,A20,D$5:D$12) | C20: =SUMIF(A$5:A$12,A20,F$5:F$12) | D20: =SUMIF(A$5:A$12,A20,G$5:G$12) | E20: =SUMIF(A$5:A$12,A20,J$5:J$12)
A22: NOTES FROM THE SENT FOLDER CHECK (29 Sep 2026)
A23: 1. 45 prospects emailed, all on 28 Sep 2026: Korea 5 dealers, Taiwan 8 dealers, Singapore 3 dealers and 29 Singapore end user clinics. Japan: none yet.
A24: 2. Bounced (4): The Animal Doctors, The Veterinary Clinic, Animal World Veterinary Clinic, Spring Veterinary Care. Phone numbers for a working email are on the Singapore End Users tab.
A25: 3. Real reply (1): AAVC asked for price; you replied on 29 Sep proposing a meeting in Yishun.
A26: 4. Auto replies (3): Amber Vet, Vet Central, Pets Avenue. Pets Avenue has moved to hello@petsavenuevet.com.
A27: 5. Sent twice: JPI Healthcare (Korea) and Amber Vet (Singapore). Counted once here.
A28: 6. Corrected: Animal Practice Pte Ltd was marked Contacted but no email to it is in the Sent folder. Reset to Not started.
A29: 7. Human diagnostics: no dealer or end user emails sent yet.

Sheet Japan Dealers
A1: JAPAN — VETERINARY DEALER / DISTRIBUTOR TARGETS
A2: Dealer model. Two columns at the far right hold a ready-to-send email for each company. Japan requires CHISON foreign-manufacturer registration with MAFF, a Japanese marketing authorisation holder and an NVAL marketing notification before any quote or order — note that Arrow Medical, KIRIKAN and Medical Space all hold veterinary device marketing-authorisation licences of their own, which is why they rank where they do.
A4: # | B4: Company (local name) | C4: Company (roman/EN) | D4: Pipeline Stage | E4: Owner | F4: Next Action | G4: Next Action Date | H4: Company background — what they do, and why it matters to CHISON | I4: Segment & expertise | J4: Carries an ultrasound line? | K4: Location / coverage | L4: Website (URL) | M4: Phone / fax | N4: Email | O4: Address & company detail | P4: CONTACT CONFIDENCE | Q4: Why this dealer for CHISON VET (fit notes) | R4: CHISON VET product to lead with | S4: Tier | T4: BUYING / DISTRIBUTION POTENTIAL | U4: Email template | V4: Source status | W4: Email subject — ready to send | X4: Email body — ready to send (copy/paste)
A5: 1 | B5: アローメディカル株式会社 | C5: Arrow Medical Co., Ltd. | D5: Not started | H5: Yokohama-based veterinary trading house founded 1978, selling nationwide to small-animal clinics. Sole Japan agent for Welch Allyn veterinary diagnostic instruments — otoscopes, ophthalmoscopes, laryngoscopes, thermometers, stethoscopes, exam lighting — plus supplements. Runs the 'WAO' clinic-opening support programme and has been involved in over a thousand new-clinic and refurbishment projects, and exhibits at JSVAS. RELEVANCE: they write the equipment list at the exact moment a vet is deciding what to buy, and there is no ultrasound anywhere in their published range — so a handheld is pure additional margin with zero channel conflict. | I5: Veterinary total trading house. Sole Japan agent for Welch Allyn veterinary diagnostic instruments; otoscopes, ophthalmoscopes, laryngoscopes, thermometers, stethoscopes, exam lighting, supplements. Runs the 'WAO' clinic-opening support programme and Japan's first vet-dedicated showroom (AMCC). | J5: NO — none visible in the published product line | K5: Nationwide; founded 1978 | L5: https://www.arrowmedical.co.jp | M5: TEL 045-481-7471 · FAX 045-481-7554 | N5: mail@arrowmedical.co.jp | O5: 〒221-0865 横浜市神奈川区片倉4-7-28 (CEO 矢野修二) | P5: A — VERIFIED DIRECT (phone + email off company profile page) | Q5: The single cleanest recruit in Japan. Deep small-animal clinic access, zero ultrasound conflict, and 1,000+ new-clinic / rebuild projects means they specify the whole equipment list at the moment a vet is deciding. A handheld is the natural first scanner in an opening package. Exhibits at JSVAS, so there is a neutral place to meet. DECISIVE NEW FACT: they hold a Class-3 veterinary device MARKETING AUTHORISATION licence (第三種動物用医療機器製造販売業), a veterinary device MANUFACTURING licence, a veterinary device REPAIR licence and a veterinary drug wholesale licence. That means they could plausibly act as the Japanese marketing authorisation holder rather than merely resell — which is the single biggest obstacle on the Japan gating list. They sell to roughly 3,000 practising vets plus Azabu University, Yamazaki Gakuen and the Yokohama, Kanazawa and Nogeyama zoos. | R5: SonoEye P3 VET (opening package) + EBit 50 VET | S5: TIER 1 | T5: HIGH — appoint-grade. No competing ultrasound line, and they already specify full equipment lists. | U5: A | V5: Verified — company profile page fetched 4 Aug 2026 | W5: Arrow Medical Co., Ltd.: a first scanner for the clinics you equip | X5: Dear アローメディカル株式会社 (Arrow Medical Co., Ltd.) team, My name is Casper Tan, Senior Regional Sales Manager at AstraMed Healthcare, a subsidiary of CHISON Medical Technologies. I cover Japan, South Korea, Taiwan and Singapore for CHISON veterinary ultrasound. I am writing to Arrow Medical Co., Ltd. specifically, not to a list. You have supported more than a thousand clinic openings and rebuilds since 1978, you sell to around three thousand practising veterinarians, and, the part that made me write, you hold a Class-3 veterinary device marketing authorisation, a manufacturing licence and a repair licence. Very few companies in Japan could both carry our line and hold the authorisation for it. CHISON makes veterinary ultrasound built around handheld and portable form factors, proper vet presets, micro-convex, linear and rectal probes, at a price well under GE, Fujifilm, Canon and Mindray. That matters most at the moment a practice is being equipped, because it turns ultrasound from a line item that gets deferred into one that fits the opening budget. For context: we have no appointed veterinary distributor in Japan and would rather build one than sell around one. The product I would put in front of you first is the SonoEye P3 VET (opening package) and EBit 50 VET. Would twenty minutes in the next fortnight be useful? I can send the veterinary line card beforehand if you would rather look before you talk. Best regards, Casper Tan Senior Regional Sales Manager AstraMed Healthcare, a subsidiary of CHISON Medical Technologies casper@astramed.sg | +65 8719 0121
A6: 2 | B6: ムナテックス株式会社 | C6: MUNATEX Corporation | D6: Not started | H6: Nationwide veterinary total trading company carrying everything from disposables and injection needles up to advanced imaging equipment, with an animal-hospital opening-support arm. RELEVANCE: the disposables business puts their rep inside every clinic on a weekly cycle, which is the cheapest demo route that exists for a pocket scanner, and the opening-support arm gives them first-fit influence. Confirm on the first call whether any ultrasound already sits in the imaging range. | I6: Veterinary total trading company: disposables and injection needles through to advanced imaging equipment; animal-hospital opening support service. | J6: NO · none in the 11 published categories (X-ray, CR and DR are listed) | K6: Japan, nationwide | L6: https://munatex.com/products/ | M6: TEL 049-256-3611 · FAX 049-256-3612 · order FAX 0120-279717 (weekdays 09:00 to 17:30) | N6: Not published; enquiry via munatex.com | O6: 〒356-0050 埼玉県ふじみ野市ふじみ野4-9-12 | P6: A · VERIFIED DIRECT (phone and fax off the products page, opened 27 Sep 2026) | Q6: v11 CHECK: products page opened 27 Sep 2026 lists X-ray, CR and DR but no ultrasound, so archetype F applies. Full-range vet trading house with an opening-support arm — same structural fit as Arrow Medical and a good second horse in the same race. Their disposables business gives them weekly contact with every clinic, which is the cheapest possible demo route for a handheld. | R6: SonoGO VET + SonoEye P3 VET | S6: TIER 1 | T6: HIGH — same structural fit as Arrow Medical; a sound second horse in the same race. | U6: A | V6: Verified 27 Sep 2026 · products page fetched | W6: MUNATEX Corporation: a first scanner for the clinics you equip | X6: Dear ムナテックス株式会社 (MUNATEX Corporation) team, My name is Casper Tan, Senior Regional Sales Manager at AstraMed Healthcare, a subsidiary of CHISON Medical Technologies. I cover Japan, South Korea, Taiwan and Singapore for CHISON veterinary ultrasound. I am writing to MUNATEX Corporation specifically, not to a list. You cover animal hospitals from disposables right through to advanced imaging, and you run an opening-support arm alongside it. That combination, daily contact through consumables plus involvement at the moment a clinic specifies its equipment, is exactly where a first scanner gets chosen. CHISON makes veterinary ultrasound built around handheld and portable form factors, proper vet presets, micro-convex, linear and rectal probes, at a price well under GE, Fujifilm, Canon and Mindray. That matters most at the moment a practice is being equipped, because it turns ultrasound from a line item that gets deferred into one that fits the opening budget. For context: we have no appointed veterinary distributor in Japan and would rather build one than sell around one. The product I would put in front of you first is the SonoGO VET and SonoEye P3 VET. Would twenty minutes in the next fortnight be useful? I can send the veterinary line card beforehand if you would rather look before you talk. Best regards, Casper Tan Senior Regional Sales Manager AstraMed Healthcare, a subsidiary of CHISON Medical Technologies casper@astramed.sg | +65 8719 0121
A7: 3 | B7: 株式会社キリカン洋行 | C7: KIRIKAN Ltd. | D7: Not started | H7: Tokyo import trading house founded 1973 for small-animal pharmaceuticals, devices and materials. Line card includes ALSA (Italy) electrosurgery, Integra LifeSciences surgical instruments, and Ortho Medical (Germany) and INTRAUMA (Italy) orthopaedic implants. RELEVANCE: importing foreign medical brands is their core competence, so the manufacturer file and the regulatory legwork are routine for them. A handheld sells into a conversation they are already having — vascular access, nerve block, peri-operative FAST — rather than competing with anything on the shelf. | I7: Import trading house founded 1973 for small-animal pharmaceuticals, devices and materials. Line card: ALSA (Italy) electrosurgery ADC140/ADC200SP, Integra LifeSciences surgical instruments, Ortho Medical (Germany) and INTRAUMA (Italy) orthopaedic implants, Nolvasan, Malaseb. | J7: NO — surgical, orthopaedic and materials only | K7: Tokyo HQ; national | L7: https://www.kirikan.com · onlinestore.kirikan.com | M7: Not published on the site — call switchboard via site | N7: Not published — enquiry via onlinestore.kirikan.com | O7: 〒108-0075 東京都港区港南5-4-12 横浜倉庫7F (CEO 村松慶一) | P7: B — VERIFIED PARTIAL (address confirmed; no phone/email published) | Q7: Surgical and orthopaedic depth with no imaging line at all. A handheld sells into their existing conversation — vascular access, nerve block, peri-operative FAST — rather than competing with anything they already carry. Import trading is their core competence, so a foreign manufacturer file is routine work for them. DECISIVE NEW FACT: they hold a Class-2 veterinary device marketing authorisation licence (第二種動物用医療機器製造販売業) plus veterinary device manufacturing, repair and wholesale licences — so they too could carry the Japanese MAH role. 50+ years importing veterinary product from the US, Italy, Australia, Germany and Austria (Zoetis, Dermcare, alsa, iM3, Integra, Sontec, Intrauma, IMEX, Burton, panno-med), and they sell not only to vets but to other veterinary device WHOLESALERS — a second layer of reach. | R7: SonoEye P3 VET (peri-op / nerve block) + SonoAir 30 VET | S7: TIER 1 | T7: HIGH — surgical and orthopaedic depth with no imaging line to defend. | U7: C | V7: Verified — company profile page fetched 4 Aug 2026 | W7: KIRIKAN Ltd.: ultrasound guidance for the surgery you already equip | X7: Dear 株式会社キリカン洋行 (KIRIKAN Ltd.) team, My name is Casper Tan, Senior Regional Sales Manager at AstraMed Healthcare, a subsidiary of CHISON Medical Technologies. I cover Japan, South Korea, Taiwan and Singapore for CHISON veterinary ultrasound. I am writing to KIRIKAN Ltd. specifically, not to a list. You have spent fifty years importing veterinary product into Japan from Zoetis, Dermcare, alsa, iM3, Integra, Intrauma, IMEX and panno-med, you hold a Class-2 veterinary device marketing authorisation, and you sell not only to veterinarians but to other veterinary device wholesalers. You also have no ultrasound in the line card. CHISON's SonoEye P3 VET is a pocket-sized veterinary scanner built for ultrasound-guided nerve blocks, vascular access in a collapsed patient and a ninety-second pre-anaesthetic FAST. It stays in theatre instead of living in another room, and it does not overlap with anything in your line card. For context: we have no appointed veterinary distributor in Japan and would rather build one than sell around one. The product I would put in front of you first is the SonoEye P3 VET (peri-op / nerve block) and SonoAir 30 VET. Are you open to a short call? I would rather show you the block and the vascular-access demo than describe them. Best regards, Casper Tan Senior Regional Sales Manager AstraMed Healthcare, a subsidiary of CHISON Medical Technologies casper@astramed.sg | +65 8719 0121
A8: 4 | B8: ミズホ株式会社（動物医療部門） | C8: MIZUHO Corporation — Animal Medical Division | D8: Not started | H8: Established Japanese manufacturer of human operating-room equipment (OR tables, neurosurgical systems) that runs a dedicated animal medical division selling veterinary operating tables and surgical and orthopaedic instruments. RELEVANCE: the human-OR brand carries real weight with veterinary surgeons, and their customer is precisely the vet who wants peri-operative imaging. Attaching a pocket scanner to an operating-table sale is high-margin and conflicts with nothing they carry. | I8: Established human operating-room manufacturer (OR tables, neurosurgery) with a dedicated animal-hospital device division: vet operating tables, orthopaedic and general surgical instruments. | J8: NO | K8: Tokyo; national | L8: https://www.mizuho.co.jp/animal/ | M8: TEL 0120-88-7554 (小動物課 / Small Animal Dept — freephone) | N8: Not published — catalogue request form on the animal page | O8: Japan (Tokyo HQ) | P8: A — VERIFIED DIRECT (dedicated small-animal department freephone) | Q8: Brand credibility from the human OR side, sold into vet operating rooms. Adding a pocket scanner to an OR-table sale is a high-margin attachment with no channel conflict, and their surgical customer is exactly the vet who wants peri-operative imaging. | R8: SonoEye P3 VET + SonoTouch VET | S8: TIER 1 | T8: HIGH — operating-room credibility, no imaging conflict. | U8: C | V8: Re-verified 27 Sep 2026 · animal page confirms surgical tables and orthopaedics, no ultrasound | W8: MIZUHO Corporation: Animal Medical Division, ultrasound guidance for the surgery you already equip | X8: Dear ミズホ株式会社 (MIZUHO Corporation) team, My name is Casper Tan, Senior Regional Sales Manager at AstraMed Healthcare, a subsidiary of CHISON Medical Technologies. I cover Japan, South Korea, Taiwan and Singapore for CHISON veterinary ultrasound. I am writing to MIZUHO Corporation specifically, not to a list. You bring operating-room credibility from the human side into veterinary theatres, and your animal division sells the tables and instruments that surgery runs on, but not imaging. A pocket scanner attaches to that sale rather than competing with it. CHISON's SonoEye P3 VET is a pocket-sized veterinary scanner built for ultrasound-guided nerve blocks, vascular access in a collapsed patient and a ninety-second pre-anaesthetic FAST. It stays in theatre instead of living in another room, and it does not overlap with anything in your line card. For context: we have no appointed veterinary distributor in Japan and would rather build one than sell around one. The product I would put in front of you first is the SonoEye P3 VET and SonoTouch VET. Are you open to a short call? I would rather show you the block and the vascular-access demo than describe them. Best regards, Casper Tan Senior Regional Sales Manager AstraMed Healthcare, a subsidiary of CHISON Medical Technologies casper@astramed.sg | +65 8719 0121
A9: 5 | B9: 日本全薬工業株式会社（ゼノアック） | C9: Nippon Zenyaku Kogyo Co., Ltd. (ZENOAQ) | D9: Not started | H9: Major Fukushima-headquartered animal-health company doing R&D, manufacture, import, export and sale of veterinary drugs AND veterinary medical devices, selling into small-animal hospitals, livestock clinics, livestock bodies and overseas distributors, and running Asia roadshows. RELEVANCE: the widest veterinary reach of any company on this tab, and — critically for Japan — an existing import/export function, which means they could carry the Japanese marketing authorisation holder role rather than merely reselling. The livestock arm makes bovine reproduction scanning a second revenue line for the same product. | I9: Major Japanese animal-health company: R&D, manufacture, import/export and sale of veterinary drugs AND veterinary medical devices. Customers span small-animal hospitals, livestock clinics, livestock bodies and overseas distributors. Runs Asia roadshow seminars (seen running events in Taiwan via ivetmall). | J9: Not identified — confirm | K9: Fukushima HQ; nationwide + Asia | L9: https://www.zenoaq.com | M9: Not published (site suppresses telephone detection) | N9: PARTNERSHIP FORM — zenoaq.com/contact/business-development/ (new business, new products, business alliances). Companion animal: zenoaq.com/contact/ca/ | O9: 〒963-0196 福島県郡山市安積町笹川字平ノ上1番地の1 (CEO 福井寿一 · 706 staff · ¥46.6bn FY2025) | P9: A — VERIFIED DIRECT (dedicated business-development enquiry route) | Q9: The widest vet reach of any company on this list and an existing import/export function — meaning they can plausibly carry the Japanese marketing-authorisation-holder role, not just resell. Livestock arm makes bovine repro scanning a second revenue line for the same product. | R9: SonoEye P3 VET (companion) + EBit 50 VET (bovine repro) | S9: TIER 1 | T9: HIGH — the one Japanese candidate that could plausibly hold the marketing-authorisation-holder role. | U9: E | V9: Verified site | W9: Nippon Zenyaku Kogyo Co., Ltd. (ZENOAQ): capital margin on the relationship you already pay for | X9: Dear 日本全薬工業株式会社 (Nippon Zenyaku Kogyo Co., Ltd.) team, My name is Casper Tan, Senior Regional Sales Manager at AstraMed Healthcare, a subsidiary of CHISON Medical Technologies. I cover Japan, South Korea, Taiwan and Singapore for CHISON veterinary ultrasound. I am writing to Nippon Zenyaku Kogyo Co., Ltd. specifically, not to a list. You research, manufacture, import, export and sell both veterinary pharmaceuticals and veterinary devices, across companion animal and livestock, and you run seminar programmes across Asia. The import and export function is the reason I am writing: we need a Japanese partner who can carry a marketing authorisation, not only resell. CHISON's veterinary range is designed to be carried and demonstrated by a rep who is already in the building, no installation crew, no site survey. A unit demonstrated on a Tuesday can be quoted on the Tuesday. It is capital margin layered onto a relationship you already pay for. For context: we have no appointed veterinary distributor in Japan and would rather build one than sell around one. The product I would put in front of you first is the SonoEye P3 VET (companion) and EBit 50 VET (bovine repro). Could we find twenty minutes? Best regards, Casper Tan Senior Regional Sales Manager AstraMed Healthcare, a subsidiary of CHISON Medical Technologies casper@astramed.sg | +65 8719 0121
A10: 6 | B10: 株式会社アスコ | C10: ASCO Corporation | D10: Not started | H10: Specialist animal-health trading company founded 1949, part of the Sala Group (Toyohashi). Sells veterinary pharmaceuticals, instruments and equipment (動物用医薬品・器具器材・機械設備) through 22 branches nationwide, across two divisions: production animals for livestock farmers, and small animals for veterinary hospitals. The name stands for Animal-health Service & Consulting. RELEVANCE: this was previously assumed to be a drugs-and-consumables channel. Their own corporate site names equipment and machinery explicitly, which upgrades them considerably — 22 branches selling equipment to both livestock and companion-animal customers matches the whole CHISON VET range, handheld and EBit 50 alike. | I10: Specialist trading house for veterinary pharmaceuticals: drugs, therapeutic diets, reagents and medical devices supplied to animal hospitals, with total practice-operation support. | J10: Not identified — confirm | K10: Japan (Sala group) | L10: https://www.asco.sala.jp/companion-animal/ | M10: Not published on the companion-animal page — check asco.sala.jp corporate contact | N10: Not published — enquiry via site | O10: Japan (Sala group) | P10: B — VERIFIED PARTIAL (page opened and live; no phone/email published there) | Q10: A pharma-and-consumables channel with a standing weekly order relationship at every clinic. Capital equipment is incremental margin on a relationship they already pay for. Low friction to place an evaluation unit because their rep is already in the building. | R10: SonoEye P3 VET (rep-carried demo unit) | S10: TIER 1 | T10: HIGH — VERIFIED AUGUST 2026: their own site states they sell equipment and machinery, not only drugs. 22 branches. | U10: E | V10: Verified site (search-indexed) | W10: ASCO Corporation: capital margin on the relationship you already pay for | X10: Dear 株式会社アスコ (ASCO Corporation) team, My name is Casper Tan, Senior Regional Sales Manager at AstraMed Healthcare, a subsidiary of CHISON Medical Technologies. I cover Japan, South Korea, Taiwan and Singapore for CHISON veterinary ultrasound. I am writing to ASCO Corporation specifically, not to a list. Your representatives are inside small-animal hospitals every week on drugs, therapeutic diets and reagents, and you already supply medical devices alongside them. That standing relationship is the cheapest demo route for a handheld that exists in Japan. CHISON's veterinary range is designed to be carried and demonstrated by a rep who is already in the building, no installation crew, no site survey. A unit demonstrated on a Tuesday can be quoted on the Tuesday. It is capital margin layered onto a relationship you already pay for. For context: we have no appointed veterinary distributor in Japan and would rather build one than sell around one. The product I would put in front of you first is the SonoEye P3 VET (rep-carried demo unit). Could we find twenty minutes? Best regards, Casper Tan Senior Regional Sales Manager AstraMed Healthcare, a subsidiary of CHISON Medical Technologies casper@astramed.sg | +65 8719 0121
A11: 7 | B11: 株式会社メディカルスペース | C11: Medical Space Inc. | D11: Not started | H11: Veterinary equipment dealer that also plans, builds and refurbishes animal hospitals, with a showroom and a used-equipment trade. Line card includes GE HealthCare Japan, Canon Medtech Supply, Fujifilm and Fujifilm Medical, Konica Minolta and esaote veterinary — 56 ultrasound SKUs listed. RELEVANCE: do NOT pitch a competing console; four of their principals already sell one. What none of those four sells is a scanner at CHISON's price point, and Medical Space builds the equipment list for every clinic they open, so a cheap handheld raises their attach rate without touching their GE or Fujifilm margin. NOTE: their 'maker index' is a supplier list, not a peer-dealer list — several MFR rows on this tab came from correcting that mistake. | I11: Veterinary equipment dealer + animal-hospital opening, planning, construction and refurbishment; showroom; used-equipment trade. Line card includes GE HealthCare Japan, Canon Medtech Supply, Fujifilm/Fujifilm Medical, Konica Minolta, esaote veterinary, Nihon Kohden, Dräger, Olympus, IDEXX. | J11: YES — GE, Canon, Fujifilm and esaote veterinary; 56 ultrasound SKUs listed | K11: Nationwide; showroom | L11: https://medical-space.co.jp | M11: TEL 048-972-5890 · FAX 048-972-5891 | N11: No public address — form: medical-space.co.jp/contact/ | O11: 〒343-0037 埼玉県越谷市恩間新田228-1 (CEO 長谷川博彦) | P11: A — VERIFIED DIRECT (phone off company profile page) | Q11: Heavy cart-tier conflict, so do NOT pitch a competing console. Pitch the pocket tier none of their four ultrasound principals sells at CHISON's price. They build the equipment list for every new clinic they open — a low-cost handheld raises their attach rate without touching their GE/Fujifilm margin. NEW FACT: they already hold a FOREIGN MANUFACTURER registration for veterinary devices (動物用医療機器外国製造業 24外製療第300号) plus a Class-2 marketing authorisation and a repair licence — so the regulatory route for a foreign brand is already built. That materially raises their value despite the ultrasound conflict. | R11: SonoEye P3 / P5 VET only (pocket tier wedge) | S11: TIER 2 | T11: MEDIUM — heavy cart-tier conflict. Pocket tier only, but their new-clinic influence is real. | U11: B | V11: Verified — company profile page fetched 4 Aug 2026 | W11: Medical Space Inc.: not a replacement for your ultrasound line, the tier below it | X11: Dear 株式会社メディカルスペース (Medical Space Inc.) team, My name is Casper Tan, Senior Regional Sales Manager at AstraMed Healthcare, a subsidiary of CHISON Medical Technologies. I cover Japan, South Korea, Taiwan and Singapore for CHISON veterinary ultrasound. I am writing to Medical Space Inc. specifically, not to a list. You carry GE, Canon, Fujifilm and esaote veterinary, so I am not going to pretend I am writing about a console. I am writing because you also hold a foreign-manufacturer registration for veterinary devices and a Class-2 marketing authorisation, and because none of your four ultrasound principals builds the pocket tier. CHISON makes veterinary ultrasound across the range, but the part that should interest you is the handheld tier, SonoEye P3 and P5. Small, vet-preset, high-frequency linear for feline and exotic work, and priced where a GP clinic buys one outright or a hospital buys three as ward units. It sits under your existing line rather than against it. For context: we have no appointed veterinary distributor in Japan and would rather build one than sell around one. The product I would put in front of you first is the SonoEye P3 / P5 VET only (pocket tier wedge). Would twenty minutes be worth it, to see whether this protects your top-tier margin rather than competing with it? Best regards, Casper Tan Senior Regional Sales Manager AstraMed Healthcare, a subsidiary of CHISON Medical Technologies casper@astramed.sg | +65 8719 0121
A12: 8 | B12: 株式会社メディカルタスクフォース | C12: Medical Task Force Inc. (MTF) | D12: Not started | H12: Veterinary medical device company publishing an animal-device catalogue that covers ultrasound imaging and portable X-ray. RELEVANCE: they already understand the ultrasound sale and its service load, which shortens the learning curve — but it also means an incumbent line. The realistic opening is the sub-USD 10k handheld tier rather than a head-to-head console pitch. | I12: Veterinary medical devices; publishes an animal-device catalogue covering ultrasound imaging and portable X-ray. | J12: YES — carries ultrasound | K12: Japan | L12: medical-taskforce.com | M12: Corporate enquiry form | N12: NOT CONFIRMED | O12: Japan | P12: D — NOT VERIFIED (no contact record; confirm the company before contacting) | Q12: Already sells ultrasound into vet, so they understand the sale and the service load. Qualify which brand and at what price band before pitching; the opening is likely the sub-USD 10k handheld tier rather than their existing console line. | R12: SonoEye P3 VET; SonoAir 30 VET if their line is cart-only | S12: TIER 2 | T12: MEDIUM — already sells ultrasound, so qualify the brand and price band first. | U12: B | V12: Verified site (search-indexed) · v11 CHECK 27 Sep 2026: medical-taskforce.com did not resolve in DNS; the site may have moved or closed, confirm before relying on it. | W12: Medical Task Force Inc. (MTF): not a replacement for your ultrasound line, the tier below it | X12: Dear 株式会社メディカルタスクフォース (Medical Task Force Inc.) team, My name is Casper Tan, Senior Regional Sales Manager at AstraMed Healthcare, a subsidiary of CHISON Medical Technologies. I cover Japan, South Korea, Taiwan and Singapore for CHISON veterinary ultrasound. I am writing to Medical Task Force Inc. specifically, not to a list. You already publish an animal-device catalogue covering ultrasound imaging and portable X-ray, so you know how this product sells and what the service load looks like. The opening is the sub-console tier rather than anything you currently list. CHISON makes veterinary ultrasound across the range, but the part that should interest you is the handheld tier, SonoEye P3 and P5. Small, vet-preset, high-frequency linear for feline and exotic work, and priced where a GP clinic buys one outright or a hospital buys three as ward units. It sits under your existing line rather than against it. For context: we have no appointed veterinary distributor in Japan and would rather build one than sell around one. The product I would put in front of you first is the SonoEye P3 VET; SonoAir 30 VET if their line is cart-only. Would twenty minutes be worth it, to see whether this protects your top-tier margin rather than competing with it? Best regards, Casper Tan Senior Regional Sales Manager AstraMed Healthcare, a subsidiary of CHISON Medical Technologies casper@astramed.sg | +65 8719 0121
A13: 9 | B13: 株式会社東京メニックス | C13: Tokyo Menix Co., Ltd. | D13: Not started | H13: Long-standing manufacturer and supplier of small-animal medical devices, described in the trade as a leading company in the Japanese veterinary device field, with 65 SKUs moving through the Medical Space channel. RELEVANCE CORRECTION: confirmed on Medical Space's SUPPLIER list — they sell INTO dealers rather than alongside them. Real brand weight with Japanese vets, so worth a complementary-line or OEM conversation, but never treat this as a distribution appointment. | I13: Long-standing manufacturer/supplier of small-animal medical devices; described as a leading company in the Japanese vet device field. 65 SKUs listed through the Medical Space channel. | J13: Not identified | K13: Tokyo; national | L13: t-menix.com | M13: Corporate enquiry form | N13: NOT CONFIRMED | O13: Tokyo; national | P13: MFR — not a distribution target. Complementary-line / OEM talk only. | Q13: RELEVANCE CORRECTION (v3): Confirmed on the Medical Space supplier list — they SELL INTO dealers. Treat as a manufacturer, i.e. a possible complementary-line or OEM conversation, NOT a distributor to appoint. Manufacturer-plus-channel hybrid with genuine brand weight among Japanese vets. Best framed as a complementary-line agreement rather than pure distribution — their catalogue reaches clinics that a foreign brand cannot cold-call. | R13: SonoEye P3 VET + EBit 50 VET | S13: MFR | T13: MEDIUM — manufacturer, not a distributor. Complementary-line or OEM conversation only. | U13: MFR | V13: Verified site (search-indexed) | W13: Tokyo Menix Co., Ltd.: a complementary veterinary ultrasound line | X13: Dear 株式会社東京メニックス (Tokyo Menix Co., Ltd.) team, My name is Casper Tan, Senior Regional Sales Manager at AstraMed Healthcare, a subsidiary of CHISON Medical Technologies. I cover Japan, South Korea, Taiwan and Singapore for CHISON veterinary ultrasound. I am writing to Tokyo Menix Co., Ltd. specifically, not to a list. You are one of the established names in Japanese small-animal medical devices, and you sell into the dealer network rather than competing with it. CHISON manufactures veterinary ultrasound, handheld SonoEye, portable SonoGO and SonoAir, and cart systems, with vet presets and a full probe range. Rather than a distribution proposal, I am writing about whether a complementary-line or OEM arrangement would be of interest to you. For context: we have no appointed veterinary distributor in Japan and would rather build one than sell around one. The product I would put in front of you first is the SonoEye P3 VET and EBit 50 VET. Would a short call be worthwhile? Best regards, Casper Tan Senior Regional Sales Manager AstraMed Healthcare, a subsidiary of CHISON Medical Technologies casper@astramed.sg | +65 8719 0121
A14: 10 | B14: 株式会社メディアーク（Mediark-VET） | C14: Mediark Inc. — Mediark VET | D14: Not started | H14: Veterinary advanced-imaging company selling animal MRI alongside a portable veterinary ultrasound line (VetEcho). RELEVANCE: positioned at the referral and advanced-imaging end of the market, which is exactly where a cheaper second scanner is bought as a ward or cage-side fleet item rather than as the hospital's primary machine. The conflict is real but narrow — pitch the fleet tier, not the flagship. | I14: Veterinary advanced imaging: animal MRI plus portable veterinary ultrasound (VetEcho line). | J14: YES — portable vet ultrasound (VetEcho) | K14: Japan | L14: vet.mediark.co.jp | M14: Site enquiry form | N14: NOT CONFIRMED | O14: Japan | P14: D — NOT VERIFIED (no contact record; confirm the company before contacting) | Q14: Positioned at the referral / advanced-imaging end, which is exactly where a second, cheaper cage-side scanner gets bought as a fleet item rather than as the hospital's main machine. Conflict is real but narrow. | R14: SonoEye P3 VET ward fleet (secondary to their console) | S14: TIER 2 | T14: MEDIUM — narrow but real conflict; they sit where a second cage-side unit gets bought. | U14: B | V14: Verified site (search-indexed) | W14: Mediark Inc.: Mediark VET, not a replacement for your ultrasound line, the tier below it | X14: Dear 株式会社メディアーク (Mediark Inc.) team, My name is Casper Tan, Senior Regional Sales Manager at AstraMed Healthcare, a subsidiary of CHISON Medical Technologies. I cover Japan, South Korea, Taiwan and Singapore for CHISON veterinary ultrasound. I am writing to Mediark Inc. specifically, not to a list. You sit at the advanced-imaging end of Japanese veterinary practice with animal MRI and portable ultrasound. That is precisely where a second, cheaper cage-side scanner gets bought as a ward fleet rather than as the hospital's main machine. CHISON makes veterinary ultrasound across the range, but the part that should interest you is the handheld tier, SonoEye P3 and P5. Small, vet-preset, high-frequency linear for feline and exotic work, and priced where a GP clinic buys one outright or a hospital buys three as ward units. It sits under your existing line rather than against it. For context: we have no appointed veterinary distributor in Japan and would rather build one than sell around one. The product I would put in front of you first is the SonoEye P3 VET ward fleet (secondary to their console). Would twenty minutes be worth it, to see whether this protects your top-tier margin rather than competing with it? Best regards, Casper Tan Senior Regional Sales Manager AstraMed Healthcare, a subsidiary of CHISON Medical Technologies casper@astramed.sg | +65 8719 0121
A15: 11 | B15: 共立製薬株式会社 | C15: Kyoritsu Seiyaku Corporation | D15: Not started | H15: Major Japanese animal-health pharmaceutical company with nationwide small-animal and livestock coverage, which also sells its own CTS-800 'KS' portable veterinary ultrasound (800 g, companion and livestock). RELEVANCE: they have already decided that portable veterinary ultrasound is a business worth being in — they built one. The CTS-800 is an entry device; the CHISON handheld range sits above it on image quality and below the console tier on price, so this is a step-up SKU inside a portfolio they already sell, not a replacement fight. | I15: Major Japanese animal-health pharmaceutical company with nationwide small-animal and livestock coverage. Sells its own CTS-800 'KS' portable veterinary ultrasound (800 g, companion + livestock). | J15: YES — own-brand CTS-800 portable | K15: Nationwide | L15: kyoritsuseiyaku.co.jp | M15: Corporate enquiry form | N15: NOT CONFIRMED | O15: Nationwide | P15: D — NOT VERIFIED (no contact record; confirm the company before contacting) | Q15: They already believe in portable vet ultrasound — they built one. The CTS-800 is an entry device; CHISON's handheld range sits above it on image quality and below the console tier on price, so the pitch is a step-up SKU inside a portfolio they already sell, not a replacement. | R15: SonoEye P5 VET (high-frequency step-up) + SonoAir 30 VET | S15: TIER 2 | T15: MEDIUM — they build their own portable scanner, but it is an entry device CHISON sits above. | U15: B | V15: Verified site (search-indexed) | W15: Kyoritsu Seiyaku Corporation: not a replacement for your ultrasound line, the tier below it | X15: Dear 共立製薬株式会社 (Kyoritsu Seiyaku Corporation) team, My name is Casper Tan, Senior Regional Sales Manager at AstraMed Healthcare, a subsidiary of CHISON Medical Technologies. I cover Japan, South Korea, Taiwan and Singapore for CHISON veterinary ultrasound. I am writing to Kyoritsu Seiyaku Corporation specifically, not to a list. You built the CTS-800, so you already believe in portable veterinary ultrasound, I am not going to pretend otherwise. What I would like to discuss is the tier above it: higher-frequency handhelds for the same customers, inside a portfolio you already sell. CHISON makes veterinary ultrasound across the range, but the part that should interest you is the handheld tier, SonoEye P3 and P5. Small, vet-preset, high-frequency linear for feline and exotic work, and priced where a GP clinic buys one outright or a hospital buys three as ward units. It sits under your existing line rather than against it. For context: we have no appointed veterinary distributor in Japan and would rather build one than sell around one. The product I would put in front of you first is the SonoEye P5 VET (high-frequency step-up) and SonoAir 30 VET. Would twenty minutes be worth it, to see whether this protects your top-tier margin rather than competing with it? Best regards, Casper Tan Senior Regional Sales Manager AstraMed Healthcare, a subsidiary of CHISON Medical Technologies casper@astramed.sg | +65 8719 0121
A16: 12 | B16: 本郷いわしや | C16: Hongo Iwashiya | D16: Not started | H16: Traditional Tokyo medical-instrument dealer lineage supplying animal hospitals, with 7 SKUs listed through the Medical Space channel. RELEVANCE CORRECTION: appears only in a supplier index, so it is not confirmed as a dealer with its own sales force. Old relationships in Kanto make it worth a call once the national houses are engaged, but as a regional sub-dealer rather than a national appointment. | I16: Traditional medical-instrument dealer lineage supplying animal hospitals; 7 SKUs listed through the Medical Space channel. | J16: Not identified | K16: Tokyo | L16: https://www.hongo-iwashiya.co.jp (animal-hospital section: /animals/ · used-equipment buy-back: /animals/secondhands/) | M16: TEL 03-5800-1848 · FAX 03-5800-2225 (weekdays 9:00–18:00) | N16: info@hongo-iwashiya.co.jp | O16: 〒113-0001 東京都文京区白山1-21-13 | P16: A — VERIFIED DIRECT (phone, fax, email and address read off the company's own animal-hospital pages, 8 Aug 2026). UPGRADED IN v9 from an unverified directory entry. | Q16: CORRECTED IN v9 — they have a clinic-facing business the v6 grading missed. Their own site carries a 動物病院関係者 section selling new AND used equipment to animal hospitals, plus a used-equipment buy-back service. A dealer who buys the old machine back is the easiest route for a clinic replacing an ageing scanner, and the buy-back gives you a trade-in structure without inventing one. Approach as a dealer conversation first and a complementary-line conversation second — but keep the MFR caution: they also supply into Medical Space, so ask openly which side of their business would own the line. || PREVIOUS NOTE: RELEVANCE CORRECTION (v3): Appears only in a supplier index. Not confirmed as a dealer with its own clinic sales force. Regional Tokyo dealer with old relationships. Worth a call once the two or three national houses are engaged; useful as a Kanto-only sub-dealer rather than a national appointment. | R16: SonoEye P3 VET | S16: MFR / DEALER — both | T16: MEDIUM — UPGRADED IN v9 from LOW. They are not only a supplier into Medical Space: their own site runs a direct animal-hospital business selling new and used equipment to clinics and buying used equipment back. That is a clinic-facing sales operation, which the v6 grading assumed they did not have. No invoice until CHISON holds MAFF foreign-manufacturer registration, a Japanese marketing authorisation holder is in place and NVAL is notified. | U16: MFR | V16: CORRECTED IN v9 — hongo-iwashiya.co.jp animal-hospital and used-equipment pages opened and read 8 Aug 2026. Supersedes the v6 classification, which came from the Medical Space maker index only. | W16: Hongo Iwashiya: a complementary veterinary ultrasound line | X16: Dear 本郷いわしや (Hongo Iwashiya) team, My name is Casper Tan, Senior Regional Sales Manager at AstraMed Healthcare, a subsidiary of CHISON Medical Technologies. I cover Japan, South Korea, Taiwan and Singapore for CHISON veterinary ultrasound. I am writing to Hongo Iwashiya specifically, not to a list. You have long-standing relationships with animal hospitals in the Kanto region. CHISON manufactures veterinary ultrasound, handheld SonoEye, portable SonoGO and SonoAir, and cart systems, with vet presets and a full probe range. Rather than a distribution proposal, I am writing about whether a complementary-line or OEM arrangement would be of interest to you. For context: we have no appointed veterinary distributor in Japan and would rather build one than sell around one. The product I would put in front of you first is the SonoEye P3 VET. Would a short call be worthwhile? Best regards, Casper Tan Senior Regional Sales Manager AstraMed Healthcare, a subsidiary of CHISON Medical Technologies casper@astramed.sg | +65 8719 0121
... A32: 28 | B32: 株式会社インターメディカル | C32: Inter Medical Co., Ltd. (intermedical.jp) | D32: Not started | H32: Tokyo used-and-new medical equipment house, founded roughly 40 years ago and describing itself as a pioneer of the Japanese used-medical-equipment trade; JAHID member. Sells, buys back and disposes of equipment across the whole life of a practice, from opening to closure. RELEVANCE: it publishes a dedicated 動物病院関連機器 (animal-hospital equipment) category, AND states it holds a 動物用高度管理医療機器等販売・賃貸業許可 — the Japanese licence to SELL AND LEASE animal high-grade medical devices. Very few companies on this tab are already licensed on the animal side. NEW IN v9 — carried across from the human-diagnostic Market Development list v3 (Japan row 10), where the veterinary side was not identified. | I32: Used and new medical equipment sales, purchase and disposal. Dedicated animal-hospital equipment category. Holds 動物用高度管理医療機器等販売・賃貸業許可 (animal high-grade device sales and lease licence). | J32: YES — but as USED STOCK, not a brand agency. Their veterinary listings show used GE Versana Active, GE Venue Go and Hitachi ARIETTA Prologue LE, and they mark veterinary ultrasound 中古希少 (scarce in the used market). No new-equipment ultrasound agency identified — confirm on the first call. | K32: Tokyo (head office, Bunkyo-ku); nationwide trade; founded c.1985 | L32: https://www.intermedical.jp | M32: NOT CONFIRMED — company pages returned 404/403 on 8 Aug 2026; enquiry via the site | N32: NOT CONFIRMED — enquiry form on intermedical.jp | O32: 〒113-0034 東京都文京区湯島2丁目27番2号 (head office). Business hours 9:00–17:30, closed weekends and holidays. | P32: C — SITE LIVE, NOT OPENED for contact. Product pages and the licence statement WERE opened and read (8 Aug 2026); the company-outline and branch pages returned 404/403, so no phone or email is confirmed. | Q32: Two things make this a real Japan opening, and neither was visible in the older list. First, the licence: this workbook already records that the Japanese marketing-authorisation obstacle may be solvable through the distributor, and a company already licensed to sell AND LEASE animal high-grade devices sits on the right side of that gate. Second, their own veterinary listings mark ultrasound 中古希少 — scarce in used stock. That is demand they cannot reliably fill, and a new value-tier veterinary line fills it without competing against any agency they hold. They also run a buy-back business, so a trade-in structure is available to a clinic replacing an ageing console. UPGRADE TO TIER 1 the moment they confirm they hold no new-equipment ultrasound agency. | R32: EBit 50 VET + SonoEye P3 VET — value tier, positioned against used stock rather than above it | S32: TIER 2 | T32: HIGH — licensed on the animal side already, and their own listings show unmet veterinary ultrasound demand. Graded TIER 2 only because they carry used competing consoles; no invoice until CHISON holds MAFF foreign-manufacturer registration, a Japanese marketing authorisation holder is in place and NVAL is notified. | U32: B/F | V32: NEW IN v9 — intermedical.jp product category 動物病院関連機器 and the licence statement opened and read 8 Aug 2026. Traced from Market Development Target List v3, Japan Dealers row 10 (listed there as a human refurb dealer only). | W32: 株式会社インターメディカル: the veterinary ultrasound your own listings call 中古希少 | X32: Dear 株式会社インターメディカル (Inter Medical Co., Ltd.) team, My name is Casper Tan, Senior Regional Sales Manager at AstraMed Healthcare, a subsidiary of CHISON Medical Technologies. I cover Japan, South Korea, Taiwan and Singapore for CHISON veterinary ultrasound. Two things on your site brought me to you. The first is that you hold a 動物用高度管理医療機器等販売・賃貸業許可, very few of the companies we look at in Japan are already licensed on the animal side. The second is your own 動物病院関連機器 listings, where veterinary ultrasound is marked 中古希少. That is demand you cannot reliably fill from used stock. CHISON manufactures a dedicated veterinary range, pocket units through portables, with animal presets rather than relabelled human systems, at a price point that sits beside refurbished equipment rather than above it. For a clinic weighing a used console against nothing at all, a new value-tier scanner with a full warranty is often the easier decision, and it competes with no agency you hold. Japan still requires CHISON's MAFF foreign-manufacturer registration, a marketing authorisation holder and NVAL notification, so this is a structural conversation rather than an offer. Could we arrange a short call? Casper Tan Senior Regional Sales Manager AstraMed Healthcare, a subsidiary of CHISON Medical Technologies casper@astramed.sg | +65 8719 0121
A33: 29 | B33: 小田島商事株式会社 | C33: Odashima Shoji Co., Ltd. | D33: Not started | E33: Casper | F33: Send intro email | H33: Trading house in Hanamaki, Iwate, serving Tohoku. Runs an animal pharmaceutical business and a dedicated small animal division that supplies drugs, vaccines, therapeutic diets and clinical instruments and equipment, and handles clinic opening support. Named by X-ray maker Mikasa as its Tohoku opening support partner. Why it matters: the strongest Tohoku player found, with both a routine call cycle and a say in opening equipment lists. | I33: Animal pharmaceutical wholesale plus small animal equipment and clinic opening support | J33: Not identified on the published pages; confirm on first call | K33: Tohoku region (HQ Hanamaki, Iwate) | L33: https://odashima-shouji.co.jp/introduction/s-animals/index.html | M33: TEL 0198-26-4151 · FAX 0198-30-2421 | N33: Not published; form: https://odashima-shouji.co.jp/inquery/index.php | O33: 〒025-0311 岩手県花巻市卸町66番地 | P33: A · VERIFIED DIRECT (phone and fax off the company's small animal page, opened 27 Sep 2026) | Q33: Regional recruit for Tohoku, where none of the national houses on this tab is strong. Drug wholesale gives them a call cycle into every clinic, and the opening support role puts them in the room when the equipment list is written. | R33: SonoEye P3 VET (opening package) and SonoGO VET portable | S33: TIER 1 | T33: HIGH · regional appoint grade for Tohoku, no competing ultrasound identified | U33: A | V33: New in v11 · company page fetched 27 Sep 2026; also listed on Mikasa's opening support dealer map (ec-mikasa.com) | W33: Odashima Shoji Co., Ltd.: a first scanner for the Tohoku clinics you equip | X33: Dear 小田島商事株式会社 (Odashima Shoji Co., Ltd.) team, My name is Casper Tan, Senior Regional Sales Manager at AstraMed Healthcare, a subsidiary of CHISON Medical Technologies. I cover Japan, South Korea, Taiwan and Singapore for CHISON veterinary ultrasound. I am writing to Odashima Shoji Co., Ltd. specifically, not to a list. Your small animal division already supplies Tohoku practices with drugs, diets and instruments, and helps new clinics open, which puts you at the exact moment a practice decides whether it can afford ultrasound. CHISON makes veterinary ultrasound in handheld, portable and cart formats, with proper veterinary presets and micro convex, linear and rectal probes. For a practice being equipped, it moves ultrasound from the line item that gets deferred to one that fits the opening budget. For context: we have no appointed veterinary distributor in Japan yet and would rather build one than sell around one. The product I would put in front of you first is the SonoEye P3 VET (opening package) and SonoGO VET portable. Would twenty minutes in the next two weeks be useful? I can send the veterinary line card beforehand if you would rather look first. Best regards, Casper Tan Senior Regional Sales Manager AstraMed Healthcare, a subsidiary of CHISON Medical Technologies casper@astramed.sg | +65 8719 0121
A34: 30 | B34: ミカサ関東商会 | C34: Mikasa Kanto Shokai | D34: Not started | E34: Casper | F34: Send intro email | H34: Kawaguchi, Saitama based sales company tied to Mikasa, the Japanese portable X-ray maker, combining maker and trading functions to support veterinary clinic openings. Publishes the national map of Mikasa's opening support dealers. Why it matters: an X-ray house with no ultrasound, and a gateway to a ready made regional dealer network. | I34: Veterinary X-ray (Mikasa) and clinic opening support; hub of Mikasa's regional dealer network | J34: Not identified; X-ray led | K34: Kanto and Koshin; network nationwide | L34: http://ec-mikasa.com/veterinary/support/dealer/ | M34: TEL 048-294-2210 (weekdays 09:00 to 17:00) | N34: Not published; enquiry via ec-mikasa.com | O34: 〒333-0801 埼玉県川口市東川口6-20-12 | P34: A · VERIFIED DIRECT (phone off the company's own dealer page, opened 27 Sep 2026) | Q34: Archetype F: an imaging house with X-ray and no ultrasound. Ultrasound completes the imaging room they already sell. If Mikasa sees value, eleven regional opening support dealers could follow. | R34: SonoAir 70 VET portable and SonoEye P3 VET | S34: TIER 1 | T34: HIGH · no ultrasound conflict, and access to a national dealer network | U34: F | V34: New in v11 · dealer page fetched 27 Sep 2026 | W34: Mikasa Kanto Shokai: ultrasound beside the X-ray room you already sell | X34: Dear ミカサ関東商会 (Mikasa Kanto Shokai) team, My name is Casper Tan, Senior Regional Sales Manager at AstraMed Healthcare, a subsidiary of CHISON Medical Technologies. I cover Japan, South Korea, Taiwan and Singapore for CHISON veterinary ultrasound. I am writing to Mikasa Kanto Shokai specifically, not to a list. Your opening support page maps Mikasa's partner dealers from Hokkaido to Okinawa, which tells me you think about the whole imaging room, not only the X-ray unit. You already sell the imaging decision in a veterinary clinic. Ultrasound is the other half of that decision, and CHISON's handheld and portable range sits naturally beside an X-ray line without competing with it. For context: we have no appointed veterinary distributor in Japan yet and would rather build one than sell around one. The product I would put in front of you first is the SonoAir 70 VET portable and SonoEye P3 VET. Would twenty minutes in the next two weeks be useful? I can send the veterinary line card beforehand if you would rather look first. Best regards, Casper Tan Senior Regional Sales Manager AstraMed Healthcare, a subsidiary of CHISON Medical Technologies casper@astramed.sg | +65 8719 0121
A35: 31 | B35: 有限会社メディカル技研 | C35: Medical Giken Co., Ltd. | D35: Not started | E35: Casper | F35: Send intro email | H35: Kasugai, Aichi based veterinary equipment dealer covering Aichi, Gifu, Mie and Shizuoka. Sells new and used animal medical equipment, supports clinic openings and maintains equipment after opening. Listed by Mikasa as a Tokai opening support partner. Why it matters: a service minded regional house that owns the Tokai relationship after the sale. | I35: Animal medical equipment sales, clinic opening support, maintenance, used equipment | J35: Not identified on the published pages; confirm | K35: Tokai: Aichi, Gifu, Mie, Shizuoka | L35: https://www.medical-giken.com | M35: TEL 0568-52-0138 (09:00 to 17:00) | N35: Not published; form: https://www.medical-giken.com/contact/ | O35: 〒487-0034 愛知県春日井市白山町3丁目19番地の15 | P35: A · VERIFIED DIRECT (phone and address off the company contact page, opened 27 Sep 2026) | Q35: Archetype A. Opening support plus in house maintenance is exactly the service capability a new ultrasound line needs in Tokai. | R35: SonoEye P3 VET (opening package) and SonoGO VET portable | S35: TIER 1 | T35: HIGH · regional appoint grade for Tokai | U35: A | V35: New in v11 · contact page fetched 27 Sep 2026 | W35: Medical Giken Co., Ltd.: an ultrasound line you can support across Tokai | X35: Dear 有限会社メディカル技研 (Medical Giken Co., Ltd.) team, My name is Casper Tan, Senior Regional Sales Manager at AstraMed Healthcare, a subsidiary of CHISON Medical Technologies. I cover Japan, South Korea, Taiwan and Singapore for CHISON veterinary ultrasound. I am writing to Medical Giken Co., Ltd. specifically, not to a list. You look after Tokai clinics from opening through maintenance, which is the service backbone any imaging line needs to succeed in the region. CHISON makes veterinary ultrasound in handheld, portable and cart formats, with proper veterinary presets and micro convex, linear and rectal probes. For a practice being equipped, it moves ultrasound from the line item that gets deferred to one that fits the opening budget. For context: we have no appointed veterinary distributor in Japan yet and would rather build one than sell around one. The product I would put in front of you first is the SonoEye P3 VET (opening package) and SonoGO VET portable. Would twenty minutes in the next two weeks be useful? I can send the veterinary line card beforehand if you would rather look first. Best regards, Casper Tan Senior Regional Sales Manager AstraMed Healthcare, a subsidiary of CHISON Medical Technologies casper@astramed.sg | +65 8719 0121
A36: 32 | B36: 有限会社ランタック | C36: Rantac Co., Ltd. | D36: Not started | E36: Casper | F36: Send intro email | H36: Ichinomiya, Aichi based total medical service company selling new and used equipment to hospitals and veterinary clinics, with installation and veterinary clinic opening support covering diagnostic, surgical, X-ray and ward rooms. Listed by Mikasa as a Tokai opening support partner. | I36: New and used equipment for human and veterinary clinics; installation; opening support | J36: Not identified; confirm | K36: Tokai (Ichinomiya, Aichi) | L36: http://rantac.jp/ | M36: TEL 0586-76-7046 | N36: Not published; enquiry form on rantac.jp | O36: Ichinomiya, Aichi (street address not shown on the home page) | P36: A · VERIFIED DIRECT (phone off the company home page, opened 27 Sep 2026) | Q36: Smaller, mixed human and veterinary house. Worth a call as a second Tokai option behind Medical Giken. | R36: SonoEye P3 VET | S36: TIER 2 | T36: MEDIUM · mixed human and vet, scale unknown | U36: A | V36: New in v11 · home page fetched 27 Sep 2026 | W36: Rantac Co., Ltd.: a first scanner for the clinics you set up | X36: Dear 有限会社ランタック (Rantac Co., Ltd.) team, My name is Casper Tan, Senior Regional Sales Manager at AstraMed Healthcare, a subsidiary of CHISON Medical Technologies. I cover Japan, South Korea, Taiwan and Singapore for CHISON veterinary ultrasound. I am writing to Rantac Co., Ltd. specifically, not to a list. You equip veterinary clinics room by room, from diagnostics to the ward, which means you see the ultrasound decision in every project. CHISON makes veterinary ultrasound in handheld, portable and cart formats, with proper veterinary presets and micro convex, linear and rectal probes. For a practice being equipped, it moves ultrasound from the line item that gets deferred to one that fits the opening budget. For context: we have no appointed veterinary distributor in Japan yet and would rather build one than sell around one. The product I would put in front of you first is the SonoEye P3 VET. Would twenty minutes in the next two weeks be useful? I can send the veterinary line card beforehand if you would rather look first. Best regards, Casper Tan Senior Regional Sales Manager AstraMed Healthcare, a subsidiary of CHISON Medical Technologies casper@astramed.sg | +65 8719 0121
A37: 33 | B37: 株式会社ナクトル | C37: Nactol Co., Ltd. | D37: Not started | E37: Casper | F37: Confirm phone and email, then send | H37: Hokkaido company working across electronics and medical fields, described by Mikasa as a specialist in veterinary clinic opening support. Why it matters: Hokkaido has a large mixed and production animal sector, and no house on this tab covers it. | I37: Electronics and medical equipment; veterinary clinic opening support | J37: Not identified; confirm | K37: Hokkaido | L37: http://www.nctl.co.jp/ | M37: NOT CONFIRMED (site refused a secure connection on 27 Sep 2026) | N37: NOT CONFIRMED | O37: Hokkaido (address not confirmed) | P37: C · SITE LISTED, NOT OPENED (named on Mikasa's dealer page; nctl.co.jp failed to load) | Q37: Only Hokkaido lead found. Confirm the company and phone before emailing; lead with EBit 50 VET if they serve dairy and equine as well as small animal. | R37: SonoEye P3 VET and EBit 50 VET (livestock and equine) | S37: TIER 2 | T37: MEDIUM · entity and lines unconfirmed | U37: A | V37: New in v11 · from Mikasa dealer map, site not opened | W37: Nactol Co., Ltd.: ultrasound for Hokkaido clinics and farms | X37: Dear 株式会社ナクトル (Nactol Co., Ltd.) team, My name is Casper Tan, Senior Regional Sales Manager at AstraMed Healthcare, a subsidiary of CHISON Medical Technologies. I cover Japan, South Korea, Taiwan and Singapore for CHISON veterinary ultrasound. I am writing to Nactol Co., Ltd. specifically, not to a list. Mikasa names you as its veterinary opening support partner in Hokkaido, a region where many practices work across companion, dairy and equine patients. CHISON makes veterinary ultrasound from handhelds for companion practice to rugged portables with rectal probes for livestock and equine work. For context: we have no appointed veterinary distributor in Japan yet and would rather build one than sell around one. The product I would put in front of you first is the SonoEye P3 VET and EBit 50 VET (livestock and equine). Could you tell me who in your company looks after new equipment lines, so I can send the veterinary line card to the right person? Best regards, Casper Tan Senior Regional Sales Manager AstraMed Healthcare, a subsidiary of CHISON Medical Technologies casper@astramed.sg | +65 8719 0121
A38: 34 | B38: ミカサ販売西日本 (丸光) | C38: Mikasa Hanbai Nishi Nihon (marukou11.co.jp) | D38: Not started | E38: Casper | F38: Confirm legal name and contact | H38: Shiga based authorised Mikasa dealer for western Japan that also offers veterinary clinic opening consultation with maintenance. Why it matters: Kansai coverage with an X-ray only veterinary line. | I38: Authorised Mikasa X-ray dealer; opening consultation and maintenance | J38: Not identified; X-ray led | K38: Kansai (Shiga) | L38: http://www.marukou11.co.jp/index.html | M38: NOT CONFIRMED | N38: NOT CONFIRMED | O38: Shiga (address not confirmed) | P38: C · SITE LISTED, NOT OPENED (named on Mikasa's dealer page) | Q38: Archetype F in Kansai. Confirm legal name and contact first; the site name suggests the trading company is 丸光. | R38: SonoAir 70 VET portable | S38: TIER 2 | T38: MEDIUM · regional, unconfirmed | U38: F | V38: New in v11 · from Mikasa dealer map · v11 CHECK 27 Sep 2026: marukou11.co.jp did not resolve in DNS; the site may have moved or closed, confirm before relying on it. | W38: Mikasa Hanbai Nishi Nihon: ultrasound beside the X-ray rooms you sell | X38: Dear ミカサ販売西日本 (Mikasa Hanbai Nishi Nihon) team, My name is Casper Tan, Senior Regional Sales Manager at AstraMed Healthcare, a subsidiary of CHISON Medical Technologies. I cover Japan, South Korea, Taiwan and Singapore for CHISON veterinary ultrasound. I am writing to Mikasa Hanbai Nishi Nihon specifically, not to a list. You sell and maintain Mikasa X-ray for veterinary clinics in western Japan, so you already own the imaging conversation there. You already sell the imaging decision in a veterinary clinic. Ultrasound is the other half of that decision, and CHISON's handheld and portable range sits naturally beside an X-ray line without competing with it. For context: we have no appointed veterinary distributor in Japan yet and would rather build one than sell around one. The product I would put in front of you first is the SonoAir 70 VET portable. Could you tell me who in your company looks after new equipment lines, so I can send the veterinary line card to the right person? Best regards, Casper Tan Senior Regional Sales Manager AstraMed Healthcare, a subsidiary of CHISON Medical Technologies casper@astramed.sg | +65 8719 0121
A39: 35 | B39: 株式会社テックミカサ | C39: Tech Mikasa Co., Ltd. | D39: Not started | E39: Casper | F39: Confirm contact | H39: Hyogo based authorised Mikasa dealer that recently began veterinary clinic opening support. Why it matters: X-ray only imaging house in Hyogo, early in building its opening business. | I39: Authorised Mikasa X-ray dealer; new opening support service | J39: Not identified; X-ray led | K39: Kansai (Hyogo) | L39: http://www.tecmikasa.com/ | M39: NOT CONFIRMED | N39: NOT CONFIRMED | O39: Hyogo (address not confirmed) | P39: C · SITE LISTED, NOT OPENED (certificate error on 27 Sep 2026) | Q39: Archetype F. A new opening support business needs a full equipment list; ultrasound is the gap. | R39: SonoAir 70 VET portable and SonoEye P3 VET | S39: TIER 2 | T39: MEDIUM · regional, unconfirmed | U39: F | V39: New in v11 · from Mikasa dealer map | W39: Tech Mikasa Co., Ltd.: completing the imaging list for new clinics | X39: Dear 株式会社テックミカサ (Tech Mikasa Co., Ltd.) team, My name is Casper Tan, Senior Regional Sales Manager at AstraMed Healthcare, a subsidiary of CHISON Medical Technologies. I cover Japan, South Korea, Taiwan and Singapore for CHISON veterinary ultrasound. I am writing to Tech Mikasa Co., Ltd. specifically, not to a list. You have recently started supporting veterinary clinic openings in Hyogo alongside Mikasa X-ray. You already sell the imaging decision in a veterinary clinic. Ultrasound is the other half of that decision, and CHISON's handheld and portable range sits naturally beside an X-ray line without competing with it. For context: we have no appointed veterinary distributor in Japan yet and would rather build one than sell around one. The product I would put in front of you first is the SonoAir 70 VET portable and SonoEye P3 VET. Could you tell me who in your company looks after new equipment lines, so I can send the veterinary line card to the right person? Best regards, Casper Tan Senior Regional Sales Manager AstraMed Healthcare, a subsidiary of CHISON Medical Technologies casper@astramed.sg | +65 8719 0121
A40: 36 | B40: グッドウィルメディカル | C40: Goodwill Medical | D40: Not started | E40: Casper | F40: Send intro email | H40: Sakurai, Nara based medical equipment dealer founded 1992 that positions itself as a total partner for animal medicine, with clinic opening support. Listed by Mikasa as a Kansai opening support partner. | I40: Medical equipment sales; veterinary clinic opening support | J40: Not identified; confirm | K40: Kansai (Nara) | L40: https://gwm1992.com/ | M40: TEL 0744-46-2464 (iTownpage listing) | N40: Not published; contact page gwm1992.com/sp/contact.html | O40: 奈良県桜井市大字慈恩寺 (iTownpage) | P40: C · SITE LIVE, NOT OPENED (site timed out; phone from iTownpage directory) | Q40: Nara coverage with opening support. Confirm the veterinary share of the business on the first call. | R40: SonoEye P3 VET (opening package) | S40: TIER 2 | T40: MEDIUM · regional | U40: A | V40: New in v11 · Mikasa dealer map plus iTownpage | W40: Goodwill Medical: a first scanner for the Nara clinics you open | X40: Dear グッドウィルメディカル (Goodwill Medical) team, My name is Casper Tan, Senior Regional Sales Manager at AstraMed Healthcare, a subsidiary of CHISON Medical Technologies. I cover Japan, South Korea, Taiwan and Singapore for CHISON veterinary ultrasound. I am writing to Goodwill Medical specifically, not to a list. You describe yourselves as a total partner for animal medicine and help Nara practices open. CHISON makes veterinary ultrasound in handheld, portable and cart formats, with proper veterinary presets and micro convex, linear and rectal probes. For a practice being equipped, it moves ultrasound from the line item that gets deferred to one that fits the opening budget. For context: we have no appointed veterinary distributor in Japan yet and would rather build one than sell around one. The product I would put in front of you first is the SonoEye P3 VET (opening package). Would twenty minutes in the next two weeks be useful? I can send the veterinary line card beforehand if you would rather look first. Best regards, Casper Tan Senior Regional Sales Manager AstraMed Healthcare, a subsidiary of CHISON Medical Technologies casper@astramed.sg | +65 8719 0121
A41: 37 | B41: 株式会社三幸医療酸素 | C41: Sanko Medical Oxygen Co., Ltd. | D41: Not started | E41: Casper | F41: Confirm contact | H41: Hyogo based medical oxygen supplier that also offers veterinary clinic opening support from an oxygen and anaesthesia angle. Listed by Mikasa. | I41: Medical gases; opening support | J41: Not identified | K41: Kansai (Hyogo) | L41: http://sanco-medical.co.jp/index.html | M41: NOT CONFIRMED | N41: NOT CONFIRMED | O41: Hyogo (address not confirmed) | P41: C · SITE LISTED, NOT OPENED | Q41: Long tail. Useful as a referral into Hyogo openings rather than a distributor. | R41: SonoEye P3 VET | S41: TIER 3 | T41: LOW · referral value only | U41: A | V41: New in v11 · from Mikasa dealer map · v11 CHECK 27 Sep 2026: sanco-medical.co.jp did not resolve in DNS; the site may have moved or closed, confirm before relying on it. | W41: Sanko Medical Oxygen Co., Ltd.: ultrasound for the clinics you help open | X41: Dear 株式会社三幸医療酸素 (Sanko Medical Oxygen Co., Ltd.) team, My name is Casper Tan, Senior Regional Sales Manager at AstraMed Healthcare, a subsidiary of CHISON Medical Technologies. I cover Japan, South Korea, Taiwan and Singapore for CHISON veterinary ultrasound. I am writing to Sanko Medical Oxygen Co., Ltd. specifically, not to a list. You support Hyogo veterinary clinics as they open, from the gas and anaesthesia side. CHISON makes veterinary ultrasound in handheld, portable and cart formats, with proper veterinary presets and micro convex, linear and rectal probes. For a practice being equipped, it moves ultrasound from the line item that gets deferred to one that fits the opening budget. For context: we have no appointed veterinary distributor in Japan yet and would rather build one than sell around one. The product I would put in front of you first is the SonoEye P3 VET. Could you tell me who in your company looks after new equipment lines, so I can send the veterinary line card to the right person? Best regards, Casper Tan Senior Regional Sales Manager AstraMed Healthcare, a subsidiary of CHISON Medical Technologies casper@astramed.sg | +65 8719 0121
A42: 38 | B42: ミヤノメディックス | C42: Miyano Medix | D42: Not started | E42: Casper | F42: Call first, no email published | H42: Hiroshima based dealer serving Chugoku and all of Shikoku, listed by Mikasa as the opening support partner for that region. No website found. | I42: Veterinary equipment and opening support | J42: Not identified | K42: Chugoku and Shikoku (Hiroshima) | L42: NOT CONFIRMED (no website found) | M42: TEL 084-924-0976 (per Mikasa's dealer page) | N42: NOT CONFIRMED | O42: Hiroshima (address not confirmed) | P42: C · PHONE FROM A THIRD PARTY PAGE (Mikasa dealer map); company site not found | Q42: Covers Shikoku, which nobody else on this tab does. Phone first; there is no published email. | R42: SonoEye P3 VET | S42: TIER 2 | T42: MEDIUM · regional, unverified | U42: A | V42: New in v11 · from Mikasa dealer map | W42: Miyano Medix: ultrasound for Chugoku and Shikoku clinics | X42: Dear ミヤノメディックス (Miyano Medix) team, My name is Casper Tan, Senior Regional Sales Manager at AstraMed Healthcare, a subsidiary of CHISON Medical Technologies. I cover Japan, South Korea, Taiwan and Singapore for CHISON veterinary ultrasound. I am writing to Miyano Medix specifically, not to a list. Mikasa lists you as its opening support partner for Chugoku and the whole of Shikoku. CHISON makes veterinary ultrasound in handheld, portable and cart formats, with proper veterinary presets and micro convex, linear and rectal probes. For a practice being equipped, it moves ultrasound from the line item that gets deferred to one that fits the opening budget. For context: we have no appointed veterinary distributor in Japan yet and would rather build one than sell around one. The product I would put in front of you first is the SonoEye P3 VET. Could you tell me who in your company looks after new equipment lines, so I can send the veterinary line card to the right person? Best regards, Casper Tan Senior Regional Sales Manager AstraMed Healthcare, a subsidiary of CHISON Medical Technologies casper@astramed.sg | +65 8719 0121
A43: 39 | B43: 有限会社メディカルクラフト | C43: Medical Craft Co., Ltd. | D43: Not started | E43: Casper | F43: Call first, no email published | H43: Okinawa based dealer providing Okinawa focused veterinary clinic opening support. Listed by Mikasa, which names 國場様 as the contact (not independently verified). | I43: Veterinary equipment and opening support, Okinawa only | J43: Not identified | K43: Okinawa | L43: NOT CONFIRMED (no website found) | M43: TEL 098-929-3461 (per Mikasa's dealer page) | N43: NOT CONFIRMED | O43: Okinawa (address not confirmed) | P43: C · PHONE FROM A THIRD PARTY PAGE (Mikasa dealer map) | Q43: Island market with its own dealer. Small, but uncontested. Phone first. | R43: SonoEye P3 VET | S43: TIER 3 | T43: LOW · small island market | U43: A | V43: New in v11 · from Mikasa dealer map | W43: Medical Craft Co., Ltd.: ultrasound for Okinawa clinics | X43: Dear 有限会社メディカルクラフト (Medical Craft Co., Ltd.) team, My name is Casper Tan, Senior Regional Sales Manager at AstraMed Healthcare, a subsidiary of CHISON Medical Technologies. I cover Japan, South Korea, Taiwan and Singapore for CHISON veterinary ultrasound. I am writing to Medical Craft Co., Ltd. specifically, not to a list. You are the opening support partner for veterinary clinics in Okinawa. CHISON makes veterinary ultrasound in handheld, portable and cart formats, with proper veterinary presets and micro convex, linear and rectal probes. For a practice being equipped, it moves ultrasound from the line item that gets deferred to one that fits the opening budget. For context: we have no appointed veterinary distributor in Japan yet and would rather build one than sell around one. The product I would put in front of you first is the SonoEye P3 VET. Could you tell me who in your company looks after new equipment lines, so I can send the veterinary line card to the right person? Best regards, Casper Tan Senior Regional Sales Manager AstraMed Healthcare, a subsidiary of CHISON Medical Technologies casper@astramed.sg | +65 8719 0121
A44: 40 | B44: 株式会社M&T | C44: M&T Co., Ltd. | D44: Not started | E44: Casper | F44: Send intro email | H44: Veterinary equipment trading company (total medical equipment trader) supporting animal hospital openings and expansions, including subsidy applications with a strong adoption record, used equipment and post opening visits by seven sales staff. Covers Kansai, Chugoku, Kyushu and Okinawa plus partners. Carries Canon ultrasound and X-ray. | I44: Animal hospital equipment, opening support, subsidy applications, used equipment | J44: YES · Canon ultrasound shown in product listings | K44: Western Japan, national via partners | L44: https://www.mandt-net.com/ | M44: TEL 084-927-6606 | N44: Not published; form: https://www.mandt-net.com/inquiry/ | O44: Fukuyama area, Hiroshima (per 084 area code; address not shown) | P44: A · VERIFIED DIRECT (phone off the company site, opened 27 Sep 2026) | Q44: Archetype B. Carries Canon consoles, so pitch the handheld tier only. Their subsidy work is a good angle: a handheld fits inside a grant budget. | R44: SonoEye P3 VET (pocket tier only, never a console) | S44: TIER 2 | T44: MEDIUM · competing Canon line | U44: B | V44: New in v11 · site fetched 27 Sep 2026 | W44: M&T Co., Ltd.: a handheld tier beside the consoles you sell | X44: Dear 株式会社M&T (M&T Co., Ltd.) team, My name is Casper Tan, Senior Regional Sales Manager at AstraMed Healthcare, a subsidiary of CHISON Medical Technologies. I cover Japan, South Korea, Taiwan and Singapore for CHISON veterinary ultrasound. I am writing to M&T Co., Ltd. specifically, not to a list. You help clinics win equipment subsidies and open within a limited budget, and you already carry Canon consoles. You already carry established ultrasound brands, so I am not asking you to replace anything. What those brands rarely offer is a true veterinary handheld that a GP clinic buys as its first scanner, or a hospital buys as ward units. That is the tier I would like to discuss. For context: we have no appointed veterinary distributor in Japan yet and would rather build one than sell around one. The product I would put in front of you first is the SonoEye P3 VET (pocket tier only, never a console). Would twenty minutes in the next two weeks be useful? I can send the veterinary line card beforehand if you would rather look first. Best regards, Casper Tan Senior Regional Sales Manager AstraMed Healthcare, a subsidiary of CHISON Medical Technologies casper@astramed.sg | +65 8719 0121
... A48: 44 | B48: 日本光電工業株式会社 | C48: Nihon Kohden Corporation | D48: Not started | E48: Casper | F48: Low priority, complementary only | H48: Japanese medical electronics maker (monitoring, ECG) with sales companies nationwide that also support animal hospital openings. Why it matters: complementary line, not a distributor. | I48: Monitoring and diagnostics maker with a national sales network | J48: Not identified in the veterinary range; confirm | K48: Nationwide | L48: https://www.nihonkohden.co.jp/iryo/practice/animal/index.html | M48: Via company site | N48: Via company site | O48: Tokyo HQ | P48: MFR · manufacturer; complementary line conversation only | Q48: MFR frame only. Relevant because their sales companies sit in every opening project; a co-selling conversation, not an appointment. | R48: SonoEye P3 VET (peri operative pairing with monitoring) | S48: MFR | T48: LOW · partnership rather than purchase | U48: MFR | V48: New in v11 · Mikasa dealer map | W48: Nihon Kohden: monitoring and ultrasound in the same opening project | X48: Dear 日本光電工業株式会社 (Nihon Kohden Corporation) team, My name is Casper Tan, Senior Regional Sales Manager at AstraMed Healthcare, a subsidiary of CHISON Medical Technologies. I cover Japan, South Korea, Taiwan and Singapore for CHISON veterinary ultrasound. I am writing to Nihon Kohden Corporation specifically, not to a list. Your sales companies support animal hospital openings across Japan with monitoring. I see this as a complementary line conversation rather than a distribution appointment: our ultrasound and your range sit side by side in the same clinic without overlap. For context: we have no appointed veterinary distributor in Japan yet and would rather build one than sell around one. The product I would put in front of you first is the SonoEye P3 VET (peri operative pairing with monitoring). Could you tell me who in your company looks after new equipment lines, so I can send the veterinary line card to the right person? Best regards, Casper Tan Senior Regional Sales Manager AstraMed Healthcare, a subsidiary of CHISON Medical Technologies casper@astramed.sg | +65 8719 0121
A50: =COUNTIF(S5:S48,"TIER 1") | B50: Tier 1: contact first
A51: =COUNTIF(S5:S48,"TIER 2") | B51: Tier 2: qualify first
A52: =COUNTIF(S5:S48,"TIER 3") | B52: Tier 3: long tail
A53: =COUNTIF(S5:S48,"MFR*") | B53: MFR: manufacturer or supplier, complementary line only
A55: =COUNTIF(T5:T48,"HIGH*") | B55: Buying / distribution potential HIGH
A56: =COUNTIF(T5:T48,"MEDIUM*") | B56: Buying / distribution potential MEDIUM
A57: =COUNTIF(T5:T48,"LOW*") | B57: Buying / distribution potential LOW
A59: =COUNTIF(P5:P48,"A*") | B59: Contacts graded A: verified phone and/or email
A60: =COUNTIF(P5:P48,"B*") | B60: Contacts graded B: site verified, enquiry form or partial
A61: =COUNTIF(P5:P48,"C*") | B61: Contacts graded C: site live or listed, not opened by us
A62: =COUNTIF(P5:P48,"D*") | B62: Contacts graded D: NOT VERIFIED, confirm before contacting
A63: =COUNTIF(N5:N48,"*@*") | B63: Rows with a real email address in column N (ready for Winmail drafting)
A65: =COUNTA(B5:B48) | B65: TOTAL companies on this tab, every one with a ready to send email

Sheet Japan VET_additional
A1: JAPAN: VETERINARY ADDITIONAL LEADS (V1 to V5), added in v18, emails added in v19
A2: CHISON veterinary ultrasound, Japan lead list v2 (AstraMed Healthcare). Built 10 Oct 2026 from web search results only: the session's network policy blocked direct page fetches, so contact pages were read through search results, not opened. Every row has at least one source link. Email column: a published company address where one exists (no personal address was guessed), otherwise the inquiry form URL or 'phone only'. Contact confidence: 'Verified' = published on the company's own site; 'Likely' = third party listing (association, chamber); 'Company inquiry only' = form or phone. Rows marked 'Qualify first' in the last column are human dealers whose animal hospital business is not yet confirmed. Fit score is the live SUM of the seven score columns on the right. None of these companies appear on the Japan Dealers, Japan End Users & KOL or Reference tabs of v17.
A4: No. | B4: Company (English) | C4: Company (Japanese) | D4: 法人番号 | E4: HQ prefecture | F4: Region | G4: Website | H4: Licences held | I4: Brands carried | J4: Companion / Large animal / Both | K4: Coverage area | L4: Est. revenue or headcount | M4: Number of clinics (Tier V5 only) | N4: Key contact name | O4: Title | P4: Email | Q4: Phone | R4: LinkedIn | S4: Contact confidence | T4: Fit score /35 | U4: Tier | V4: Why they fit | W4: Suggested opening angle | X4: Also in human list (Y/N) | Y4: Source links | Z4: Score: regulatory | AA4: Score: imaging and US | AB4: Score: brand conflict | AC4: Score: companion coverage | AD4: Score: large animal | AE4: Score: service engineers | AF4: Score: openness to CN/KR | AG4: Evidence status
A5: 1 | B5: Central Scientific Commerce, Inc. | C5: セントラル科学貿易株式会社 | D5: Not found (NTA lookup blocked; dedupe by Japanese name) | E5: Tokyo | F5: Kanto | G5: https://cscjp.co.jp/csc-medical/products/vet-videoscope.html | H5: Imports AOHUA vet videoscopes (vet device notification implied) | I5: AOHUA (China) vet endoscopes; no ultrasound | J5: Companion | K5: National | L5: Not found | M5: n/a | N5: Not identified | O5: Not identified | P5: cscsupport@cscjp.co.jp | Q5: 03 5627 8150 | R5: Not identified | S5: Likely (third party listing) | T5: =SUM(Z5:AF5) -> 26 | U5: V1 | V5: Already imports a Chinese vet imaging brand (AOHUA), which shows openness to Chinese manufacturers and a working NVAL route. | W5: Lead with CHISON credentials (FDA, OEM for global brands) as the ultrasound companion to AOHUA. | X5: Not checked (human list not in v17) | Y5: https://cscjp.co.jp/csc-medical/products/vet-videoscope.html ; https://sia-tokyo.gr.jp/co-list/748 ; https://cscjp.co.jp/contact/ | Z5: 5 | AA5: 3 | AB5: 5 | AC5: 4 | AD5: 1 | AE5: 3 | AF5: 5 | AG5: Evidence backed
A6: 2 | B6: ARKRAY, Inc. (Veterinary) | C6: アークレイ株式会社 (アークレイファクトリー) | D6: Not found (NTA lookup blocked; dedupe by Japanese name) | E6: Kyoto | F6: Kansai | G6: https://arkraythinkanimal.com | H6: Vet device MAH via ARKRAY Factory (NVAL: thinka CB1010) | I6: Vet analysers (Vcheck V200); no ultrasound | J6: Companion | K6: National vet sales force | L6: Large | M6: n/a | N6: Not identified | O6: Not identified | P6: thinka@arkray.co.jp | Q6: 050 5527 7700 | R6: Not identified | S6: Verified (published on own site, read via search) | T6: =SUM(Z6:AF6) -> 25 | U6: V1 | V6: Runs a dedicated vet brand (Think Animal) and exhibits at JBVP; national animal hospital coverage and service. | W6: In clinic diagnostics plus point of care ultrasound bundle. | X6: Not checked (human list not in v17) | Y6: https://www.vm.nval.go.jp/public/detail/16030 ; https://arkraythinkanimal.com/2025/09/03/information95/ ; https://arkraythinkanimal.com/company/ ; https://arkraythinkanimal.com/contact/ | Z6: 5 | AA6: 2 | AB6: 5 | AC6: 5 | AD6: 1 | AE6: 4 | AF6: 3 | AG6: Evidence backed
A7: 3 | B7: Nozawa Corporation | C7: 株式会社野澤組 | D7: Not found (NTA lookup blocked; dedupe by Japanese name) | E7: Tokyo | F7: Kanto | G7: https://www.nosawa.co.jp/ | H7: Vet ultrasound MAH per NVAL listing (iScan2 and MyLab series) | I7: iScan2 (Draminski) and MyLab series listed | J7: Both | K7: National import trading house | L7: Not found | M7: n/a | N7: Not identified | O7: Not identified | P7: gg@nosawa.co.jp | Q7: 03 3528 8101 | R7: Not identified | S7: Verified (published on own site, read via search) | T7: =SUM(Z7:AF7) -> 25 | U7: V1 | V7: Trading house already holding vet ultrasound notifications, including large animal scanners; regulatory capability proven. FLAG: MyLab may indicate an Esaote relationship; confirm brand conflict. | W7: Mid tier companion portables to complement their large animal scanner, if their MyLab line is not exclusive. | X7: Not checked (human list not in v17) | Y7: https://vm.nval.go.jp/?mfg_dealer_name=&sort=MANUFACTURING_DEALER&submit=submit ; https://www.vm.nval.go.jp/public/detail/9148 ; https://www.totalapproach.co.jp/askme/askme.html ; https://www.nosawa.co.jp/inquiry/ | Z7: 5 | AA7: 5 | AB7: 2 | AC7: 3 | AD7: 4 | AE7: 3 | AF7: 3 | AG7: Evidence backed
A8: 4 | B8: Olympus Marketing, Inc. (Animal Medical) | C8: オリンパスマーケティング株式会社 | D8: Not found (NTA lookup blocked; dedupe by Japanese name) | E8: Tokyo | F8: Kanto | G8: https://www.olympus-marketing.co.jp/business/animal/ | H8: Vet endoscopy systems marketed (VES Be one); Olympus group MAH capability | I8: Own endoscopes; no ultrasound in vet range | J8: Companion | K8: National | L8: Large (Olympus group) | M8: n/a | N8: Not identified | O8: Not identified | P8: Not published; inquiry form: https://www.olympus-marketing.co.jp/contact/ | Q8: 042 642 4002 | R8: Not identified | S8: Company inquiry only (form) | T8: =SUM(Z8:AF8) -> 25 | U8: V1 | V8: Runs a dedicated animal endoscopy business with national service engineers; imaging culture and hospital relationships. | W8: Endoscopy plus ultrasound GI work up; propose a co marketing pilot rather than distribution first. | X8: Not checked (human list not in v17) | Y8: https://www.olympus-marketing.co.jp/business/animal/ ; https://www.olympus-marketing.co.jp/contact/ | Z8: 5 | AA8: 4 | AB8: 4 | AC8: 4 | AD8: 1 | AE8: 5 | AF8: 2 | AG8: Evidence backed
A9: 5 | B9: Kyoritsu Shokai Co., Ltd. | C9: 株式会社共立商会 | D9: Not found (NTA lookup blocked; dedupe by Japanese name) | E9: Tokyo | F9: Kanto | G9: https://www.kyoritsu-shokai.com | H9: 第二種動物用医療機器製造販売業許可 (licence page on own site); 動物用医薬品 import and sales | I9: Imported vet drugs and instruments; no ultrasound line identified | J9: Both | K9: Kanto base, national import channel | L9: Not found | M9: n/a | N9: Not identified | O9: Not identified | P9: pet@kyoritsu-shokai.com | Q9: 03 3424 6201 | R9: Not identified | S9: Verified (published on own site, read via search); page notes the address was changed, confirm | T9: =SUM(Z9:AF9) -> 24 | U9: V1 | V9: Imports and sells vet drugs and instruments and displays a second class vet device MAH licence, so it could hold the CHISON notification itself. Its executive chairs the JADIDA Kanto Koshinetsu block, giving reach into every regional wholesaler. FLAG: Licence page last indexed about 18 months ago; confirm the licence is current. | W9: Ask whether they would act as MAH and master importer for a portable vet ultrasound line, with regional JADIDA members as sub dealers. | X9: Not checked (human list not in v17) | Y9: https://www.kyoritsu-shokai.com/company/%E5%8C%BB%E8%96%AC%E5%93%81%E3%83%BB%E5%8B%95%E7%89%A9%E7%94%A8%E5%8C%BB%E8%96%AC%E5%93%81%E8%A8%B1%E5%8F%AF%E8%A8%BC%E9%96%A2%E9%80%A3/ ; https://jadida.or.jp/aboutus.html ; https://www.kyoritsu-shokai.com/%E7%89%B9%E5%AE%9A%E5%95%86%E5%8F%96%E5%BC%95%E6%B3%95%E3%81%AB%E5%9F%BA%E3%81%A5%E3%81%8F%E8%A1%A8%E8%A8%98/ ; https://www.kyoritsu-shokai.com/%E3%81%8A%E5%95%8F%E3%81%84%E5%90%88%E3%82%8F%E3%81%9B/ | Z9: 5 | AA9: 1 | AB9: 5 | AC9: 4 | AD9: 4 | AE9: 2 | AF9: 3 | AG9: Evidence backed
A10: 6 | B10: T&S Co., Ltd. | C10: 株式会社ティーアンドエス | D10: Not found (NTA lookup blocked; dedupe by Japanese name) | E10: Chiba | F10: Kanto | G10: https://ts-xray.com | H10: Animal device manufacturing licence (2003); NVAL approval VPX200 vet X ray (2004) | I10: Own X ray; no ultrasound | J10: Both | K10: Noda, Chiba; national | L10: Not found | M10: n/a | N10: Not identified | O10: Not identified | P10: contact@ts-xray.com | Q10: 04 7127 7323 | R10: Not identified | S10: Verified (published on own site, read via search); listed on recruiting page | T10: =SUM(Z10:AF10) -> 24 | U10: V1 | V10: Domestic X ray maker with a vet approval; imaging focused and unconflicted on ultrasound. | W10: Pair portable ultrasound with their vet X ray for clinic openings. | X10: Not checked (human list not in v17) | Y10: https://www.pref.saitama.lg.jp/documents/236933/0343_tands.pdf ; https://www.vm.nval.go.jp/public/detail/6769 ; https://ts-xray.com/recruit/ ; https://ts-xray.com/inquiry/ | Z10: 5 | AA10: 3 | AB10: 5 | AC10: 3 | AD10: 2 | AE10: 3 | AF10: 3 | AG10: Evidence backed
A11: 7 | B11: Nipro Corporation (Veterinary) | C11: ニプロ株式会社 | D11: Not found (NTA lookup blocked; dedupe by Japanese name) | E11: Osaka | F11: Kansai | G11: Not found | H11: Vet device MAH (NVAL: vet syringe 2018, infusion set) | I11: Disposables; no vet ultrasound | J11: Both | K11: National and Asia | L11: Large | M11: n/a | N11: Not identified | O11: Not identified | P11: Not published; inquiry form: https://www.nipro.co.jp/contact/device/ | Q11: 0120 226 410 (device info desk) | R11: Not identified | S11: Company inquiry only (form) | T11: =SUM(Z11:AF11) -> 23 | U11: V1 | V11: Major human device group with vet MAH registrations; dealer network reaches animal hospitals. | W11: Long shot; explore OEM or MAH service. | X11: Not checked (human list not in v17) | Y11: https://www.vm.nval.go.jp/public/detail/17793 ; https://www.vm.nval.go.jp/public/detail/6784 ; https://www.nipro.co.jp/contact/device/ | Z11: 5 | AA11: 1 | AB11: 5 | AC11: 3 | AD11: 2 | AE11: 5 | AF11: 2 | AG11: Evidence backed
A12: 8 | B12: Aison Co., Ltd. | C12: アイソン株式会社 | D12: Not found (NTA lookup blocked; dedupe by Japanese name) | E12: Saitama | F12: Kanto | G12: https://aison.jp/ | H12: Vet ultrasound MAH: NVAL notification 超音波画像診断装置 Vシリーズ (9 Jul 2024) | I12: Holds a vet ultrasound line (V series; origin brand not confirmed) | J12: Companion | K12: Kawaguchi, Saitama | L12: Not found | M12: n/a | N12: Not identified | O12: Not identified | P12: saito@aison.jp | Q12: 048 299 3597 | R12: Not identified | S12: Likely (third party listing); named staff address, may be old | T12: =SUM(Z12:AF12) -> 23 | U12: V1 | V12: One of the few MAHs that notified a vet ultrasound in 2024, so it knows the exact NVAL route CHISON needs. FLAG: Brand behind the V series not confirmed; check it is not SonoScape or Mindray exclusive. | W12: Ask whether they would add a second OEM source or act as MAH for CHISON vet SKUs. | X12: Not checked (human list not in v17) | Y12: https://www.vm.nval.go.jp/public/detail/19613 ; https://www.pmda.go.jp/PmdaSearch/kikiDetail/ResultDataSetPDF/112161_306ADBZX00058000_V_01_01 ; http://www.kawaguchicci.or.jp/plat/pl_disp_company_detail.cgi?company=2209 | Z12: 5 | AA12: 5 | AB12: 2 | AC12: 3 | AD12: 1 | AE12: 3 | AF12: 4 | AG12: Evidence backed
A13: 9 | B13: IDEXX Laboratories K.K. | C13: アイデックス ラボラトリーズ株式会社 | D13: Not found (NTA lookup blocked; dedupe by Japanese name) | E13: Tokyo | F13: Kanto | G13: Not found | H13: Vet device MAH (NVAL: Catalyst Dx) | I13: Lab analysers; no ultrasound | J13: Companion | K13: National | L13: Large (IDEXX group) | M13: n/a | N13: Not identified | O13: Not identified | P13: Not published; inquiry form: https://www.idexx.co.jp/ja/about-idexx/contact-idexx/ | Q13: 0120 71 4921 | R13: Not identified | S13: Company inquiry only (form) | T13: =SUM(Z13:AF13) -> 23 | U13: V1 | V13: Largest in clinic diagnostics vendor with direct hospital coverage; MAH capability. FLAG: Global corporate; partnering unlikely, keep as awareness. | W13: Long shot; useful for co promotion. | X13: Not checked (human list not in v17) | Y13: https://www.vm.nval.go.jp/public/detail/12549 ; https://www.idexx.co.jp/ja/about-idexx/contact-idexx/ | Z13: 5 | AA13: 1 | AB13: 5 | AC13: 5 | AD13: 1 | AE13: 5 | AF13: 1 | AG13: Evidence backed
A14: 10 | B14: Karl Storz Endoscopy Japan K.K. | C14: カールストルツ・エンドスコピー・ジャパン株式会社 | D14: Not found (NTA lookup blocked; dedupe by Japanese name) | E14: Tokyo | F14: Kanto | G14: Not found | H14: Vet device MAH (NVAL listing) | I14: Endoscopy; no ultrasound in vet range | J14: Companion | K14: National | L14: Large (Karl Storz group) | M14: n/a | N14: Not identified | O14: Not identified | P14: Not published; phone only | Q14: Not found | R14: Not identified | S14: Unverified (no contact found in search) | T14: =SUM(Z14:AF14) -> 23 | U14: V1 | V14: Holds vet device notifications and serves referral hospitals with endoscopy; imaging service engineers. | W14: Referral centre co marketing; low probability of distribution but useful KOL access. | X14: Not checked (human list not in v17) | Y14: https://www.vm.nval.go.jp/public/detail/6770 | Z14: 5 | AA14: 3 | AB14: 4 | AC14: 3 | AD14: 1 | AE14: 5 | AF14: 2 | AG14: Evidence backed
A15: 11 | B15: Metran Co., Ltd. | C15: 株式会社メトラン | D15: Not found (NTA lookup blocked; dedupe by Japanese name) | E15: Saitama | F15: Kanto | G15: https://www.metran.co.jp/ | H15: Vet device MAH (NVAL: BM7Vet Pro monitor, 2020) | I15: Own ventilators and monitors; no ultrasound | J15: Companion | K15: National via vet dealers | L15: Not found | M15: n/a | N15: Not identified | O15: Not identified | P15: support@metran.co.jp | Q15: 048 242 0333 | R15: Not identified | S15: Verified (published on own site, read via search) | T15: =SUM(Z15:AF15) -> 23 | U15: V1 | V15: Vet ventilator pioneer (since 1984) that already notifies vet devices with NVAL and imports monitors; natural MAH partner for ICU and anaesthesia adjacent imaging. | W15: Propose a peri operative point of care ultrasound bundle with their Compos X ventilator. | X15: Not checked (human list not in v17) | Y15: https://www.vm.nval.go.jp/public/detail/18306 ; https://medical-space.co.jp/products/3096/ ; https://www.metran.co.jp/links | Z15: 5 | AA15: 1 | AB15: 5 | AC15: 4 | AD15: 1 | AE15: 4 | AF15: 3 | AG15: Evidence backed
A16: 12 | B16: RayVision Co., Ltd. | C16: 株式会社RayVision | D16: Not found (NTA lookup blocked; dedupe by Japanese name) | E16: Saitama | F16: Kanto | G16: https://rayvision.co.jp/ | H16: Vet flat panel detector maker and seller (vet device notification implied) | I16: Own vet DR; no ultrasound | J16: Companion | K16: Saitama; national via Medical Space and others | L16: Not found | M16: n/a | N16: Not identified | O16: Not identified | P16: Not published; inquiry form: https://rayvision.co.jp/contact/ | Q16: 048 657 2601 | R16: Not identified | S16: Company inquiry only (form) | T16: =SUM(Z16:AF16) -> 23 | U16: V1 | V16: Vet specific DR maker with maintenance support; imaging buyers are the same clinics. | W16: Cross sell: DR plus ultrasound package for new clinics. | X16: Not checked (human list not in v17) | Y16: https://rayvision.co.jp/ ; https://medical-space.co.jp/products/9109/ ; https://rayvision.co.jp/contact/ | Z16: 4 | AA16: 3 | AB16: 5 | AC16: 4 | AD16: 1 | AE16: 3 | AF16: 3 | AG16: Evidence backed
... A263: 259 | B263: Will Animal Hospital Group | C263: 株式会社ウイル動物病院グループ | D263: Not found (NTA lookup blocked; dedupe by Japanese name) | E263: Miyagi | F263: Tohoku and Hokkaido | G263: https://animal-99.com/ | H263: End user (animal hospital group) | I263: Not identified | J263: Companion | K263: Miyagi (Sendai, Shiogama, Kakuda, Watari) | L263: Not found | M263: 9 | N263: Not identified | O263: Not identified | P263: Not published; inquiry form: https://animal-99.com/contact_form.html | Q263: 022 355 8492 | R263: Not identified | S263: Company inquiry only (form) | T263: =SUM(Z263:AF263) -> 18 | U263: V5 | V263: Nine hospital Sendai group incl. Sendai Animal Medical Center. FLAG: Part of MiraiVets/JPAC. | W263: Fleet evaluation: 30 day placement in two sites, then a group standard. | X263: Not checked (human list not in v17) | Y263: https://animal-99.com/ ; https://forbesjapan.com/articles/detail/82089 ; https://animal-99.com/contact_form.html | Z263: 1 | AA263: 4 | AB263: 3 | AC263: 5 | AD263: 1 | AE263: 1 | AF263: 3 | AG263: Evidence backed

Sheet Korea Dealers
A1: SOUTH KOREA — VETERINARY DEALER / DISTRIBUTOR TARGETS
A2: Dealer model. RULE AGREED WITH JERRY: discuss every Korean distributor with Jerry BEFORE first contact. Korean veterinary devices are licensed through QIA, not MFDS. Two columns at the far right hold a ready to send email for each company.
A4: # | B4: Company (local name) | C4: Company (roman/EN) | D4: Pipeline Stage | E4: Owner | F4: Next Action | G4: Next Action Date | H4: Company background — what they do, and why it matters to CHISON | I4: Segment & expertise | J4: Carries an ultrasound line? | K4: Location / coverage | L4: Website (URL) | M4: Phone / fax | N4: Email | O4: Address & company detail | P4: CONTACT CONFIDENCE | Q4: Why this dealer for CHISON VET (fit notes) | R4: CHISON VET product to lead with | S4: Tier | T4: BUYING / DISTRIBUTION POTENTIAL | U4: Email template | V4: Source status | W4: Email subject — ready to send | X4: Email body — ready to send (copy/paste)
A5: 4 | B5: ㈜오르바이오 (AureBIO) | C5: AureBIO Co., Ltd. | D5: Not started | F5: Clear with Jerry before first contact | H5: Seoul veterinary ultrasound training academy running small-group hands-on courses — abdominal completion, cardiac completion, feline comprehensive, canine intermediate, POCUS and small-animal practical — taught by Prof. Choi Min-cheol of the SNU College of Veterinary Medicine, with affiliated supply of units. RELEVANCE: Prof. Choi has published the argument himself, stating that ultrasound ought to be the best value-for-money device in an animal hospital and in practice is not, and setting out his buying criteria as image quality within a price band and probe frequency range. That is CHISON's positioning stated by a Korean KOL before you walk in. Training academies also convert unusually well: every student scans on the machine in the room. | I5: Veterinary ultrasound training academy. Small-group hands-on courses — abdominal completion, cardiac completion, feline comprehensive, canine intermediate, POCUS, small-animal practical — taught by Prof. CHOI Min-cheol, SNU College of Veterinary Medicine emeritus professor and Korean veterinary radiology specialist, 30 years' experience. Publishes his serialised 'Ultrasound Story' column (also carried by Dailyvet). Also runs the Dr.PET-BORII product line. An affiliated body has supplied ultrasound units to animal hospitals. | J5: Partially — affiliated supply of units | K5: Seoul | L5: https://aurebio.co.kr (/ultrasound_story · /drpetborii) | M5: Not published — course enquiry via site | N5: Not published — form only | O5: Seoul · courses led by Prof. CHOI Min-cheol (SNU emeritus) | P5: B — VERIFIED PARTIAL (site opened and live; no phone/email published) | Q5: The strongest single opening in Korea, and the argument is already written for you. Prof. Choi's own published column states that ultrasound SHOULD be the best value-for-money device in an animal hospital and in practice is not; his buying criteria are image quality within a price band, probe frequency matched to patient size, the clinic's finances, and — pointedly — model production year, discontinuation risk and A/S, after a Japanese unit he owned became unrepairable. That is CHISON's pitch verbatim. Placing units in his teaching room puts the brand in the hands of every Korean vet about to buy one, and it is legitimate pre-market work that can begin before an importer is appointed. | R5: SonoEye P3 VET teaching fleet + SonoAir 70 VET | S5: TIER 1 | T5: HIGH — the strongest single opening in Korea, and the argument has already been written for you. | U5: G | V5: Verified site — fetched 4 Aug 2026 | W5: AureBIO Co., Ltd.: equipment for your programme, not a sales call | X5: Dear ㈜오르바이오 (AureBIO Co., Ltd.) team, My name is Casper Tan, Senior Regional Sales Manager at AstraMed Healthcare, a subsidiary of CHISON Medical Technologies. I cover Japan, South Korea, Taiwan and Singapore for CHISON veterinary ultrasound. I am writing to AureBIO Co., Ltd. specifically, not to a list. I read Professor Choi Min-cheol's ultrasound column. His argument, that ultrasound ought to be the best value-for-money device in an animal hospital and usually is not, and that discontinued models with no local service are a real buying risk, is, almost word for word, the case CHISON exists to make. CHISON manufactures veterinary ultrasound, handheld, portable and cart. We are building our presence in your market and would rather earn a position through your programme than through advertising, because vets buy the scanner they were trained on or the one they can actually compare on price. For context: we have no appointed veterinary distributor in Korea yet. Veterinary devices there are licensed through QIA rather than MFDS, and we would want a partner who already understands that route. The product I would put in front of you first is the SonoEye P3 VET teaching fleet and SonoAir 70 VET. Could we talk about what a sensible arrangement would look like? Best regards, Casper Tan Senior Regional Sales Manager AstraMed Healthcare, a subsidiary of CHISON Medical Technologies casper@astramed.sg | +65 8719 0121
A6: 16 | B6: ㈜바이오노트 (BioNote) | C6: BioNote, Inc. | D6: Not started | F6: Clear with Jerry before first contact | H6: KOSPI-listed (377740, listed December 2022), founded 2003, headquartered in Hwaseong, Gyeonggi. Develops, manufactures and DISTRIBUTES veterinary diagnostic reagents and instruments built on recombinant antigen and antibody technology, and holds the number-one global market share in its niche. RELEVANCE: a listed company with a real distribution organisation reaching Korean animal hospitals and export markets, and nothing at all in imaging. Their point-of-care philosophy — the answer at the patient rather than in a lab — is the same sentence a handheld scanner sells on. | I6: KOSPI-listed (377740, listed Dec 2022), founded 2003, HQ Hwaseong, Gyeonggi. Develops, manufactures and DISTRIBUTES veterinary diagnostic reagents and instruments on recombinant antigen/antibody technology. Holds the number-one GLOBAL market share in veterinary immunodiagnostic devices. Vcheck C is a multi-channel all-in-one point-of-care platform covering chemistry, urine and immunoassay. Actively expanding into the US and the wider global animal diagnostics market. | J6: NO — diagnostics only | K6: Hwaseong, Gyeonggi; global | L6: https://www.bionote.co.kr · en.bionote.co.kr | M6: NOT CONFIRMED (site fetch timed out) | N6: NOT CONFIRMED | O6: 경기도 화성시 · KOSPI 377740 · est. 2003 | P6: C — SITE LIVE, NOT OPENED (fetch timed out twice; listing and company facts confirmed via KOSPI coverage and Korean pharma press) | Q6: The largest Korean veterinary diagnostics company and a global number one in its niche, with a distribution organisation reaching Korean animal hospitals and export markets. No imaging line at all. The point-of-care philosophy — answers at the patient rather than in a lab — is the same argument a handheld scanner makes, and a POC diagnostics plus POCUS bundle is a proposition nobody in Korea is currently selling. | R6: SonoEye P3 VET (POC bundle) + EBit 50 VET | S6: TIER 1 | T6: HIGH — the largest Korean veterinary diagnostics company, with distribution and no imaging line. | U6: D | V6: Verified — company site, KOSPI listing, Korean pharma trade press | W6: BioNote, Inc.: a second capital line for the customers you already have | X6: Dear ㈜바이오노트 (BioNote, Inc.) team, My name is Casper Tan, Senior Regional Sales Manager at AstraMed Healthcare, a subsidiary of CHISON Medical Technologies. I cover Japan, South Korea, Taiwan and Singapore for CHISON veterinary ultrasound. I am writing to BioNote, Inc. specifically, not to a list. You hold the number-one global position in veterinary immunodiagnostic devices, and Vcheck C is built on the principle that the answer should come at the patient rather than from a laboratory. There is no imaging in your line, and a point-of-care diagnostics plus point-of-care ultrasound proposition is one nobody in Korea is currently selling. CHISON makes veterinary ultrasound, handheld through portable, and it is an unusually easy second capital line: same buyer, same service skillset as the electronics you already support, no overlap with what you carry, and a price point that closes without a long capital cycle. For context: we have no appointed veterinary distributor in Korea yet. Veterinary devices there are licensed through QIA rather than MFDS, and we would want a partner who already understands that route. The product I would put in front of you first is the SonoEye P3 VET (POC bundle) and EBit 50 VET. If it is of interest I will send the line card and dealer terms, no obligation, and you can decide from the numbers. Best regards, Casper Tan Senior Regional Sales Manager AstraMed Healthcare, a subsidiary of CHISON Medical Technologies casper@astramed.sg | +65 8719 0121
A7: 18 | B7: ㈜디알젬 (DRGEM) | C7: DRGEM Corporation | D7: Not started | F7: Clear with Jerry before first contact | H7: Korean diagnostic X-ray manufacturer with a dedicated veterinary system line (VXR-E / VXR-EC) on its healthcare site, supplying veterinary supply companies that serve animal hospitals. RELEVANCE: the veterinary channel and the regulatory groundwork already exist, and there is no ultrasound to defend. Same structural fit as Woorien and Genoray — a complete imaging line missing one modality. | I7: Korean diagnostic X-ray manufacturer with a dedicated VETERINARY system line (VXR-E / VXR-EC) published on its healthcare site. Supplies veterinary supply companies serving animal hospitals. | J7: NO — X-ray only | K7: Korea + export | L7: https://www.drgemhealthcare.com/vet-system-vxr-e-ec/ | M7: NOT CONFIRMED | N7: NOT CONFIRMED | O7: Korea | P7: C — SITE LIVE, NOT OPENED (veterinary product page returned by search) | Q7: Publishes a veterinary X-ray system line, so the veterinary channel and the regulatory work are already in place. No ultrasound to defend. Same structural fit as Woorien and Genoray — a complete imaging line minus the one modality CHISON makes. | R7: SonoEye P3 VET + SonoGO VET | S7: TIER 1 | T7: HIGH — publishes a veterinary X-ray line, so channel and regulatory work are already done. | U7: F | V7: Verified — corporate veterinary product page | W7: DRGEM Corporation: the gap in your imaging line | X7: Dear ㈜디알젬 (DRGEM Corporation) team, My name is Casper Tan, Senior Regional Sales Manager at AstraMed Healthcare, a subsidiary of CHISON Medical Technologies. I cover Japan, South Korea, Taiwan and Singapore for CHISON veterinary ultrasound. I am writing to DRGEM Corporation specifically, not to a list. You publish a dedicated veterinary X-ray system line, so the veterinary channel and the regulatory work are already built at your end. The one modality missing from it is the one we make. CHISON makes veterinary ultrasound across the whole range, handheld SonoEye, portable SonoGO and SonoAir, up to cart systems, with vet presets and probes throughout. It completes your imaging line without touching your existing principals, and it suits a bundled equipment-plus-service model far better than most brands do. For context: we have no appointed veterinary distributor in Korea yet. Veterinary devices there are licensed through QIA rather than MFDS, and we would want a partner who already understands that route. The product I would put in front of you first is the SonoEye P3 VET and SonoGO VET. Would you be open to a call to look at the numbers together? Best regards, Casper Tan Senior Regional Sales Manager AstraMed Healthcare, a subsidiary of CHISON Medical Technologies casper@astramed.sg | +65 8719 0121
A8: 17 | B8: ㈜제노레이 (Genoray) | C8: Genoray Co., Ltd. | D8: Not started | F8: Clear with Jerry before first contact | H8: Korean digital X-ray specialist founded 2001, researching, manufacturing and selling C-arms, mammography, 3D CT, panoramic dental and portable X-ray, and publishing a veterinary product line including the Oscar Classic C-arm. RELEVANCE: a C-arm customer is a surgical or interventional veterinary hospital — exactly the account that also wants a pocket scanner for vascular access and guidance. Manufacturer-to-manufacturer conversations move faster than dealer negotiations because both sides understand the regulatory work. | I8: Digital X-ray specialist founded 2001. Researches, develops, manufactures and sells medical C-arms, mammography, 3D CT, panoramic dental and portable X-ray — and publishes a VETERINARY product line including the Oscar Classic C-arm. | J8: NO — X-ray and CT only | K8: Korea + export | L8: https://www.genoray.com (also profiled on komachine.com/ko/companies/genoray) | M8: NOT CONFIRMED | N8: NOT CONFIRMED | O8: Korea · est. 2001 | P8: C — SITE LIVE BUT BOT-BLOCKED (genoray.com served a human-verification challenge on 4 Aug 2026; open it in a normal browser. Company confirmed via Komachine profile.) | Q8: An established Korean imaging manufacturer with an existing veterinary product line and no ultrasound in it. A C-arm customer is a surgical or interventional veterinary hospital — exactly the account that also wants a pocket scanner for vascular access and guidance. Manufacturer-to-manufacturer conversations also open the possibility of them holding the Korean import licence. | R8: SonoEye P3 VET + SonoAir 70 VET | S8: TIER 1 | T8: HIGH — established imaging manufacturer with a veterinary line and no ultrasound in it. | U8: F | V8: Verified — corporate site + Komachine profile | W8: Genoray Co., Ltd.: the gap in your imaging line | X8: Dear ㈜제노레이 (Genoray Co., Ltd.) team, My name is Casper Tan, Senior Regional Sales Manager at AstraMed Healthcare, a subsidiary of CHISON Medical Technologies. I cover Japan, South Korea, Taiwan and Singapore for CHISON veterinary ultrasound. I am writing to Genoray Co., Ltd. specifically, not to a list. You already publish a veterinary line, including the Oscar Classic C-arm, and a C-arm customer is a surgical or interventional veterinary hospital. There is no ultrasound anywhere in your catalogue. CHISON makes veterinary ultrasound across the whole range, handheld SonoEye, portable SonoGO and SonoAir, up to cart systems, with vet presets and probes throughout. It completes your imaging line without touching your existing principals, and it suits a bundled equipment-plus-service model far better than most brands do. For context: we have no appointed veterinary distributor in Korea yet. Veterinary devices there are licensed through QIA rather than MFDS, and we would want a partner who already understands that route. The product I would put in front of you first is the SonoEye P3 VET and SonoAir 70 VET. Would you be open to a call to look at the numbers together? Best regards, Casper Tan Senior Regional Sales Manager AstraMed Healthcare, a subsidiary of CHISON Medical Technologies casper@astramed.sg | +65 8719 0121
A9: 3 | B9: 아이메디컴㈜ | C9: IMEDICOM Co., Ltd. | D9: Not started | F9: Clear with Jerry before first contact | H9: Korean manufacturer founded 2004 making orthopaedic, spinal, ENT and veterinary products — surgical handpieces, blades, balloon catheters and veterinary implants. Holds CE, US FDA, MDSAP and ISO 13485 and exports to more than 40 countries. Publicly expanding into companion-animal diagnostics. RELEVANCE: they already understand device registration and hold their own quality system, which is directly useful given Korea's QIA import-licence requirement. An imaging line fits the diversification they have already announced. | I9: Korean manufacturer of orthopaedic, spinal, ENT and VETERINARY products — surgical handpieces, blades, balloon catheters, veterinary implants. Est. 2004. CE, US FDA, MDSAP, ISO 13485; exports to 40+ countries. Expanding into companion-animal diagnostic kits (heartworm, giardia, parvo, corona). | J9: NO | K9: Korea; 40+ export markets | L9: https://imedicom.co.kr/orthopedics/ · imedicom.co.kr/ent/ (vet: imedicomvet.com) | M9: NOT CONFIRMED | N9: NOT CONFIRMED | O9: Korea · est. 2004 · CE/FDA/MDSAP/ISO 13485 · 40+ export markets | P9: C — PARTIAL (imedicom.co.kr root and imedicomvet.com both returned EMPTY pages on 4 Aug 2026; the /orthopedics and /ent sections are search-indexed. Use the section pages.) | Q9: A manufacturer, so they hold their own quality system and understand device registration — which matters because Korea requires a locally licensed importer for veterinary devices. They are actively broadening from implants into vet diagnostics, so an imaging line fits their stated direction. Candidate to hold the QIA import licence. | R9: SonoEye P3 VET + EBit 50 VET; SonoTouch VET for ortho | S9: TIER 1 | T9: HIGH — a manufacturer with its own quality system, which matters because Korea needs a locally licensed importer. | U9: C | V9: PARTIAL — imedicom.co.kr root returned an empty page on 4 Aug 2026; the /orthopedics and /ent sections and the separate imedicomvet.com are search-indexed. Use imedicomvet.com as the entry point. | W9: IMEDICOM Co., Ltd.: ultrasound guidance for the surgery you already equip | X9: Dear 아이메디컴㈜ (IMEDICOM Co., Ltd.) team, My name is Casper Tan, Senior Regional Sales Manager at AstraMed Healthcare, a subsidiary of CHISON Medical Technologies. I cover Japan, South Korea, Taiwan and Singapore for CHISON veterinary ultrasound. I am writing to IMEDICOM Co., Ltd. specifically, not to a list. You manufacture veterinary implants and surgical handpieces, you hold CE, US FDA, MDSAP and ISO 13485, and you export to more than forty countries. You are also moving into companion-animal diagnostics. Korea requires a locally licensed importer for veterinary devices, and you already run a quality system. CHISON's SonoEye P3 VET is a pocket-sized veterinary scanner built for ultrasound-guided nerve blocks, vascular access in a collapsed patient and a ninety-second pre-anaesthetic FAST. It stays in theatre instead of living in another room, and it does not overlap with anything in your line card. For context: we have no appointed veterinary distributor in Korea yet. Veterinary devices there are licensed through QIA rather than MFDS, and we would want a partner who already understands that route. The product I would put in front of you first is the SonoEye P3 VET and EBit 50 VET; SonoTouch VET for ortho. Are you open to a short call? I would rather show you the block and the vascular-access demo than describe them. Best regards, Casper Tan Senior Regional Sales Manager AstraMed Healthcare, a subsidiary of CHISON Medical Technologies casper@astramed.sg | +65 8719 0121
A10: 2 | B10: ㈜메디레이 | C10: Mediray Co., Ltd. | D10: Not started | F10: Clear with Jerry before first contact | H10: Seoul-based veterinary distributor of premium surgical and interventional equipment, and official partner for Medtronic, Johnson & Johnson MedTech (Ethicon, DePuy Synthes), Stryker, Boston Scientific and B.Braun. Runs medileimall.com with a diagnostic and imaging equipment category. RELEVANCE: they sell the highest-value surgical kit in Korean veterinary practice, so the buying committee already trusts them on capital goods. A pocket scanner for vascular access, nerve block and interventional guidance rides on a sale they are already making. Confirm whether their imaging category already includes ultrasound before pitching. | I10: Veterinary distributor of premium surgical and interventional equipment: official partner for Medtronic, Johnson & Johnson MedTech (Ethicon, DePuy Synthes), Stryker, Boston Scientific and B.Braun. Categories on medileimall.com: diagnostic/test equipment, anaesthesia-pump-warm air, IMAGING EQUIPMENT, brain navigation, drills and SonoPet aspiration, electro/laser surgery and ablation, endoscopy, OR fit-out, smoke evacuation and disinfection, used equipment; plus sutures, staplers, TPLO plates and saw blades, shunts, interventional catheters and pacemakers. Runs VET STAR and the MVP neurosurgery live-surgery seminar programme. | J10: Has an 'imaging equipment' category — CONFIRM whether it includes ultrasound before pitching | K10: Seoul; national | L10: https://medileimall.com · blog.naver.com/medilei | M10: TEL +82-2-6327-8777 | N10: KakaoTalk channel / site enquiry | O10: Seoul | P10: A — VERIFIED DIRECT (phone published for product enquiries) | Q10: Sells the highest-value surgical kit in Korean vet, so the buying committee already trusts them on capital equipment. A pocket scanner for vascular access, nerve block and interventional guidance rides on a sale they are already making. Their live-surgery seminars are a ready-made demo stage. | R10: SonoEye P3 VET (vascular access / nerve block) + SonoAir 70 VET | S10: TIER 1 | T10: HIGH — trusted on capital equipment, with a live-surgery seminar programme that is a ready-made demo stage. | U10: C | V10: Verified (medileimall.com) + Dailyvet coverage | W10: Mediray Co., Ltd.: ultrasound guidance for the surgery you already equip | X10: Dear ㈜메디레이 (Mediray Co., Ltd.) team, My name is Casper Tan, Senior Regional Sales Manager at AstraMed Healthcare, a subsidiary of CHISON Medical Technologies. I cover Japan, South Korea, Taiwan and Singapore for CHISON veterinary ultrasound. I am writing to Mediray Co., Ltd. specifically, not to a list. You supply Medtronic, Johnson & Johnson, Stryker, Boston Scientific and B.Braun into Korean veterinary surgery, and you run VET STAR and the MVP live-surgery seminars. The veterinarians buying that kit are increasingly doing ultrasound-guided blocks and vascular access, and most are borrowing the radiology machine to do it. CHISON's SonoEye P3 VET is a pocket-sized veterinary scanner built for ultrasound-guided nerve blocks, vascular access in a collapsed patient and a ninety-second pre-anaesthetic FAST. It stays in theatre instead of living in another room, and it does not overlap with anything in your line card. For context: we have no appointed veterinary distributor in Korea yet. Veterinary devices there are licensed through QIA rather than MFDS, and we would want a partner who already understands that route. The product I would put in front of you first is the SonoEye P3 VET (vascular access / nerve block) and SonoAir 70 VET. Are you open to a short call? I would rather show you the block and the vascular-access demo than describe them. Best regards, Casper Tan Senior Regional Sales Manager AstraMed Healthcare, a subsidiary of CHISON Medical Technologies casper@astramed.sg | +65 8719 0121
A11: 15 | B11: ㈜포스콤 (POSKOM) | C11: POSKOM Co., Ltd. | D11: Contacted | E11: Casper | F11: Intro email sent 28 Sep 2026 from casper@astramed.sg with CHISON VET Introduction 2027 attached. Follow up by phone or email if no reply | G11: 46300 | H11: Korean medical device manufacturer specialising in ultra-low-dose, ultra-lightweight battery-powered portable X-ray that runs without mains power or a shielded room. Published application areas include emergency and intensive care, disaster response and veterinary. Exports widely. RELEVANCE: they have built an entire business on the argument that imaging should be battery-powered, portable and usable outside a fixed room — which is precisely the argument a handheld scanner makes. They already sell into veterinary and they have no ultrasound. The strategic case does not need to be explained to them. | I11: Korean medical device manufacturer specialising in ULTRA-LOW-DOSE, ULTRA-LIGHTWEIGHT battery-powered portable X-ray. Devices run without mains power or a separate shielded room. Published application areas include emergency and intensive care, disaster and field medicine, remote mountain and island healthcare, defence, industrial NDT — and LARGE-ANIMAL VETERINARY DIAGNOSIS, which they name explicitly. | J11: NO — portable X-ray only | K11: Korea + export | L11: https://www.poskom.com (veterinary: /kor/product/list.php?pt1Idx=26) | M11: 대표전화 TEL +82-31-906-9007 · FAX +82-31-908-4208 | N11: sales@poskom.com (구매문의 / purchasing enquiries) | O11: (10534) 경기도 고양시 덕양구 소원로 227 포스콤타워 · CEO 박종래 · exhibits KIMES, RSNA, MEDICA, Arab Health | P11: A — VERIFIED DIRECT (phone + sales email off the site footer) | Q11: The closest philosophical match to CHISON in Korea. They have built a business on the argument that imaging should be battery-powered, portable and usable outside a fixed room — which is the same argument a handheld scanner makes. They already sell into veterinary, they have no ultrasound, and their engineers already understand portable-device service and battery logistics. | R11: SonoEye P6 VET handheld and the SonoAir VET portable, both of which pair naturally with portable X-ray | S11: TIER 1 | T11: HIGH — the closest philosophical match to CHISON anywhere in Korea. | U11: F | V11: Verified — Korean medical trade press interview + corporate site | W11: POSKOM Co., Ltd.: the gap in your imaging line | X11: Dear ㈜포스콤 (POSKOM Co., Ltd.) team, My name is Casper Tan, Senior Regional Sales Manager at AstraMed Healthcare, a subsidiary of CHISON Medical Technologies. I cover Japan, South Korea, Taiwan and Singapore for CHISON veterinary ultrasound. I am writing to POSKOM Co., Ltd. specifically, not to a list. You built a business on the argument that diagnostic imaging should be battery-powered, portable and usable without a shielded room, and you name large-animal veterinary diagnosis as one of your application areas. That is the same argument a handheld scanner makes, from the other modality. CHISON makes veterinary ultrasound across the whole range, handheld SonoEye, portable SonoAir and SonoVet 8, up to cart systems, with vet presets and probes throughout. It completes your imaging line without touching your existing principals, and it suits a bundled equipment-plus-service model far better than most brands do. For context: we have no appointed veterinary distributor in Korea yet. Veterinary devices there are licensed through QIA rather than MFDS, and we would want a partner who already understands that route. The product I would put in front of you first is the SonoEye P6 VET handheld and the SonoAir VET portable, both of which pair naturally with portable X-ray. I have also attached our CHISON VET introduction, which covers the full veterinary range from the SonoEye handhelds to the SonoMax cart. Would you be open to a call to look at the numbers together? Best regards, Casper Tan Senior Regional Sales Manager AstraMed Healthcare, a subsidiary of CHISON Medical Technologies casper@astramed.sg | +65 8719 0121
A12: 1 | B12: ㈜우리엔 | C12: Woorien Co., Ltd. | D12: Not started | F12: Clear with Jerry before first contact | H12: Veterinary imaging and diagnostic specialist, part of the listed VATECH NETWORKS group (VATECH, Rayence, VATECH Korea, Ewoosoft, VATECH E&G). CEO Ko Seok-bin. Sells myvet CT, dental CT, surgical DR and DR solutions plus radiology reading services, exports to North America, runs a national service organisation and reaches roughly 1,800 Korean clinics through its own EMR product. RELEVANCE: they own the imaging conversation inside Korean animal hospitals, they have manufacturing and detector capability behind them, they have service engineers in the field — and there is no ultrasound anywhere on their imaging menu. That is a complete imaging line missing exactly the one modality CHISON makes. | I12: Veterinary imaging and diagnostic solutions specialist, and part of the VATECH NETWORKS group (VATECH, Rayence, VATECH Korea, Ewoosoft, VATECH E&G). CEO KO Seok-bin. Imaging line: myvet CT, Dental CT, dental solutions, surgical DR, DR Solution and an EQUINE line. Own-developed MyVet DR (Rayence CSI detector + 400 mA). Bundles the Vericare radiology reading service, read by SNU, Chungbuk and Chonnam vet faculty. Software platform: Woorien PMS, e-Friends, Wooricare, eLab, weInsight, Wewebchart, Woorien Pharm, weManager. Acquired PnV (No.1 Korean vet EMR, ~1,800 hospitals) and A-Pharm (drug distribution). Exhibits at VMX; growing North American revenue. HQ Hwaseong, Gyeonggi. | J12: NO — CT, DR, dental and reading services. Confirmed no ultrasound on the imaging menu. | K12: Korea nationwide + North America export | L12: https://www.woorien.com (imaging: /CT · /DR_Solution · /page_CzDy27 equine) | M12: Not published — enquiry form woorien.com/inquiry · A/S form woorien.com/order | N12: Not published — form only | O12: 본사 경기도 화성시 삼성1로2길 13 · 우리엔팜 서울특별시 동대문구 천호대로81길 47 1층 · CEO 고석빈 · biz reg 135-86-27385 · VATECH NETWORKS group | P12: B — VERIFIED PARTIAL (site opened, address and CEO confirmed; no phone/email published) | Q12: The best-shaped partner in any of the three dealer markets. They own the imaging conversation in Korean animal hospitals, sit inside a listed dental-imaging group with real manufacturing and detector capability, run a national service organisation, reach ~1,800 clinics through their own EMR — and have a hole in the line card exactly where CHISON sits. They already sell imaging bundled with a reading service, which is precisely how a handheld should be sold. Their equine line also opens a rectal-probe conversation. | R12: SonoEye P3 / P5 VET + SonoGO VET (completes the imaging suite); EBit 50 VET for the equine line | S12: TIER 1 | T12: HIGH — the single best-shaped partner in any of the three dealer markets. | U12: F | V12: Verified site — fetched 4 Aug 2026 | W12: Woorien Co., Ltd.: the gap in your imaging line | X12: Dear ㈜우리엔 (Woorien Co., Ltd.) team, My name is Casper Tan, Senior Regional Sales Manager at AstraMed Healthcare, a subsidiary of CHISON Medical Technologies. I cover Japan, South Korea, Taiwan and Singapore for CHISON veterinary ultrasound. I am writing to Woorien Co., Ltd. specifically, not to a list. You own the imaging conversation in Korean animal hospitals, MyVet DR and CT, an equine line, the Vericare reading service read by SNU, Chungbuk and Chonnam faculty, and PnV reaching roughly eighteen hundred clinics. There is one gap in all of that: the veterinarian who buys your X-ray buys their ultrasound from someone else. CHISON makes veterinary ultrasound across the whole range, handheld SonoEye, portable SonoGO and SonoAir, up to cart systems, with vet presets and probes throughout. It completes your imaging line without touching your existing principals, and it suits a bundled equipment-plus-service model far better than most brands do. For context: we have no appointed veterinary distributor in Korea yet. Veterinary devices there are licensed through QIA rather than MFDS, and we would want a partner who already understands that route. The product I would put in front of you first is the SonoEye P3 / P5 VET and SonoGO VET (completes the imaging suite); EBit 50 VET for the equine line. Would you be open to a call to look at the numbers together? Best regards, Casper Tan Senior Regional Sales Manager AstraMed Healthcare, a subsidiary of CHISON Medical Technologies casper@astramed.sg | +65 8719 0121
A13: 27 | B13: ㈜제이피아이헬스케어 | C13: JPI Healthcare Co., Ltd. (JPI Animal Health) | D13: Contacted | E13: Casper | F13: Intro email sent 28 Sep 2026 from casper@astramed.sg with CHISON VET Introduction 2027 attached. Follow up by phone or email if no reply | G13: 46300 | H13: Korean digital X-ray manufacturer built on X-ray grid technology, with imaging systems, detectors and AI-based image processing; manufacturing at Ansan and Sihwa, head office in Guro-gu, Seoul, and a US arm at Edgewood, New York. Their website carries SEPARATE 인체용 (human) and 동물용 (veterinary) product lines, and the veterinary business runs under its own brand, JPI Animal Health — DirectVet, DynaVue Duo, DeteCT Vet, ExamVue Duo and JPI Cloud PACS. RELEVANCE: Korean trade press reports they are actively EXPANDING the animal-hospital lineup into veterinary anaesthesia and patient monitoring, pursuing an 'All-in-One' turnkey offer for new and upgrading animal hospitals. NEW IN v9 — carried across from the human-diagnostic Market Development list v3 (Korea row 54), where only the human X-ray business was recorded. v11: on 16 Jun 2026 Edaily reported JPI adding anaesthesia and monitoring to DeteCT Vet to offer turnkey animal hospital packages. No ultrasound was in that expansion, which is the opening. | I13: Veterinary and human diagnostic imaging manufacturer: X-ray grids, digital radiography, cone-beam CT (DeteCT / DeteCT Vet), acquisition and diagnostic software, cloud PACS. Actively building a turnkey animal-hospital equipment package. | J13: NO — no ultrasound anywhere in either the human or the veterinary line. X-ray, CT, software and PACS only. This is the whole argument. | K13: Seoul (Guro-gu HQ) · Ansan · Sihwa · US arm at Edgewood, New York; nationwide Korea + export | L13: https://www.jpi-korea.com · https://www.jpianimalhealth.com | M13: TEL 02-2108-2580 (Seoul) · 031-491-3435 (Ansan) · 031-488-8232 (Sihwa) | N13: sales@jpi.co.kr · global@jpi.co.kr | O13: (08377) 서울특별시 구로구 디지털로33길 28, 우림e-biz센터1차 608호 · US: 100-B Executive Dr, Edgewood, NY 11717 | P13: A — VERIFIED DIRECT (phone numbers and both email addresses read off the company's own site, opened 8 Aug 2026) | Q13: The Woorien archetype, second door — and arguably a better-timed one. A veterinary imaging company with X-ray and cone-beam CT, its own veterinary brand, and NO ultrasound line to defend. What makes it urgent rather than merely suitable is their own stated strategy: they are assembling an All-in-One turnkey package for animal hospitals so a customer can equip a room from one supplier and call one number. Ultrasound is the modality a small-animal hospital reaches for daily, and it is the conspicuous hole in that package — today their customer has to source it elsewhere, which is precisely the compatibility and after-sales problem the turnkey pitch exists to remove. Use their own argument. NOTE: no named individual verified — find the animal-health business owner via the LinkedIn workflow before sending. | R13: SonoVet 8, which works as a cart, a laptop portable and a touch unit in one, as the ultrasound room in a turnkey opening package, with the SonoEye P6 VET handheld alongside | S13: TIER 1 | T13: HIGH — appoint-grade. Manufacturer-scale, an established veterinary brand and channel, no competing ultrasound line, and a published turnkey strategy that ultrasound completes. No invoice until a Korean entity holds the QIA (not MFDS) veterinary device import business licence. | U13: F | V13: NEW IN v9 — jpi-korea.com and jpianimalhealth.com opened 8 Aug 2026; veterinary lineup expansion reported by Korean pharma/medtech trade press (팜이데일리 / edaily). Traced from Market Development Target List v3, Korea Dealers row 54 (recorded there as a human X-ray/DR maker only). | W13: JPI Healthcare Co., Ltd. (JPI Animal Health): the ultrasound room in your turnkey package | X13: Dear ㈜제이피아이헬스케어 (JPI Healthcare Co., Ltd.) team, My name is Casper Tan, Senior Regional Sales Manager at AstraMed Healthcare, a subsidiary of CHISON Medical Technologies. I cover Japan, South Korea, Taiwan and Singapore for CHISON veterinary ultrasound. I am writing to JPI Healthcare Co., Ltd. specifically, not to a list. Edaily reported in June that you are adding anaesthesia and monitoring to DeteCT Vet so an animal hospital can equip from one supplier. Ultrasound is the room that package does not yet cover. CHISON makes veterinary ultrasound in handheld, portable and cart formats, and it would complete a turnkey package without competing with anything you manufacture. For context: we have no appointed veterinary distributor in Korea yet. Veterinary devices there are licensed through QIA rather than MFDS, and we would want a partner who already understands that route. The product I would put in front of you first is the SonoVet 8, which works as a cart, a laptop portable and a touch unit in one, as the ultrasound room in a turnkey opening package, with the SonoEye P6 VET handheld alongside. I have also attached our CHISON VET introduction, which covers the full veterinary range from the SonoEye handhelds to the SonoMax cart. Would twenty minutes in the next two weeks be useful? I can send the veterinary line card beforehand if you would rather look first. Best regards, Casper Tan Senior Regional Sales Manager AstraMed Healthcare, a subsidiary of CHISON Medical Technologies casper@astramed.sg | +65 8719 0121
A14: 13 | B14: 비브라운코리아 (동물헬스케어) | C14: B.Braun Korea — Veterinary business | D14: Not started | F14: Clear with Jerry before first contact | H14: Korean subsidiary of B.Braun, which launched a dedicated veterinary healthcare business in 2019 covering disinfection and infection control, general surgery and emergency medicine, and catheters and infusion therapy for animal hospitals. RELEVANCE: they already hold Korean device import and regulatory competence, and their infusion and catheter customers are the emergency and critical-care vets who use a cage-side scanner. No imaging line to defend. Expect a slow multinational process, but a complementary-line conversation is well founded. | I14: B.Braun's Korean subsidiary launched a dedicated VETERINARY healthcare business in 2019. Portfolio: disinfection and infection control, general surgery and emergency medicine, catheters and infusion therapy devices for animal hospitals. | J14: NO | K14: Korea | L14: bbraun.co.kr | M14: Corporate enquiry form | N14: NOT CONFIRMED | O14: Korea | P14: D — NOT VERIFIED (no contact record; confirm the company before contacting) | Q14: A multinational that deliberately built a Korean vet channel from scratch and has no imaging line in it. They already hold Korean device import and regulatory competence, and infusion/catheter customers are exactly the emergency and critical-care vets who use a cage-side scanner. A complementary-line conversation, not a displacement one. | R14: SonoEye P3 VET (vascular access / emergency) | S14: TIER 2 | T14: MEDIUM — a multinational that built a Korean vet channel deliberately, with no imaging in it. | U14: D | V14: Verified — B.Braun Korea corporate news release | W14: B.Braun Korea: Veterinary business, a second capital line for the customers you already have | X14: Dear 비브라운코리아 (B.Braun Korea) team, My name is Casper Tan, Senior Regional Sales Manager at AstraMed Healthcare, a subsidiary of CHISON Medical Technologies. I cover Japan, South Korea, Taiwan and Singapore for CHISON veterinary ultrasound. I am writing to B.Braun Korea specifically, not to a list. You deliberately built a Korean veterinary channel from scratch, infection control, surgery, emergency medicine, catheters and infusion, and there is no imaging in it. Your infusion and catheter customers are exactly the critical-care veterinarians who use a cage-side scanner. CHISON makes veterinary ultrasound, handheld through portable, and it is an unusually easy second capital line: same buyer, same service skillset as the electronics you already support, no overlap with what you carry, and a price point that closes without a long capital cycle. For context: we have no appointed veterinary distributor in Korea yet. Veterinary devices there are licensed through QIA rather than MFDS, and we would want a partner who already understands that route. The product I would put in front of you first is the SonoEye P3 VET (vascular access / emergency). If it is of interest I will send the line card and dealer terms, no obligation, and you can decide from the numbers. Best regards, Casper Tan Senior Regional Sales Manager AstraMed Healthcare, a subsidiary of CHISON Medical Technologies casper@astramed.sg | +65 8719 0121
A15: 5 | B15: 코벳 (COVET) | C15: COVET | D15: Not started | F15: Clear with Jerry before first contact | H15: Vet-led animal hospital network and alliance (Co-work + Veterinarian) offering members joint marketing, HR, tax and legal services, JOINT PURCHASING of drugs and consumables, on- and offline veterinary education and staff CS training. Distributes SK Telecom's X-Caliber AI radiography product. RELEVANCE: group purchasing gives them reach into independent Korean clinics that no single dealer has, and they already run an ultrasound education programme — with Samsung, which is the conflict. The wedge is the price tier Samsung does not build: a handheld their member clinics can afford as a second unit rather than as the hospital machine. | I15: Vet-led animal hospital network and alliance (Co-work + Veterinarian). Member benefits: joint marketing, HR/tax/legal services, JOINT PURCHASING of drugs and consumables, on/offline vet education, staff CS training. Distributes SK Telecom's X-Caliber AI diagnostic aid to animal hospitals. Runs the Samsung Sono VET Academy with Samsung Medison monthly, nationwide. Operates shop.covet.kr and Vet2Home logistics. | J15: Indirect — Samsung Medison ultrasound education partnership | K15: Korea nationwide | L15: https://covet.kr · shop.covet.kr | M15: NOT CONFIRMED | N15: NOT CONFIRMED | O15: Korea | P15: C — SITE LIVE, NOT OPENED | Q15: Unmatched reach into independent Korean clinics through group purchasing, and they already run an ultrasound education programme — with Samsung. That is the conflict. The wedge is the price tier Samsung does not build: a handheld their member clinics can actually afford as a second unit. Group-purchase pricing is exactly the mechanism CHISON's cost position is built for. | R15: SonoEye P3 VET as a member group-buy SKU | S15: TIER 2 | T15: MEDIUM — unmatched reach into independent clinics, but an existing Samsung ultrasound education partnership. | U15: B | V15: Verified site + Dailyvet coverage | W15: COVET: not a replacement for your ultrasound line, the tier below it | X15: Dear 코벳 (COVET) team, My name is Casper Tan, Senior Regional Sales Manager at AstraMed Healthcare, a subsidiary of CHISON Medical Technologies. I cover Japan, South Korea, Taiwan and Singapore for CHISON veterinary ultrasound. I am writing to COVET specifically, not to a list. Your member network and joint purchasing reach independent Korean clinics in a way no equipment company can, and you already run ultrasound education. I know that education runs with Samsung Medison, so let me be direct about what I am and am not proposing. CHISON makes veterinary ultrasound across the range, but the part that should interest you is the handheld tier, SonoEye P3 and P5. Small, vet-preset, high-frequency linear for feline and exotic work, and priced where a GP clinic buys one outright or a hospital buys three as ward units. It sits under your existing line rather than against it. For context: we have no appointed veterinary distributor in Korea yet. Veterinary devices there are licensed through QIA rather than MFDS, and we would want a partner who already understands that route. The product I would put in front of you first is the SonoEye P3 VET as a member group-buy SKU. Would twenty minutes be worth it, to see whether this protects your top-tier margin rather than competing with it? Best regards, Casper Tan Senior Regional Sales Manager AstraMed Healthcare, a subsidiary of CHISON Medical Technologies casper@astramed.sg | +65 8719 0121
A16: 19 | B16: ㈜에코레이 (ECORAY) | C16: ECORAY Co., Ltd. | D16: Not started | F16: Clear with Jerry before first contact | H16: Korean X-ray imaging manufacturer built on generator technology, publishing a dedicated 동물용 엑스레이 (veterinary X-ray) category, with portable generators also used in human emergency and field settings. RELEVANCE: a veterinary line already in the catalogue and a portable-first engineering culture. Smaller companies take second lines more readily and decide faster than the market leaders. | I16: Korean X-ray imaging manufacturer built on generator technology, supplying a range of X-ray imaging equipment. Publishes a dedicated 동물용 엑스레이 (VETERINARY X-RAY) product category. Its portable generators are used for human emergency and field use as well as for animal diagnostic imaging. | J16: NO — X-ray only | K16: Korea + export | L16: http://www.eco-ray.co.kr (veterinary: /products/index.jsp?scategory_fk=2) | M16: NOT CONFIRMED | N16: NOT CONFIRMED | O16: Korea | P16: C — SITE LIVE, NOT OPENED (veterinary X-ray category page returned by search) | Q16: A veterinary X-ray line already in the catalogue and a portable-first engineering culture. Smaller than Genoray or DRGEM, which usually means faster decisions and more interest in a second line. | R16: SonoEye P3 VET | S16: TIER 2 | T16: MEDIUM-HIGH — smaller than Genoray or DRGEM, which usually means a faster decision. | U16: F | V16: Verified — corporate veterinary X-ray product page | W16: ECORAY Co., Ltd.: the gap in your imaging line | X16: Dear ㈜에코레이 (ECORAY Co., Ltd.) team, My name is Casper Tan, Senior Regional Sales Manager at AstraMed Healthcare, a subsidiary of CHISON Medical Technologies. I cover Japan, South Korea, Taiwan and Singapore for CHISON veterinary ultrasound. I am writing to ECORAY Co., Ltd. specifically, not to a list. You already list veterinary X-ray as its own product category, and your engineering culture is portable-first, generators that work without mains power or a shielded room. CHISON makes veterinary ultrasound across the whole range, handheld SonoEye, portable SonoGO and SonoAir, up to cart systems, with vet presets and probes throughout. It completes your imaging line without touching your existing principals, and it suits a bundled equipment-plus-service model far better than most brands do. For context: we have no appointed veterinary distributor in Korea yet. Veterinary devices there are licensed through QIA rather than MFDS, and we would want a partner who already understands that route. The product I would put in front of you first is the SonoEye P3 VET. Would you be open to a call to look at the numbers together? Best regards, Casper Tan Senior Regional Sales Manager AstraMed Healthcare, a subsidiary of CHISON Medical Technologies casper@astramed.sg | +65 8719 0121
A17: 6 | B17: 아이엠디티 (벳아너스) | C17: IMDT — VetHonors alliance | D17: Not started | F17: Clear with Jerry before first contact | H17: Operator of the VetHonors animal-hospital alliance, which raised a KRW 7.5 bn Series A. RELEVANCE: a second group-purchasing route into independent Korean clinics. Being funded means they are actively building purchasing scale, and alliances standardise equipment across members — one agreement, many clinics. | I17: Operator of the VetHonors animal-hospital alliance; raised a KRW 7.5 bn Series A. | J17: Not identified | K17: Korea | L17: NOT CONFIRMED — search 아이엠디티 벳아너스 | M17: NOT CONFIRMED | N17: NOT CONFIRMED | O17: Korea | P17: D — NOT VERIFIED (known only from Dailyvet funding coverage) | Q17: Second alliance / group-purchasing route into independent clinics, and a hedge if COVET's Samsung relationship blocks the conversation. Funded, so they are building purchasing scale. | R17: SonoEye P3 VET group-buy SKU | S17: TIER 2 | T17: MEDIUM — funded and building purchasing scale; the hedge if COVET's Samsung tie blocks the conversation. | U17: B | V17: From search (Dailyvet) — verify entity and contact | W17: IMDT: VetHonors alliance, not a replacement for your ultrasound line, the tier below it | X17: Dear 아이엠디티 (IMDT) team, My name is Casper Tan, Senior Regional Sales Manager at AstraMed Healthcare, a subsidiary of CHISON Medical Technologies. I cover Japan, South Korea, Taiwan and Singapore for CHISON veterinary ultrasound. I am writing to IMDT specifically, not to a list. You operate a funded animal-hospital alliance, which means you are building genuine purchasing scale across independent clinics, and group pricing is exactly the mechanism our cost position is built for. CHISON makes veterinary ultrasound across the range, but the part that should interest you is the handheld tier, SonoEye P3 and P5. Small, vet-preset, high-frequency linear for feline and exotic work, and priced where a GP clinic buys one outright or a hospital buys three as ward units. It sits under your existing line rather than against it. For context: we have no appointed veterinary distributor in Korea yet. Veterinary devices there are licensed through QIA rather than MFDS, and we would want a partner who already understands that route. The product I would put in front of you first is the SonoEye P3 VET group-buy SKU. Would twenty minutes be worth it, to see whether this protects your top-tier margin rather than competing with it? Best regards, Casper Tan Senior Regional Sales Manager AstraMed Healthcare, a subsidiary of CHISON Medical Technologies casper@astramed.sg | +65 8719 0121
A18: 8 | B18: ㈜아이센스 | C18: i-SENS, Inc. | D18: Not started | F18: Clear with Jerry before first contact | H18: Global point-of-care diagnostics company with a veterinary range including the i-Smart 300VET blood gas analyser and CareSign-V, and the first company worldwide to release a point-of-care analyser for early CKD markers in animals. RELEVANCE: real regulatory competence, and their customer is the emergency and critical-care vet — precisely where a cage-side handheld is used. Nothing in imaging to defend, so a bundled point-of-care diagnostics plus POCUS proposition is a genuine conversation rather than a stretch. | I18: Global point-of-care diagnostics company with a veterinary line: i-Smart 300VET blood gas analyser, CareSign-V. First in the world to release a POCT analyser for early CKD markers in animals. | J18: NO | K18: Korea + global | L18: https://www.i-sens.com | M18: NOT CONFIRMED | N18: NOT CONFIRMED | O18: Korea | P18: C — company confirmed via Dailyvet product coverage; site not opened | Q18: Serious diagnostics company, global regulatory competence, and an emergency/critical-care customer — precisely where a cage-side handheld is used. No imaging line to defend. Worth a conversation about a bundled POC diagnostics + POCUS proposition. | R18: SonoEye P3 VET (POCUS / emergency) | S18: TIER 2 | T18: MEDIUM — serious diagnostics company, emergency and critical-care customer, no imaging line. | U18: D | V18: Verified — Dailyvet product coverage | W18: i-SENS, Inc.: a second capital line for the customers you already have | X18: Dear ㈜아이센스 (i-SENS, Inc.) team, My name is Casper Tan, Senior Regional Sales Manager at AstraMed Healthcare, a subsidiary of CHISON Medical Technologies. I cover Japan, South Korea, Taiwan and Singapore for CHISON veterinary ultrasound. I am writing to i-SENS, Inc. specifically, not to a list. You released the world's first point-of-care analyser for early CKD markers in animals, and your customer is the emergency and critical-care veterinarian, precisely where a cage-side handheld is used. You have no imaging line to defend. CHISON makes veterinary ultrasound, handheld through portable, and it is an unusually easy second capital line: same buyer, same service skillset as the electronics you already support, no overlap with what you carry, and a price point that closes without a long capital cycle. For context: we have no appointed veterinary distributor in Korea yet. Veterinary devices there are licensed through QIA rather than MFDS, and we would want a partner who already understands that route. The product I would put in front of you first is the SonoEye P3 VET (POCUS / emergency). If it is of interest I will send the line card and dealer terms, no obligation, and you can decide from the numbers. Best regards, Casper Tan Senior Regional Sales Manager AstraMed Healthcare, a subsidiary of CHISON Medical Technologies casper@astramed.sg | +65 8719 0121
A19: 9 | B19: 펫닥 '벳화점' | C19: PetDoc — 'Vet Department Store' platform | D19: Not started | F19: Clear with Jerry before first contact | H19: Veterinary-only commerce and information platform listing animal medical devices including CT, MRI and ultrasound, with real-time consultation-to-purchase. RELEVANCE: getting CHISON listed here puts the price advantage directly in front of Korean vets who are actively shopping for imaging, and generates enquiries the eventual QIA-licensed importer can close. Cheap market presence before a channel exists — but they will not hold stock or service. | I19: Veterinary-only comprehensive commerce and information platform. Lists animal medical devices including CT, MRI and ultrasound with real-time consultation-to-purchase. | J19: YES — lists competing ultrasound | K19: Korea | L19: https://xn--tl3bw1s9pl.com (벳화점.com) | M19: NOT CONFIRMED | N19: NOT CONFIRMED | O19: Korea | P19: C — SITE LIVE, NOT OPENED | Q19: Not a distributor — a lead-generation and price-discovery surface. Getting CHISON listed here puts the price advantage in front of Korean vets shopping for imaging, and generates enquiries the eventual importer can close. | R19: Full VET range listing | S19: TIER 2 | T19: MEDIUM — not a distributor. A price-discovery surface that generates leads for whoever imports. | U19: G | V19: Verified site (search-indexed) | W19: PetDoc: 'Vet Department Store' platform, equipment for your programme, not a sales call | X19: Dear 펫닥 '벳화점' (PetDoc) team, My name is Casper Tan, Senior Regional Sales Manager at AstraMed Healthcare, a subsidiary of CHISON Medical Technologies. I cover Japan, South Korea, Taiwan and Singapore for CHISON veterinary ultrasound. I am writing to PetDoc specifically, not to a list. Your platform is where Korean veterinarians go to compare imaging equipment and prices before they buy. That is a useful place for a brand whose entire argument is price-performance to be visible. CHISON manufactures veterinary ultrasound, handheld, portable and cart. We are building our presence in your market and would rather earn a position through your programme than through advertising, because vets buy the scanner they were trained on or the one they can actually compare on price. For context: we have no appointed veterinary distributor in Korea yet. Veterinary devices there are licensed through QIA rather than MFDS, and we would want a partner who already understands that route. The product I would put in front of you first is the Full VET range listing. Could we talk about what a sensible arrangement would look like? Best regards, Casper Tan Senior Regional Sales Manager AstraMed Healthcare, a subsidiary of CHISON Medical Technologies casper@astramed.sg | +65 8719 0121
A20: 20 | B20: 레이언스 (Rayence) | C20: Rayence Co., Ltd. | D20: Not started | F20: Clear with Jerry before first contact | H20: Digital X-ray detector and system manufacturer, part of VATECH NETWORKS, publishing a dedicated veterinary detector range and supplying the CSI detector inside Woorien's MyVet DR system. RELEVANCE AND GROUP OVERLAP: Rayence and Woorien are both VATECH group companies — Rayence is the component and systems side, Woorien the veterinary channel side. Approaching both independently is one conversation with two doors and looks like poor homework. Woorien is the better first door. | I20: Digital X-ray DETECTOR and system manufacturer, part of the VATECH NETWORKS group. Publishes a dedicated VETERINARY detector range. Supplies the CSI detector inside Woorien's MyVet DR system. | J20: NO — detectors and systems, no ultrasound | K20: Korea + global | L20: https://www.rayence.com/Veterinary | M20: TEL +82 31-8015-6245 | N20: NOT CONFIRMED | O20: 14, Samsung 1-ro 1-gil, Hwaseong-si, Gyeonggi-do 18449 | P20: A · VERIFIED DIRECT (phone and address off the veterinary product page, opened 27 Sep 2026) | Q20: NOTE THE OVERLAP: Rayence and Woorien are both VATECH group companies, so approaching both is really one conversation with two doors. Rayence is the component and systems side, Woorien the veterinary channel side. Decide which door you want before writing, or you will look like you have not done the homework. | R20: SonoEye P3 / P5 VET | S20: TIER 2 | T20: MEDIUM — same group as Woorien. Decide which door you want before writing. | U20: F | V20: Verified — corporate veterinary page; group link confirmed via Woorien | W20: Rayence Co., Ltd.: the gap in your imaging line | X20: Dear 레이언스 (Rayence Co., Ltd.) team, My name is Casper Tan, Senior Regional Sales Manager at AstraMed Healthcare, a subsidiary of CHISON Medical Technologies. I cover Japan, South Korea, Taiwan and Singapore for CHISON veterinary ultrasound. I am writing to Rayence Co., Ltd. specifically, not to a list. You publish a veterinary detector range and you supply the detector inside Woorien's MyVet DR. I should say plainly that I am also writing to Woorien; since you are both VATECH group companies, tell me which of you should own this conversation and I will follow your lead. CHISON makes veterinary ultrasound across the whole range, handheld SonoEye, portable SonoGO and SonoAir, up to cart systems, with vet presets and probes throughout. It completes your imaging line without touching your existing principals, and it suits a bundled equipment-plus-service model far better than most brands do. For context: we have no appointed veterinary distributor in Korea yet. Veterinary devices there are licensed through QIA rather than MFDS, and we would want a partner who already understands that route. The product I would put in front of you first is the SonoEye P3 / P5 VET. Would you be open to a call to look at the numbers together? Best regards, Casper Tan Senior Regional Sales Manager AstraMed Healthcare, a subsidiary of CHISON Medical Technologies casper@astramed.sg | +65 8719 0121
A21: 7 | B21: ㈜벳컴 (VET COM) | C21: VETCOM Co., Ltd. | D21: Not started | F21: Clear with Jerry before first contact | H21: Korean veterinary medical device company with a clinical-pathology and in-house laboratory focus. RELEVANCE: the vet who buys an analyser is the vet building in-house diagnostic capability, and ultrasound is the next line in that same budget. No imaging line identified to conflict with. | I21: Veterinary medical devices with a clinical-pathology / in-house laboratory focus. | J21: Not identified — confirm | K21: Korea | L21: https://www.vetcom.co.kr/ko/product_list.html | M21: NOT CONFIRMED | N21: NOT CONFIRMED | O21: Korea | P21: C — SITE LIVE, NOT OPENED | Q21: Diagnostics-led channel: the vet who buys an analyser is the vet building out in-house diagnostic capability, and ultrasound is the next line item in that same budget. No imaging conflict identified. | R21: SonoEye P3 VET + EBit 50 VET | S21: TIER 2 | T21: MEDIUM — diagnostics-led channel with no imaging conflict identified. | U21: D | V21: Verified site (search-indexed) | W21: VETCOM Co., Ltd.: a second capital line for the customers you already have | X21: Dear ㈜벳컴 (VETCOM Co., Ltd.) team, My name is Casper Tan, Senior Regional Sales Manager at AstraMed Healthcare, a subsidiary of CHISON Medical Technologies. I cover Japan, South Korea, Taiwan and Singapore for CHISON veterinary ultrasound. I am writing to VETCOM Co., Ltd. specifically, not to a list. Your strength is in-house diagnostics, and the veterinarian who invests in laboratory capability is the same one whose next line item is imaging. There is no overlap with anything you currently carry. CHISON makes veterinary ultrasound, handheld through portable, and it is an unusually easy second capital line: same buyer, same service skillset as the electronics you already support, no overlap with what you carry, and a price point that closes without a long capital cycle. For context: we have no appointed veterinary distributor in Korea yet. Veterinary devices there are licensed through QIA rather than MFDS, and we would want a partner who already understands that route. The product I would put in front of you first is the SonoEye P3 VET and EBit 50 VET. If it is of interest I will send the line card and dealer terms, no obligation, and you can decide from the numbers. Best regards, Casper Tan Senior Regional Sales Manager AstraMed Healthcare, a subsidiary of CHISON Medical Technologies casper@astramed.sg | +65 8719 0121
A22: 22 | B22: 벳플레이스 (Vetplace) | C22: Vetplace | D22: Not started | F22: Clear with Jerry before first contact | H22: Veterinary equipment and supply distributor / procurement platform serving Korean animal hospitals. Entity not yet confirmed. RELEVANCE: procurement platforms give visibility across many clinics at once and convert quickly on low-ticket capital items, which suits the handheld tier. Confirm the legal entity and its QIA position before anything else. | I22: Veterinary equipment and supply distributor / procurement platform serving Korean animal hospitals. | J22: Not identified — confirm on first contact | K22: South Korea; nationwide | L22: NOT CONFIRMED — search 벳플레이스 동물병원 | M22: NOT CONFIRMED | N22: NOT CONFIRMED | O22: South Korea | P22: D — NOT VERIFIED (name only, carried from workbook v2.0; no confirmed URL) | Q22: A procurement-platform shape rather than a field dealer. Worth qualifying because platforms convert quickly on the pocket tier and give visibility across many clinics at once — but confirm the entity and its QIA position before anything else. | R22: SonoEye P3 VET (pocket tier) | S22: TIER 2 | T22: MEDIUM — procurement platform shape; platforms convert quickly on the pocket tier. | U22: A | V22: Carried from CHISON_VET_Dealer_and_EndUser_Workbook_v2.0 (merged into v6, 6 Aug 2026) | W22: Vetplace: CHISON veterinary ultrasound, an introduction | X22: Dear 벳플레이스 (Vetplace) team, My name is Casper Tan, Senior Regional Sales Manager at AstraMed Healthcare, a subsidiary of CHISON Medical Technologies. I cover Singapore, Japan, South Korea and Taiwan for CHISON veterinary ultrasound. Vetplace reaches Korean animal hospitals through a purchasing channel rather than a rep visit, which is exactly the route a pocket-format scanner sells through. To be simple: a Korean entity must hold the QIA veterinary device import licence before anything ships, so this note is about the relationship and an evaluation, not an order. The product I would lead with for you is SonoEye P3 VET (pocket tier). Could we have a short call about whether a veterinary handheld scanner fits your range, and whether your group holds or works with a QIA veterinary device import licence? Kind regards, Casper Tan Senior Regional Sales Manager, AstraMed Healthcare CHISON veterinary ultrasound (Singapore · Japan · South Korea · Taiwan) casper@astramed.sg
A23: 23 | B23: 베토 (Vetto) | C23: Vetto | D23: Not started | F23: Clear with Jerry before first contact | H23: Veterinary supply and equipment distributor to Korean animal hospitals. Entity not confirmed. RELEVANCE: sells into the small and mid-size Korean animal hospitals where a first ultrasound is still an open decision — which is the right customer — but nothing about the company has been verified. Reasonable target if the clinic coverage turns out to be real. | I23: Veterinary supply and equipment distributor to Korean animal hospitals. | J23: Not identified — confirm on first contact | K23: South Korea | L23: NOT CONFIRMED — search 베토 동물병원 기자재 | M23: NOT CONFIRMED | N23: NOT CONFIRMED | O23: South Korea | P23: D — NOT VERIFIED (name only, carried from workbook v2.0; no confirmed URL) | Q23: Unqualified. Confirm the legal entity, the segment and whether they already carry an imaging line before spending time. Reasonable Tier 2 if the clinic coverage is real. | R23: SonoEye P3 VET | S23: TIER 2 | T23: MEDIUM — unqualified. Confirm the entity, the segment and any incumbent imaging line. | U23: A | V23: Carried from CHISON_VET_Dealer_and_EndUser_Workbook_v2.0 (merged into v6, 6 Aug 2026) | W23: Vetto: CHISON veterinary ultrasound, an introduction | X23: Dear 베토 (Vetto) team, My name is Casper Tan, Senior Regional Sales Manager at AstraMed Healthcare, a subsidiary of CHISON Medical Technologies. I cover Singapore, Japan, South Korea and Taiwan for CHISON veterinary ultrasound. Vetto sells into the same small and mid-size Korean animal hospitals where a first ultrasound is still an open decision. To be simple: a Korean entity must hold the QIA veterinary device import licence before anything ships, so this note is about the relationship and an evaluation, not an order. The product I would lead with for you is SonoEye P3 VET. Could we have a short introductory call, and could you confirm your legal company name and whether you already carry an ultrasound line? Kind regards, Casper Tan Senior Regional Sales Manager, AstraMed Healthcare CHISON veterinary ultrasound (Singapore · Japan · South Korea · Taiwan) casper@astramed.sg
A24: 21 | B24: ㈜우진비앤지 (WooGene B&G) | C24: WooGene B&G Co., Ltd. | D24: Not started | F24: Clear with Jerry before first contact | H24: Korean animal pharmaceutical company producing veterinary medicines and biologicals, distributing into animal hospitals and livestock. RELEVANCE: the same logic as the Japanese animal-drug wholesalers — the representative is already in the building every month, and a pocket scanner is the rare capital item a drug rep can physically carry. The open question is whether they handle devices at all. | I24: Korean animal pharmaceutical company — veterinary medicines and biologicals, with distribution into animal hospitals and livestock. | J24: Not identified — confirm | K24: Korea | L24: NOT CONFIRMED — search 우진비앤지 | M24: NOT CONFIRMED | N24: NOT CONFIRMED | O24: Korea | P24: D — NOT VERIFIED (company referenced in Korean VC database only) | Q24: A veterinary pharmaceutical channel with standing clinic relationships. Same logic as the Japanese animal-drug wholesalers: the representative is already in the building, and a pocket scanner is the rare capital item a drug rep can carry. Qualify whether they handle devices at all. | R24: SonoEye P3 VET | S24: TIER 2 | T24: MEDIUM — pharma channel with standing clinic relationships; confirm they handle devices at all. | U24: E | V24: From search — verify entity and device capability | W24: WooGene B&G Co., Ltd.: capital margin on the relationship you already pay for | X24: Dear ㈜우진비앤지 (WooGene B&G Co., Ltd.) team, My name is Casper Tan, Senior Regional Sales Manager at AstraMed Healthcare, a subsidiary of CHISON Medical Technologies. I cover Japan, South Korea, Taiwan and Singapore for CHISON veterinary ultrasound. I am writing to WooGene B&G Co., Ltd. specifically, not to a list. You have standing relationships with Korean animal hospitals through veterinary pharmaceuticals, and a pocket scanner is the rare piece of capital equipment a pharmaceutical representative can physically carry and demonstrate. CHISON's veterinary range is designed to be carried and demonstrated by a rep who is already in the building, no installation crew, no site survey. A unit demonstrated on a Tuesday can be quoted on the Tuesday. It is capital margin layered onto a relationship you already pay for. For context: we have no appointed veterinary distributor in Korea yet. Veterinary devices there are licensed through QIA rather than MFDS, and we would want a partner who already understands that route. The product I would put in front of you first is the SonoEye P3 VET. Could we find twenty minutes? Best regards, Casper Tan Senior Regional Sales Manager AstraMed Healthcare, a subsidiary of CHISON Medical Technologies casper@astramed.sg | +65 8719 0121
A25: 28 | B25: ㈜메디아나 | C25: Mediana Co., Ltd. (KOSDAQ 041920) | D25: Not started | F25: Clear with Jerry before first contact | H25: KOSDAQ-listed Korean medical electronics manufacturer in the Wonju medtech cluster, making patient monitors, defibrillators and AEDs, both under its own brand and as ODM for export. RELEVANCE: Mediana publishes a dedicated ANIMAL-LABELLED monitor range — M20 Vet, M40 Vet and M50 Vet — on both the Korean site and mediana-global.com. Building veterinary versions rather than leaving vets to adapt human monitors means they treat the segment as a real market and already have a route into animal hospitals. NEW IN v9 — carried across from the human-diagnostic Market Development list v3 (Korea row 23), where only the human monitor business was recorded. | I25: Patient monitoring, defibrillators and AEDs — manufacturer and ODM. Veterinary multi-parameter monitor line M20 Vet / M40 Vet / M50 Vet. | J25: NO — monitoring and defibrillation only. No imaging of any kind, human or veterinary. | K25: Wonju, Gangwon (manufacturing / medtech cluster) · Korea nationwide + export | L25: https://www.mediana.co.kr · https://www.mediana-global.com | M25: NOT CONFIRMED — corporate contact page returned 403 on 8 Aug 2026 | N25: NOT CONFIRMED — enquiry via mediana.co.kr | O25: Wonju, Gangwon-do (registered manufacturer; exact street address not confirmed on 8 Aug 2026) | P25: C — SITE LIVE, NOT OPENED for contact. The veterinary product range WAS confirmed from the published M20/M40/M50 Vet pages and catalogue listings (8 Aug 2026); the corporate contact page returned 403, so no phone or email is confirmed. Listed company — the KOSDAQ disclosure filing is a reliable second route. | Q25: Anaesthesia monitoring and ultrasound sit on the same table, in the same room, bought by the same person out of the same budget. Mediana already sells the monitor; nobody in their catalogue sells the scanner. There is no product overlap at all — they watch the patient, we image the patient. Two things are worth establishing on the first call: whether a complementary imaging line has a place beside their veterinary monitors, and whether the channel that already carries M-series Vet into Korean animal hospitals would carry it. Treat this as a complementary-line and co-sell conversation, NOT a distribution appointment on day one — they are a manufacturer, and manufacturers sell into dealers. | R25: SonoEye P3 VET — peri-operative and vascular access, sold alongside their veterinary monitors | S25: TIER 2 | T25: MEDIUM — a genuine veterinary channel with zero imaging conflict, but they are a manufacturer rather than a distributor, so the shape of the relationship has to be established first. No invoice until a Korean entity holds the QIA veterinary device import business licence. | U25: MFR/D | V25: NEW IN v9 — M20 Vet / M40 Vet / M50 Vet confirmed from published product pages and catalogue listings, 8 Aug 2026. Traced from Market Development Target List v3, Korea Dealers row 23 (recorded there as a human patient-monitor and AED maker only). | W25: ㈜메디아나 (Mediana): a complementary line for the animal hospitals already buying M-series Vet | X25: Dear ㈜메디아나 (Mediana Co., Ltd.) team, My name is Casper Tan, Senior Regional Sales Manager at AstraMed Healthcare, a subsidiary of CHISON Medical Technologies. I cover Japan, South Korea, Taiwan and Singapore for CHISON veterinary ultrasound. I am writing because of your veterinary monitor range, the M20, M40 and M50 Vet. Building animal-labelled versions rather than leaving veterinarians to adapt human monitors tells me you take that segment seriously, and it puts your name in the one room where our product also lives: the veterinary theatre and the peri-operative bench. CHISON manufactures a dedicated veterinary ultrasound range, from pocket-sized units to portables. There is no overlap with anything you make, you monitor the patient, we image them, and the two are bought by the same person, on the same table, out of the same budget. I am not proposing anything formal at this stage. Two things seem worth exploring: whether a complementary imaging line has a place alongside your veterinary monitors, and whether the channel that already carries M-series Vet would carry it. Anything beyond that waits on a Korean entity holding the QIA veterinary device import business licence. Would a short introductory call be useful? Casper Tan Senior Regional Sales Manager AstraMed Healthcare, a subsidiary of CHISON Medical Technologies casper@astramed.sg | +65 8719 0121
... A33: 29 | B33: DK메디칼시스템 (동물용 등록 미확인) | C33: DK Medical Systems — VETERINARY REGISTRATION UNVERIFIED | D33: Not started | F33: Clear with Jerry before first contact | H33: Korean diagnostic-imaging maker and distributor operating since 1992 — digital X-ray and fluoroscopy — with a related entity, DK Medical Solution (dkms.co.kr), active in intelligent X-ray and South-East Asian export. CARRIED ACROSS WITH A CORRECTION: the Market Development list v3 graded this a Tier 1 Korean target on the basis that it is 'ALSO registered for veterinary devices (동물용의료용구)'. That claim could NOT be verified in this pass — see the CONTACT CONFIDENCE and fit-note columns. It is carried at TIER 3 / VERIFY FIRST rather than dropped, because if the registration is real the company belongs near the top of this tab. | I33: Digital X-ray and fluoroscopy manufacture and distribution. Veterinary device registration CLAIMED, NOT VERIFIED. | J33: No ultrasound line identified — meaning we did not find one, not that none exists. | K33: Seoul; related entity DK Medical Solution | L33: http://www.dk.co.kr (SEE NOTE) · related: https://www.dkms.co.kr | M33: NOT CONFIRMED | N33: NOT CONFIRMED | O33: Seoul (exact address not confirmed) | P33: D — NOT VERIFIED. On 8 Aug 2026 dk.co.kr could not be opened at all: the TLS certificate was rejected as too weak. Searches surfaced only DK Medical Solution X-ray material, with no veterinary page and no QIA entry found. Confirm the company trades, and confirm the veterinary registration, BEFORE contacting. | Q33: CORRECTION ROW. The older list's Tier 1 grade rested entirely on an unverified veterinary registration, and a Tier 1 grade should never rest on a claim nobody has checked. THE ACTION IS A LOOKUP, NOT A CALL: search the QIA 동물용의료기기 업허가·품목등록 현황 register at qia.go.kr for the company. If the registration is there and current, this is a Korean X-ray manufacturer with veterinary licensing and no ultrasound — the same structural opportunity as Woorien and JPI, and it should be re-tiered to TIER 1 immediately. If it is not there, delete the row. Do not spend a call finding out what a register will tell you in five minutes. | R33: SonoEye P3 VET + EBit 50 VET (only once the veterinary registration is confirmed) | S33: TIER 3 | T33: LOW until verified — the entity and its veterinary registration are both unconfirmed. Re-grade to HIGH and TIER 1 if the QIA register confirms the registration. | U33: F | V33: CARRIED WITH CORRECTION IN v9 from Market Development Target List v3, Korea Dealers row 21. Verification attempted 8 Aug 2026 and FAILED: dk.co.kr unreachable (TLS certificate rejected), no veterinary page or QIA entry located. | W33: DK메디칼시스템 (DK Medical Systems): a second capital line for the animal hospitals you already reach | X33: Dear DK메디칼시스템 (DK Medical Systems) team, My name is Casper Tan, Senior Regional Sales Manager at AstraMed Healthcare, a subsidiary of CHISON Medical Technologies. I cover Japan, South Korea, Taiwan and Singapore for CHISON veterinary ultrasound. You are on our list as a Korean diagnostic X-ray manufacturer holding a veterinary device registration. If that is still current, it is the profile we look for hardest: an imaging company with real access to animal hospitals and no ultrasound line of its own to defend. CHISON manufactures a dedicated veterinary ultrasound range, pocket units through portables, with animal presets rather than human systems relabelled. Beside an X-ray room it completes the diagnostic picture instead of competing with it, and it gives an existing salesforce a second capital product for customers they already visit. Before taking up more of your time, could you confirm two things, that the veterinary registration is current, and who in your organisation owns the animal-hospital business? Nothing can be supplied into Korea until a Korean entity holds the QIA veterinary device import business licence, so this is a fit conversation only. VERIFY FIRST, do not send this until the QIA register confirms the veterinary registration and a working address is found. Casper Tan Senior Regional Sales Manager AstraMed Healthcare, a subsidiary of CHISON Medical Technologies casper@astramed.sg | +65 8719 0121
