Workbook

Sheet Master List
A1: Japan VET Lead List: Master List
A2: CHISON veterinary ultrasound, Japan lead list v2 (AstraMed Healthcare). Built 10 Oct 2026 from web search results only: the session's network policy blocked direct page fetches, so contact pages were read through search results, not opened. Every row has at least one source link. Email column: a published company address where one exists (no personal address was guessed), otherwise the inquiry form URL or 'phone only'. Contact confidence: 'Verified' = published on the company's own site; 'Likely' = third party listing (association, chamber); 'Company inquiry only' = form or phone. Rows marked 'Qualify first' in the last column are human dealers whose animal hospital business is not yet confirmed. Fit score is the live SUM of the seven score columns on the right.
A4: No. | B4: Company (English) | C4: Company (Japanese) | D4: 法人番号 | E4: HQ prefecture | F4: Region | G4: Website | H4: Licences held | I4: Brands carried | J4: Companion / Large animal / Both | K4: Coverage area | L4: Est. revenue or headcount | M4: Number of clinics (Tier V5 only) | N4: Key contact name | O4: Title | P4: Email | Q4: Phone | R4: LinkedIn | S4: Contact confidence | T4: Fit score /35 | U4: Tier | V4: Why they fit | W4: Suggested opening angle | X4: Also in human list (Y/N) | Y4: Source links | Z4: Score: regulatory | AA4: Score: imaging and US | AB4: Score: brand conflict | AC4: Score: companion coverage | AD4: Score: large animal | AE4: Score: service engineers | AF4: Score: openness to CN/KR | AG4: Evidence status
A5: 1 | B5: Central Scientific Commerce, Inc. | C5: セントラル科学貿易株式会社 | D5: Not found (NTA lookup blocked; dedupe by Japanese name) | E5: Tokyo | F5: Kanto | G5: https://cscjp.co.jp/csc-medical/products/vet-videoscope.html | H5: Imports AOHUA vet videoscopes (vet device notification implied) | I5: AOHUA (China) vet endoscopes; no ultrasound | J5: Companion | K5: National | L5: Not found | M5: n/a | N5: Not identified | O5: Not identified | P5: cscsupport@cscjp.co.jp | Q5: 03 5627 8150 | R5: Not identified | S5: Likely (third party listing) | T5: =SUM(Z5:AF5) -> 26 | U5: V1 | V5: Already imports a Chinese vet imaging brand (AOHUA), which shows openness to Chinese manufacturers and a working NVAL route. | W5: Lead with CHISON credentials (FDA, OEM for global brands) as the ultrasound companion to AOHUA. | X5: Not checked (human list not in v17) | Y5: https://cscjp.co.jp/csc-medical/products/vet-videoscope.html ; https://sia-tokyo.gr.jp/co-list/748 ; https://cscjp.co.jp/contact/ | Z5: 5 | AA5: 3 | AB5: 5 | AC5: 4 | AD5: 1 | AE5: 3 | AF5: 5 | AG5: Evidence backed
A6: 2 | B6: ARKRAY, Inc. (Veterinary) | C6: アークレイ株式会社 (アークレイファクトリー) | D6: Not found (NTA lookup blocked; dedupe by Japanese name) | E6: Kyoto | F6: Kansai | G6: https://arkraythinkanimal.com | H6: Vet device MAH via ARKRAY Factory (NVAL: thinka CB1010) | I6: Vet analysers (Vcheck V200); no ultrasound | J6: Companion | K6: National vet sales force | L6: Large | M6: n/a | N6: Not identified | O6: Not identified | P6: thinka@arkray.co.jp | Q6: 050 5527 7700 | R6: Not identified | S6: Verified (published on own site, read via search) | T6: =SUM(Z6:AF6) -> 25 | U6: V1 | V6: Runs a dedicated vet brand (Think Animal) and exhibits at JBVP; national animal hospital coverage and service. | W6: In clinic diagnostics plus point of care ultrasound bundle. | X6: Not checked (human list not in v17) | Y6: https://www.vm.nval.go.jp/public/detail/16030 ; https://arkraythinkanimal.com/2025/09/03/information95/ ; https://arkraythinkanimal.com/company/ ; https://arkraythinkanimal.com/contact/ | Z6: 5 | AA6: 2 | AB6: 5 | AC6: 5 | AD6: 1 | AE6: 4 | AF6: 3 | AG6: Evidence backed
A7: 3 | B7: Nozawa Corporation | C7: 株式会社野澤組 | D7: Not found (NTA lookup blocked; dedupe by Japanese name) | E7: Tokyo | F7: Kanto | G7: https://www.nosawa.co.jp/ | H7: Vet ultrasound MAH per NVAL listing (iScan2 and MyLab series) | I7: iScan2 (Draminski) and MyLab series listed | J7: Both | K7: National import trading house | L7: Not found | M7: n/a | N7: Not identified | O7: Not identified | P7: gg@nosawa.co.jp | Q7: 03 3528 8101 | R7: Not identified | S7: Verified (published on own site, read via search) | T7: =SUM(Z7:AF7) -> 25 | U7: V1 | V7: Trading house already holding vet ultrasound notifications, including large animal scanners; regulatory capability proven. FLAG: MyLab may indicate an Esaote relationship; confirm brand conflict. | W7: Mid tier companion portables to complement their large animal scanner, if their MyLab line is not exclusive. | X7: Not checked (human list not in v17) | Y7: https://vm.nval.go.jp/?mfg_dealer_name=&sort=MANUFACTURING_DEALER&submit=submit ; https://www.vm.nval.go.jp/public/detail/9148 ; https://www.totalapproach.co.jp/askme/askme.html ; https://www.nosawa.co.jp/inquiry/ | Z7: 5 | AA7: 5 | AB7: 2 | AC7: 3 | AD7: 4 | AE7: 3 | AF7: 3 | AG7: Evidence backed
A8: 4 | B8: Olympus Marketing, Inc. (Animal Medical) | C8: オリンパスマーケティング株式会社 | D8: Not found (NTA lookup blocked; dedupe by Japanese name) | E8: Tokyo | F8: Kanto | G8: https://www.olympus-marketing.co.jp/business/animal/ | H8: Vet endoscopy systems marketed (VES Be one); Olympus group MAH capability | I8: Own endoscopes; no ultrasound in vet range | J8: Companion | K8: National | L8: Large (Olympus group) | M8: n/a | N8: Not identified | O8: Not identified | P8: Not published; inquiry form: https://www.olympus-marketing.co.jp/contact/ | Q8: 042 642 4002 | R8: Not identified | S8: Company inquiry only (form) | T8: =SUM(Z8:AF8) -> 25 | U8: V1 | V8: Runs a dedicated animal endoscopy business with national service engineers; imaging culture and hospital relationships. | W8: Endoscopy plus ultrasound GI work up; propose a co marketing pilot rather than distribution first. | X8: Not checked (human list not in v17) | Y8: https://www.olympus-marketing.co.jp/business/animal/ ; https://www.olympus-marketing.co.jp/contact/ | Z8: 5 | AA8: 4 | AB8: 4 | AC8: 4 | AD8: 1 | AE8: 5 | AF8: 2 | AG8: Evidence backed
A9: 5 | B9: Kyoritsu Shokai Co., Ltd. | C9: 株式会社共立商会 | D9: Not found (NTA lookup blocked; dedupe by Japanese name) | E9: Tokyo | F9: Kanto | G9: https://www.kyoritsu-shokai.com | H9: 第二種動物用医療機器製造販売業許可 (licence page on own site); 動物用医薬品 import and sales | I9: Imported vet drugs and instruments; no ultrasound line identified | J9: Both | K9: Kanto base, national import channel | L9: Not found | M9: n/a | N9: Not identified | O9: Not identified | P9: pet@kyoritsu-shokai.com | Q9: 03 3424 6201 | R9: Not identified | S9: Verified (published on own site, read via search); page notes the address was changed, confirm | T9: =SUM(Z9:AF9) -> 24 | U9: V1 | V9: Imports and sells vet drugs and instruments and displays a second class vet device MAH licence, so it could hold the CHISON notification itself. Its executive chairs the JADIDA Kanto Koshinetsu block, giving reach into every regional wholesaler. FLAG: Licence page last indexed about 18 months ago; confirm the licence is current. | W9: Ask whether they would act as MAH and master importer for a portable vet ultrasound line, with regional JADIDA members as sub dealers. | X9: Not checked (human list not in v17) | Y9: https://www.kyoritsu-shokai.com/company/%E5%8C%BB%E8%96%AC%E5%93%81%E3%83%BB%E5%8B%95%E7%89%A9%E7%94%A8%E5%8C%BB%E8%96%AC%E5%93%81%E8%A8%B1%E5%8F%AF%E8%A8%BC%E9%96%A2%E9%80%A3/ ; https://jadida.or.jp/aboutus.html ; https://www.kyoritsu-shokai.com/%E7%89%B9%E5%AE%9A%E5%95%86%E5%8F%96%E5%BC%95%E6%B3%95%E3%81%AB%E5%9F%BA%E3%81%A5%E3%81%8F%E8%A1%A8%E8%A8%98/ ; https://www.kyoritsu-shokai.com/%E3%81%8A%E5%95%8F%E3%81%84%E5%90%88%E3%82%8F%E3%81%9B/ | Z9: 5 | AA9: 1 | AB9: 5 | AC9: 4 | AD9: 4 | AE9: 2 | AF9: 3 | AG9: Evidence backed
A10: 6 | B10: T&S Co., Ltd. | C10: 株式会社ティーアンドエス | D10: Not found (NTA lookup blocked; dedupe by Japanese name) | E10: Chiba | F10: Kanto | G10: https://ts-xray.com | H10: Animal device manufacturing licence (2003); NVAL approval VPX200 vet X ray (2004) | I10: Own X ray; no ultrasound | J10: Both | K10: Noda, Chiba; national | L10: Not found | M10: n/a | N10: Not identified | O10: Not identified | P10: contact@ts-xray.com | Q10: 04 7127 7323 | R10: Not identified | S10: Verified (published on own site, read via search); listed on recruiting page | T10: =SUM(Z10:AF10) -> 24 | U10: V1 | V10: Domestic X ray maker with a vet approval; imaging focused and unconflicted on ultrasound. | W10: Pair portable ultrasound with their vet X ray for clinic openings. | X10: Not checked (human list not in v17) | Y10: https://www.pref.saitama.lg.jp/documents/236933/0343_tands.pdf ; https://www.vm.nval.go.jp/public/detail/6769 ; https://ts-xray.com/recruit/ ; https://ts-xray.com/inquiry/ | Z10: 5 | AA10: 3 | AB10: 5 | AC10: 3 | AD10: 2 | AE10: 3 | AF10: 3 | AG10: Evidence backed
A11: 7 | B11: Nipro Corporation (Veterinary) | C11: ニプロ株式会社 | D11: Not found (NTA lookup blocked; dedupe by Japanese name) | E11: Osaka | F11: Kansai | G11: Not found | H11: Vet device MAH (NVAL: vet syringe 2018, infusion set) | I11: Disposables; no vet ultrasound | J11: Both | K11: National and Asia | L11: Large | M11: n/a | N11: Not identified | O11: Not identified | P11: Not published; inquiry form: https://www.nipro.co.jp/contact/device/ | Q11: 0120 226 410 (device info desk) | R11: Not identified | S11: Company inquiry only (form) | T11: =SUM(Z11:AF11) -> 23 | U11: V1 | V11: Major human device group with vet MAH registrations; dealer network reaches animal hospitals. | W11: Long shot; explore OEM or MAH service. | X11: Not checked (human list not in v17) | Y11: https://www.vm.nval.go.jp/public/detail/17793 ; https://www.vm.nval.go.jp/public/detail/6784 ; https://www.nipro.co.jp/contact/device/ | Z11: 5 | AA11: 1 | AB11: 5 | AC11: 3 | AD11: 2 | AE11: 5 | AF11: 2 | AG11: Evidence backed
A12: 8 | B12: Aison Co., Ltd. | C12: アイソン株式会社 | D12: Not found (NTA lookup blocked; dedupe by Japanese name) | E12: Saitama | F12: Kanto | G12: https://aison.jp/ | H12: Vet ultrasound MAH: NVAL notification 超音波画像診断装置 Vシリーズ (9 Jul 2024) | I12: Holds a vet ultrasound line (V series; origin brand not confirmed) | J12: Companion | K12: Kawaguchi, Saitama | L12: Not found | M12: n/a | N12: Not identified | O12: Not identified | P12: saito@aison.jp | Q12: 048 299 3597 | R12: Not identified | S12: Likely (third party listing); named staff address, may be old | T12: =SUM(Z12:AF12) -> 23 | U12: V1 | V12: One of the few MAHs that notified a vet ultrasound in 2024, so it knows the exact NVAL route CHISON needs. FLAG: Brand behind the V series not confirmed; check it is not SonoScape or Mindray exclusive. | W12: Ask whether they would add a second OEM source or act as MAH for CHISON vet SKUs. | X12: Not checked (human list not in v17) | Y12: https://www.vm.nval.go.jp/public/detail/19613 ; https://www.pmda.go.jp/PmdaSearch/kikiDetail/ResultDataSetPDF/112161_306ADBZX00058000_V_01_01 ; http://www.kawaguchicci.or.jp/plat/pl_disp_company_detail.cgi?company=2209 | Z12: 5 | AA12: 5 | AB12: 2 | AC12: 3 | AD12: 1 | AE12: 3 | AF12: 4 | AG12: Evidence backed
A13: 9 | B13: IDEXX Laboratories K.K. | C13: アイデックス ラボラトリーズ株式会社 | D13: Not found (NTA lookup blocked; dedupe by Japanese name) | E13: Tokyo | F13: Kanto | G13: Not found | H13: Vet device MAH (NVAL: Catalyst Dx) | I13: Lab analysers; no ultrasound | J13: Companion | K13: National | L13: Large (IDEXX group) | M13: n/a | N13: Not identified | O13: Not identified | P13: Not published; inquiry form: https://www.idexx.co.jp/ja/about-idexx/contact-idexx/ | Q13: 0120 71 4921 | R13: Not identified | S13: Company inquiry only (form) | T13: =SUM(Z13:AF13) -> 23 | U13: V1 | V13: Largest in clinic diagnostics vendor with direct hospital coverage; MAH capability. FLAG: Global corporate; partnering unlikely, keep as awareness. | W13: Long shot; useful for co promotion. | X13: Not checked (human list not in v17) | Y13: https://www.vm.nval.go.jp/public/detail/12549 ; https://www.idexx.co.jp/ja/about-idexx/contact-idexx/ | Z13: 5 | AA13: 1 | AB13: 5 | AC13: 5 | AD13: 1 | AE13: 5 | AF13: 1 | AG13: Evidence backed
A14: 10 | B14: Karl Storz Endoscopy Japan K.K. | C14: カールストルツ・エンドスコピー・ジャパン株式会社 | D14: Not found (NTA lookup blocked; dedupe by Japanese name) | E14: Tokyo | F14: Kanto | G14: Not found | H14: Vet device MAH (NVAL listing) | I14: Endoscopy; no ultrasound in vet range | J14: Companion | K14: National | L14: Large (Karl Storz group) | M14: n/a | N14: Not identified | O14: Not identified | P14: Not published; phone only | Q14: Not found | R14: Not identified | S14: Unverified (no contact found in search) | T14: =SUM(Z14:AF14) -> 23 | U14: V1 | V14: Holds vet device notifications and serves referral hospitals with endoscopy; imaging service engineers. | W14: Referral centre co marketing; low probability of distribution but useful KOL access. | X14: Not checked (human list not in v17) | Y14: https://www.vm.nval.go.jp/public/detail/6770 | Z14: 5 | AA14: 3 | AB14: 4 | AC14: 3 | AD14: 1 | AE14: 5 | AF14: 2 | AG14: Evidence backed
A15: 11 | B15: Metran Co., Ltd. | C15: 株式会社メトラン | D15: Not found (NTA lookup blocked; dedupe by Japanese name) | E15: Saitama | F15: Kanto | G15: https://www.metran.co.jp/ | H15: Vet device MAH (NVAL: BM7Vet Pro monitor, 2020) | I15: Own ventilators and monitors; no ultrasound | J15: Companion | K15: National via vet dealers | L15: Not found | M15: n/a | N15: Not identified | O15: Not identified | P15: support@metran.co.jp | Q15: 048 242 0333 | R15: Not identified | S15: Verified (published on own site, read via search) | T15: =SUM(Z15:AF15) -> 23 | U15: V1 | V15: Vet ventilator pioneer (since 1984) that already notifies vet devices with NVAL and imports monitors; natural MAH partner for ICU and anaesthesia adjacent imaging. | W15: Propose a peri operative point of care ultrasound bundle with their Compos X ventilator. | X15: Not checked (human list not in v17) | Y15: https://www.vm.nval.go.jp/public/detail/18306 ; https://medical-space.co.jp/products/3096/ ; https://www.metran.co.jp/links | Z15: 5 | AA15: 1 | AB15: 5 | AC15: 4 | AD15: 1 | AE15: 4 | AF15: 3 | AG15: Evidence backed
A16: 12 | B16: RayVision Co., Ltd. | C16: 株式会社RayVision | D16: Not found (NTA lookup blocked; dedupe by Japanese name) | E16: Saitama | F16: Kanto | G16: https://rayvision.co.jp/ | H16: Vet flat panel detector maker and seller (vet device notification implied) | I16: Own vet DR; no ultrasound | J16: Companion | K16: Saitama; national via Medical Space and others | L16: Not found | M16: n/a | N16: Not identified | O16: Not identified | P16: Not published; inquiry form: https://rayvision.co.jp/contact/ | Q16: 048 657 2601 | R16: Not identified | S16: Company inquiry only (form) | T16: =SUM(Z16:AF16) -> 23 | U16: V1 | V16: Vet specific DR maker with maintenance support; imaging buyers are the same clinics. | W16: Cross sell: DR plus ultrasound package for new clinics. | X16: Not checked (human list not in v17) | Y16: https://rayvision.co.jp/ ; https://medical-space.co.jp/products/9109/ ; https://rayvision.co.jp/contact/ | Z16: 4 | AA16: 3 | AB16: 5 | AC16: 4 | AD16: 1 | AE16: 3 | AF16: 3 | AG16: Evidence backed
... A263: 259 | B263: Will Animal Hospital Group | C263: 株式会社ウイル動物病院グループ | D263: Not found (NTA lookup blocked; dedupe by Japanese name) | E263: Miyagi | F263: Tohoku and Hokkaido | G263: https://animal-99.com/ | H263: End user (animal hospital group) | I263: Not identified | J263: Companion | K263: Miyagi (Sendai, Shiogama, Kakuda, Watari) | L263: Not found | M263: 9 | N263: Not identified | O263: Not identified | P263: Not published; inquiry form: https://animal-99.com/contact_form.html | Q263: 022 355 8492 | R263: Not identified | S263: Company inquiry only (form) | T263: =SUM(Z263:AF263) -> 18 | U263: V5 | V263: Nine hospital Sendai group incl. Sendai Animal Medical Center. FLAG: Part of MiraiVets/JPAC. | W263: Fleet evaluation: 30 day placement in two sites, then a group standard. | X263: Not checked (human list not in v17) | Y263: https://animal-99.com/ ; https://forbesjapan.com/articles/detail/82089 ; https://animal-99.com/contact_form.html | Z263: 1 | AA263: 4 | AB263: 3 | AC263: 5 | AD263: 1 | AE263: 1 | AF263: 3 | AG263: Evidence backed

Sheet Distributor Shortlist
A1: Distributor Shortlist: Tier V1 and V2, sorted by fit score
A2: V1 can import and hold MAFF notifications (MAH route); V2 sells vet equipment. Brand conflicts and unconfirmed items are written into 'Why they fit'.
A4: No. | B4: Company (English) | C4: Company (Japanese) | D4: 法人番号 | E4: HQ prefecture | F4: Region | G4: Website | H4: Licences held | I4: Brands carried | J4: Companion / Large animal / Both | K4: Coverage area | L4: Est. revenue or headcount | M4: Number of clinics (Tier V5 only) | N4: Key contact name | O4: Title | P4: Email | Q4: Phone | R4: LinkedIn | S4: Contact confidence | T4: Fit score /35 | U4: Tier | V4: Why they fit | W4: Suggested opening angle | X4: Also in human list (Y/N) | Y4: Source links | Z4: Score: regulatory | AA4: Score: imaging and US | AB4: Score: brand conflict | AC4: Score: companion coverage | AD4: Score: large animal | AE4: Score: service engineers | AF4: Score: openness to CN/KR | AG4: Evidence status
A5: 1 | B5: Central Scientific Commerce, Inc. | C5: セントラル科学貿易株式会社 | D5: Not found (NTA lookup blocked; dedupe by Japanese name) | E5: Tokyo | F5: Kanto | G5: https://cscjp.co.jp/csc-medical/products/vet-videoscope.html | H5: Imports AOHUA vet videoscopes (vet device notification implied) | I5: AOHUA (China) vet endoscopes; no ultrasound | J5: Companion | K5: National | L5: Not found | M5: n/a | N5: Not identified | O5: Not identified | P5: cscsupport@cscjp.co.jp | Q5: 03 5627 8150 | R5: Not identified | S5: Likely (third party listing) | T5: =SUM(Z5:AF5) -> 26 | U5: V1 | V5: Already imports a Chinese vet imaging brand (AOHUA), which shows openness to Chinese manufacturers and a working NVAL route. | W5: Lead with CHISON credentials (FDA, OEM for global brands) as the ultrasound companion to AOHUA. | X5: Not checked (human list not in v17) | Y5: https://cscjp.co.jp/csc-medical/products/vet-videoscope.html ; https://sia-tokyo.gr.jp/co-list/748 ; https://cscjp.co.jp/contact/ | Z5: 5 | AA5: 3 | AB5: 5 | AC5: 4 | AD5: 1 | AE5: 3 | AF5: 5 | AG5: Evidence backed
A6: 2 | B6: ARKRAY, Inc. (Veterinary) | C6: アークレイ株式会社 (アークレイファクトリー) | D6: Not found (NTA lookup blocked; dedupe by Japanese name) | E6: Kyoto | F6: Kansai | G6: https://arkraythinkanimal.com | H6: Vet device MAH via ARKRAY Factory (NVAL: thinka CB1010) | I6: Vet analysers (Vcheck V200); no ultrasound | J6: Companion | K6: National vet sales force | L6: Large | M6: n/a | N6: Not identified | O6: Not identified | P6: thinka@arkray.co.jp | Q6: 050 5527 7700 | R6: Not identified | S6: Verified (published on own site, read via search) | T6: =SUM(Z6:AF6) -> 25 | U6: V1 | V6: Runs a dedicated vet brand (Think Animal) and exhibits at JBVP; national animal hospital coverage and service. | W6: In clinic diagnostics plus point of care ultrasound bundle. | X6: Not checked (human list not in v17) | Y6: https://www.vm.nval.go.jp/public/detail/16030 ; https://arkraythinkanimal.com/2025/09/03/information95/ ; https://arkraythinkanimal.com/company/ ; https://arkraythinkanimal.com/contact/ | Z6: 5 | AA6: 2 | AB6: 5 | AC6: 5 | AD6: 1 | AE6: 4 | AF6: 3 | AG6: Evidence backed
A7: 3 | B7: Nozawa Corporation | C7: 株式会社野澤組 | D7: Not found (NTA lookup blocked; dedupe by Japanese name) | E7: Tokyo | F7: Kanto | G7: https://www.nosawa.co.jp/ | H7: Vet ultrasound MAH per NVAL listing (iScan2 and MyLab series) | I7: iScan2 (Draminski) and MyLab series listed | J7: Both | K7: National import trading house | L7: Not found | M7: n/a | N7: Not identified | O7: Not identified | P7: gg@nosawa.co.jp | Q7: 03 3528 8101 | R7: Not identified | S7: Verified (published on own site, read via search) | T7: =SUM(Z7:AF7) -> 25 | U7: V1 | V7: Trading house already holding vet ultrasound notifications, including large animal scanners; regulatory capability proven. FLAG: MyLab may indicate an Esaote relationship; confirm brand conflict. | W7: Mid tier companion portables to complement their large animal scanner, if their MyLab line is not exclusive. | X7: Not checked (human list not in v17) | Y7: https://vm.nval.go.jp/?mfg_dealer_name=&sort=MANUFACTURING_DEALER&submit=submit ; https://www.vm.nval.go.jp/public/detail/9148 ; https://www.totalapproach.co.jp/askme/askme.html ; https://www.nosawa.co.jp/inquiry/ | Z7: 5 | AA7: 5 | AB7: 2 | AC7: 3 | AD7: 4 | AE7: 3 | AF7: 3 | AG7: Evidence backed
A8: 4 | B8: Olympus Marketing, Inc. (Animal Medical) | C8: オリンパスマーケティング株式会社 | D8: Not found (NTA lookup blocked; dedupe by Japanese name) | E8: Tokyo | F8: Kanto | G8: https://www.olympus-marketing.co.jp/business/animal/ | H8: Vet endoscopy systems marketed (VES Be one); Olympus group MAH capability | I8: Own endoscopes; no ultrasound in vet range | J8: Companion | K8: National | L8: Large (Olympus group) | M8: n/a | N8: Not identified | O8: Not identified | P8: Not published; inquiry form: https://www.olympus-marketing.co.jp/contact/ | Q8: 042 642 4002 | R8: Not identified | S8: Company inquiry only (form) | T8: =SUM(Z8:AF8) -> 25 | U8: V1 | V8: Runs a dedicated animal endoscopy business with national service engineers; imaging culture and hospital relationships. | W8: Endoscopy plus ultrasound GI work up; propose a co marketing pilot rather than distribution first. | X8: Not checked (human list not in v17) | Y8: https://www.olympus-marketing.co.jp/business/animal/ ; https://www.olympus-marketing.co.jp/contact/ | Z8: 5 | AA8: 4 | AB8: 4 | AC8: 4 | AD8: 1 | AE8: 5 | AF8: 2 | AG8: Evidence backed
A9: 5 | B9: Kyoritsu Shokai Co., Ltd. | C9: 株式会社共立商会 | D9: Not found (NTA lookup blocked; dedupe by Japanese name) | E9: Tokyo | F9: Kanto | G9: https://www.kyoritsu-shokai.com | H9: 第二種動物用医療機器製造販売業許可 (licence page on own site); 動物用医薬品 import and sales | I9: Imported vet drugs and instruments; no ultrasound line identified | J9: Both | K9: Kanto base, national import channel | L9: Not found | M9: n/a | N9: Not identified | O9: Not identified | P9: pet@kyoritsu-shokai.com | Q9: 03 3424 6201 | R9: Not identified | S9: Verified (published on own site, read via search); page notes the address was changed, confirm | T9: =SUM(Z9:AF9) -> 24 | U9: V1 | V9: Imports and sells vet drugs and instruments and displays a second class vet device MAH licence, so it could hold the CHISON notification itself. Its executive chairs the JADIDA Kanto Koshinetsu block, giving reach into every regional wholesaler. FLAG: Licence page last indexed about 18 months ago; confirm the licence is current. | W9: Ask whether they would act as MAH and master importer for a portable vet ultrasound line, with regional JADIDA members as sub dealers. | X9: Not checked (human list not in v17) | Y9: https://www.kyoritsu-shokai.com/company/%E5%8C%BB%E8%96%AC%E5%93%81%E3%83%BB%E5%8B%95%E7%89%A9%E7%94%A8%E5%8C%BB%E8%96%AC%E5%93%81%E8%A8%B1%E5%8F%AF%E8%A8%BC%E9%96%A2%E9%80%A3/ ; https://jadida.or.jp/aboutus.html ; https://www.kyoritsu-shokai.com/%E7%89%B9%E5%AE%9A%E5%95%86%E5%8F%96%E5%BC%95%E6%B3%95%E3%81%AB%E5%9F%BA%E3%81%A5%E3%81%8F%E8%A1%A8%E8%A8%98/ ; https://www.kyoritsu-shokai.com/%E3%81%8A%E5%95%8F%E3%81%84%E5%90%88%E3%82%8F%E3%81%9B/ | Z9: 5 | AA9: 1 | AB9: 5 | AC9: 4 | AD9: 4 | AE9: 2 | AF9: 3 | AG9: Evidence backed
A10: 6 | B10: T&S Co., Ltd. | C10: 株式会社ティーアンドエス | D10: Not found (NTA lookup blocked; dedupe by Japanese name) | E10: Chiba | F10: Kanto | G10: https://ts-xray.com | H10: Animal device manufacturing licence (2003); NVAL approval VPX200 vet X ray (2004) | I10: Own X ray; no ultrasound | J10: Both | K10: Noda, Chiba; national | L10: Not found | M10: n/a | N10: Not identified | O10: Not identified | P10: contact@ts-xray.com | Q10: 04 7127 7323 | R10: Not identified | S10: Verified (published on own site, read via search); listed on recruiting page | T10: =SUM(Z10:AF10) -> 24 | U10: V1 | V10: Domestic X ray maker with a vet approval; imaging focused and unconflicted on ultrasound. | W10: Pair portable ultrasound with their vet X ray for clinic openings. | X10: Not checked (human list not in v17) | Y10: https://www.pref.saitama.lg.jp/documents/236933/0343_tands.pdf ; https://www.vm.nval.go.jp/public/detail/6769 ; https://ts-xray.com/recruit/ ; https://ts-xray.com/inquiry/ | Z10: 5 | AA10: 3 | AB10: 5 | AC10: 3 | AD10: 2 | AE10: 3 | AF10: 3 | AG10: Evidence backed
A11: 7 | B11: Aison Co., Ltd. | C11: アイソン株式会社 | D11: Not found (NTA lookup blocked; dedupe by Japanese name) | E11: Saitama | F11: Kanto | G11: https://aison.jp/ | H11: Vet ultrasound MAH: NVAL notification 超音波画像診断装置 Vシリーズ (9 Jul 2024) | I11: Holds a vet ultrasound line (V series; origin brand not confirmed) | J11: Companion | K11: Kawaguchi, Saitama | L11: Not found | M11: n/a | N11: Not identified | O11: Not identified | P11: saito@aison.jp | Q11: 048 299 3597 | R11: Not identified | S11: Likely (third party listing); named staff address, may be old | T11: =SUM(Z11:AF11) -> 23 | U11: V1 | V11: One of the few MAHs that notified a vet ultrasound in 2024, so it knows the exact NVAL route CHISON needs. FLAG: Brand behind the V series not confirmed; check it is not SonoScape or Mindray exclusive. | W11: Ask whether they would add a second OEM source or act as MAH for CHISON vet SKUs. | X11: Not checked (human list not in v17) | Y11: https://www.vm.nval.go.jp/public/detail/19613 ; https://www.pmda.go.jp/PmdaSearch/kikiDetail/ResultDataSetPDF/112161_306ADBZX00058000_V_01_01 ; http://www.kawaguchicci.or.jp/plat/pl_disp_company_detail.cgi?company=2209 | Z11: 5 | AA11: 5 | AB11: 2 | AC11: 3 | AD11: 1 | AE11: 3 | AF11: 4 | AG11: Evidence backed
A12: 8 | B12: IDEXX Laboratories K.K. | C12: アイデックス ラボラトリーズ株式会社 | D12: Not found (NTA lookup blocked; dedupe by Japanese name) | E12: Tokyo | F12: Kanto | G12: Not found | H12: Vet device MAH (NVAL: Catalyst Dx) | I12: Lab analysers; no ultrasound | J12: Companion | K12: National | L12: Large (IDEXX group) | M12: n/a | N12: Not identified | O12: Not identified | P12: Not published; inquiry form: https://www.idexx.co.jp/ja/about-idexx/contact-idexx/ | Q12: 0120 71 4921 | R12: Not identified | S12: Company inquiry only (form) | T12: =SUM(Z12:AF12) -> 23 | U12: V1 | V12: Largest in clinic diagnostics vendor with direct hospital coverage; MAH capability. FLAG: Global corporate; partnering unlikely, keep as awareness. | W12: Long shot; useful for co promotion. | X12: Not checked (human list not in v17) | Y12: https://www.vm.nval.go.jp/public/detail/12549 ; https://www.idexx.co.jp/ja/about-idexx/contact-idexx/ | Z12: 5 | AA12: 1 | AB12: 5 | AC12: 5 | AD12: 1 | AE12: 5 | AF12: 1 | AG12: Evidence backed
A13: 9 | B13: Karl Storz Endoscopy Japan K.K. | C13: カールストルツ・エンドスコピー・ジャパン株式会社 | D13: Not found (NTA lookup blocked; dedupe by Japanese name) | E13: Tokyo | F13: Kanto | G13: Not found | H13: Vet device MAH (NVAL listing) | I13: Endoscopy; no ultrasound in vet range | J13: Companion | K13: National | L13: Large (Karl Storz group) | M13: n/a | N13: Not identified | O13: Not identified | P13: Not published; phone only | Q13: Not found | R13: Not identified | S13: Unverified (no contact found in search) | T13: =SUM(Z13:AF13) -> 23 | U13: V1 | V13: Holds vet device notifications and serves referral hospitals with endoscopy; imaging service engineers. | W13: Referral centre co marketing; low probability of distribution but useful KOL access. | X13: Not checked (human list not in v17) | Y13: https://www.vm.nval.go.jp/public/detail/6770 | Z13: 5 | AA13: 3 | AB13: 4 | AC13: 3 | AD13: 1 | AE13: 5 | AF13: 2 | AG13: Evidence backed
A14: 10 | B14: Metran Co., Ltd. | C14: 株式会社メトラン | D14: Not found (NTA lookup blocked; dedupe by Japanese name) | E14: Saitama | F14: Kanto | G14: https://www.metran.co.jp/ | H14: Vet device MAH (NVAL: BM7Vet Pro monitor, 2020) | I14: Own ventilators and monitors; no ultrasound | J14: Companion | K14: National via vet dealers | L14: Not found | M14: n/a | N14: Not identified | O14: Not identified | P14: support@metran.co.jp | Q14: 048 242 0333 | R14: Not identified | S14: Verified (published on own site, read via search) | T14: =SUM(Z14:AF14) -> 23 | U14: V1 | V14: Vet ventilator pioneer (since 1984) that already notifies vet devices with NVAL and imports monitors; natural MAH partner for ICU and anaesthesia adjacent imaging. | W14: Propose a peri operative point of care ultrasound bundle with their Compos X ventilator. | X14: Not checked (human list not in v17) | Y14: https://www.vm.nval.go.jp/public/detail/18306 ; https://medical-space.co.jp/products/3096/ ; https://www.metran.co.jp/links | Z14: 5 | AA14: 1 | AB14: 5 | AC14: 4 | AD14: 1 | AE14: 4 | AF14: 3 | AG14: Evidence backed
A15: 11 | B15: Nipro Corporation (Veterinary) | C15: ニプロ株式会社 | D15: Not found (NTA lookup blocked; dedupe by Japanese name) | E15: Osaka | F15: Kansai | G15: Not found | H15: Vet device MAH (NVAL: vet syringe 2018, infusion set) | I15: Disposables; no vet ultrasound | J15: Both | K15: National and Asia | L15: Large | M15: n/a | N15: Not identified | O15: Not identified | P15: Not published; inquiry form: https://www.nipro.co.jp/contact/device/ | Q15: 0120 226 410 (device info desk) | R15: Not identified | S15: Company inquiry only (form) | T15: =SUM(Z15:AF15) -> 23 | U15: V1 | V15: Major human device group with vet MAH registrations; dealer network reaches animal hospitals. | W15: Long shot; explore OEM or MAH service. | X15: Not checked (human list not in v17) | Y15: https://www.vm.nval.go.jp/public/detail/17793 ; https://www.vm.nval.go.jp/public/detail/6784 ; https://www.nipro.co.jp/contact/device/ | Z15: 5 | AA15: 1 | AB15: 5 | AC15: 3 | AD15: 2 | AE15: 5 | AF15: 2 | AG15: Evidence backed
A16: 12 | B16: RayVision Co., Ltd. | C16: 株式会社RayVision | D16: Not found (NTA lookup blocked; dedupe by Japanese name) | E16: Saitama | F16: Kanto | G16: https://rayvision.co.jp/ | H16: Vet flat panel detector maker and seller (vet device notification implied) | I16: Own vet DR; no ultrasound | J16: Companion | K16: Saitama; national via Medical Space and others | L16: Not found | M16: n/a | N16: Not identified | O16: Not identified | P16: Not published; inquiry form: https://rayvision.co.jp/contact/ | Q16: 048 657 2601 | R16: Not identified | S16: Company inquiry only (form) | T16: =SUM(Z16:AF16) -> 23 | U16: V1 | V16: Vet specific DR maker with maintenance support; imaging buyers are the same clinics. | W16: Cross sell: DR plus ultrasound package for new clinics. | X16: Not checked (human list not in v17) | Y16: https://rayvision.co.jp/ ; https://medical-space.co.jp/products/9109/ ; https://rayvision.co.jp/contact/ | Z16: 4 | AA16: 3 | AB16: 5 | AC16: 4 | AD16: 1 | AE16: 3 | AF16: 3 | AG16: Evidence backed
... A60: 56 | B60: Telcom Co., Ltd. | C60: テルコム株式会社 | D60: Not found (NTA lookup blocked; dedupe by Japanese name) | E60: Kanagawa | F60: Kanto | G60: https://www.terucom.co.jp/ | H60: Vet device business (JAMO member) | I60: Not identified | J60: Companion | K60: Yokohama; national | L60: Not found | M60: n/a | N60: Not identified | O60: Not identified | P60: terucom_info@terucom.co.jp | Q60: 045 947 2904 | R60: Not identified | S60: Verified (published on own site, read via search); maker of pet oxygen houses | T60: =SUM(Z60:AF60) -> 17 | U60: V2 | V60: Yokohama member of the vet device association JAMO. FLAG: Product focus not confirmed. | W60: Qualify product focus; possible Kanagawa sub dealer. | X60: Not checked (human list not in v17) | Y60: https://www.jamo.or.jp/member/ ; https://www.terucom.co.jp/company/outline/ | Z60: 3 | AA60: 1 | AB60: 4 | AC60: 3 | AD60: 1 | AE60: 2 | AF60: 3 | AG60: Evidence backed

Sheet Hospital Groups
A1: Hospital Groups: Tier V5 direct end user leads (cap 50)
A2: Companion animal groups and NOSAI livestock clinic networks. NOSAI rows are the large animal (bovine) channel in Hokkaido, Tohoku and Kyushu.
A4: No. | B4: Company (English) | C4: Company (Japanese) | D4: 法人番号 | E4: HQ prefecture | F4: Region | G4: Website | H4: Licences held | I4: Brands carried | J4: Companion / Large animal / Both | K4: Coverage area | L4: Est. revenue or headcount | M4: Number of clinics (Tier V5 only) | N4: Key contact name | O4: Title | P4: Email | Q4: Phone | R4: LinkedIn | S4: Contact confidence | T4: Fit score /35 | U4: Tier | V4: Why they fit | W4: Suggested opening angle | X4: Also in human list (Y/N) | Y4: Source links | Z4: Score: regulatory | AA4: Score: imaging and US | AB4: Score: brand conflict | AC4: Score: companion coverage | AD4: Score: large animal | AE4: Score: service engineers | AF4: Score: openness to CN/KR | AG4: Evidence status
A5: 1 | B5: Homma Veterinary Clinic Group | C5: 本間獣医科医院グループ | D5: Not found (NTA lookup blocked; dedupe by Japanese name) | E5: Shizuoka | F5: Chubu | G5: Not found | H5: End user (animal hospital group) | I5: Not identified | J5: Companion | K5: Shizuoka and overseas | L5: Not found | M5: 40 (AHHD 2021) | N5: Not identified | O5: Not identified | P5: Not published; phone only | Q5: 0538 35 9911 (Iwata main hospital) | R5: Not identified | S5: Company inquiry only (phone); FLAG renamed DCC動物病院 in 2024 | T5: =SUM(Z5:AF5) -> 18 | U5: V5 | V5: Ranked second by hospital count in 2021 with 40 sites. FLAG: Operating entity and current count not confirmed. | W5: Fleet evaluation: 30 day placement in two sites, then a group standard. | X5: Not checked (human list not in v17) | Y5: https://ahhd.jp/I0000003 ; https://dccpets.jp/clinictop/dcc-shimizutorisaka/ | Z5: 1 | AA5: 4 | AB5: 3 | AC5: 5 | AD5: 1 | AE5: 1 | AF5: 3 | AG5: Evidence backed
A6: 2 | B6: Okayama Animal Medical Center Group | C6: 岡山動物医療センターグループ | D6: Not found (NTA lookup blocked; dedupe by Japanese name) | E6: Okayama | F6: Chugoku and Shikoku | G6: https://www.okayama-amc.com/ | H6: End user (animal hospital group) | I6: Not identified | J6: Companion | K6: Okayama, Kurashiki, Takamatsu | L6: Not found | M6: 5 | N6: Not identified | O6: Not identified | P6: Not published; phone only | Q6: 086 246 8100 | R6: Not identified | S6: Company inquiry only (phone) | T6: =SUM(Z6:AF6) -> 18 | U6: V5 | V6: Five hospitals led by an advanced core hospital. | W6: Fleet evaluation: 30 day placement in two sites, then a group standard. | X6: Not checked (human list not in v17) | Y6: https://www.okayama-amc.com/ | Z6: 1 | AA6: 4 | AB6: 3 | AC6: 5 | AD6: 1 | AE6: 1 | AF6: 3 | AG6: Evidence backed
A7: 3 | B7: Doubutsu Byoin Kyoto Co., Ltd. (CUaRE) | C7: どうぶつ病院京都株式会社 | D7: Not found (NTA lookup blocked; dedupe by Japanese name) | E7: Kyoto | F7: Kansai | G7: https://ahk-cuare.com/ | H7: End user (animal hospital group) | I7: Not identified | J7: Companion | K7: Kyoto and Chiba | L7: Not found | M7: 6 | N7: Not identified | O7: Not identified | P7: info@cuareofficial.com | Q7: 075 334 8122 | R7: Not identified | S7: Verified (published on own site, read via search); product business page | T7: =SUM(Z7:AF7) -> 18 | U7: V5 | V7: Six hospitals plus four grooming salons. | W7: Fleet evaluation: 30 day placement in two sites, then a group standard. | X7: Not checked (human list not in v17) | Y7: https://ahk-cuare.com/ ; https://ahk-cuare.com/%E4%BA%8B%E6%A5%AD%E7%B4%B9%E4%BB%8B%E3%83%88%E3%83%83%E3%83%97/%E3%81%A9%E3%81%86%E3%81%B6%E3%81%A4%E7%97%85%E9%99%A2%E4%BA%AC%E9%83%BD%E3%82%B0%E3%83%AB%E3%83%BC%E3%83%97%E4%BA%8B%E6%A5%AD/product%E4%BA%8B%E6%A5%AD/ | Z7: 1 | AA7: 4 | AB7: 3 | AC7: 5 | AD7: 1 | AE7: 1 | AF7: 3 | AG7: Evidence backed
A8: 4 | B8: Elsa Animal Hospital Group (Elsa Kreis) | C8: エルザ動物病院グループ (株式会社エルザクライス) | D8: Not found (NTA lookup blocked; dedupe by Japanese name) | E8: Hyogo | F8: Kansai | G8: https://www.elsa-hp.com | H8: End user (animal hospital group) | I8: Not identified | J8: Companion | K8: Hyogo | L8: Not found | M8: 8 | N8: Not identified | O8: Not identified | P8: Not published; inquiry form: https://www.elsa-hp.com/contact/ | Q8: 079 297 8181 | R8: Not identified | S8: Company inquiry only (form) | T8: =SUM(Z8:AF8) -> 18 | U8: V5 | V8: Eight hospital Hyogo group inside MiraiVets/JPAC. FLAG: Part of MiraiVets/JPAC. | W8: Fleet evaluation: 30 day placement in two sites, then a group standard. | X8: Not checked (human list not in v17) | Y8: https://www.kobe-np.co.jp/info/prtimes/202602/c170012_r8.shtml ; https://www.ondeck.jp/library/interview/20526 ; https://www.elsa-hp.com/contact/ | Z8: 1 | AA8: 4 | AB8: 3 | AC8: 5 | AD8: 1 | AE8: 1 | AF8: 3 | AG8: Evidence backed
A9: 5 | B9: Hazukikai Co., Ltd. | C9: 株式会社葉月会 | D9: Not found (NTA lookup blocked; dedupe by Japanese name) | E9: Osaka | F9: Kansai | G9: https://hadukikai.co.jp/ | H9: End user (animal hospital group) | I9: Not identified | J9: Companion | K9: North Osaka and East Hyogo | L9: Not found | M9: 100 plus participating hospitals | N9: Not identified | O9: Not identified | P9: Not published; phone only | Q9: 072 730 8200 | R9: Not identified | S9: Company inquiry only (phone) | T9: =SUM(Z9:AF9) -> 18 | U9: V5 | V9: Network of more than 100 animal hospitals in North Osaka and East Hyogo (Nishinomiya, Amagasaki, Takarazuka). FLAG: A cooperative network, not one owner; purchasing may be per hospital. HQ prefecture assumed Osaka. | W9: Fleet evaluation: 30 day placement in two sites, then a group standard. | X9: Not checked (human list not in v17) | Y9: https://hadukikai.co.jp/group_hosp/hyougo/ ; https://hadukikai.co.jp/info/ | Z9: 1 | AA9: 4 | AB9: 3 | AC9: 5 | AD9: 1 | AE9: 1 | AF9: 3 | AG9: Evidence backed
A10: 6 | B10: Junishikai Co., Ltd. (Osaka Night Emergency) | C10: 株式会社十二志会 | D10: Not found (NTA lookup blocked; dedupe by Japanese name) | E10: Osaka | F10: Kansai | G10: https://doubutsuyakan.jp | H10: End user (animal hospital group) | I10: Not identified | J10: Companion | K10: Osaka | L10: Not found | M10: Night ER owned by member hospitals | N10: Not identified | O10: Not identified | P10: Not published; phone only | Q10: 06 4259 1212 | R10: Not identified | S10: Company inquiry only (phone) | T10: =SUM(Z10:AF10) -> 18 | U10: V5 | V10: Shareholder hospitals jointly run Osaka's night emergency centre; ER is a point of care ultrasound use case. | W10: Fleet evaluation: 30 day placement in two sites, then a group standard. | X10: Not checked (human list not in v17) | Y10: https://doubutsuyakan.jp/about.html | Z10: 1 | AA10: 4 | AB10: 3 | AC10: 5 | AD10: 1 | AE10: 1 | AF10: 3 | AG10: Evidence backed
A11: 7 | B11: WOLVES HAND Co., Ltd. | C11: 株式会社WOLVES HAND | D11: Not found (NTA lookup blocked; dedupe by Japanese name) | E11: Osaka | F11: Kansai | G11: https://wolveshand.jp/ | H11: End user (animal hospital group) | I11: Not identified | J11: Companion | K11: Kansai, Kanto, Okinawa | L11: Not found | M11: 29 (AHHD 2021) incl. 9 in Osaka | N11: Not identified | O11: Not identified | P11: Not published; inquiry form: https://wolveshand.jp/ir/ | Q11: 06 6599 9106 | R11: Not identified | S11: Company inquiry only (form) | T11: =SUM(Z11:AF11) -> 18 | U11: V5 | V11: Listed group (EDINET filer) with Osaka as its largest cluster. | W11: Fleet evaluation: 30 day placement in two sites, then a group standard. | X11: Not checked (human list not in v17) | Y11: https://ahhd.jp/I0000003 ; https://edinetdb.jp/company/E39640/text?fy=2024 ; https://wolveshand.jp/ir/ | Z11: 1 | AA11: 4 | AB11: 3 | AC11: 5 | AD11: 1 | AE11: 1 | AF11: 3 | AG11: Evidence backed
A12: 8 | B12: ALLONE Animal Hospital Group (FOR Inc.) | C12: ALLONE動物病院グループ (株式会社FOR) | D12: Not found (NTA lookup blocked; dedupe by Japanese name) | E12: Tokyo | F12: Kanto | G12: https://allone-ah.co.jp | H12: End user (animal hospital group) | I12: Not identified | J12: Companion | K12: Tokyo and Kanagawa | L12: Not found | M12: 6 to 7 | N12: Not identified | O12: Not identified | P12: info@allone-ah.co.jp | Q12: Not found (use site) | R12: Not identified | S12: Verified (published on own site, read via search); published in site terms for link requests, ask to forward | T12: =SUM(Z12:AF12) -> 18 | U12: V5 | V12: Young group (2017) growing across Tokyo and Kanagawa. | W12: Fleet evaluation: 30 day placement in two sites, then a group standard. | X12: Not checked (human list not in v17) | Y12: https://allone-ah.co.jp/company ; https://allone-ah.co.jp/terms ; https://allone-ah.co.jp/contact | Z12: 1 | AA12: 4 | AB12: 3 | AC12: 5 | AD12: 1 | AE12: 1 | AF12: 3 | AG12: Evidence backed
A13: 9 | B13: Ai Animal Medical Center Group | C13: アイ動物医療センターグループ | D13: Not found (NTA lookup blocked; dedupe by Japanese name) | E13: Ibaraki | F13: Kanto | G13: https://www.aitom.jp/ | H13: End user (animal hospital group) | I13: Not identified | J13: Companion | K13: Ibaraki | L13: Not found | M13: 6 | N13: Not identified | O13: Not identified | P13: Not published; phone only | Q13: 0293 24 3535 (Takahagi main) | R13: Not identified | S13: Company inquiry only (phone) | T13: =SUM(Z13:AF13) -> 18 | U13: V5 | V13: Six hospital Ibaraki group offering advanced care. FLAG: Part of MiraiVets/JPAC. | W13: Fleet evaluation: 30 day placement in two sites, then a group standard. | X13: Not checked (human list not in v17) | Y13: https://www.aitom.jp/about/ ; https://www.ondeck.jp/library/interview/20468 | Z13: 1 | AA13: 4 | AB13: 3 | AC13: 5 | AD13: 1 | AE13: 1 | AF13: 3 | AG13: Evidence backed
A14: 10 | B14: Anicom Senshin Iryo Kenkyusho / Anicom Pafe | C14: アニコム先進医療研究所株式会社 / アニコム パフェ株式会社 | D14: Not found (NTA lookup blocked; dedupe by Japanese name) | E14: Tokyo | F14: Kanto | G14: https://www.anicom-pafe.com | H14: End user (animal hospital group) | I14: Not identified | J14: Companion | K14: National | L14: Not found | M14: 17 (2021); Anicom group runs 50 plus | N14: Not identified | O14: Not identified | P14: Not published; inquiry form: https://www.anicom-pafe.com/inquiry.html | Q14: 0570 09 1212 (opening support) | R14: Not identified | S14: Company inquiry only (form) | T14: =SUM(Z14:AF14) -> 18 | U14: V5 | V14: Insurer owned hospital network plus a clinic opening support arm. | W14: Fleet evaluation: 30 day placement in two sites, then a group standard. | X14: Not checked (human list not in v17) | Y14: https://ahhd.jp/I0000003 ; https://www.anicom-pafe.com/hospital/openingsupport.html ; https://www.anicom-pafe.com/inquiry.html | Z14: 1 | AA14: 4 | AB14: 3 | AC14: 5 | AD14: 1 | AE14: 1 | AF14: 3 | AG14: Evidence backed
A15: 11 | B15: Fanimedic Animal Medical Group | C15: ファニメディック動物医療グループ | D15: Not found (NTA lookup blocked; dedupe by Japanese name) | E15: Chiba | F15: Kanto | G15: https://www.fanimedic-ah.com | H15: End user (animal hospital group) | I15: Not identified | J15: Companion | K15: Chiba, Tokyo, Saitama | L15: Not found | M15: About 20 | N15: Not identified | O15: Not identified | P15: Not published; inquiry form: https://www.fanimedic.com/about-us.php | Q15: 04 7158 9722 (management office) | R15: Not identified | S15: Company inquiry only (form) | T15: =SUM(Z15:AF15) -> 18 | U15: V5 | V15: About 20 hospitals incl. three advanced centres. | W15: Fleet evaluation: 30 day placement in two sites, then a group standard. | X15: Not checked (human list not in v17) | Y15: https://www.fanimedic-ah.com/group-hospitals/ ; https://www.fanimedic.com/about-us.php | Z15: 1 | AA15: 4 | AB15: 3 | AC15: 5 | AD15: 1 | AE15: 1 | AF15: 3 | AG15: Evidence backed
A16: 12 | B16: Inagaki Animal Hospital | C16: いながき動物病院 | D16: Not found (NTA lookup blocked; dedupe by Japanese name) | E16: Saitama | F16: Kanto | G16: https://inagakiah.com/ | H16: End user (animal hospital group) | I16: Not identified | J16: Companion | K16: Saitama, Gunma, Chiba, Ibaraki | L16: Not found | M16: 6 plus (Koshigaya main and branches) | N16: Not identified | O16: Not identified | P16: Not published; inquiry form: https://inagakiah.com/contact/ | Q16: 080 7715 7321 | R16: Not identified | S16: Company inquiry only (form) | T16: =SUM(Z16:AF16) -> 18 | U16: V5 | V16: Multi branch TNR focused group across North Kanto. | W16: Fleet evaluation: 30 day placement in two sites, then a group standard. | X16: Not checked (human list not in v17) | Y16: https://inagakiah.com/ ; https://inagakiah.com/contact/ | Z16: 1 | AA16: 4 | AB16: 3 | AC16: 5 | AD16: 1 | AE16: 1 | AF16: 3 | AG16: Evidence backed
... A54: 50 | B54: Total Herd Management Service Co., Ltd. | C54: 株式会社トータルハードマネージメントサービス | D54: Not found (NTA lookup blocked; dedupe by Japanese name) | E54: Hokkaido | F54: Tohoku and Hokkaido | G54: https://www.thms.jp | H54: End user (livestock clinic network) | I54: Not identified | J54: Large animal | K54: Dairy farms | L54: Not found | M54: Herd health team | N54: Not identified | O54: Not identified | P54: Not published; inquiry form: https://www.thms.jp/contact/ | Q54: 0153 75 6589 | R54: Not identified | S54: Company inquiry only (form); HQ Betsukai, Hokkaido | T54: =SUM(Z54:AF54) -> 18 | U54: V5 | V54: Dairy herd health service whose vets run routine repro (pregnancy) checks. FLAG: HQ not confirmed. | W54: Field trial of a rugged livestock portable (EBit 50) with clinic vets during pregnancy checks. | X54: Not checked (human list not in v17) | Y54: https://www.thms.jp/service/juuika/breeding/hanshokukenshin/ ; https://www.thms.jp/contact/ | Z54: 1 | AA54: 4 | AB54: 3 | AC54: 1 | AD54: 5 | AE54: 1 | AF54: 3 | AG54: Evidence backed

Sheet By Region
A1: Lead count by region against minimum quota
A3: Region | B3: Quota (minimum) | C3: Rows in Master List | D3: Gap to quota | E3: Evidence backed | F3: Qualify first | G3: Status
A4: Kanto | B4: 80 | C4: =COUNTIF('Master List'!F:F,A4) -> 87 | D4: =C4-B4 -> 7 | E4: =COUNTIFS('Master List'!F:F,A4,'Master List'!AG:AG,"Evidence backed") -> 66 | F4: =COUNTIFS('Master List'!F:F,A4,'Master List'!AG:AG,"Qualify first") -> 21 | G4: Met
A5: Kansai | B5: 50 | C5: =COUNTIF('Master List'!F:F,A5) -> 47 | D5: =C5-B5 -> -3 | E5: =COUNTIFS('Master List'!F:F,A5,'Master List'!AG:AG,"Evidence backed") -> 21 | F5: =COUNTIFS('Master List'!F:F,A5,'Master List'!AG:AG,"Qualify first") -> 26 | G5: SHORT by 3
A6: Chubu | B6: 38 | C6: =COUNTIF('Master List'!F:F,A6) -> 40 | D6: =C6-B6 -> 2 | E6: =COUNTIFS('Master List'!F:F,A6,'Master List'!AG:AG,"Evidence backed") -> 13 | F6: =COUNTIFS('Master List'!F:F,A6,'Master List'!AG:AG,"Qualify first") -> 27 | G6: Met
A7: Kyushu and Okinawa | B7: 30 | C7: =COUNTIF('Master List'!F:F,A7) -> 33 | D7: =C7-B7 -> 3 | E7: =COUNTIFS('Master List'!F:F,A7,'Master List'!AG:AG,"Evidence backed") -> 15 | F7: =COUNTIFS('Master List'!F:F,A7,'Master List'!AG:AG,"Qualify first") -> 18 | G7: Met
A8: Tohoku and Hokkaido | B8: 28 | C8: =COUNTIF('Master List'!F:F,A8) -> 30 | D8: =C8-B8 -> 2 | E8: =COUNTIFS('Master List'!F:F,A8,'Master List'!AG:AG,"Evidence backed") -> 12 | F8: =COUNTIFS('Master List'!F:F,A8,'Master List'!AG:AG,"Qualify first") -> 18 | G8: Met
A9: Chugoku and Shikoku | B9: 24 | C9: =COUNTIF('Master List'!F:F,A9) -> 22 | D9: =C9-B9 -> -2 | E9: =COUNTIFS('Master List'!F:F,A9,'Master List'!AG:AG,"Evidence backed") -> 12 | F9: =COUNTIFS('Master List'!F:F,A9,'Master List'!AG:AG,"Qualify first") -> 10 | G9: SHORT by 2
A10: Not confirmed | B10: n/a | C10: =COUNTIF('Master List'!F:F,A10) -> 0 | D10: n/a | E10: =COUNTIFS('Master List'!F:F,A10,'Master List'!AG:AG,"Evidence backed") -> 0 | F10: =COUNTIFS('Master List'!F:F,A10,'Master List'!AG:AG,"Qualify first") -> 0 | G10: HQ prefecture not confirmed
A11: Total | B11: =SUM(B4:B9) -> 250 | C11: =SUM(C4:C10) -> 259 | E11: =SUM(E4:E10) -> 139 | F11: =SUM(F4:F10) -> 120
A13: Region definitions: Kanto = Tokyo, Kanagawa, Saitama, Chiba, Ibaraki, Tochigi, Gunma. Kansai = Osaka, Kyoto, Hyogo, Nara, Shiga, Wakayama, Mie. Chubu = Aichi, Shizuoka, Gifu, Nagano, Yamanashi, Niigata, Toyama, Ishikawa, Fukui. Chugoku and Shikoku = Tottori, Shimane, Okayama, Hiroshima, Yamaguchi, Tokushima, Kagawa, Ehime, Kochi.

Sheet Summary
A1: Summary
A3: Totals by tier
A4: Tier | B4: Definition | C4: Rows | D4: Evidence backed | E4: Qualify first
A5: V1 | B5: Vet imaging or equipment business holding 動物用医療機器 製造販売業許可 (can import and hold approvals) | C5: =COUNTIF('Master List'!U:U,A5) -> 35 | D5: =COUNTIFS('Master List'!U:U,A5,'Master List'!AG:AG,"Evidence backed") -> 35 | E5: =COUNTIFS('Master List'!U:U,A5,'Master List'!AG:AG,"Qualify first") -> 0
A6: V2 | B6: Vet equipment dealer with 動物用医療機器 販売業 licence or vet sales, no 製造販売業許可 found | C6: =COUNTIF('Master List'!U:U,A6) -> 21 | D6: =COUNTIFS('Master List'!U:U,A6,'Master List'!AG:AG,"Evidence backed") -> 21 | E6: =COUNTIFS('Master List'!U:U,A6,'Master List'!AG:AG,"Qualify first") -> 0
A7: V3 | B7: Vet drug wholesaler (動物用医薬品卸) with equipment sales potential | C7: =COUNTIF('Master List'!U:U,A7) -> 28 | D7: =COUNTIFS('Master List'!U:U,A7,'Master List'!AG:AG,"Evidence backed") -> 28 | E7: =COUNTIFS('Master List'!U:U,A7,'Master List'!AG:AG,"Qualify first") -> 0
A8: V4 | B8: Human medical equipment dealer that also sells, or may sell, to animal hospitals | C8: =COUNTIF('Master List'!U:U,A8) -> 125 | D8: =COUNTIFS('Master List'!U:U,A8,'Master List'!AG:AG,"Evidence backed") -> 5 | E8: =COUNTIFS('Master List'!U:U,A8,'Master List'!AG:AG,"Qualify first") -> 120
A9: V5 | B9: Multi site animal hospital group or livestock clinic network (direct end user; max 50) | C9: =COUNTIF('Master List'!U:U,A9) -> 50 | D9: =COUNTIFS('Master List'!U:U,A9,'Master List'!AG:AG,"Evidence backed") -> 50 | E9: =COUNTIFS('Master List'!U:U,A9,'Master List'!AG:AG,"Qualify first") -> 0
A10: Total | C10: =SUM(C5:C9) -> 259
A12: Totals by region: see the 'By Region' sheet (quota check).
A13: Kanto | B13: Quota 80 | C13: =COUNTIF('Master List'!F:F,A13) -> 87
A14: Kansai | B14: Quota 50 | C14: =COUNTIF('Master List'!F:F,A14) -> 47
A15: Chubu | B15: Quota 38 | C15: =COUNTIF('Master List'!F:F,A15) -> 40
A16: Kyushu and Okinawa | B16: Quota 30 | C16: =COUNTIF('Master List'!F:F,A16) -> 33
A17: Tohoku and Hokkaido | B17: Quota 28 | C17: =COUNTIF('Master List'!F:F,A17) -> 30
A18: Chugoku and Shikoku | B18: Quota 24 | C18: =COUNTIF('Master List'!F:F,A18) -> 22
A19: Not confirmed | B19: Quota n/a | C19: =COUNTIF('Master List'!F:F,A19) -> 0
A21: Email and contact coverage
A22: Published email, Verified (own site) | C22: 31
A23: Published email, Likely (third party listing) | C23: 15
A24: No email published; inquiry form | C24: 54
A25: No email published; phone only | C25: 89
A26: Not searched yet (search budget; all are V4 qualify first) | C26: 70
A28: Top 15 to approach first
A29: Rank | B29: Company | C29: Tier | D29: Region | E29: Fit /35 | F29: Why first
A30: 1 | B30: Central Scientific Commerce, Inc. / セントラル科学貿易株式会社 | C30: V1 | D30: Kanto | E30: 26 | F30: Already imports a Chinese vet imaging brand (AOHUA), which shows openness to Chinese manufacturers and a working NVAL route.
A31: 2 | B31: ARKRAY, Inc. (Veterinary) / アークレイ株式会社 (アークレイファクトリー) | C31: V1 | D31: Kansai | E31: 25 | F31: Runs a dedicated vet brand (Think Animal) and exhibits at JBVP; national animal hospital coverage and service.
A32: 3 | B32: Olympus Marketing, Inc. (Animal Medical) / オリンパスマーケティング株式会社 | C32: V1 | D32: Kanto | E32: 25 | F32: Runs a dedicated animal endoscopy business with national service engineers; imaging culture and hospital relationships.
A33: 4 | B33: T&S Co., Ltd. / 株式会社ティーアンドエス | C33: V1 | D33: Kanto | E33: 24 | F33: Domestic X ray maker with a vet approval; imaging focused and unconflicted on ultrasound.
A34: 5 | B34: Atol Co., Ltd. / 株式会社アトル | C34: V3 | D34: Kyushu and Okinawa | E34: 23 | F34: Fukuoka based wholesaler listed among Japan's animal drug wholesalers; Kyushu livestock and companion coverage.
A35: 6 | B35: Metran Co., Ltd. / 株式会社メトラン | C35: V1 | D35: Kanto | E35: 23 | F35: Vet ventilator pioneer (since 1984) that already notifies vet devices with NVAL and imports monitors; natural MAH partner for ICU and anaesthesia adjacent imaging.
A36: 7 | B36: Nagasaki Juiyakuhin Co., Ltd. / 長崎獣医薬品株式会社 | C36: V3 | D36: Kyushu and Okinawa | E36: 23 | F36: Nagasaki vet drug wholesaler (JADIDA Kyushu block).
A37: 8 | B37: RayVision Co., Ltd. / 株式会社RayVision | C37: V1 | D37: Kanto | E37: 23 | F37: Vet specific DR maker with maintenance support; imaging buyers are the same clinics.
A38: 9 | B38: TOP Corporation (Veterinary Division) / 株式会社トップ | C38: V1 | D38: Kanto | E38: 23 | F38: Human device maker with a dedicated vet division since 2002 and several MAFF approved vet pumps; national sales footprint into animal hospitals.
A39: 10 | B39: Taishodo Co., Ltd. / 株式会社大正堂 | C39: V3 | D39: Kanto | E39: 23 | F39: JADIDA member with a Hokkaido division in Obihiro, the heart of Tokachi dairy, plus a Gunma office.
A40: 11 | B40: Acti Co., Ltd. / アクティ株式会社 | C40: V3 | D40: Chubu | E40: 22 | F40: Regional vet drug wholesaler named in Fuji Keizai's 2025 vet dealer ranking study.
A41: 12 | B41: Chubu Kasei Yakuhin Co., Ltd. / 中部化成薬品株式会社 | C41: V3 | D41: Chubu | E41: 22 | F41: Gifu JADIDA member.
... A44: 15 | B44: Hikari Sakamoto Co., Ltd. / ヒカリサカモト株式会社 | C44: V3 | D44: Chugoku and Shikoku | E44: 22 | F44: Hiroshima JADIDA member with a Yamaguchi office.

Sheet Sources
A1: Sources used
A2: Every URL cited in the Master List, with the rows that cite it. All were reached through web search results; direct page fetch was blocked in this session, so pages were not opened.
A4: # | B4: Source URL | C4: Rows citing it (Master List No.) | D4: Count
A5: 1 | B5: https://www.maff.go.jp/j/keiei/nogyohoken/contact.html | C5: 213, 214, 216, 217, 218, 235, 236, 237, 245, 248, 249, 255 | D5: 12
A6: 2 | B6: https://www.jamo.or.jp/member/ | C6: 32, 37, 39, 43, 44, 46, 49, 56, 87 | D6: 9
A7: 3 | B7: https://jadida.or.jp/doc/KaiinList20250822.pdf | C7: 65, 66, 67, 68, 69, 70, 74, 76, 82 | D7: 9
A8: 4 | B8: https://jadida.or.jp/doc/KaiinList20250401.pdf | C8: 57, 62, 63, 70, 72, 76, 80, 81 | D8: 8
A9: 5 | B9: https://www.jadida.or.jp/doc/KaiinList20241001.pdf | C9: 64, 68, 71, 73, 77, 79, 83, 84 | D9: 8
A10: 6 | B10: https://www.nosai.or.jp/nosai_kasou/nosai_kakuchi01.html | C10: 212, 214, 216, 217, 235, 237, 249 | D10: 7
A11: 7 | B11: https://news.jprpet.com/company/list/174/ | C11: 58, 61, 63, 73, 75, 79 | D11: 6
A12: 8 | B12: https://baseconnect.in/companies/prefecture/63038c5a-e328-472b-b9cc-039738609ba7/category/b2358a1c-c4c6-46f4-a0b1-dee3a1b30a0b | C12: 93, 135, 137, 138, 141, 156 | D12: 6
A13: 9 | B13: https://www.fukuda.co.jp/company/lt/lt_area05.html | C13: 126, 127, 129, 130, 132, 133 | D13: 6
A14: 10 | B14: https://note.com/arrows_column/n/nd4fd35a1d8b1 | C14: 86, 97, 123, 150, 182 | D14: 5
A15: 11 | B15: https://tohoku-ikihan.com/memberlist_category/iwate/ | C15: 199, 202, 203, 205, 209 | D15: 5
A16: 12 | B16: https://ahhd.jp/I0000004 | C16: 19, 25, 27, 28 | D16: 4
... A369: 365 | B369: https://animal-99.com/contact_form.html | C369: 259 | D369: 1
