Workbook

Sheet Read Me
A1: CHISON Ultrasound: Radiology and Vet Event Plan | Singapore, Taiwan, South Korea, Japan | Dec 2026 to Dec 2027
A2: Version 1, prepared 25 Oct 2026 for Casper Tan, Senior Regional Sales Manager and Manager KOL Engagement, AstraMed (CHISON Medical Technologies)
A4: WHAT THIS WORKBOOK DOES
A5: Objective | B5: Find radiology and vet events in Singapore, Taiwan, South Korea and Japan from Dec 2026 to Dec 2027 to recruit distributors, raise CHISON ultrasound publicity and support your KOL engagement.
A6: Tabs | B6: Coverage Summary (counts versus your targets, live formulas) | Next 60 Days (events starting soon, live Days Left) | Diagnostics Events | Vet Events | Competitor and Dealer Intel.
A7: Competitor columns | B7: Each event row shows which competitors (SonoScape, Mindray, Samsung, Philips, GE and others) are present or expected, and how strong the evidence is. Local dealers of competitors are listed where found.
A8: Format notes | B8: Dates are real Excel dates where the organiser has published them. TBC rows show only the month pattern from the last edition. No future date has been invented.
A10: THE THREE EVENTS TO COMMIT TO FIRST
A11: 1. JRC 2027 with ITEM 2027 (Japan, imaging) | B11: 15 to 18 Apr 2027, Pacifico Yokohama. Japan's biggest imaging floor and radiology KOL meeting in one place (ITEM 2026: 153 exhibitors, 18,180 visitors). Siemens, Canon, Fujifilm and GE were seen at recent editions. Cost: not published (JIRA sets terms). Deadline: ITEM exhibitor window not found, so ask JIRA by end of November.
A12: 2. KIMES 2027 (Korea, dealers) | B12: 18 to 21 Mar 2027, COEX Seoul. Korea's #1 medtech show and the best floor for importer and dealer recruitment. Samsung Medison and GE HealthCare were confirmed at KIMES 2026. Cost: not published. Deadline: booth form not published, so ask Korea E and Ex in November for the early bird rate.
A13: 3. JCVIM 2027 (Japan, vet) | B13: 19 to 21 Feb 2027, Pacifico Yokohama North. The only vet event on this list with a documented sponsorship path (sponsor recruitment opened 7 Jul 2026). Fujifilm VET Systems exhibited at the last three editions. Cost: tiers on smartconf.jp, fees not retrieved. Deadline: closing date not stated, so assume it is close and ask this month.
A15: COUNTRY ANCHOR EVENTS
A16: Singapore | B16: SGCR WIRES 2027 with the 14th Asian Congress of Abdominal Radiology, 19 to 22 Aug 2027 (venue to be announced). Vet: confirm Singapore Vet Show dates with CloserStill.
A17: Taiwan | B17: Visit Healthcare+ Expo Taiwan 3 to 6 Dec 2026 as a buyer, then target SUMROC 2027 and TAOG 2027 (both TBC). Vet: AiCVS and AiCVIM Joint Congress, Kaohsiung, 12 to 13 Dec 2026.
A18: South Korea | B18: KIMES 2027 (18 to 21 Mar), KSUM 2027 (May, TBC), KCR 2027 (22 to 25 Sep). Vet: 24th KAHA Conference, COEX Magok, 4 to 6 Jun 2027. Samsung Medison has a training partnership with KAHA.
A19: Japan | B19: JRC and ITEM (15 to 18 Apr), JSUM 100th (28 to 30 May), JSS 52nd (19 to 20 Jun), Medical Japan Osaka (29 Sep to 1 Oct). Vet: JCVIM (Feb), WJVF (31 Jul to 1 Aug), JBVP Annual (25 to 26 Sep).
A21: DO THIS IN THE NEXT 30 DAYS
A22: 1 | B22: Korea vet: ask KVECCS for a scanner slot in the POCUS practical at its seminar on 4 to 6 Dec 2026.
A23: 2 | B23: Korea: ask the Korean Association of Clinical Ultrasound about lending scanners to the ISCU 2026 Hands On School, 5 to 6 Dec 2026, COEX Magok.
A24: 3 | B24: Taiwan vet: contact the AiCVS and AiCVIM organisers (aicvs-aicvim2026.tw) about sponsor or imaging session space, event on 12 to 13 Dec 2026 in Kaohsiung.
A25: 4 | B25: Japan vet: ask the JSVDI secretariat if exhibit space remains for 5 to 6 Dec 2026, Fukuoka.
A26: 5 | B26: Taiwan: plan one Kaohsiung trip for 11 to 14 Dec 2026 (Chanchao Pets Show plus AiCVS and AiCVIM), and Taipei for Healthcare+ Expo on 3 to 6 Dec 2026.
A27: 6 | B27: Japan vet: open smartconf.jp/content/jcvim2027/sponsorship and request the sponsor tier list.
A28: 7 | B28: Request 2027 exhibitor guides and prices from: JIRA (ITEM), Korea E and Ex (KIMES), JSUM secretariat, JSS secretariat, CloserStill (Singapore Vet Show), SUMROC, TAOG, KAHA.
A29: 8 | B29: If your diary allows, SUMROC 2026 runs 31 Oct to 1 Nov in Taipei (6 days away, before the window). GE HealthCare Ultrasound, Alpinion and Rotary (Canon agent) support it.
A31: COMPETITOR HEADLINES
A32: Samsung in Korea vet | B32: Samsung Medison signed an MoU with the Korean Animal Hospital Association (KAHA) in Feb 2026 to build a nationwide Samsung Sono VET Academy ultrasound training network, including a KAHA STARTER basic ultrasound course. Expect a strong Samsung presence at KAHA events. The MoU names no event, so attendance at a specific event is not confirmed.
A33: Fujifilm in Japan | B33: Fujifilm (including Fujifilm VET Systems) is the benchmark: luncheon seminar at JSUM 2026, booth at ITEM 2026, exhibition and luncheon seminars at JCVIM 2024 to 2026 and JBVP 2025.
A34: Japan vet dealers | B34: Shoei Japan is the Japan importer for SonoScape vet models (S6V, A6V, X5V, E2V) and Mindray 6600vet. Mediark, Canon Medtech Supply and Frontier International (livestock) also sell vet ultrasound.
A35: Taiwan vet dealers | B35: Uni Soar (GE vet series), Soarmed (VINNO), Eastech (Esaote) and Getech (Philips cardiac) carry other brands, per their websites. No Taiwan vet distributor for Mindray, Samsung or SonoScape was found.
A36: Taiwan human ultrasound | B36: The SUMROC 2026 annual meeting page shows GE HealthCare Ultrasound, Alpinion and Rotary Trading (Canon Medical agent) logos. ASUS and Daikso showed handheld ultrasound at Healthcare+ Expo 2025.
A37: Korea human ultrasound | B37: KIMES 2026: Samsung Medison and GE HealthCare booths confirmed. KSUM 2026: Canon Medical Korea ran a luncheon symposium. KCR 2026: GE HealthCare ran a luncheon symposium.
A38: Mindray and SonoScape | B38: No public evidence was found of either company exhibiting at the human ultrasound congresses checked in the four markets. Absence in search results is not proof, so check each organiser's exhibitor list.
A40: HOW TO READ THE EVENT TABS
A41: Priority | B41: P1 = must attend: top KOL congress or #1 trade show for the market, with an open vendor path or competitors present. P2 = strong value for a specific specialty. P3 = optional, attend if already in town or a deal requires it.
A42: Segment | B42: Diagnostics (blue), Vet (green), Both (yellow). Both marks general medtech shows where vet distributors also walk the floor. They appear on both tabs and are counted on both.
A43: Date Class | B43: Confirmed = the organiser's own page shows the date (the venue may still be pending). Provisional = a media report or single third party source, an organiser page I could not read directly, conflicting sources, or an unclear listing. TBC = the organiser has not published 2027, and the row shows the last edition's pattern only.
A44: Competitor Evidence | B44: Confirmed = a press release, organiser page or sponsor logo was found for that edition. Partly confirmed = some brands confirmed, others not. Likely = normal for this type of event but not seen. Unverified = no information, and the competitor column then starts with Expected, not verified. Gap (Competitor and Dealer Intel tab only) = searched and nothing found.
A45: KOL and Dealer potential | B45: High, Medium or Low is my judgement of realistic payoff for CHISON, not the prestige of the event.
A46: Cost Info | B46: Exhibitor prices are almost never published. Where blank, request the exhibitor guide from the organiser.
A48: HONEST GAPS AND CAVEATS
A49: Counts include optional events | B49: Counts include P3 optional events, consumer pet shows (Interpets, MEGAZOO, Chanchao, PetExpo, SG Pet Festival) and general medtech shows (Segment = Both). Pet shows are listed because you asked for 10 per country and specialist vet events are scarce, but they are not clinical. The Coverage Summary shows clinical only counts and P1 plus P2 counts so you can see the real number worth a trip. At the time of writing, clinical vet events (no pet or general shows) number about 5 in Singapore, 4 in Taiwan, 9 in South Korea and 19 in Japan.
A50: Singapore vet is short | B50: Only 7 genuine Singapore vet entries were found (target 10). Singapore has one trade focused vet show, two consumer pet expos and a few ultrasound courses. Aggregator listings of generic Singapore vet symposia were checked and excluded as low credibility.
A51: Many 2027 dates are TBC | B51: Societies publish 2027 dates in 2027. Rows marked TBC show the 2026 pattern. Re check each in January and April 2027.
A52: Competitor evidence is thin | B52: Exhibitor lists for 2027 do not exist yet, and many 2026 lists could not be read. Where only the type of event suggests a competitor, the row says Likely or Unverified.
A53: Conflicting sources | B53: JOA 100th: organiser site says 13 to 16 May 2027 Yokohama, one JOA PDF says 15 to 16 Jul 2027 Sapporo. PetExpo Singapore: official site 9 to 11 Apr, some listings 2 to 4 Apr. Singapore Vet Show: organiser says dates TBC, a third party lists 24 to 25 Oct 2026. Busan and Yeongnam vet conference merger: Daegu or Busan Haeundae.
A54: Date read from a search summary | B54: kimes.kr, radiology.or.kr, rsroc.org.tw and expo.taiwan-healthcare.org returned no usable text to my fetch. The KIMES 2027, KCR 2027 and ASCI TRC 2027 dates were read from search extracts of those official pages (KIMES and ASCI TRC are marked Provisional for that reason). A reviewer confirmed the KCR 2027 dates directly on radiology.or.kr, but its venue text is garbled. JBVP dates come from search summaries because jbvp.org blocked my fetch. Re check these on the organiser sites before booking.
A55: Left out on purpose | B55: Medical Fair Asia 2027: an aggregator lists 1 to 3 Sep 2027, but the organiser page shows only the 2026 edition (9 to 11 Sep 2026) and the show has run every second year. Treat as 2028 until the organiser says otherwise. Third party calendars (showsbee, eventseye, 10times) were used to find events, never as proof of a date.
A56: Not covered | B56: KOL name directory and detailed product fit per event. Ask for a v2 with KOL names pulled from congress presidents and course chairs.
A57: Singapore Vet Show 2026 | B57: The organiser page says new dates are to be confirmed, but a third party lists 24 to 25 Oct 2026, which is this weekend. If it is running, visit it in person and check its 2027 plans.
A58: Research date | B58: Built on 25 Oct 2026 from organiser pages, press releases and search, then checked by an independent review pass. Verify before booking travel.
A60: JUST BEFORE THE WINDOW (FOR AWARENESS, NOT COUNTED)
A61: 31 Oct to 1 Nov 2026 | B61: SUMROC Annual Meeting and 8th Asia Pacific Forum, Taipei International Convention Center.
A62: 1 to 3 Nov 2026 | B62: Korean Society of Veterinary Science autumn meeting with East Asia joint symposium, Jeju ICC.
A63: 5 to 7 Nov 2026 | B63: JDDW 2026, Kobe Convention Center.
A64: 7 to 8 Nov 2026 | B64: Gyeonggi North Veterinary Conference with veterinary cardiology society, KINTEX Ilsan.
A65: 13 to 14 Nov 2026 | B65: KSOG autumn congress, Seoul.
A66: 18 to 20 Nov 2026 | B66: HOSPEX Japan 2026, Tokyo Big Sight West 2.
A67: 20 to 22 Nov 2026 | B67: MEGAZOO 2026 Season 2, KINTEX Ilsan.
A69: VET ALTERNATIVES OUTSIDE THE FOUR MARKETS (NOT COUNTED)
A70: 27 to 29 Jan 2027 | B70: FAVA Congress 2027 (24th), Subic Bay, Philippines. Federation of Asian Veterinary Associations.
A71: 5 to 7 Nov 2027 | B71: WSAVA World Congress 2027, Yashobhoomi, New Delhi, India. Includes large vet equipment exhibition.
A73: KEY SOURCES
A74: Japan | B74: jsum.or.jp calendar, radiology.jp and convention.co.jp (JRS), congre.co.jp (JCS, JSOG, JOA), jse.gr.jp, c-lef.co.jp (JSS), jddw.jp, jbvp.org (via search), jcvim.org, jsvas.net, jsvdi.com, interpets.jp.messefrankfurt.com, medical-jpn.jp, noma-hs.com.
A75: South Korea | B75: ksecho.org, iscu.or.kr, kimes.kr, radiology.or.kr, 2026.ksum.or.kr, khospital.org, ksog.org, circulation.or.kr, dailyvet.co.kr, koreabiomed.com, megazoo.co.kr, svma.or.kr.
A76: Taiwan | B76: expo.taiwan-healthcare.org, medicaltaiwan.com.tw, rsroc.org.tw, sumroc.org.tw, taog.org.tw, tsoc.org.tw, anesth.org.tw, aicvs-aicvim2026.tw, chanchao.com.tw, tcvs.tw, tavim.org, tpvma.org.tw.
A77: Singapore | B77: sgcr-wires.com, shbc.com.sg, nhcs.com.sg, ssr.org.sg, sua.sg, nysora.com, singhealthacademy.edu.sg, vetshow.com, petexposg.com, sgpetfestival.com, sva.org.sg.

Sheet Coverage Summary
A1: Coverage against your target (live formulas, they update when you edit the event tabs)
A3: Diagnostics and radiology events (sheet: Diagnostics Events)
A4: Country | B4: Target | C4: Listed | D4: Clinical or specialist events only (excl. general shows and pet shows) | E4: General medtech shows (Both) | F4: Pet industry shows | G4: Date Confirmed | H4: Date Provisional (verify) | I4: Date TBC (annual pattern) | J4: P1 | K4: P2 | L4: P3 | M4: Worth a trip (P1 plus P2) | N4: Meets target?
A5: Singapore | B5: 10 | C5: =COUNTIFS('Diagnostics Events'!$D$3:$D$400,A5) -> 13 | D5: =COUNTIFS('Diagnostics Events'!$D$3:$D$400,A5,'Diagnostics Events'!$C$3:$C$400,"Diagnostics",'Diagnostics Events'!$M$3:$M$400,"<>*Pet*") -> 13 | E5: =COUNTIFS('Diagnostics Events'!$D$3:$D$400,A5,'Diagnostics Events'!$C$3:$C$400,"Both") -> 0 | F5: =COUNTIFS('Diagnostics Events'!$D$3:$D$400,A5,'Diagnostics Events'!$M$3:$M$400,"*Pet*") -> 0 | G5: =COUNTIFS('Diagnostics Events'!$D$3:$D$400,A5,'Diagnostics Events'!$J$3:$J$400,"Confirmed") -> 5 | H5: =COUNTIFS('Diagnostics Events'!$D$3:$D$400,A5,'Diagnostics Events'!$J$3:$J$400,"Provisional") -> 7 | I5: =COUNTIFS('Diagnostics Events'!$D$3:$D$400,A5,'Diagnostics Events'!$J$3:$J$400,"TBC") -> 1 | J5: =COUNTIFS('Diagnostics Events'!$D$3:$D$400,A5,'Diagnostics Events'!$B$3:$B$400,"P1") -> 2 | K5: =COUNTIFS('Diagnostics Events'!$D$3:$D$400,A5,'Diagnostics Events'!$B$3:$B$400,"P2") -> 5 | L5: =COUNTIFS('Diagnostics Events'!$D$3:$D$400,A5,'Diagnostics Events'!$B$3:$B$400,"P3") -> 6 | M5: =J5+K5 -> 7 | N5: =IF(C5>=B5,"Yes","SHORT by "&(B5-C5)) -> Yes
A6: Taiwan | B6: 10 | C6: =COUNTIFS('Diagnostics Events'!$D$3:$D$400,A6) -> 12 | D6: =COUNTIFS('Diagnostics Events'!$D$3:$D$400,A6,'Diagnostics Events'!$C$3:$C$400,"Diagnostics",'Diagnostics Events'!$M$3:$M$400,"<>*Pet*") -> 9 | E6: =COUNTIFS('Diagnostics Events'!$D$3:$D$400,A6,'Diagnostics Events'!$C$3:$C$400,"Both") -> 3 | F6: =COUNTIFS('Diagnostics Events'!$D$3:$D$400,A6,'Diagnostics Events'!$M$3:$M$400,"*Pet*") -> 0 | G6: =COUNTIFS('Diagnostics Events'!$D$3:$D$400,A6,'Diagnostics Events'!$J$3:$J$400,"Confirmed") -> 3 | H6: =COUNTIFS('Diagnostics Events'!$D$3:$D$400,A6,'Diagnostics Events'!$J$3:$J$400,"Provisional") -> 1 | I6: =COUNTIFS('Diagnostics Events'!$D$3:$D$400,A6,'Diagnostics Events'!$J$3:$J$400,"TBC") -> 8 | J6: =COUNTIFS('Diagnostics Events'!$D$3:$D$400,A6,'Diagnostics Events'!$B$3:$B$400,"P1") -> 3 | K6: =COUNTIFS('Diagnostics Events'!$D$3:$D$400,A6,'Diagnostics Events'!$B$3:$B$400,"P2") -> 9 | L6: =COUNTIFS('Diagnostics Events'!$D$3:$D$400,A6,'Diagnostics Events'!$B$3:$B$400,"P3") -> 0 | M6: =J6+K6 -> 12 | N6: =IF(C6>=B6,"Yes","SHORT by "&(B6-C6)) -> Yes
A7: South Korea | B7: 10 | C7: =COUNTIFS('Diagnostics Events'!$D$3:$D$400,A7) -> 13 | D7: =COUNTIFS('Diagnostics Events'!$D$3:$D$400,A7,'Diagnostics Events'!$C$3:$C$400,"Diagnostics",'Diagnostics Events'!$M$3:$M$400,"<>*Pet*") -> 12 | E7: =COUNTIFS('Diagnostics Events'!$D$3:$D$400,A7,'Diagnostics Events'!$C$3:$C$400,"Both") -> 1 | F7: =COUNTIFS('Diagnostics Events'!$D$3:$D$400,A7,'Diagnostics Events'!$M$3:$M$400,"*Pet*") -> 0 | G7: =COUNTIFS('Diagnostics Events'!$D$3:$D$400,A7,'Diagnostics Events'!$J$3:$J$400,"Confirmed") -> 4 | H7: =COUNTIFS('Diagnostics Events'!$D$3:$D$400,A7,'Diagnostics Events'!$J$3:$J$400,"Provisional") -> 1 | I7: =COUNTIFS('Diagnostics Events'!$D$3:$D$400,A7,'Diagnostics Events'!$J$3:$J$400,"TBC") -> 8 | J7: =COUNTIFS('Diagnostics Events'!$D$3:$D$400,A7,'Diagnostics Events'!$B$3:$B$400,"P1") -> 3 | K7: =COUNTIFS('Diagnostics Events'!$D$3:$D$400,A7,'Diagnostics Events'!$B$3:$B$400,"P2") -> 8 | L7: =COUNTIFS('Diagnostics Events'!$D$3:$D$400,A7,'Diagnostics Events'!$B$3:$B$400,"P3") -> 2 | M7: =J7+K7 -> 11 | N7: =IF(C7>=B7,"Yes","SHORT by "&(B7-C7)) -> Yes
A8: Japan | B8: 20 | C8: =COUNTIFS('Diagnostics Events'!$D$3:$D$400,A8) -> 23 | D8: =COUNTIFS('Diagnostics Events'!$D$3:$D$400,A8,'Diagnostics Events'!$C$3:$C$400,"Diagnostics",'Diagnostics Events'!$M$3:$M$400,"<>*Pet*") -> 21 | E8: =COUNTIFS('Diagnostics Events'!$D$3:$D$400,A8,'Diagnostics Events'!$C$3:$C$400,"Both") -> 2 | F8: =COUNTIFS('Diagnostics Events'!$D$3:$D$400,A8,'Diagnostics Events'!$M$3:$M$400,"*Pet*") -> 0 | G8: =COUNTIFS('Diagnostics Events'!$D$3:$D$400,A8,'Diagnostics Events'!$J$3:$J$400,"Confirmed") -> 19 | H8: =COUNTIFS('Diagnostics Events'!$D$3:$D$400,A8,'Diagnostics Events'!$J$3:$J$400,"Provisional") -> 1 | I8: =COUNTIFS('Diagnostics Events'!$D$3:$D$400,A8,'Diagnostics Events'!$J$3:$J$400,"TBC") -> 3 | J8: =COUNTIFS('Diagnostics Events'!$D$3:$D$400,A8,'Diagnostics Events'!$B$3:$B$400,"P1") -> 4 | K8: =COUNTIFS('Diagnostics Events'!$D$3:$D$400,A8,'Diagnostics Events'!$B$3:$B$400,"P2") -> 13 | L8: =COUNTIFS('Diagnostics Events'!$D$3:$D$400,A8,'Diagnostics Events'!$B$3:$B$400,"P3") -> 6 | M8: =J8+K8 -> 17 | N8: =IF(C8>=B8,"Yes","SHORT by "&(B8-C8)) -> Yes
A9: Total | B9: =SUM(B5:B8) -> 50 | C9: =SUM(C5:C8) -> 61 | D9: =SUM(D5:D8) -> 55 | E9: =SUM(E5:E8) -> 6 | F9: =SUM(F5:F8) -> 0 | G9: =SUM(G5:G8) -> 31 | H9: =SUM(H5:H8) -> 10 | I9: =SUM(I5:I8) -> 20 | ... M9: =SUM(M5:M8) -> 47 | N9: =IF(COUNTIF(N5:N8,"Yes")=4,"Yes","SHORT in "&(4-COUNTIF(N5:N8,"Yes"))&" market(s)") -> Yes
A12: Vet events (sheet: Vet Events)
A13: Country | B13: Target | C13: Listed | D13: Clinical or specialist events only (excl. general shows and pet shows) | E13: General medtech shows (Both) | F13: Pet industry shows | G13: Date Confirmed | H13: Date Provisional (verify) | I13: Date TBC (annual pattern) | J13: P1 | K13: P2 | L13: P3 | M13: Worth a trip (P1 plus P2) | N13: Meets target?
A14: Singapore | B14: 10 | C14: =COUNTIFS('Vet Events'!$D$3:$D$400,A14) -> 7 | D14: =COUNTIFS('Vet Events'!$D$3:$D$400,A14,'Vet Events'!$C$3:$C$400,"Vet",'Vet Events'!$M$3:$M$400,"<>*Pet*") -> 5 | E14: =COUNTIFS('Vet Events'!$D$3:$D$400,A14,'Vet Events'!$C$3:$C$400,"Both") -> 0 | F14: =COUNTIFS('Vet Events'!$D$3:$D$400,A14,'Vet Events'!$M$3:$M$400,"*Pet*") -> 2 | G14: =COUNTIFS('Vet Events'!$D$3:$D$400,A14,'Vet Events'!$J$3:$J$400,"Confirmed") -> 0 | H14: =COUNTIFS('Vet Events'!$D$3:$D$400,A14,'Vet Events'!$J$3:$J$400,"Provisional") -> 2 | I14: =COUNTIFS('Vet Events'!$D$3:$D$400,A14,'Vet Events'!$J$3:$J$400,"TBC") -> 5 | J14: =COUNTIFS('Vet Events'!$D$3:$D$400,A14,'Vet Events'!$B$3:$B$400,"P1") -> 1 | K14: =COUNTIFS('Vet Events'!$D$3:$D$400,A14,'Vet Events'!$B$3:$B$400,"P2") -> 4 | L14: =COUNTIFS('Vet Events'!$D$3:$D$400,A14,'Vet Events'!$B$3:$B$400,"P3") -> 2 | M14: =J14+K14 -> 5 | N14: =IF(C14>=B14,"Yes","SHORT by "&(B14-C14)) -> SHORT by 3
A15: Taiwan | B15: 10 | C15: =COUNTIFS('Vet Events'!$D$3:$D$400,A15) -> 11 | D15: =COUNTIFS('Vet Events'!$D$3:$D$400,A15,'Vet Events'!$C$3:$C$400,"Vet",'Vet Events'!$M$3:$M$400,"<>*Pet*") -> 4 | E15: =COUNTIFS('Vet Events'!$D$3:$D$400,A15,'Vet Events'!$C$3:$C$400,"Both") -> 2 | F15: =COUNTIFS('Vet Events'!$D$3:$D$400,A15,'Vet Events'!$M$3:$M$400,"*Pet*") -> 5 | G15: =COUNTIFS('Vet Events'!$D$3:$D$400,A15,'Vet Events'!$J$3:$J$400,"Confirmed") -> 4 | H15: =COUNTIFS('Vet Events'!$D$3:$D$400,A15,'Vet Events'!$J$3:$J$400,"Provisional") -> 1 | I15: =COUNTIFS('Vet Events'!$D$3:$D$400,A15,'Vet Events'!$J$3:$J$400,"TBC") -> 6 | J15: =COUNTIFS('Vet Events'!$D$3:$D$400,A15,'Vet Events'!$B$3:$B$400,"P1") -> 1 | K15: =COUNTIFS('Vet Events'!$D$3:$D$400,A15,'Vet Events'!$B$3:$B$400,"P2") -> 4 | L15: =COUNTIFS('Vet Events'!$D$3:$D$400,A15,'Vet Events'!$B$3:$B$400,"P3") -> 6 | M15: =J15+K15 -> 5 | N15: =IF(C15>=B15,"Yes","SHORT by "&(B15-C15)) -> Yes
A16: South Korea | B16: 10 | C16: =COUNTIFS('Vet Events'!$D$3:$D$400,A16) -> 12 | D16: =COUNTIFS('Vet Events'!$D$3:$D$400,A16,'Vet Events'!$C$3:$C$400,"Vet",'Vet Events'!$M$3:$M$400,"<>*Pet*") -> 9 | E16: =COUNTIFS('Vet Events'!$D$3:$D$400,A16,'Vet Events'!$C$3:$C$400,"Both") -> 1 | F16: =COUNTIFS('Vet Events'!$D$3:$D$400,A16,'Vet Events'!$M$3:$M$400,"*Pet*") -> 2 | G16: =COUNTIFS('Vet Events'!$D$3:$D$400,A16,'Vet Events'!$J$3:$J$400,"Confirmed") -> 0 | H16: =COUNTIFS('Vet Events'!$D$3:$D$400,A16,'Vet Events'!$J$3:$J$400,"Provisional") -> 3 | I16: =COUNTIFS('Vet Events'!$D$3:$D$400,A16,'Vet Events'!$J$3:$J$400,"TBC") -> 9 | J16: =COUNTIFS('Vet Events'!$D$3:$D$400,A16,'Vet Events'!$B$3:$B$400,"P1") -> 2 | K16: =COUNTIFS('Vet Events'!$D$3:$D$400,A16,'Vet Events'!$B$3:$B$400,"P2") -> 5 | L16: =COUNTIFS('Vet Events'!$D$3:$D$400,A16,'Vet Events'!$B$3:$B$400,"P3") -> 5 | M16: =J16+K16 -> 7 | N16: =IF(C16>=B16,"Yes","SHORT by "&(B16-C16)) -> Yes
A17: Japan | B17: 20 | C17: =COUNTIFS('Vet Events'!$D$3:$D$400,A17) -> 23 | D17: =COUNTIFS('Vet Events'!$D$3:$D$400,A17,'Vet Events'!$C$3:$C$400,"Vet",'Vet Events'!$M$3:$M$400,"<>*Pet*") -> 19 | E17: =COUNTIFS('Vet Events'!$D$3:$D$400,A17,'Vet Events'!$C$3:$C$400,"Both") -> 2 | F17: =COUNTIFS('Vet Events'!$D$3:$D$400,A17,'Vet Events'!$M$3:$M$400,"*Pet*") -> 2 | G17: =COUNTIFS('Vet Events'!$D$3:$D$400,A17,'Vet Events'!$J$3:$J$400,"Confirmed") -> 16 | H17: =COUNTIFS('Vet Events'!$D$3:$D$400,A17,'Vet Events'!$J$3:$J$400,"Provisional") -> 0 | I17: =COUNTIFS('Vet Events'!$D$3:$D$400,A17,'Vet Events'!$J$3:$J$400,"TBC") -> 7 | J17: =COUNTIFS('Vet Events'!$D$3:$D$400,A17,'Vet Events'!$B$3:$B$400,"P1") -> 4 | K17: =COUNTIFS('Vet Events'!$D$3:$D$400,A17,'Vet Events'!$B$3:$B$400,"P2") -> 8 | L17: =COUNTIFS('Vet Events'!$D$3:$D$400,A17,'Vet Events'!$B$3:$B$400,"P3") -> 11 | M17: =J17+K17 -> 12 | N17: =IF(C17>=B17,"Yes","SHORT by "&(B17-C17)) -> Yes
A18: Total | B18: =SUM(B14:B17) -> 50 | C18: =SUM(C14:C17) -> 53 | D18: =SUM(D14:D17) -> 37 | E18: =SUM(E14:E17) -> 5 | F18: =SUM(F14:F17) -> 11 | G18: =SUM(G14:G17) -> 20 | H18: =SUM(H14:H17) -> 6 | I18: =SUM(I14:I17) -> 27 | ... M18: =SUM(M14:M17) -> 29 | N18: =IF(COUNTIF(N14:N17,"Yes")=4,"Yes","SHORT in "&(4-COUNTIF(N14:N17,"Yes"))&" market(s)") -> SHORT in 1 market(s)
A20: Blue numbers in the Target column are your targets (10 per country, 20 for Japan). Edit them if the target changes.
A21: Listed counts every row on the tab, including P3 optional events. General medtech shows (Segment = Both) are on both tabs because vet distributors walk medtech floors. Consumer pet shows are counted as vet events only to reach your target, so read the clinical only column and the P1 plus P2 column for the real number worth a trip.
A22: Date Confirmed means the organiser's own page shows the date. Provisional means a single or conflicting source. TBC means the organiser has not published 2027 yet, and the row shows the annual pattern only. No future date has been invented.
A23: Singapore vet is SHORT of 10 because few genuine vet events exist in Singapore. Aggregator listings of generic Singapore vet symposia were checked and excluded as low credibility. See the Read Me for regional alternatives.

Sheet Next 60 Days
A1: EVENTS STARTING WITHIN 60 DAYS OF THE REFERENCE DATE. Contact organisers this week, because exhibitor windows for these have mostly closed or are closing.
A2: Reference date (edit) | B2: 46320 | C2: Change this date to re age the list. Days Left and Urgency recalculate (CRITICAL = 42 days or less, HIGH = 43 to 56, MEDIUM = more). Rows are events starting within 60 days of 25 Oct 2026.
A3: Start Date | B3: Days Left | C3: Urgency | D3: Priority | E3: Segment | F3: Country | G3: Event | H3: Dates | I3: City and Venue | J3: Deadline or Action | K3: Source
A4: 46359 | B4: =A4-$B$2 -> 39 | C4: =IF(B4<0,"PASSED",IF(B4<=42,"CRITICAL",IF(B4<=56,"HIGH","MEDIUM"))) -> CRITICAL | D4: P1 | E4: Both | F4: Taiwan | G4: Healthcare+ Expo Taiwan 2026 | H4: 3 to 6 Dec 2026 | I4: Taipei Nangang Exhibition Center Hall 1 (1F and 4F), Taipei | J4: Exhibitor sales for 2026 probably closed. Confirm with the organiser. Attend as a visitor. Walk the ultrasound and imaging aisles and collect importer cards. Nearest event on this list. | K4: https://expo.taiwan-healthcare.org/en/
A5: 46360 | B5: =A5-$B$2 -> 40 | C5: =IF(B5<0,"PASSED",IF(B5<=42,"CRITICAL",IF(B5<=56,"HIGH","MEDIUM"))) -> CRITICAL | D5: P1 | E5: Vet | F5: South Korea | G5: KVECCS Academic Seminar with RECOVER workshop and POCUS ultrasound practice (Korean Veterinary Emergency and Critical Care Society) | H5: 4 to 6 Dec 2026 | I5: Seoul (venue to be confirmed) | J5: Event is 6 weeks away. Ask the society now for a scanner loan slot. Contact KVECCS this week: offer 3 to 4 scanners for the POCUS practical session. | K5: https://www.dailyvet.co.kr/news/academy
A6: 46361 | B6: =A6-$B$2 -> 41 | C6: =IF(B6<0,"PASSED",IF(B6<=42,"CRITICAL",IF(B6<=56,"HIGH","MEDIUM"))) -> CRITICAL | D6: P2 | E6: Diagnostics | F6: South Korea | G6: KSE 2026, 61st Korean Society of Echocardiography Autumn Meeting | H6: 5 to 6 Dec 2026 | I6: Grand Walkerhill Seoul, Seoul | J6: Event is 6 weeks away. Ask the society office now. Ask for visitor access. Note names of the hands on session faculty. | K6: https://www.ksecho.org/academic_event/annual_schedule_all.php
A7: 46361 | B7: =A7-$B$2 -> 41 | C7: =IF(B7<0,"PASSED",IF(B7<=42,"CRITICAL",IF(B7<=56,"HIGH","MEDIUM"))) -> CRITICAL | D7: P2 | E7: Diagnostics | F7: South Korea | G7: ISCU 2026 and 29th Regular Meeting of the Korean Association of Clinical Ultrasound, with Hands On School | H7: 5 to 6 Dec 2026 | I7: COEX Magok, Seoul | J7: Abstract deadline 30 Oct 2026 (not relevant for vendors). Sponsor terms not found, event is 6 weeks away. Contact KACU this week to ask about equipment loan for the hands on school. | K7: https://iscu.or.kr/
A8: 46361 | B8: =A8-$B$2 -> 41 | C8: =IF(B8<0,"PASSED",IF(B8<=42,"CRITICAL",IF(B8<=56,"HIGH","MEDIUM"))) -> CRITICAL | D8: P2 | E8: Vet | F8: Japan | G8: JSVDI 79th Japanese Society of Veterinary Diagnostic Imaging Meeting | H8: 5 to 6 Dec 2026 | I8: Fukuoka International Congress Center, Fukuoka | J8: Event is 6 weeks away. Ask the secretariat now for any remaining exhibit space. Request an exhibit slot or visit to meet imaging KOLs. Plan the June 2027 meeting as the booth event. | K8: https://jsvdi.com/conference/3332/
A9: 46367 | B9: =A9-$B$2 -> 47 | C9: =IF(B9<0,"PASSED",IF(B9<=42,"CRITICAL",IF(B9<=56,"HIGH","MEDIUM"))) -> HIGH | D9: P3 | E9: Vet | F9: Taiwan | G9: Chanchao Kaohsiung Pets Show, December 2026 edition | H9: 11 to 14 Dec 2026 | I9: Kaohsiung Exhibition Center, Kaohsiung | J9: Closed for exhibitors. Optional. Walk it on 12 Dec if attending AiCVS. | K9: https://www.chanchao.com.tw/PetsShow/kaohsiung/
A10: 46368 | B10: =A10-$B$2 -> 48 | C10: =IF(B10<0,"PASSED",IF(B10<=42,"CRITICAL",IF(B10<=56,"HIGH","MEDIUM"))) -> HIGH | D10: P2 | E10: Diagnostics | F10: Taiwan | G10: TSOC Winter Scientific Meeting 2026 (Taiwan Society of Cardiology) | H10: 12 to 13 Dec 2026 | I10: Taipei International Convention Center (TICC), Taipei | J10: Not published. Event is 7 weeks away. Optional. Attend only if combined with Healthcare+ Expo trip. | K10: https://tsocmeeting.org/
A11: 46368 | B11: =A11-$B$2 -> 48 | C11: =IF(B11<0,"PASSED",IF(B11<=42,"CRITICAL",IF(B11<=56,"HIGH","MEDIUM"))) -> HIGH | D11: P2 | E11: Diagnostics | F11: Japan | G11: JSUM Kansai 53rd Regional Meeting and 30th Regional Seminar | H11: 12 Dec 2026 | I11: Osaka International Convention Center, Osaka | J11: Corporate exhibition terms not found. Event is 7 weeks away, so ask the secretariat this week. Email the secretariat for the exhibitor form. If closed, attend as a visitor and map Kansai KOLs and dealers. | K11: https://www.jsum.or.jp/members/calendar/2026/
A12: 46368 | B12: =A12-$B$2 -> 48 | C12: =IF(B12<0,"PASSED",IF(B12<=42,"CRITICAL",IF(B12<=56,"HIGH","MEDIUM"))) -> HIGH | D12: P1 | E12: Vet | F12: Taiwan | G12: AiCVS and AiCVIM Joint Congress 2026 (Asian veterinary surgery and internal medicine colleges) | H12: 12 to 13 Dec 2026 | I12: Kaohsiung Exhibition Center, Kaohsiung (venue per host association pages, the congress site names no venue) | J12: Event is 7 weeks away. Sponsor and exhibitor slots may still be open. Email the organiser (aicvs-aicvim2026.tw) this week. Offer a scanner for the imaging session. | K12: https://www.aicvs-aicvim2026.tw/
A13: 46372 | B13: =A13-$B$2 -> 52 | C13: =IF(B13<0,"PASSED",IF(B13<=42,"CRITICAL",IF(B13<=56,"HIGH","MEDIUM"))) -> HIGH | D13: P3 | E13: Vet | F13: Japan | G13: Skyvets abdominal ultrasound hands on seminar series (monthly, third Wednesday) | H13: 16 Dec 2026, 20 Jan, 17 Feb, 17 Mar 2027 | I13: Not stated (online imaging service with hands on) | J13: Registration per session. Ask Skyvets which scanners are used. | K13: https://sky-vets.com/seminar/
A14: 46374 | B14: =A14-$B$2 -> 54 | C14: =IF(B14<0,"PASSED",IF(B14<=42,"CRITICAL",IF(B14<=56,"HIGH","MEDIUM"))) -> HIGH | D14: P2 | E14: Vet | F14: Japan | G14: JSVAS 113th Japanese Society of Veterinary Anesthesia and Surgery Meeting | H14: 18 to 20 Dec 2026 | I14: Congress Square Grand Green Osaka, Osaka | J14: Event is 8 weeks away. Ask the secretariat now. Visit or exhibit if a Kansai vet dealer partner is in place. | K14: https://www.jsvas.net/conference/index.php

Sheet Diagnostics Events
A1: CHISON Ultrasound Diagnostics Event Plan | Singapore, Taiwan, South Korea, Japan | Dec 2026 to Dec 2027 | v1, prepared 25 Oct 2026
A2: # | B2: Priority | C2: Segment | D2: Country | E2: Event Name | F2: Start Date | G2: End Date | H2: Month (for sorting) | I2: Date as Published or Expected | J2: Date Class | K2: Date Status and Source Note | L2: City and Venue | M2: Type | N2: Field or Specialty | O2: Why It Matters for CHISON (product angle) | P2: Competitors Present or Expected | Q2: Competitor Evidence | R2: Local Dealers and Distributors to Meet | S2: KOL Potential | T2: Dealer Potential | U2: Scale or Attendance | V2: Cost Info (published) | W2: Deadlines That Bite | X2: Recommended Action | Y2: Source
A3: 1 | B3: P3 | C3: Diagnostics | D3: Singapore | E3: Singapore LIVE 2027 (National Heart Centre Singapore) | F3: 46415 | G3: 46417 | H3: 46388 | I3: 28 to 30 Jan 2027 | J3: Confirmed | K3: Confirmed per organiser page | L3: Singapore (venue not stated) | M3: Live case course | N3: Interventional cardiology, imaging | O3: Cardiology KOLs at NHCS. Interventional focus, so ultrasound relevance is limited. | P3: Expected, not verified: Philips, GE HealthCare, Abbott expected. | Q3: Unverified. Exhibitor list not published. | R3: Singapore distributors and regional ASEAN distributors who attend Singapore congresses. | S3: Medium | T3: Low | U3: Not published | V3: Not published. Request the exhibitor guide from the organiser. | W3: Not published. | X3: Optional. Contact NHCS only if a cardiology KOL is on the target list. | Y3: https://www.nhcs.com.sg/singlivecourse
A4: 2 | B4: P2 | C4: Diagnostics | D4: Singapore | E4: SSR 10th Annual Scientific Meeting (Singapore Society of Radiographers) | F4: 46479 | G4: 46480 | H4: 46478 | I4: 2 to 3 Apr 2027 | J4: Provisional | K4: Listed by the society. Location and theme to be confirmed | L4: Singapore (to be confirmed) | M4: Society annual meeting | N4: Radiography and sonography | O4: Radiographers and sonographers who evaluate ultrasound in public hospitals. | P4: Brands normally active in Singapore (market knowledge, not verified per event): Philips, GE HealthCare, Siemens Healthineers, Canon Medical, Samsung Medison, Mindray, SonoScape. No event specific exhibitor list found. | Q4: Unverified. Exhibitor list not published. | R4: Singapore distributors and regional ASEAN distributors who attend Singapore congresses. | S4: Medium | T4: Medium | U4: Not published | V4: Not published. Request the exhibitor guide from the organiser. | W4: Not published. Society page age looks stale, so verify. | X4: Email SSR to confirm the date and sponsor options. | Y4: https://www.ssr.org.sg/conference-list
A5: 3 | B5: P2 | C5: Diagnostics | D5: Singapore | E5: SingHealth Academy Basic POCUS Workshop, session 1 | F5: 46514 | G5: 46514 | H5: 46508 | I5: 7 May 2027 | J5: Provisional | K5: Provisional. Course page lists both sessions but its date format is unclear, verify | L5: Academia, 20 College Road, Singapore | M5: CME course | N5: Point of care ultrasound | O5: Residents in emergency, internal medicine and anaesthesia train here. Scanner supply for hands on is a practical opening for SonoEye and SonoAir. | P5: Training equipment supplier not stated. | Q5: Unverified. Exhibitor list not published. | R5: Singapore distributors and regional ASEAN distributors who attend Singapore congresses. | S5: High | T5: Low | U5: Small class | V5: Participant fee S$420 incl GST. | W5: Registration closes before each session. | X5: Contact SingHealth Academy to ask who supplies the scanners and whether CHISON can lend units. | Y5: https://www.singhealthacademy.edu.sg/sims/events-programmes/academia/point-of-care-ultrasound
A6: 4 | B6: P2 | C6: Diagnostics | D6: Singapore | E6: NYSORA Regional Anesthesia Conference Singapore 2027 | F6: 46515 | G6: 46516 | H6: 46508 | I6: 8 to 9 May 2027 | J6: Confirmed | K6: Confirmed per organiser listing | L6: Singapore (venue not stated) | M6: Hands on conference | N6: Ultrasound guided regional anaesthesia | O6: Hands on ultrasound nerve block training. Handheld and portable ultrasound fit. Sponsor tables are common at NYSORA courses. | P6: Expected, not verified: Fujifilm Sonosite, GE HealthCare (Vscan), Butterfly typical at NYSORA events. Unverified for this event. | Q6: Unverified. Exhibitor list not published. | R6: Singapore distributors and regional ASEAN distributors who attend Singapore congresses. | S6: High | T6: Medium | U6: Hands on course, under 300 (est.) | V6: Not published. Request the exhibitor guide from the organiser. | W6: Not published. | X6: Ask NYSORA for the industry sponsor pack. A scanner loan for the workshop is the cheapest option. | Y6: https://nysora.com/event/conferences/regional-anesthesia-conference-singapore-2027/
A7: 5 | B7: P3 | C7: Diagnostics | D7: Singapore | E7: Asia Healthcare Week 2027 (IQPC) | F7: 46532 | G7: 46535 | H7: 46508 | I7: 25 to 28 May 2027 | J7: Provisional | K7: Listed by an aggregator | L7: Singapore (venue not found) | M7: Conference | N7: Hospital planning and care journey | O7: Hospital planners and administrators. Useful for contacts, light on ultrasound. | P7: Not documented. | Q7: Unverified. Exhibitor list not published. | R7: Singapore distributors and regional ASEAN distributors who attend Singapore congresses. | S7: Low | T7: Medium | U7: Not published | V7: Not published. Request the exhibitor guide from the organiser. | W7: Not published. | X7: Optional. | Y7: https://www.iqpc.com/events-asiahealthcareweek
A8: 6 | B8: P3 | C8: Diagnostics | D8: Singapore | E8: HealthTechX Asia 2027 (3rd edition) | F8: 46547 | G8: 46548 | H8: 46539 | I8: 9 to 10 Jun 2027 | J8: Provisional | K8: Listed on organiser and 10times pages | L8: Sands Expo and Convention Centre, Marina Bay Sands, Singapore | M8: Digital health trade show | N8: Health tech | O8: Digital health. AI ultrasound software partners rather than distributors. | P8: Not relevant for ultrasound OEMs. | Q8: Unverified. Exhibitor list not published. | R8: Singapore distributors and regional ASEAN distributors who attend Singapore congresses. | S8: Low | T8: Low | U8: Over 90 exhibitors (organiser) | V8: Not published. Request the exhibitor guide from the organiser. | W8: Not published. | X8: Skip unless AI partnerships are in scope. | Y8: https://www.healthtechx-asia.com/
A9: 7 | B9: P3 | C9: Diagnostics | D9: Singapore | E9: Smart Health Asia 2027 | F9: 46575 | G9: 46576 | H9: 46569 | I9: 7 to 8 Jul 2027 | J9: Provisional | K9: Listed by organiser (Messe Berlin Singapore) | L9: Sands Expo and Convention Centre, Singapore | M9: Digital health trade show | N9: Digital health | O9: Digital health; small imaging share. | P9: Not relevant for ultrasound OEMs. | Q9: Unverified. Exhibitor list not published. | R9: Singapore distributors and regional ASEAN distributors who attend Singapore congresses. | S9: Low | T9: Low | U9: 150+ exhibitors, 5,000+ visitors (organiser claim) | V9: Not published. Request the exhibitor guide from the organiser. | W9: Not published. | X9: Skip. | Y9: https://smarthealthasia.com/
A10: 8 | B10: P3 | C10: Diagnostics | D10: Singapore | E10: UROFAIR 2027 (Singapore Urological Association) | F10: 46583 | G10: 46585 | H10: 46569 | I10: 15 to 17 Jul 2027 | J10: Confirmed | K10: Confirmed per society page | L10: Grand Copthorne Waterfront Hotel, Singapore | M10: Society meeting with fair | N10: Urology | O10: Urology ultrasound (prostate, bladder). Small but easy to approach. | P10: Brands normally active in Singapore (market knowledge, not verified per event): Philips, GE HealthCare, Siemens Healthineers, Canon Medical, Samsung Medison, Mindray, SonoScape. No event specific exhibitor list found. | Q10: Unverified. Exhibitor list not published. | R10: Singapore distributors and regional ASEAN distributors who attend Singapore congresses. | S10: Medium | T10: Low | U10: Not published | V10: Not published. Request the exhibitor guide from the organiser. | W10: Not published. | X10: Optional. Ask SUA for the exhibitor prospectus. | Y10: https://sua.sg/urofair-2027/
A11: 9 | B11: P2 | C11: Diagnostics | D11: Singapore | E11: APICS 2027, Asia Pacific Intensive Care Symposium | F11: 46617 | G11: 46622 | H11: 46600 | I11: 18 to 23 Aug 2027 | J11: Provisional | K11: Provisional. Listed by an aggregator only. The six day span looks too long and overlaps SGCR week, so it is likely an aggregator error. Verify with the organiser | L11: Singapore EXPO (per listing) | M11: Regional symposium | N11: Critical care ultrasound | O11: ICU physicians use POCUS and echo daily. Handheld and portable systems fit. | P11: Expected, not verified: GE HealthCare, Philips, Fujifilm Sonosite typical. Unverified. | Q11: Unverified. Exhibitor list not published. | R11: Singapore distributors and regional ASEAN distributors who attend Singapore congresses. | S11: High | T11: Medium | U11: Not published | V11: Not published. Request the exhibitor guide from the organiser. | W11: Not published. | X11: Confirm dates with the organiser before planning. | Y11: https://conferencealerts.co.in/singapore/medicine-and-medical-science
A12: 10 | B12: P1 | C12: Diagnostics | D12: Singapore | E12: ACAR SGCR WIRES 2027 (Asian Congress of Abdominal Radiology with the Singapore Congress of Radiology and WIRES) | F12: 46618 | G12: 46621 | H12: 46600 | I12: 19 to 22 Aug 2027 | J12: Confirmed | K12: Dates confirmed on organiser site. Venue to be announced | L12: Singapore (venue not yet announced). The 2026 edition was at Singapore EXPO | M12: National and Asian congress | N12: Radiology, abdominal and interventional imaging | O12: Singapore's top radiology congress (35th meeting per the organiser welcome page), joined by the 14th Asian abdominal radiology congress. Regional KOLs come to Singapore, so one trip covers ASEAN and North Asia. Abdominal ultrasound and elastography are core topics. | P12: Brands normally active in Singapore (market knowledge, not verified per event): Philips, GE HealthCare, Siemens Healthineers, Canon Medical, Samsung Medison, Mindray, SonoScape. No event specific exhibitor list found. | Q12: Unverified. 2026 AOCR plus SGCR exhibitor list not retrieved. | R12: Singapore distributors and regional ASEAN distributors who attend Singapore congresses. | S12: High | T12: High | U12: Not published | V12: Not published. Request the exhibitor guide from the organiser. | W12: Exhibitor prospectus not published. Ask the secretariat from Jan 2027. | X12: Priority 1 in Singapore. Request the prospectus and plan a regional distributor meeting around it. | Y12: https://www.sgcr-wires.com/acar2027
A13: 11 | B13: P2 | C13: Diagnostics | D13: Singapore | E13: SingHealth Academy Basic POCUS Workshop, session 2 | F13: 46640 | G13: 46640 | H13: 46631 | I13: 10 Sep 2027 | J13: Provisional | K13: Provisional. Course page lists both sessions but its date format is unclear, verify | L13: Academia, 20 College Road, Singapore | M13: CME course | N13: Point of care ultrasound | O13: Residents in emergency, internal medicine and anaesthesia train here. Scanner supply for hands on is a practical opening for SonoEye and SonoAir. | P13: Training equipment supplier not stated. | Q13: Unverified. Exhibitor list not published. | R13: Singapore distributors and regional ASEAN distributors who attend Singapore congresses. | S13: High | T13: Low | U13: Small class | V13: Participant fee S$420 incl GST. | W13: Registration closes before each session. | X13: Contact SingHealth Academy to ask who supplies the scanners and whether CHISON can lend units. | Y13: https://www.singhealthacademy.edu.sg/sims/events-programmes/academia/point-of-care-ultrasound
A14: 12 | B14: P3 | C14: Diagnostics | D14: Singapore | E14: IEEE International Ultrasonics Symposium 2027 | F14: 46642 | G14: 46645 | H14: 46631 | I14: 12 to 15 Sep 2027 | J14: Confirmed | K14: Confirmed per IEEE listing | L14: Singapore (venue not named) | M14: Engineering symposium | N14: Ultrasound physics and transducers | O14: Engineering audience. Awareness of competitor technology, not a sales event. | P14: Ultrasound OEM engineers. | Q14: Unverified. Exhibitor list not published. | R14: Not applicable. | S14: Low | T14: Low | U14: Not published | V14: Not published. Request the exhibitor guide from the organiser. | W14: Not published. | X14: Awareness only. | Y14: https://ieee-uffc.org/event/conference/2027-ieee-international-ultrasonics-symposium
A15: 13 | B15: P1 | C15: Diagnostics | D15: Singapore | E15: Singapore Health and Biomedical Congress (SHBC) 2027 | H15: 46661 | I15: Oct 2027 (not published) | J15: TBC | K15: TBC. Annual pattern: early October (2026: 8 to 9 Oct, 2025: 9 to 10 Oct at Singapore EXPO) | L15: Singapore EXPO (venue of recent editions) | M15: National healthcare congress with exhibition | N15: All specialties, public healthcare | O15: Largest multi specialty healthcare meeting in Singapore, run by NHG Health (National Healthcare Group) per its site. KOLs and procurement staff of public hospitals attend. | P15: Brands normally active in Singapore (market knowledge, not verified per event): Philips, GE HealthCare, Siemens Healthineers, Canon Medical, Samsung Medison, Mindray, SonoScape. No event specific exhibitor list found. | Q15: Unverified. Exhibitor list not published. | R15: Singapore distributors and regional ASEAN distributors who attend Singapore congresses. | S15: High | T15: High | U15: Not published | V15: Delegate day pass SGD 180 (2026). Exhibitor cost not published. | W15: Not published. | X15: Check shbc.com.sg after the 2026 edition for the 2027 call for exhibitors. | Y15: https://shbc.com.sg/
A16: 1 | B16: P1 | C16: Both | D16: Taiwan | E16: Healthcare+ Expo Taiwan 2026 | F16: 46359 | G16: 46362 | H16: 46357 | I16: 3 to 6 Dec 2026 | J16: Confirmed | K16: Confirmed | L16: Taipei Nangang Exhibition Center Hall 1 (1F and 4F), Taipei | M16: Trade exhibition | N16: Medical devices, smart hospital, digital health, precision medicine | O16: Taiwan's largest healthcare expo. Importers, hospital buyers and KOLs attend. The only large Taiwan show inside the first month of the window. | P16: Confirmed at the 2025 edition: ASUS (handheld ultrasound LU800 and EchoLab) and Daikso (portable ultrasound AI). Big five brands not found in the search. Official 2026 exhibitor list is on the expo site. | Q16: Partly confirmed. Large brand presence unverified. | R16: Rotary Trading (Canon Medical agent) is a known ultrasound dealer. Other Taiwan importers to scout at the show floor. | S16: Medium | T16: High | U16: Third party: 650+ exhibitors; 130,000 to 150,000 visitors (est.) | V16: Not published. | W16: Exhibitor sales for 2026 probably closed. Confirm with the organiser. | X16: Attend as a visitor. Walk the ultrasound and imaging aisles and collect importer cards. Nearest event on this list. | Y16: https://expo.taiwan-healthcare.org/en/
A17: 2 | B17: P2 | C17: Diagnostics | D17: Taiwan | E17: TSOC Winter Scientific Meeting 2026 (Taiwan Society of Cardiology) | F17: 46368 | G17: 46369 | H17: 46357 | I17: 12 to 13 Dec 2026 | J17: Confirmed | K17: Confirmed | L17: Taipei International Convention Center (TICC), Taipei | M17: Society scientific meeting | N17: Cardiology and echo | O17: Cardiology KOL access in Taipei. | P17: Expected, not verified: GE HealthCare, Philips, Canon expected. | Q17: Unverified. | R17: Rotary Trading (Canon Medical agent) is a known ultrasound dealer. Other Taiwan importers to scout at the show floor. | S17: High | T17: Low | U17: Not published | V17: Not published. Request the exhibitor guide from the organiser. | W17: Not published. Event is 7 weeks away. | X17: Optional. Attend only if combined with Healthcare+ Expo trip. | Y17: https://tsocmeeting.org/
A18: 3 | B18: P1 | C18: Diagnostics | D18: Taiwan | E18: ASCI 2027 and TRC 2027 (Radiological Society of the ROC annual meeting) | F18: 46464 | G18: 46467 | H18: 46447 | I18: 18 to 21 Mar 2027 | J18: Provisional | K18: Reported in the RSROC annual schedule (read through a search extract, site blocked my fetch). Verify | L18: NTUH International Convention Center, Taipei | M18: National congress with Asian cardiovascular imaging society | N18: Radiology, cardiovascular imaging | O18: Taiwan's top radiology meeting. TRC 2026 was at Kaohsiung Exhibition Center in April. | P18: Expected, not verified: GE HealthCare, Philips, Canon Medical (agent: Rotary Trading), Alpinion, Samsung Medison, Siemens Healthineers. Mindray and SonoScape: no Taiwan exhibitor evidence found. | Q18: Unverified. | R18: Rotary Trading (Canon Medical agent) is a known ultrasound dealer. Other Taiwan importers to scout at the show floor. | S18: High | T18: Medium | U18: Not published | V18: Not published. Request the exhibitor guide from the organiser. | W18: Not published. Ask RSROC secretariat (02 25865331). | X18: Request the exhibitor guide. KOL meetings with radiologists. | Y18: https://www.rsroc.org.tw/news/news_detail.asp?news_id=96
A19: 4 | B19: P2 | C19: Diagnostics | D19: Taiwan | E19: TAOG 66th Annual Congress 2027 (Taiwan Association of Obstetrics and Gynecology) | H19: 46447 | I19: Late Mar 2027 (not published) | J19: TBC | K19: TBC. Annual pattern: late March (65th was 28 to 29 Mar 2026 at TICC) | L19: Taipei International Convention Center (TICC) expected | M19: Society congress | N19: OB/GYN ultrasound | O19: OB/GYN ultrasound buyers. TAOG publishes a vendor exhibition registration form each year, so there is a documented booth path. | P19: Expected, not verified: GE HealthCare, Samsung Medison, Philips, Alpinion expected. | Q19: Unverified. | R19: Rotary Trading (Canon Medical agent) is a known ultrasound dealer. Other Taiwan importers to scout at the show floor. | S19: High | T19: High | U19: Not published | V19: Not published (registration form exists). | W19: 2024 exhibitor registration form was published; the 2027 form should appear around late 2026. | X19: Watch taog.org.tw and email the secretariat in November. | Y19: https://www.taog.org.tw/year_list.php
A20: 5 | B20: P2 | C20: Diagnostics | D20: Taiwan | E20: Taiwan Association of Radiological Technologists 60th Annual Meeting 2027 | H20: 46447 | I20: March 2027 (not published) | J20: TBC | K20: TBC. Annual pattern: March (59th was March 2026 at Kaohsiung Exhibition Center) | L20: Rotating city | M20: Society annual meeting | N20: Radiographers and sonographers | O20: Daily users who influence purchases. | P20: Expected, not verified: GE HealthCare, Philips, Canon Medical (agent: Rotary Trading), Alpinion, Samsung Medison, Siemens Healthineers. Mindray and SonoScape: no Taiwan exhibitor evidence found. | Q20: Unverified. | R20: Rotary Trading (Canon Medical agent) is a known ultrasound dealer. Other Taiwan importers to scout at the show floor. | S20: Medium | T20: Medium | U20: Not published | V20: Not published. Request the exhibitor guide from the organiser. | W20: Not published. | X20: Search for the official notice in January. | Y20: https://www.rsroc.org.tw/
A21: 6 | B21: P2 | C21: Diagnostics | D21: Taiwan | E21: TSOC Annual Meeting 2027 (Taiwan Society of Cardiology) | H21: 46508 | I21: May 2027 (not published) | J21: TBC | K21: TBC. Annual pattern: May (2026 was 15 to 17 May at TICC and WTC Hall 1A) | L21: Taipei (TICC expected) | M21: Society annual meeting | N21: Cardiology and echo | O21: Largest Taiwan cardiology meeting. | P21: Expected, not verified: GE HealthCare, Philips, Canon expected. | Q21: Unverified. | R21: Rotary Trading (Canon Medical agent) is a known ultrasound dealer. Other Taiwan importers to scout at the show floor. | S21: High | T21: Low | U21: Large | V21: Not published. Request the exhibitor guide from the organiser. | W21: Not published. | X21: Optional. Check tsoc.org.tw in early 2027. | Y21: https://www.tsoc.org.tw/
A22: 7 | B22: P2 | C22: Diagnostics | D22: Taiwan | E22: Taiwan Society of Emergency Medicine Annual Meeting 2027 | H22: 46539 | I22: June 2027 (not published) | J22: TBC | K22: TBC. Annual pattern: June (2026 was 26 to 27 Jun at NTUH) | L22: Taipei (NTUH expected) | M22: Society annual meeting | N22: Emergency medicine, POCUS | O22: Handheld and portable ultrasound buyers. | P22: Expected, not verified: GE HealthCare (Vscan), Philips (Lumify), Butterfly expected. | Q22: Unverified. | R22: Rotary Trading (Canon Medical agent) is a known ultrasound dealer. Other Taiwan importers to scout at the show floor. | S22: Medium | T22: Medium | U22: Not published | V22: Not published. Request the exhibitor guide from the organiser. | W22: Not published. | X22: Check sem.org.tw in spring 2027. | Y22: https://www.sem.org.tw/News/12/Index
A23: 8 | B23: P2 | C23: Both | D23: Taiwan | E23: Medical Taiwan 2027 | F23: 46576 | G23: 46578 | H23: 46569 | I23: 8 to 10 Jul 2027 | J23: Confirmed | K23: Confirmed per organiser page | L23: Taipei Nangang Exhibition Center Hall 1, Taipei | M23: International trade exhibition | N23: Smart medical, elderly care, innovative devices | O23: Second Taiwan show a year, focused on devices and exports. Good for importers and OEM contacts. | P23: Not documented. | Q23: Unverified. | R23: Rotary Trading (Canon Medical agent) is a known ultrasound dealer. Other Taiwan importers to scout at the show floor. | S23: Low | T23: High | U23: Not published | V23: Not published. | W23: Booth sales likely open. Ask the organiser. | X23: Visit or exhibit with a local importer. Compare cost with Healthcare+ Expo. | Y23: https://www.medicaltaiwan.com.tw/zh-tw/index.html
A24: 9 | B24: P2 | C24: Diagnostics | D24: Taiwan | E24: Taipei International Breast Cancer Symposium 2027 (Taiwan Breast Cancer Society) | H24: 46631 | I24: Sep to Oct 2027 (not published) | J24: TBC | K24: TBC. Annual or two yearly pattern: 2026 is 19 to 20 Sep, 2024 was 26 to 27 Oct | L24: Taipei Nangang Exhibition Center Hall 2 (7F) in 2024 and 2026 | M24: International symposium | N24: Breast imaging, ABUS | O24: Breast imaging KOLs. SUMROC activity pages list the 2024 edition. | P24: Unverified. | Q24: Unverified. | R24: Rotary Trading (Canon Medical agent) is a known ultrasound dealer. Other Taiwan importers to scout at the show floor. | S24: High | T24: Low | U24: Not published | V24: Not published. Request the exhibitor guide from the organiser. | W24: Not published. | X24: Check bcst.org.tw in mid 2027. | Y24: https://www.tpta.org.tw/articles.php?type=forwarded&pid=520
A25: 10 | B25: P2 | C25: Diagnostics | D25: Taiwan | E25: TSA 71st Annual Meeting 2027 (Taiwan Society of Anesthesiologists) | H25: 46631 | I25: Sep 2027 (not published) | J25: TBC | K25: TBC. Annual pattern: late September (70th is 26 to 27 Sep 2026 at NTUH) | L25: Taipei (NTUH International Convention Center in 2026) | M25: Society annual meeting | N25: Anaesthesia, regional block ultrasound | O25: Nerve block ultrasound users. Handheld and portable fit. | P25: Expected, not verified: Fujifilm Sonosite, GE HealthCare expected. | Q25: Unverified. | R25: Rotary Trading (Canon Medical agent) is a known ultrasound dealer. Other Taiwan importers to scout at the show floor. | S25: Medium | T25: Medium | U25: Not published | V25: Not published. Request the exhibitor guide from the organiser. | W25: Not published. | X25: Check anesth.org.tw in 2027. | Y25: https://www.anesth.org.tw/events/content.asp?ID=3091&EduType=1
A26: 11 | B26: P1 | C26: Diagnostics | D26: Taiwan | E26: SUMROC Annual Meeting and 9th Asia Pacific Forum 2027 (Society of Ultrasound in Medicine, ROC) | H26: 46661 | I26: Oct to Nov 2027 (not published) | J26: TBC | K26: TBC. Annual pattern: mid to late October (2026 is 31 Oct to 1 Nov, TICC) | L26: Taipei International Convention Center or NTU College of Medicine | M26: Society annual meeting | N26: All clinical ultrasound | O26: Taiwan's ultrasound society. The 2026 page shows GE HealthCare Ultrasound, Alpinion and Rotary Trading (Canon agent) as supporters. KOL access is the main prize. | P26: Confirmed on the 2026 page: GE HealthCare Ultrasound, Alpinion, Rotary Trading (Canon Medical agent). | Q26: Confirmed for GE, Alpinion, Canon agent (2026 page logos). | R26: Rotary Trading (Canon Medical agent) is a known ultrasound dealer. Other Taiwan importers to scout at the show floor. | S26: High | T26: Medium | U26: Not published. Past venues: TICC and NTU basic medical building | V26: Not published. Request the exhibitor guide from the organiser. | W26: Sponsor terms not published. The 2026 meeting is 31 Oct, so ask for the 2027 terms right after it. | X26: Attend SUMROC 2026 on 31 Oct if possible to meet the board. Otherwise email sumroc@sumroc.org.tw. | Y26: https://www.sumroc.org.tw/index.php?action=annual
A27: 12 | B27: P2 | C27: Both | D27: Taiwan | E27: Healthcare+ Expo Taiwan 2027 | H27: 46722 | I27: Early Dec 2027 (not published) | J27: TBC | K27: TBC. Annual pattern: first week of December (2026 is 3 to 6 Dec, 2025 was 4 to 7 Dec) | L27: Taipei Nangang Exhibition Center Hall 1, Taipei | M27: Trade exhibition | N27: Medical devices, smart hospital | O27: Same show as Dec 2026. Plan to exhibit with an importer after seeing the 2026 floor. | P27: Expected, not verified: Same as 2026. See the Dec 2026 row. | Q27: Unverified. | R27: Rotary Trading (Canon Medical agent) is a known ultrasound dealer. Other Taiwan importers to scout at the show floor. | S27: Medium | T27: High | U27: See 2026 row | V27: Not published. | W27: Booth sales typically open 6 to 9 months ahead. | X27: Decide after the Dec 2026 visit. Ask the organiser for the 2027 booth price. | Y27: https://expo.taiwan-healthcare.org/en/
A28: 1 | B28: P2 | C28: Diagnostics | D28: South Korea | E28: KSE 2026, 61st Korean Society of Echocardiography Autumn Meeting | F28: 46361 | G28: 46362 | H28: 46357 | I28: 5 to 6 Dec 2026 | J28: Confirmed | K28: Confirmed | L28: Grand Walkerhill Seoul, Seoul | M28: Society scientific meeting | N28: Echocardiography | O28: Cardiac echo KOLs and sonographers. Also the Yeongnam echo winter workshop on 12 Dec 2026 at Keimyung University, Daegu. | P28: Expected, not verified: Samsung Medison, GE HealthCare, Philips, Canon expected. | Q28: Likely. Not verified for this edition. | R28: Korean importers and regional dealers. Note that Samsung Medison and Alpinion sell direct, so dealer recruitment should focus on Chinese OEM friendly importers. | S28: High | T28: Low | U28: About 1,000 (est.) | V28: Not published. Request the exhibitor guide from the organiser. | W28: Event is 6 weeks away. Ask the society office now. | X28: Ask for visitor access. Note names of the hands on session faculty. | Y28: https://www.ksecho.org/academic_event/annual_schedule_all.php
A29: 2 | B29: P2 | C29: Diagnostics | D29: South Korea | E29: ISCU 2026 and 29th Regular Meeting of the Korean Association of Clinical Ultrasound, with Hands On School | F29: 46361 | G29: 46362 | H29: 46357 | I29: 5 to 6 Dec 2026 | J29: Confirmed | K29: Confirmed | L29: COEX Magok, Seoul | M29: International symposium and hands on school | N29: Clinical and point of care ultrasound | O29: Clinical ultrasound used by non radiologists (family medicine, internal medicine, orthopaedics). A hands on school normally needs scanners from vendors, a cheap route to get probes in doctors' hands. Suits SonoEye, SonoAir and SonoBook. | P29: Expected, not verified: Samsung Medison likely. Others unverified. | Q29: Unverified. Sponsor page not retrieved. | R29: Korean importers and regional dealers. Note that Samsung Medison and Alpinion sell direct, so dealer recruitment should focus on Chinese OEM friendly importers. | S29: High | T29: Medium | U29: Not published | V29: Not published. Request the exhibitor guide from the organiser. | W29: Abstract deadline 30 Oct 2026 (not relevant for vendors). Sponsor terms not found, event is 6 weeks away. | X29: Contact KACU this week to ask about equipment loan for the hands on school. | Y29: https://iscu.or.kr/
A30: 3 | B30: P1 | C30: Both | D30: South Korea | E30: KIMES 2027, 42nd Korea International Medical and Hospital Equipment Show | F30: 46464 | G30: 46467 | H30: 46447 | I30: 18 to 21 Mar 2027 | J30: Provisional | K30: Reported on the official site listing (read through a search extract, my direct fetch of kimes.kr returned no text). Third party listings agree. Re check on kimes.kr when booth sales open | L30: COEX Halls, Gangnam, Seoul (about 45,000 sqm) | M30: Trade exhibition | N30: Medical devices, ultrasound, radiology, hospital equipment | O30: Korea's #1 medtech show and the main dealer scouting floor. Importers and regional dealers walk it. Samsung Medison and GE HealthCare use it as a launch stage. | P30: Confirmed at KIMES 2026: Samsung Medison (One Platform, V4, EVO Q10) and GE HealthCare (booth C200, ultrasound and fatty liver quantification). Mindray, SonoScape, Philips: not found. | Q30: Confirmed for Samsung and GE (2026 press releases). | R30: Korean importers and regional dealers. Note that Samsung Medison and Alpinion sell direct, so dealer recruitment should focus on Chinese OEM friendly importers. | S30: Medium | T30: High | U30: KIMES 2026: about 1,500 booths (media). Organiser Korea E and Ex | V30: Not published. | W30: Booth application dates not found. KIMES opens exhibitor recruitment roughly 6 to 9 months ahead, so ask the organiser now. | X30: Priority 1 for distributor recruitment. Ask Korea E and Ex for the 2027 booth form and early bird rate. | Y30: https://www.kimes.kr/
A31: 4 | B31: P3 | C31: Diagnostics | D31: South Korea | E31: KSC Spring Conference 2027 (Korean Society of Cardiology) | H31: 46478 | I31: April 2027 (not published) | J31: TBC | K31: TBC. Annual pattern: April (2026 was 17 to 18 Apr, Gyeongju, with ACC Asia) | L31: Rotating city | M31: Society conference | N31: Cardiology | O31: Cardiology KOL access. Secondary to the autumn meeting. | P31: Expected, not verified: GE HealthCare, Philips, Samsung Medison expected. | Q31: Unverified. | R31: Korean importers and regional dealers. Note that Samsung Medison and Alpinion sell direct, so dealer recruitment should focus on Chinese OEM friendly importers. | S31: Medium | T31: Low | U31: Not published | V31: Not published. Request the exhibitor guide from the organiser. | W31: Not published. | X31: Check circulation.or.kr in January. | Y31: https://www.circulation.or.kr/bbs/?code=meeting
A32: 5 | B32: P2 | C32: Diagnostics | D32: South Korea | E32: KSEM 2027 Spring Conference (Korean Society of Emergency Medicine) | H32: 46478 | I32: Apr to Jun 2027 (not published) | J32: TBC | K32: TBC. No pattern: 2025 was 17 to 18 Apr (Gwangju), 2024 was 27 to 28 Jun (Daegu) | L32: Rotating city | M32: Society conference | N32: Emergency medicine, POCUS | O32: Emergency physicians buy handheld and portable ultrasound (SonoEye, SonoBook). | P32: Expected, not verified: Samsung Medison, GE HealthCare (Vscan) likely. | Q32: Unverified. | R32: Korean importers and regional dealers. Note that Samsung Medison and Alpinion sell direct, so dealer recruitment should focus on Chinese OEM friendly importers. | S32: Medium | T32: Medium | U32: Not published | V32: Not published. Request the exhibitor guide from the organiser. | W32: Not published. Society was recruiting an event agency in 2026. | X32: Check emergency.or.kr in January. | Y32: https://emergency.or.kr/
A33: 6 | B33: P3 | C33: Diagnostics | D33: South Korea | E33: GBCC 2027, Global Breast Cancer Conference (Korean Breast Cancer Society) | H33: 46478 | I33: Spring 2027 (not published) | J33: TBC | K33: TBC. 2026 edition held at Grand Walkerhill Seoul (press), month not confirmed | L33: Seoul (expected) | M33: International conference | N33: Breast cancer, breast imaging | O33: Breast surgeons and radiologists. Smaller exhibition. | P33: Unverified. | Q33: Unverified. | R33: Korean importers and regional dealers. Note that Samsung Medison and Alpinion sell direct, so dealer recruitment should focus on Chinese OEM friendly importers. | S33: Medium | T33: Low | U33: Not published | V33: Not published. Request the exhibitor guide from the organiser. | W33: Not published. | X33: Optional. Check kbcs.or.kr in January. | Y33: https://www.kbcs.or.kr/html/
A34: 7 | B34: P1 | C34: Diagnostics | D34: South Korea | E34: KSUM 2027, 58th Annual Congress of the Korean Society of Ultrasound in Medicine | H34: 46508 | I34: May 2027 (not published) | J34: TBC | K34: TBC. Annual pattern: early May (2026 was 7 to 8 May at COEX) | L34: COEX, Seoul (venue used in 2025 and 2026) | M34: National society congress | N34: All clinical ultrasound | O34: Korea's top ultrasound KOL meeting. English language, international delegates. The right place for CHISON publicity. | P34: Confirmed at KSUM 2026: Canon Medical Korea ran a luncheon symposium. Sponsors listed on 10times include Philips, GE HealthCare and Canon (unofficial listing). Samsung Medison, Mindray, SonoScape not found. | Q34: Confirmed for Canon. Philips and GE from an unofficial listing. | R34: Korean importers and regional dealers. Note that Samsung Medison and Alpinion sell direct, so dealer recruitment should focus on Chinese OEM friendly importers. | S34: High | T34: Medium | U34: KSUM 2026: about 1,000 attendees from 30 countries (press) | V34: Not published. Request the exhibitor guide from the organiser. | W34: Sponsor terms not published. The 2026 edition had abstract deadline on 23 Feb. Expect sponsor call from January. | X34: Email the KSUM office in January for the sponsorship tier list and luncheon symposium slots. | Y34: https://2026.ksum.or.kr/about/about.php
A35: 8 | B35: P2 | C35: Diagnostics | D35: South Korea | E35: KHF 2027, K Hospital and Healthtech Fair (Korean Hospital Association) | H35: 46600 | I35: August 2027 (not published) | J35: TBC | K35: TBC. Annual pattern: August (2026 was 19 to 21 Aug at COEX) | L35: COEX Halls C and D, Seoul | M35: Hospital trade fair | N35: Hospital equipment and health tech | O35: Hospital purchasing managers and hospital owners. Runs by the Korean Hospital Association with Messe eSang. | P35: Not documented. | Q35: Unverified. | R35: Korean importers and regional dealers. Note that Samsung Medison and Alpinion sell direct, so dealer recruitment should focus on Chinese OEM friendly importers. | S35: Low | T35: High | U35: Not published | V35: Not published. | W35: Not published. | X35: Visit as buyer in 2027 if KIMES dealer meetings are productive. | Y35: https://khospital.org/
A36: 9 | B36: P1 | C36: Diagnostics | D36: South Korea | E36: KCR 2027, 83rd Korean Congress of Radiology | F36: 46652 | G36: 46655 | H36: 46631 | I36: 22 to 25 Sep 2027 | J36: Confirmed | K36: Dates confirmed on radiology.or.kr. Venue reported as COEX Magok (page text garbled, verify) | L36: COEX Magok, Seoul (reported) | M36: National congress | N36: Radiology | O36: Radiology KOL meeting with a large exhibition. KCR 2026 moved to KINTEX for the first time in 20 years. | P36: Confirmed at KCR 2026: GE HealthCare luncheon symposium. Samsung Medison, Philips, Canon expected. | Q36: Confirmed for GE (2026). Others likely. | R36: Korean importers and regional dealers. Note that Samsung Medison and Alpinion sell direct, so dealer recruitment should focus on Chinese OEM friendly importers. | S36: High | T36: Medium | U36: KCR 2026: 2,135 abstracts submitted (press) | V36: Not published. Request the exhibitor guide from the organiser. | W36: Exhibitor call normally opens in spring. | X36: Ask KCR secretariat in March 2027 for the exhibitor guide. | Y36: https://www.radiology.or.kr/
A37: 10 | B37: P2 | C37: Diagnostics | D37: South Korea | E37: KSC Autumn Scientific Meeting 2027 (71st, Korean Society of Cardiology) | H37: 46661 | I37: October 2027 (not published) | J37: TBC | K37: TBC. Annual pattern: mid October (70th was 15 to 17 Oct 2026, Seoul) | L37: Seoul (2026 reported at Walkerhill) | M37: Society scientific meeting | N37: Cardiology and echo | O37: Largest Korean cardiology meeting. | P37: Expected, not verified: GE HealthCare, Philips, Samsung Medison expected. | Q37: Unverified. | R37: Korean importers and regional dealers. Note that Samsung Medison and Alpinion sell direct, so dealer recruitment should focus on Chinese OEM friendly importers. | S37: High | T37: Low | U37: Large (est. over 5,000) | V37: Not published. Request the exhibitor guide from the organiser. | W37: Not published. | X37: Check in spring 2027. | Y37: https://www.circulation.or.kr/bbs/?code=meeting
A38: 11 | B38: P2 | C38: Diagnostics | D38: South Korea | E38: KSUOG 2027 International Congress (Korean Society of Ultrasound in Obstetrics and Gynecology) | H38: 46661 | I38: Oct to Nov 2027 (not published) | J38: TBC | K38: TBC. Annual pattern: late October (2026 is 30 to 31 Oct, Grand Hyatt Incheon) | L38: Incheon or Seoul (unconfirmed) | M38: Society international congress | N38: OB/GYN ultrasound | O38: OB/GYN ultrasound KOLs. Samsung Medison is strong here, so use for KOL contacts, not dealers. | P38: Expected, not verified: Samsung Medison, GE HealthCare expected. | Q38: Unverified. | R38: Korean importers and regional dealers. Note that Samsung Medison and Alpinion sell direct, so dealer recruitment should focus on Chinese OEM friendly importers. | S38: High | T38: Low | U38: Not published | V38: Not published. Request the exhibitor guide from the organiser. | W38: Not published. | X38: Check ksuog.or.kr in mid 2027. | Y38: https://ksuog.or.kr/
A39: 12 | B39: P2 | C39: Diagnostics | D39: South Korea | E39: KSOG Autumn Congress 2027 (Korean Society of Obstetrics and Gynecology) | F39: 46703 | G39: 46704 | H39: 46692 | I39: 12 to 13 Nov 2027 | J39: Confirmed | K39: Confirmed in KSOG schedule | L39: COEX Magok, Seoul | M39: Society congress | N39: OB/GYN | O39: Large OB/GYN meeting. At the 111th (2025) congress Samsung was listed as a Gold sponsor, so Samsung owns this room. | P39: Samsung (Gold sponsor tier on the 111th congress page, image file names). Others unverified. | Q39: Partly confirmed (Samsung, prior edition). | R39: Korean importers and regional dealers. Note that Samsung Medison and Alpinion sell direct, so dealer recruitment should focus on Chinese OEM friendly importers. | S39: High | T39: Medium | U39: Large (est. over 3,000) | V39: Not published. Request the exhibitor guide from the organiser. | W39: Not published. | X39: Request sponsor guide in summer 2027. Consider only if budget allows after KSUM. | Y39: https://ksog.org/bbs/?category=1&code=schedule2
A40: 13 | B40: P2 | C40: Diagnostics | D40: South Korea | E40: KSE 2027, 62nd Korean Society of Echocardiography Autumn Meeting | H40: 46722 | I40: Early Dec 2027 (not published) | J40: TBC | K40: TBC. Annual pattern: early December (61st is 5 to 6 Dec 2026) | L40: Seoul (2026 at Grand Walkerhill) | M40: Society scientific meeting | N40: Echocardiography | O40: Same audience as KSE 2026. Falls at the end of the window. | P40: Expected, not verified: Samsung Medison, GE HealthCare, Philips expected. | Q40: Unverified. | R40: Korean importers and regional dealers. Note that Samsung Medison and Alpinion sell direct, so dealer recruitment should focus on Chinese OEM friendly importers. | S40: High | T40: Low | U40: About 1,000 (est.) | V40: Not published. Request the exhibitor guide from the organiser. | W40: Not published. | X40: Decide after attending KSE 2026. | Y40: https://www.ksecho.org/
A41: 1 | B41: P2 | C41: Diagnostics | D41: Japan | E41: JSUM Kansai 53rd Regional Meeting and 30th Regional Seminar | F41: 46368 | G41: 46368 | H41: 46357 | I41: 12 Dec 2026 | J41: Confirmed | K41: Confirmed | L41: Osaka International Convention Center, Osaka | M41: Society regional meeting | N41: General ultrasound (abdomen, breast, vascular) | O41: One of the first events inside the window. Seeds KOL contact with Kansai ultrasound physicians and sonographers. Demo slot for SonoMax and SonoBook. | P41: Expected, not verified: Fujifilm (ex Hitachi ultrasound), Canon Medical, GE HealthCare, Philips Japan, Siemens Healthineers. Mindray and SonoScape: no Japan exhibitor evidence found. Samsung Medison: no direct Japan sales found (sold via Hitachi in 2017). | Q41: Likely. The meeting notice (us53kansai intent PDF) has a corporate exhibition item, but no exhibitor names. | R41: Regional medical equipment trading houses and Fujifilm or Canon sales agents. Cross check against Japan_Distributor_List_Human_v1.xlsx in this repo. | S41: High | T41: Medium | U41: Regional meeting, several hundred delegates (est.) | V41: Not published. Request the exhibitor guide from the organiser. | W41: Corporate exhibition terms not found. Event is 7 weeks away, so ask the secretariat this week. | X41: Email the secretariat for the exhibitor form. If closed, attend as a visitor and map Kansai KOLs and dealers. | Y41: https://www.jsum.or.jp/members/calendar/2026/
A42: 2 | B42: P3 | C42: Diagnostics | D42: Japan | E42: JSUM Diagnostic Ultrasound Seminar, General | F42: 46410 | G42: 46410 | H42: 46388 | I42: 23 Jan 2027 | J42: Confirmed | K42: Confirmed | L42: Knowledge Capital Conference Room, Osaka | M42: Society CME seminar | N42: General ultrasound training | O42: Hands on teaching seminar. Instructors are future KOLs. Possible equipment loan for the practical session. | P42: Expected, not verified: Fujifilm (ex Hitachi ultrasound), Canon Medical, GE HealthCare, Philips Japan, Siemens Healthineers. Mindray and SonoScape: no Japan exhibitor evidence found. Samsung Medison: no direct Japan sales found (sold via Hitachi in 2017). | Q42: Unverified. Seminar format, vendor presence not documented. | R42: Low. Educational audience. | S42: Medium | T42: Low | U42: Seminar, under 300 (est.) | V42: Not published. Request the exhibitor guide from the organiser. | W42: Not published. | X42: Ask JSUM office whether vendors can lend devices for the practical session. | Y42: https://www.jsum.or.jp/members/calendar/2027/
A43: 3 | B43: P3 | C43: Diagnostics | D43: Japan | E43: Medical Messe 2027 Nagoya | F43: 46435 | G43: 46436 | H43: 46419 | I43: 17 to 18 Feb 2027 | J43: Confirmed | K43: Confirmed | L43: STATION Ai, Nagoya | M43: Regional trade fair and business matching | N43: Medical devices (Aichi and Chubu cluster) | O43: Local device makers and dealers in the Chubu region. Small, but a cheap way to meet Chubu dealers. | P43: Not documented. Mostly regional device makers. | Q43: Unverified. | R43: Chubu region dealers and device makers. | S43: Low | T43: Medium | U43: 2 day regional show, size not published | V43: Not published. Exhibitor applications have opened. | W43: Exhibitor applications open now. Closing date not found. | X43: Visit as a buyer to scout Chubu dealers. Only exhibit if a dealer partner asks. | Y43: https://www.nagoya-cci.or.jp/koho/news-release/pr/newsrelease20260818_19.pdf
A44: 4 | B44: P3 | C44: Diagnostics | D44: Japan | E44: JSUM Diagnostic Ultrasound Seminar, Breast | F44: 46439 | G44: 46439 | H44: 46419 | I44: 21 Feb 2027 | J44: Confirmed | K44: Confirmed | L44: Otemachi Sankei Plaza, Chiyoda, Tokyo | M44: Society CME seminar | N44: Breast ultrasound | O44: Breast ultrasound teaching day. Useful for elastography and breast probe positioning. | P44: Expected, not verified: Fujifilm (ex Hitachi ultrasound), Canon Medical, GE HealthCare, Philips Japan, Siemens Healthineers. Mindray and SonoScape: no Japan exhibitor evidence found. Samsung Medison: no direct Japan sales found (sold via Hitachi in 2017). | Q44: Unverified. | R44: Low. | S44: Medium | T44: Low | U44: Seminar, under 300 (est.) | V44: Not published. Request the exhibitor guide from the organiser. | W44: Not published. | X44: Attend if in Tokyo. Collect names of breast ultrasound instructors. | Y44: https://www.jsum.or.jp/members/calendar/2027/
A45: 5 | B45: P3 | C45: Diagnostics | D45: Japan | E45: JSUM Diagnostic Ultrasound Seminar, Digestive Organs | F45: 46452 | G45: 46452 | H45: 46447 | I45: 6 Mar 2027 | J45: Confirmed | K45: Confirmed (JSUM lists venue as tentative) | L45: Okinawa (venue tentative) | M45: Society CME seminar | N45: Abdominal ultrasound | O45: Abdominal teaching day for physicians and sonographers. | P45: Expected, not verified: Fujifilm (ex Hitachi ultrasound), Canon Medical, GE HealthCare, Philips Japan, Siemens Healthineers. Mindray and SonoScape: no Japan exhibitor evidence found. Samsung Medison: no direct Japan sales found (sold via Hitachi in 2017). | Q45: Unverified. | R45: Low. | S45: Medium | T45: Low | U45: Seminar, under 300 (est.) | V45: Not published. Request the exhibitor guide from the organiser. | W45: Not published. | X45: Low priority. Check venue again in January. | Y45: https://www.jsum.or.jp/members/calendar/2027/
A46: 6 | B46: P3 | C46: Diagnostics | D46: Japan | E46: JSUM Tohoku 73rd Regional Meeting and 51st Seminar | F46: 46453 | G46: 46453 | H46: 46447 | I46: 7 Mar 2027 | J46: Confirmed | K46: Confirmed | L46: Sendai SME Activation Center Multipurpose Hall, Sendai | M46: Society regional meeting | N46: General ultrasound | O46: Tohoku region KOL and dealer access. | P46: Expected, not verified: Fujifilm (ex Hitachi ultrasound), Canon Medical, GE HealthCare, Philips Japan, Siemens Healthineers. Mindray and SonoScape: no Japan exhibitor evidence found. Samsung Medison: no direct Japan sales found (sold via Hitachi in 2017). | Q46: Unverified. | R46: Tohoku regional dealers. | S46: Medium | T46: Medium | U46: Regional meeting, a few hundred (est.) | V46: Not published. Request the exhibitor guide from the organiser. | W46: Not published. | X46: Attend only if a Tohoku dealer visit is planned for the same week. | Y46: https://www.jsum.or.jp/members/calendar/2027/
A47: 7 | B47: P2 | C47: Diagnostics | D47: Japan | E47: JCS 2027, 91st Japanese Circulation Society Annual Meeting (with APSC 2027) | F47: 46472 | G47: 46474 | H47: 46447 | I47: 26 to 28 Mar 2027 | J47: Confirmed | K47: Confirmed | L47: Pacifico Yokohama, Yokohama | M47: National congress | N47: Cardiology, echocardiography | O47: Largest Japanese cardiology meeting. Cardiac echo is the hardest segment to enter, but KOL exposure is strong. Position SonoMax or XBit for general cardiology and SonoEye for bedside use. | P47: Expected, not verified: GE HealthCare (Vivid), Philips, Canon, Fujifilm, Siemens expected. | Q47: Likely. GE Japan runs Vivid Talks events; no 2027 exhibitor list yet. | R47: Regional medical equipment trading houses and Fujifilm or Canon sales agents. Cross check against Japan_Distributor_List_Human_v1.xlsx in this repo. | S47: High | T47: Medium | U47: Very large national congress (est. over 10,000) | V47: Not published. Request the exhibitor guide from the organiser. | W47: Exhibitor and seminar sponsor terms not found. Typically open about 6 months ahead, so ask now. | X47: Request the exhibitor prospectus. Decide visit versus booth by December. | Y47: https://www.congre.co.jp/jcs2027/
A48: 8 | B48: P1 | C48: Diagnostics | D48: Japan | E48: JRC 2027, 86th Japan Radiological Society Annual Meeting, with ITEM 2027 | F48: 46492 | G48: 46495 | H48: 46478 | I48: 15 to 18 Apr 2027 | J48: Confirmed | K48: Confirmed for JRS meeting. ITEM 2027 dates TBC (ITEM 2026 ran 17 to 19 Apr 2026) | L48: Pacifico Yokohama, Yokohama | M48: National congress plus trade exhibition | N48: Diagnostic imaging, radiology, medical imaging industry | O48: Japan's #1 imaging event. ITEM is the dealer and OEM floor, JRS is the radiology KOL meeting. Best single trip for both objectives. | P48: Confirmed at ITEM 2026: Siemens Healthineers, Canon, Fujifilm listed. GE HealthCare exhibited at ITEM 2025. Philips expected. Mindray, SonoScape, Samsung: not found. | Q48: Confirmed from prior edition pages (Siemens flyer, Fujifilm booth page, GE Japan PDF). | R48: Regional medical equipment trading houses and Fujifilm or Canon sales agents. Cross check against Japan_Distributor_List_Human_v1.xlsx in this repo. | S48: High | T48: High | U48: ITEM 2026: 153 exhibitors, 18,180 visitors (JIRA via Yakuji Nippo) | V48: Not published. JIRA sets terms. | W48: ITEM exhibitor application window not found. Past shows opened about 6 to 8 months ahead, so ask JIRA now. | X48: Contact JIRA (item.jira-net.or.jp) this month for exhibitor eligibility and fees. Plan KOL dinner during JRS. | Y48: https://site2.convention.co.jp/jrs86/
A49: 9 | B49: P2 | C49: Diagnostics | D49: Japan | E49: JSE 38th Japanese Society of Echocardiography Annual Meeting | F49: 46493 | G49: 46495 | H49: 46478 | I49: 16 to 18 Apr 2027 | J49: Confirmed | K49: Confirmed | L49: Hotel Buena Vista and Alpico Plaza Hotel, Matsumoto, Nagano | M49: Society annual meeting | N49: Echocardiography | O49: Echo specialists and cardiac sonographers. Overlaps with JRC dates, so choose one. | P49: Expected, not verified: GE HealthCare, Philips, Canon, Fujifilm expected. | Q49: Likely, not verified. Vendor seminars are normal at echo society meetings. | R49: Regional medical equipment trading houses and Fujifilm or Canon sales agents. Cross check against Japan_Distributor_List_Human_v1.xlsx in this repo. | S49: High | T49: Low | U49: About 2,000 delegates (est.) | V49: Not published. Request the exhibitor guide from the organiser. | W49: Not published. Site opened 18 May 2026. | X49: Skip unless a cardiac KOL introduction is arranged. Clashes with JRC 2027. | Y49: https://www.jse.gr.jp/
A50: 10 | B50: P2 | C50: Diagnostics | D50: Japan | E50: 32nd Japan Medical Congress 2027 Osaka, academic exhibition | F50: 46499 | G50: 46502 | H50: 46478 | I50: 22 to 25 Apr 2027 (public exhibition at Umekita 20 to 28 Mar 2027) | J50: Confirmed | K50: Confirmed (exhibition dates). Lectures 23 to 25 Apr | L50: Nakanoshima area, Osaka (Osaka International Convention Center, Regal Royal Hotel Osaka and others) | M50: Multi specialty national congress, held every 4 years | N50: All specialties (JAMS member societies) | O50: Once in four years. Reaches physicians from every Japan medical society in one place. Strong KOL discovery and publicity value. | P50: Expected, not verified: Fujifilm (ex Hitachi ultrasound), Canon Medical, GE HealthCare, Philips Japan, Siemens Healthineers. Mindray and SonoScape: no Japan exhibitor evidence found. Samsung Medison: no direct Japan sales found (sold via Hitachi in 2017). | Q50: Unverified. Exhibition is branded as an information exchange space. | R50: Regional medical equipment trading houses and Fujifilm or Canon sales agents. Cross check against Japan_Distributor_List_Human_v1.xlsx in this repo. | S50: High | T50: Medium | U50: Very large (est. tens of thousands) | V50: Not found. | W50: Exhibitor terms not found on the site. Ask the exhibition committee. | X50: Confirm whether foreign OEMs or dealers can exhibit. Upgrade to P1 if a booth path exists. | Y50: https://isoukai2027.jp/index.html
A51: 11 | B51: P2 | C51: Diagnostics | D51: Japan | E51: JSOG 79th Japan Society of Obstetrics and Gynecology Annual Meeting | F51: 46500 | G51: 46502 | H51: 46478 | I51: 23 to 25 Apr 2027 | J51: Confirmed | K51: Confirmed | L51: Pacifico Yokohama North, Exhibition Hall D, Yokohama | M51: National congress | N51: OB/GYN ultrasound | O51: OB/GYN is a core ultrasound segment. Large exhibition hall and many private clinic owners who buy their own systems. | P51: Expected, not verified: GE HealthCare (Voluson), Fujifilm, Canon, Philips, Samsung Medison (OB focus) expected. | Q51: Likely. Exhibition Hall D is booked, no exhibitor list yet. | R51: Regional medical equipment trading houses and Fujifilm or Canon sales agents. Cross check against Japan_Distributor_List_Human_v1.xlsx in this repo. | S51: High | T51: High | U51: Large national congress (est. over 5,000) | V51: Not published. Request the exhibitor guide from the organiser. | W51: Not published. Check the organiser (Congre) exhibitor page. | X51: Request exhibitor prospectus. Private clinic buyers make this a dealer lead source. | Y51: https://www.congre.co.jp/jsog2027/
A52: 12 | B52: P2 | C52: Diagnostics | D52: Japan | E52: JOA 100th Japanese Orthopaedic Association Annual Meeting | F52: 46520 | G52: 46523 | H52: 46508 | I52: 13 to 16 May 2027 | J52: Confirmed | K52: Confirmed per organiser site. One JOA schedule PDF shows 15 to 16 Jul 2027 Sapporo, which conflicts | L52: Pacifico Yokohama (Conference Center, Exhibition Hall, Annex Hall) | M52: National congress (100th anniversary) | N52: Musculoskeletal ultrasound | O52: MSK and sports medicine ultrasound is growing fast. Handheld and portable models fit orthopaedic clinics. | P52: Expected, not verified: Fujifilm (Sonosite), GE HealthCare, Canon expected. Others unverified. | Q52: Unverified. | R52: Regional medical equipment trading houses and Fujifilm or Canon sales agents. Cross check against Japan_Distributor_List_Human_v1.xlsx in this repo. | S52: Medium | T52: High | U52: Very large (est. over 10,000) | V52: Not published. Request the exhibitor guide from the organiser. | W52: Not published. | X52: Trust the organiser site. Confirm date again in January. | Y52: https://www.congre.co.jp/joa2027/
... A56: 16 | B56: P2 | C56: Diagnostics | D56: Japan | E56: JBCS 35th Japan Breast Cancer Society Annual Meeting | F56: 46576 | G56: 46578 | H56: 46569 | I56: 8 to 10 Jul 2027 | J56: Confirmed | K56: Confirmed | L56: Kumamoto Castle Hall, Shimin Kaikan Shears Home Yume Hall, Kumamoto International Exchange Hall, Kumamoto | M56: National congress | N56: Breast cancer, breast ultrasound | O56: Breast surgeons are major ultrasound buyers. Pair with JABTS in September. | P56: Expected, not verified: Fujifilm, Canon, GE HealthCare expected. | Q56: Unverified. | R56: Regional medical equipment trading houses and Fujifilm or Canon sales agents. Cross check against Japan_Distributor_List_Human_v1.xlsx in this repo. | S56: High | T56: Medium | U56: Large (est. over 5,000) | V56: Not published. Request the exhibitor guide from the organiser. | W56: Not published. | X56: Request prospectus. Kyushu dealer visit can be bundled. | Y56: https://www.c-linkage.co.jp/jbcs2027/
A57: 17 | B57: P2 | C57: Both | D57: Japan | E57: International Modern Hospital Show (IMHS) 2027 | H57: 46569 | I57: July 2027 (date not published) | J57: TBC | K57: TBC. Annual pattern: mid July (2026 was 8 to 10 Jul, 2025 was 16 to 18 Jul) | L57: Tokyo Big Sight West Halls, Tokyo | M57: Hospital trade show | N57: Hospital equipment, IT, medical devices | O57: Hospital purchasing audience, run by the Japan Hospital Association. Good for dealer and system integrator contacts. | P57: Mostly hospital IT and facility firms. Imaging OEMs not confirmed. | Q57: Unverified. | R57: Hospital system integrators and equipment dealers. | S57: Low | T57: High | U57: 2026: 300 exhibitors planned, 35,316 visitors (organiser report) | V57: Not published. | W57: Exhibitor call for the 2026 show opened about a year ahead. Expect the 2027 call from late 2026. | X57: Check noma-hs.com in December. Visit as buyer for dealer scouting. | Y57: https://www.noma-hs.com/
A58: 18 | B58: P2 | C58: Diagnostics | D58: Japan | E58: Japan Society of Ningen Dock and Preventive Medicine 68th Annual Meeting | F58: 46633 | G58: 46634 | H58: 46631 | I58: 3 to 4 Sep 2027 | J58: Provisional | K58: Planned per the society's 2025 organiser tender. Not yet confirmed by the congress site | L58: Grand Cube Osaka, Osaka | M58: Society annual meeting | N58: Health check centres, abdominal and vascular screening | O58: Health screening centres buy abdominal and carotid ultrasound in volume. A direct buyer audience. | P58: Fujifilm has an event page for the 67th meeting (Sep 2026, Kumamoto). Others unverified. | Q58: Confirmed for Fujifilm (prior edition). Others unverified. | R58: Dealers that supply health check centres. | S58: Medium | T58: High | U58: Several thousand (est.) | V58: Not published. Request the exhibitor guide from the organiser. | W58: Not published. | X58: Verify the date in January. Good venue for a screening focused demo. | Y58: https://www.ningen-dock.jp/
A59: 19 | B59: P2 | C59: Diagnostics | D59: Japan | E59: JABTS 55th Japan Association of Breast and Thyroid Sonology Annual Meeting | F59: 46648 | G59: 46649 | H59: 46631 | I59: 18 to 19 Sep 2027 | J59: Confirmed | K59: Confirmed (dates). Venue TBC | L59: Gifu (venue not published) | M59: Society annual meeting | N59: Breast and thyroid ultrasound | O59: Specialist ultrasound audience. Previous meetings had vendor seminars. | P59: Expected, not verified: Fujifilm, Canon, GE HealthCare expected. | Q59: Unverified. | R59: Regional medical equipment trading houses and Fujifilm or Canon sales agents. Cross check against Japan_Distributor_List_Human_v1.xlsx in this repo. | S59: High | T59: Medium | U59: About 1,500 (est.) | V59: Not published. Request the exhibitor guide from the organiser. | W59: Not published. | X59: Request the sponsorship guide in spring 2027. | Y59: https://jabts.jp/jabtsgakujutsushunki/gakujutushukai/
A60: 20 | B60: P2 | C60: Diagnostics | D60: Japan | E60: JSUM autumn regional meetings 2027 (Kanto Koshinetsu, Chubu, Chugoku, Kyushu, Shikoku, Hokkaido, Tohoku) | H60: 46631 | I60: Sep to Oct 2027 (dates not published) | J60: TBC | K60: TBC. Annual pattern: September to October (2026 ran 5 Sep to 17 Oct) | L60: Rotating cities across Japan | M60: Society regional meetings | N60: General ultrasound | O60: Seven regional meetings. Good for building a dealer and KOL map outside Tokyo and Osaka. | P60: Expected, not verified: Fujifilm (ex Hitachi ultrasound), Canon Medical, GE HealthCare, Philips Japan, Siemens Healthineers. Mindray and SonoScape: no Japan exhibitor evidence found. Samsung Medison: no direct Japan sales found (sold via Hitachi in 2017). | Q60: Unverified. | R60: Regional medical equipment trading houses and Fujifilm or Canon sales agents. Cross check against Japan_Distributor_List_Human_v1.xlsx in this repo. | S60: Medium | T60: Medium | U60: Regional, a few hundred each (est.) | V60: Not published. Request the exhibitor guide from the organiser. | W60: Not published. | X60: Check the JSUM calendar in spring 2027 and pick two regions near target dealers. | Y60: https://www.jsum.or.jp/members/calendar/2026/
A61: 21 | B61: P1 | C61: Both | D61: Japan | E61: Medical Japan Osaka 2027 | F61: 46659 | G61: 46661 | H61: 46631 | I61: 29 Sep to 1 Oct 2027 | J61: Confirmed | K61: Confirmed | L61: INTEX Osaka, Osaka | M61: Trade exhibition (13th edition, organised by RX Japan) | N61: Medical devices, hospital and care equipment | O61: Open commercial show. Many overseas OEMs exhibit, and dealers visit to find new brands. Best Japan show for distributor recruitment. | P61: Not documented. Chinese and Korean OEMs usually exhibit at RX Japan shows. | Q61: Unverified. | R61: Japanese dealers looking for new overseas brands. | S61: Low | T61: High | U61: Several hundred exhibitors (est.) | V61: Not published. RX Japan sells booths. | W61: Booth sales are open. Space is normally sold in tiers until about 3 months ahead. | X61: Priority for distributor search. Ask RX Japan for the 2026 exhibitor list to see which OEMs return. | Y61: https://medical-jpn.jp/osaka/en-gb.html
A62: 22 | B62: P2 | C62: Diagnostics | D62: Japan | E62: JDDW 2027, 35th Japan Digestive Disease Week | F62: 46688 | G62: 46690 | H62: 46661 | I62: 28 to 30 Oct 2027 | J62: Confirmed | K62: Confirmed | L62: Kobe Convention Center and other Kobe venues, Kobe | M62: National congress (5 societies together) | N62: Gastroenterology, hepatology, abdominal ultrasound, elastography | O62: Hepatology and GI ultrasound with liver fibrosis and fat quantification. Big hybrid meeting. | P62: Expected, not verified: Fujifilm, Canon, GE HealthCare, Philips expected. JDDW publishes exhibition PDFs each year. | Q62: Likely. exhibition PDF exists for JDDW 2026, 2025, 2024. | R62: Regional medical equipment trading houses and Fujifilm or Canon sales agents. Cross check against Japan_Distributor_List_Human_v1.xlsx in this repo. | S62: High | T62: Medium | U62: Very large (est. over 20,000) | V62: Not published. Request the exhibitor guide from the organiser. | W62: Exhibition PDFs are published about 6 months ahead. Ask JDDW office. | X62: Request the 2027 exhibition guide in spring 2027. | Y62: https://www.jddw.jp/jddw2027/index.html
A63: 23 | B63: P3 | C63: Diagnostics | D63: Japan | E63: HOSPEX Japan 2027 | H63: 46692 | I63: November 2027 (date not published) | J63: TBC | K63: TBC. Annual pattern: mid to late November (2026 is 18 to 20 Nov, before the window) | L63: Tokyo Big Sight West Halls, Tokyo | M63: Hospital equipment trade show | N63: Hospital facilities and equipment | O63: Hospital facility buyers. Imaging is a minor part of the floor. | P63: Not documented. | Q63: Unverified. | R63: Hospital equipment dealers. | S63: Low | T63: Medium | U63: Not published | V63: Not published. | W63: Not published. | X63: Check jma.or.jp/hospex in mid 2027. Optional. | Y63: https://www.jma.or.jp/hospex/

Sheet Vet Events
A1: CHISON Ultrasound Vet Event Plan | Singapore, Taiwan, South Korea, Japan | Dec 2026 to Dec 2027 | v1, prepared 25 Oct 2026
A2: # | B2: Priority | C2: Segment | D2: Country | E2: Event Name | F2: Start Date | G2: End Date | H2: Month (for sorting) | I2: Date as Published or Expected | J2: Date Class | K2: Date Status and Source Note | L2: City and Venue | M2: Type | N2: Field or Specialty | O2: Why It Matters for CHISON (product angle) | P2: Competitors Present or Expected | Q2: Competitor Evidence | R2: Local Dealers and Distributors to Meet | S2: KOL Potential | T2: Dealer Potential | U2: Scale or Attendance | V2: Cost Info (published) | W2: Deadlines That Bite | X2: Recommended Action | Y2: Source
A3: 1 | B3: P2 | C3: Vet | D3: Singapore | E3: SVA Small Animal Abdomen Ultrasound Workshop series (Singapore Veterinary Association) | H3: 46419 | I3: 2027 (not published) | J3: TBC | K3: TBC. Workshop notice on the SVA site; 2027 dates not published | L3: Singapore (venue not retrieved) | M3: Association workshop | N3: Small animal abdominal ultrasound | O3: SVA workshops reach the working vets in Singapore. Equipment loan again. | P3: Unverified. | Q3: Unverified. | R3: SVA corporate members. | S3: High | T3: Low | U3: Small | V3: Not retrieved. | W3: Not published. | X3: Contact the SVA secretariat about sponsor or equipment support. | Y3: https://sva.org.sg/news/small-animal-abdomen-ultrasound-workshop/
A4: 2 | B4: P2 | C4: Vet | D4: Singapore | E4: Temasek Polytechnic and Singapore Veterinary Imaging (SVI) vet ultrasound courses, supported by the Singapore Veterinary Association | H4: 46447 | I4: 2027 intake (dates not published) | J4: TBC | K4: TBC. Course run is announced on the SVA site without dates | L4: Temasek Polytechnic, Singapore (course page) | M4: Part time vet ultrasound courses | N4: Small animal abdominal and cardiac ultrasound | O4: Beginner to advanced vet ultrasound training for Singapore vets, subsidised for citizens and PRs. Scanner supply for hands on days is the opening. | P4: Training equipment supplier not stated. | Q4: Unverified. | R4: SVI and local vet suppliers. | S4: High | T4: Low | U4: Small classes | V4: Subsidised course fee (amount not retrieved) | W4: Course intake dates not published. | X4: Ask SVI and the SVA who supplies the scanners and whether CHISON can lend units. | Y4: https://sva.org.sg/news/tp-svi-small-animal-vet-ultrasound-courses/
A5: 3 | B5: P2 | C5: Vet | D5: Singapore | E5: PetExpo Singapore 2027 (13th) | F5: 46486 | G5: 46488 | H5: 46478 | I5: 9 to 11 Apr 2027 | J5: Provisional | K5: Official site shows 9 to 11 Apr. Some listings show 2 to 4 Apr, so verify | L5: Singapore EXPO Halls 5B and 6, Singapore | M5: Pet industry show (mostly consumer) | N5: Pets, pet products, services | O5: Consumer focused. Pet clinics and suppliers exhibit. Dealer contact value only. | P5: Not documented. | Q5: Unverified. | R5: Local vet equipment suppliers and regional ASEAN vet distributors who attend the Singapore Vet Show. | S5: Low | T5: Medium | U5: Not published | V5: Not published. | W5: Not published. | X5: Optional. Verify dates. | Y5: https://petexposg.com/
A6: 4 | B6: P3 | C6: Vet | D6: Singapore | E6: Vetducate Singapore introductory ultrasound workshop | H6: 46539 | I6: 2027 (not published) | J6: TBC | K6: TBC. One day in person workshop; 2027 date not on the page | L6: Singapore | M6: Commercial CE workshop | N6: Basic vet ultrasound | O6: Early career vets, nurses and technicians learning ultrasound. Probe exposure for new users. | P6: Unverified. | Q6: Unverified. | R6: Not applicable. | S6: Medium | T6: Low | U6: Small | V6: Not retrieved. | W6: Not published. | X6: Ask Vetducate which scanners are used. | Y6: https://www.vetducate.com/product-page/foundations-in-ultrasonography
A7: 5 | B7: P3 | C7: Vet | D7: Singapore | E7: SG Pet Festival 2027 | F7: 46598 | G7: 46600 | H7: 46569 | I7: 30 Jul to 1 Aug 2027 | J7: Provisional | K7: Organiser homepage shows 30 Jul to 1 Aug 2027 (page also has stale text), treat as provisional | L7: Marina Bay Sands Convention Centre, Singapore | M7: Consumer pet expo | N7: Pets | O7: Consumer show: 216 booths, 400+ brands in 2024. No B2B or vet track found. | P7: Not documented. | Q7: Unverified. | R7: Local vet equipment suppliers and regional ASEAN vet distributors who attend the Singapore Vet Show. | S7: Low | T7: Low | U7: 2024: 216 booths | V7: Not published. | W7: Not published. | X7: Skip unless a vet clinic partner exhibits. | Y7: https://www.sgpetfestival.com/
A8: 6 | B8: P2 | C8: Vet | D8: Singapore | E8: SVA Annual Conference 2027 (Singapore Veterinary Association) | H8: 46631 | I8: 2027 (not published) | J8: TBC | K8: TBC. The SVA advertised an Annual Conference for 2025; no 2027 date or venue found | L8: Singapore (venue not published) | M8: Association annual conference | N8: Small animal practice, continuing education | O8: The association of Singapore vets. Sponsor and exhibitor slots reach every practice owner in the country. | P8: Not documented for this event. Pretta Ultrasound exhibited at the Singapore Vet Show 2025. Other brands: unverified. | Q8: Unverified. | R8: Local vet equipment suppliers and regional ASEAN vet distributors who attend the Singapore Vet Show. | S8: High | T8: High | U8: Not published | V8: Not published. | W8: Not published. | X8: Email the SVA secretariat for 2027 dates and sponsor options (sva.org.sg). | Y8: https://sva.org.sg/about/
A9: 7 | B9: P1 | C9: Vet | D9: Singapore | E9: Singapore Vet Show 2027 (CloserStill Media) | H9: 46661 | I9: Oct 2027 likely (not confirmed) | J9: TBC | K9: TBC. Organiser page says new dates to be confirmed. A third party lists 24 to 25 Oct 2026; 2025 edition ran 24 to 25 Oct. Verify whether 2026 was held | L9: Suntec Singapore Convention and Exhibition Centre | M9: Conference led exhibition | N9: Small animal vets, clinical programme | O9: The only trade focused vet show in Singapore. Clinical programme for small animal vets, WSAVA education partnership reported. Best place to meet Singapore and ASEAN vet distributors. | P9: Pretta Ultrasound exhibited at the Singapore Vet Show 2025 (stand E30). Mindray, SonoScape, Esaote and other brands: unverified. | Q9: Partly confirmed: Pretta Ultrasound at Singapore Vet Show 2025. Others unverified. | R9: Local vet equipment suppliers and regional ASEAN vet distributors who attend the Singapore Vet Show. | S9: High | T9: High | U9: Over 110 brands (organiser). Listings range from 80 to 262 exhibitors | V9: Not published. | W9: Not published. Contact singaporevet@closerstillmedia.com. | X9: Email CloserStill now to confirm the next dates and the exhibitor price list. A third party lists the 2026 show as 24 to 25 Oct 2026, which is this weekend. If it is running, visit it in person. | Y9: https://www.vetshow.com/singapore-vet
A10: 1 | B10: P2 | C10: Both | D10: Taiwan | E10: Healthcare+ Expo Taiwan 2026 (general medtech show, vet distributors attend) | F10: 46359 | G10: 46362 | H10: 46357 | I10: 3 to 6 Dec 2026 | J10: Confirmed | K10: Confirmed | L10: Taipei Nangang Exhibition Center Hall 1, Taipei | M10: Trade exhibition | N10: Medical devices (human). Vet importers visit | O10: No dedicated vet hall, but importers of vet equipment walk the floor. See the Diagnostics tab. | P10: ASUS and Daikso showed handheld and portable ultrasound at the 2025 edition. | Q10: Partly confirmed (2025 edition). | R10: Uni Soar (GE vet series), Soarmed (VINNO), Eastech (Esaote), Getech (Philips cardiac), Vetsupply (Lilin, ultrasound category). These dealers already carry vet ultrasound from other brands, per their websites. | S10: Low | T10: Medium | U10: Third party: 650+ exhibitors | V10: Not published. | W10: Exhibitor sales probably closed. | X10: Visit. Look for vet ultrasound importers. | Y10: https://expo.taiwan-healthcare.org/en/
A11: 2 | B11: P3 | C11: Vet | D11: Taiwan | E11: Chanchao Kaohsiung Pets Show, December 2026 edition | F11: 46367 | G11: 46370 | H11: 46357 | I11: 11 to 14 Dec 2026 | J11: Confirmed | K11: Confirmed per organiser | L11: Kaohsiung Exhibition Center, Kaohsiung | M11: Pet industry show (consumer and trade) | N11: Pet food, products, services, health care | O11: Southern Taiwan pet industry. Held next to the AiCVS and AiCVIM congress, so one Kaohsiung trip covers both. | P11: Not documented. No vet booths mentioned in the listing. | Q11: Unverified. Exhibitor list for this edition is not published. | R11: Pet shops and pet clinic suppliers. | S11: Low | T11: Low | U11: 150 to 300 brands (organiser, figures conflict) | V11: Not published. | W11: Closed for exhibitors. | X11: Optional. Walk it on 12 Dec if attending AiCVS. | Y11: https://www.chanchao.com.tw/PetsShow/kaohsiung/
A12: 3 | B12: P1 | C12: Vet | D12: Taiwan | E12: AiCVS and AiCVIM Joint Congress 2026 (Asian veterinary surgery and internal medicine colleges) | F12: 46368 | G12: 46369 | H12: 46357 | I12: 12 to 13 Dec 2026 | J12: Confirmed | K12: Confirmed | L12: Kaohsiung Exhibition Center, Kaohsiung (venue per host association pages, the congress site names no venue) | M12: Specialist congress with sponsors | N12: Veterinary surgery and internal medicine (first joint meeting, first time in southern Taiwan) | O12: Specialist vets from across Asia. Hosts include the Taiwan College of Veterinary Surgeons, Kaohsiung Formosa Veterinary Clinical Medicine Association, Kaohsiung Veterinary Association and the Taiwan veterinary dermatology society. Only specialist vet event in Taiwan inside the window. | P12: Expected, not verified: Vet ultrasound brands shown on Taiwan distributor websites: GE vet series (Uni Soar), VINNO (Soarmed), Esaote (Eastech), Philips cardiac (Getech). Mindray, Samsung, SonoScape vet distributors in Taiwan: not found. | Q12: Unverified. The site has a Main Sponsors section but names did not load. | R12: Uni Soar (GE vet series), Soarmed (VINNO), Eastech (Esaote), Getech (Philips cardiac), Vetsupply (Lilin, ultrasound category). These dealers already carry vet ultrasound from other brands, per their websites. | S12: High | T12: Medium | U12: Not published | V12: Not published. Request the exhibitor guide from the organiser. | W12: Event is 7 weeks away. Sponsor and exhibitor slots may still be open. | X12: Email the organiser (aicvs-aicvim2026.tw) this week. Offer a scanner for the imaging session. | Y12: https://www.aicvs-aicvim2026.tw/
A13: 4 | B13: P3 | C13: Vet | D13: Taiwan | E13: Taipei Veterinary Medical Association continuing education series 2027 | H13: 46388 | I13: Through 2027 (dates not published) | J13: TBC | K13: TBC. The association runs about 10 sessions a year (2026 session 11 was on 30 Oct) | L13: National Taiwan University, Taipei (typical) | M13: Local CE sessions | N13: Small animal practice | O13: Taipei practitioners. Small, but a way to offer scanner demos and meet clinic owners. | P13: Expected, not verified: Vet ultrasound brands shown on Taiwan distributor websites: GE vet series (Uni Soar), VINNO (Soarmed), Esaote (Eastech), Philips cardiac (Getech). Mindray, Samsung, SonoScape vet distributors in Taiwan: not found. | Q13: Unverified. Exhibitor list for this edition is not published. | R13: Uni Soar (GE vet series), Soarmed (VINNO), Eastech (Esaote), Getech (Philips cardiac), Vetsupply (Lilin, ultrasound category). These dealers already carry vet ultrasound from other brands, per their websites. | S13: Medium | T13: Medium | U13: Under 300 per session (est.) | V13: Not published. Request the exhibitor guide from the organiser. | W13: Not published. | X13: Ask the association about vendor demo slots (tpvma.org.tw). | Y13: https://www.tpvma.org.tw/
A14: 5 | B14: P2 | C14: Vet | D14: Taiwan | E14: Taiwan Association of Veterinary Internal Medicine (TAVIM) academic events 2027 | H14: 46447 | I14: Spring 2027 (not published) | J14: TBC | K14: TBC. 2026 lectures ran on 28 to 29 Mar | L14: Taiwan (venue not published) | M14: Specialist society lectures | N14: Veterinary internal medicine | O14: Internal medicine specialists decide on ultrasound brands for referral hospitals. | P14: Expected, not verified: Vet ultrasound brands shown on Taiwan distributor websites: GE vet series (Uni Soar), VINNO (Soarmed), Esaote (Eastech), Philips cardiac (Getech). Mindray, Samsung, SonoScape vet distributors in Taiwan: not found. | Q14: Unverified. Exhibitor list for this edition is not published. | R14: Uni Soar (GE vet series), Soarmed (VINNO), Eastech (Esaote), Getech (Philips cardiac), Vetsupply (Lilin, ultrasound category). These dealers already carry vet ultrasound from other brands, per their websites. | S14: High | T14: Low | U14: Small | V14: Not published. Request the exhibitor guide from the organiser. | W14: Not published. | X14: Follow tavim.org and ask for sponsorship options. | Y14: https://tavim.org/
A15: 6 | B15: P3 | C15: Vet | D15: Taiwan | E15: Chanchao Taichung Pets and Aquarium Show 2027 | F15: 46521 | G15: 46524 | H15: 46508 | I15: 14 to 17 May 2027 | J15: Provisional | K15: Listed on a third party database. Verify with Chanchao | L15: Greater Taichung International Expo Center, Taichung | M15: Pet industry show | N15: Pets and aquarium | O15: Central Taiwan pet industry. | P15: Not documented. | Q15: Unverified. Exhibitor list for this edition is not published. | R15: Pet industry suppliers. | S15: Low | T15: Low | U15: Not published | V15: Not published. | W15: Not published. | X15: Optional. | Y15: https://www.eventseye.com/fairs/cst1_trade-shows_taiwan_pet-animals.html
A16: 7 | B16: P2 | C16: Vet | D16: Taiwan | E16: Taiwan College of Veterinary Surgeons (TCVS) continuing education events 2027 | H16: 46508 | I16: 2027 (not published) | J16: TBC | K16: TBC. The college runs events through the year; the 2026 joint congress is the anchor | L16: Taiwan (venue not published) | M16: Specialist society events | N16: Veterinary surgery | O16: Surgeon KOLs. The college lists annual sponsors. | P16: Expected, not verified: Vet ultrasound brands shown on Taiwan distributor websites: GE vet series (Uni Soar), VINNO (Soarmed), Esaote (Eastech), Philips cardiac (Getech). Mindray, Samsung, SonoScape vet distributors in Taiwan: not found. | Q16: Unverified. Exhibitor list for this edition is not published. | R16: Uni Soar (GE vet series), Soarmed (VINNO), Eastech (Esaote), Getech (Philips cardiac), Vetsupply (Lilin, ultrasound category). These dealers already carry vet ultrasound from other brands, per their websites. | S16: High | T16: Low | U16: Small | V16: Not published. Request the exhibitor guide from the organiser. | W16: Not published. | X16: Ask TCVS about annual sponsor tiers (tcvs.tw). | Y16: https://www.tcvs.tw/
A17: 8 | B17: P3 | C17: Vet | D17: Taiwan | E17: Chanchao Kaohsiung Pets Show, 2027 editions (held twice a year) | H17: 46539 | I17: 2027 (not published) | J17: TBC | K17: TBC. EventsEye lists the show as twice a year; the December edition is 11 Dec 2026 | L17: Kaohsiung Exhibition Center, Kaohsiung | M17: Pet industry show | N17: Pets | O17: Southern Taiwan pet industry. | P17: Not documented. | Q17: Unverified. Exhibitor list for this edition is not published. | R17: Pet industry suppliers. | S17: Low | T17: Low | U17: Not published | V17: Not published. | W17: Not published. | X17: Optional. | Y17: https://www.chanchao.com.tw/PetsShow/kaohsiung/
A18: 9 | B18: P2 | C18: Both | D18: Taiwan | E18: Medical Taiwan 2027 (general medtech show, vet distributors attend) | F18: 46576 | G18: 46578 | H18: 46569 | I18: 8 to 10 Jul 2027 | J18: Confirmed | K18: Confirmed per organiser page | L18: Taipei Nangang Exhibition Center Hall 1, Taipei | M18: Trade exhibition | N18: Medical devices (human) | O18: See the Diagnostics tab. Vet importers visit. | P18: Not documented. | Q18: Unverified. Exhibitor list for this edition is not published. | R18: Uni Soar (GE vet series), Soarmed (VINNO), Eastech (Esaote), Getech (Philips cardiac), Vetsupply (Lilin, ultrasound category). These dealers already carry vet ultrasound from other brands, per their websites. | S18: Low | T18: Medium | U18: Not published | V18: Not published. | W18: Not published. | X18: Visit. | Y18: https://www.medicaltaiwan.com.tw/zh-tw/index.html
A19: 10 | B19: P3 | C19: Vet | D19: Taiwan | E19: Chanchao Taipei Pets Show 2027 | H19: 46569 | I19: July 2027 (not confirmed) | J19: TBC | K19: TBC. Pattern: early July (2026 was 3 to 6 Jul, Nangang Hall 1). EventsEye lists July 2027 with a question mark | L19: Taipei Nangang Exhibition Center Hall 1, Taipei | M19: Pet industry show | N19: Pets, pet health | O19: Largest Taiwan pet show; some vet suppliers exhibit. | P19: Not documented. | Q19: Unverified. Exhibitor list for this edition is not published. | R19: Pet industry suppliers. | S19: Low | T19: Medium | U19: Not published | V19: Not published. | W19: Not published. | X19: Optional. Check chanchao.com.tw. | Y19: https://www.chanchao.com.tw/en/expoDetail.asp?id=AQP2026
A20: 11 | B20: P3 | C20: Vet | D20: Taiwan | E20: Chanchao Meow Expo 2027 | H20: 46661 | I20: Oct 2027 (not published) | J20: TBC | K20: TBC. Pattern: October (2026 is 8 to 11 Oct) | L20: Taipei Nangang Exhibition Center, Taipei | M20: Pet industry show (cats) | N20: Pet food, health care | O20: Cat owners and cat product makers. | P20: Not documented. | Q20: Unverified. Exhibitor list for this edition is not published. | R20: Pet industry suppliers. | S20: Low | T20: Low | U20: Not published | V20: Not published. | W20: Not published. | X20: Optional. | Y20: https://www.eventseye.com/fairs/f-chanchao-meow-expo-27744-1.html
A21: 1 | B21: P1 | C21: Vet | D21: South Korea | E21: KVECCS Academic Seminar with RECOVER workshop and POCUS ultrasound practice (Korean Veterinary Emergency and Critical Care Society) | F21: 46360 | G21: 46362 | H21: 46357 | I21: 4 to 6 Dec 2026 | J21: Provisional | K21: Reported by Daily Vet (media headline). Venue not stated. Past seminars were at Yuhan Corporation HQ, Seoul | L21: Seoul (venue to be confirmed) | M21: Society seminar with hands on workshops | N21: Veterinary emergency, critical care, POCUS ultrasound | O21: Hands on POCUS ultrasound practice for vets, a direct route to put CHISON probes in practitioners' hands. First vet event inside the window. | P21: Samsung Medison is the main Korean vet ultrasound competitor (Feb 2026 MoU with KAHA for a Samsung Sono VET Academy training network, not tied to this event). Presence at this event: unverified. Mindray and SonoScape vet: no Korean evidence found. | Q21: Unverified. Exhibitor list for this edition is not published. | R21: Korean vet equipment importers and Samsung Medison's vet channel. Dealer names not found in public sources. Collect importer cards at KAHA and Seoul conferences. | S21: High | T21: Medium | U21: Hundreds (est.) | V21: Not published. Request the exhibitor guide from the organiser. | W21: Event is 6 weeks away. Ask the society now for a scanner loan slot. | X21: Contact KVECCS this week: offer 3 to 4 scanners for the POCUS practical session. | Y21: https://www.dailyvet.co.kr/news/academy
A22: 2 | B22: P2 | C22: Both | D22: South Korea | E22: KIMES 2027 (general medtech show, vet distributors attend) | F22: 46464 | G22: 46467 | H22: 46447 | I22: 18 to 21 Mar 2027 | J22: Provisional | K22: Reported on the official site listing (read through a search extract). Third party listings agree. Re check on kimes.kr | L22: COEX Halls, Seoul | M22: Trade exhibition | N22: Medical devices (human). Vet importers visit | O22: Korean vet equipment importers walk KIMES. See the Diagnostics tab for the full entry. | P22: Samsung Medison confirmed at KIMES 2026 (human ultrasound). Vet booth presence not documented. | Q22: Confirmed for Samsung (human range). | R22: Korean vet equipment importers and Samsung Medison's vet channel. Dealer names not found in public sources. Collect importer cards at KAHA and Seoul conferences. | S22: Low | T22: High | U22: About 1,500 booths (2026, media) | V22: Not published. | W22: Booth dates not found. | X22: Use the visit to collect vet importer contacts. | Y22: https://www.kimes.kr/
A23: 3 | B23: P2 | C23: Vet | D23: South Korea | E23: Seoul Veterinary Clinical Conference, Spring 2027 (Seoul Veterinary Medical Association) | H23: 46447 | I23: Late Mar 2027 (not published) | J23: TBC | K23: TBC. Annual pattern: late March (2026 was 28 to 29 Mar at Sejong University Convention Center) | L23: Sejong University Convention Center, Seoul (2026 venue) | M23: Practitioner conference with exhibition | N23: Small animal practice | O23: Seoul clinic owners who buy equipment. Exhibitors reported that booth visitors are mostly junior vets, so target the clinic director sessions. | P23: Samsung Medison is the main Korean vet ultrasound competitor (Feb 2026 MoU with KAHA for a Samsung Sono VET Academy training network, not tied to this event). Presence at this event: unverified. Mindray and SonoScape vet: no Korean evidence found. | Q23: The Samsung and KAHA MoU is confirmed (Korea Biomedical Review, Feb 2026). Presence at this event is unverified. | R23: Korean vet equipment importers and Samsung Medison's vet channel. Dealer names not found in public sources. Collect importer cards at KAHA and Seoul conferences. | S23: Medium | T23: High | U23: Hundreds to low thousands (est.) | V23: Not published. Request the exhibitor guide from the organiser. | W23: Not published. Check svma.or.kr from January. | X23: Request the exhibitor guide in January. | Y23: https://www.svma.or.kr/conference/conferenceList.do
A24: 4 | B24: P3 | C24: Vet | D24: South Korea | E24: Korean Society of Veterinary Science (KSVS) Spring Meeting 2027 | H24: 46478 | I24: Apr 2027 (not published) | J24: TBC | K24: TBC. Annual pattern: April (2026 was 23 Apr at Hotel Intercity) | L24: Seoul area (2026 venue) | M24: Academic meeting | N24: Veterinary science (research) | O24: Academic audience and university vet hospitals. Useful for KOL links. | P24: Not documented. | Q24: Unverified. Exhibitor list for this edition is not published. | R24: Low. | S24: Medium | T24: Low | U24: Hundreds (est.) | V24: Not published. Request the exhibitor guide from the organiser. | W24: Not published. | X24: Optional. | Y24: https://www.ksvs.or.kr/conference/conferenceList.do
A25: 5 | B25: P3 | C25: Vet | D25: South Korea | E25: Korean Society of Veterinary Surgery regular meeting and academic session 2027 | H25: 46478 | I25: Spring 2027 (not published) | J25: TBC | K25: TBC. Pattern: spring (2026 was 5 Apr at Seoul National University Schofield Hall) | L25: Seoul National University College of Veterinary Medicine (2026 venue) | M25: Society meeting | N25: Veterinary surgery | O25: Surgeon KOLs at university hospitals. | P25: Not documented. | Q25: Unverified. Exhibitor list for this edition is not published. | R25: Low. | S25: Medium | T25: Low | U25: Small | V25: Not published. Request the exhibitor guide from the organiser. | W25: Not published. | X25: Optional. | Y25: https://www.dailyvet.co.kr/events/20260405ksvs
A26: 6 | B26: P3 | C26: Vet | D26: South Korea | E26: MEGAZOO 2027 Season 1 (KINTEX, Ilsan) | H26: 46508 | I26: Late May 2027 (not published) | J26: TBC | K26: TBC. Two seasons a year (2026 Season 1 was 29 to 31 May) | L26: KINTEX, Goyang, Gyeonggi | M26: Pet industry show (consumer and trade) | N26: Pet products, services, animal health | O26: Largest Korean pet show: about 500 brands. Not clinical, but animal hospital owners and pet product distributors attend. | P26: Not documented. | Q26: Unverified. Exhibitor list for this edition is not published. | R26: Pet industry distributors. | S26: Low | T26: Medium | U26: 2025: over 50,000 visitors (press) | V26: Not published. | W26: Not published. | X26: Optional dealer scouting visit. | Y26: https://megazoo.co.kr/
A27: 7 | B27: P1 | C27: Vet | D27: South Korea | E27: 24th KAHA Conference with KSVC Spring Meeting 2027 (Korean Animal Hospital Association and Korean Society of Veterinary Clinics) | F27: 46542 | G27: 46544 | H27: 46539 | I27: 4 to 6 Jun 2027 | J27: Provisional | K27: Reported by Daily Vet (media, Oct 2026). Verify on the KAHA site | L27: COEX Magok, Seoul | M27: Practitioner congress with hands on training | N27: Small animal practice, cardiac ultrasound, anaesthesia | O27: The main Korean small animal practitioner congress. At the Oct 2026 joint edition in Gyeongju the hands on cardiac ultrasound and anaesthesia sessions were already fully booked (Daily Vet). Samsung Medison has a training partnership with KAHA, so expect it to be strong here. Still the best place to meet clinic owners and importers. | P27: Samsung Medison: signed a training partnership with KAHA in Feb 2026 (Samsung Sono VET Academy, KAHA STARTER ultrasound course), so a strong presence is likely. Presence at this conference is not yet confirmed. Mindray and SonoScape vet: no Korean evidence found. | Q27: The Samsung and KAHA MoU is confirmed. Event presence is unverified. | R27: Korean vet equipment importers and Samsung Medison's vet channel. Dealer names not found in public sources. Collect importer cards at KAHA and Seoul conferences. | S27: High | T27: High | U27: KSVC meeting received about 250 abstracts (Daily Vet) | V27: Not published. Request the exhibitor guide from the organiser. | W27: Exhibitor terms not found. Joint organising committee formed Oct 2026, so call the KAHA secretariat in November. | X27: Priority 1 for Korea vet. Ask KAHA for exhibitor tiers and whether an independent hands on station is possible next to Samsung. | Y27: https://www.dailyvet.co.kr/news/academy/299184
A28: 8 | B28: P2 | C28: Vet | D28: South Korea | E28: Seoul Veterinary Clinical Conference, Autumn 2027 (Seoul Veterinary Medical Association) | H28: 46631 | I28: Sep 2027 (not published) | J28: TBC | K28: TBC. Annual pattern: September (2026 was 19 to 20 Sep, Sejong University) | L28: Sejong University Convention Center, Seoul (2026 venue) | M28: Practitioner conference with exhibition | N28: Small animal practice | O28: Second Seoul clinic owner conference of the year. | P28: Samsung Medison is the main Korean vet ultrasound competitor (Feb 2026 MoU with KAHA for a Samsung Sono VET Academy training network, not tied to this event). Presence at this event: unverified. Mindray and SonoScape vet: no Korean evidence found. | Q28: The Samsung and KAHA MoU is confirmed (Korea Biomedical Review, Feb 2026). Presence at this event is unverified. | R28: Korean vet equipment importers and Samsung Medison's vet channel. Dealer names not found in public sources. Collect importer cards at KAHA and Seoul conferences. | S28: Medium | T28: High | U28: Hundreds to low thousands (est.) | V28: Not published. Request the exhibitor guide from the organiser. | W28: Not published. | X28: Decide after the spring edition. | Y28: https://www.svma.or.kr/conference/conferenceList.do
A29: 9 | B29: P2 | C29: Vet | D29: South Korea | E29: Second KAHA, KSVC and Yeongnam joint veterinary conference 2027 (Yeongnam region) | H29: 46661 | I29: H2 2027, likely Aug to Oct (not published) | J29: TBC | K29: TBC. Reports conflict: Daegu (Yeongnam Conference) and Busan Haeundae (merged Busan and Yeongnam conference). First joint event was 17 to 18 Oct 2026 at Gyeongju | L29: Daegu or Busan (conflicting reports) | M29: Practitioner congress, expo style | N29: Small animal practice, hands on ultrasound and anaesthesia | O29: Southeast Korea clinic owners. The organisers are rebuilding the event as an expo to link vendors with clinics, citing VMX as a model, and will expand hands on ultrasound practice. Exhibitors can run product demos and practicals. | P29: Samsung Medison is the main Korean vet ultrasound competitor (Feb 2026 MoU with KAHA for a Samsung Sono VET Academy training network, not tied to this event). Presence at this event: unverified. Mindray and SonoScape vet: no Korean evidence found. | Q29: The Samsung and KAHA MoU is confirmed (Korea Biomedical Review, Feb 2026). Presence at this event is unverified. | R29: Korean vet equipment importers and Samsung Medison's vet channel. Dealer names not found in public sources. Collect importer cards at KAHA and Seoul conferences. | S29: Medium | T29: High | U29: Not published | V29: Not published. Request the exhibitor guide from the organiser. | W29: Not published. | X29: Ask the organisers about vendor hands on slots; this is an opening for an independent ultrasound practical. | Y29: https://www.dailyvet.co.kr/news/association/282228
A30: 10 | B30: P2 | C30: Vet | D30: South Korea | E30: Gyeonggi North Veterinary Conference 2027 with Korean Society of Veterinary Cardiology (KINTEX) | H30: 46692 | I30: Nov 2027 (not published) | J30: TBC | K30: TBC. Annual pattern: early November (2026 was 7 to 8 Nov at KINTEX Ilsan) | L30: KINTEX, Ilsan, Gyeonggi | M30: Regional practitioner conference | N30: Small animal practice, cardiology | O30: Northern Gyeonggi practitioners. Held with the cardiology society, so cardiac ultrasound users attend. | P30: Samsung Medison is the main Korean vet ultrasound competitor (Feb 2026 MoU with KAHA for a Samsung Sono VET Academy training network, not tied to this event). Presence at this event: unverified. Mindray and SonoScape vet: no Korean evidence found. | Q30: Unverified. Exhibitor list for this edition is not published. | R30: Korean vet equipment importers and Samsung Medison's vet channel. Dealer names not found in public sources. Collect importer cards at KAHA and Seoul conferences. | S30: Medium | T30: Medium | U30: Not published | V30: Not published. Request the exhibitor guide from the organiser. | W30: Not published. | X30: Check dailyvet.co.kr in summer 2027. | Y30: https://www.dailyvet.co.kr/news/academy/300170
A31: 11 | B31: P3 | C31: Vet | D31: South Korea | E31: MEGAZOO 2027 Season 2 (KINTEX, Ilsan) | H31: 46692 | I31: Nov 2027 (not published) | J31: TBC | K31: TBC. 2026 Season 2 is 20 to 22 Nov | L31: KINTEX, Goyang, Gyeonggi | M31: Pet industry show (consumer and trade) | N31: Pet products and animal health | O31: Second MEGAZOO of the year. | P31: Not documented. | Q31: Unverified. Exhibitor list for this edition is not published. | R31: Pet industry distributors. | S31: Low | T31: Medium | U31: See Season 1 | V31: Not published. | W31: Not published. | X31: Optional. | Y31: https://megazoo.co.kr/
A32: 12 | B32: P3 | C32: Vet | D32: South Korea | E32: Korean Society of Veterinary Science (KSVS) Autumn International Meeting 2027 | H32: 46692 | I32: Nov 2027 (not published) | J32: TBC | K32: TBC. Annual pattern: early November (2026 is 1 to 3 Nov at Jeju ICC) | L32: Rotating city (2026: Jeju) | M32: Academic international meeting | N32: Veterinary science (research) | O32: Academic. | P32: Not documented. | Q32: Unverified. Exhibitor list for this edition is not published. | R32: Low. | S32: Medium | T32: Low | U32: Hundreds (est.) | V32: Not published. Request the exhibitor guide from the organiser. | W32: Not published. | X32: Optional. | Y32: https://www.ksvs.or.kr/conference/conferenceList.do
A33: 1 | B33: P2 | C33: Vet | D33: Japan | E33: JSVDI 79th Japanese Society of Veterinary Diagnostic Imaging Meeting | F33: 46361 | G33: 46362 | H33: 46357 | I33: 5 to 6 Dec 2026 | J33: Confirmed | K33: Confirmed | L33: Fukuoka International Congress Center, Fukuoka | M33: Society scientific meeting (twice a year) | N33: Veterinary diagnostic imaging, ultrasound, CT, MRI | O33: The imaging society. Veterinary ultrasound specialists are the KOLs who set brand preference. The 78th meeting offered exhibit slots to vendors. | P33: Expected, not verified: Fujifilm VET Systems (market leader, wireless echo), Canon Medtech Supply (vet ultrasound), Mediark. SonoScape and Mindray vet models are imported by Shoei Japan. Samsung: no Japan vet distributor found. | Q33: Likely. The 78th meeting (Jun 2026) sold exhibits, vendors not named. | R33: Shoei Japan (importer of SonoScape S6V, A6V, X5V, E2V and Mindray 6600vet), Mediark, Nittoku Medical, Frontier International (livestock ultrasound). Approach these as competitor dealers who may take a second brand. | S33: High | T33: Medium | U33: Several hundred (est.) | V33: Not published. Request the exhibitor guide from the organiser. | W33: Event is 6 weeks away. Ask the secretariat now for any remaining exhibit space. | X33: Request an exhibit slot or visit to meet imaging KOLs. Plan the June 2027 meeting as the booth event. | Y33: https://jsvdi.com/conference/3332/
A34: 2 | B34: P3 | C34: Vet | D34: Japan | E34: Skyvets abdominal ultrasound hands on seminar series (monthly, third Wednesday) | F34: 46372 | G34: 46372 | H34: 46357 | I34: 16 Dec 2026, 20 Jan, 17 Feb, 17 Mar 2027 | J34: Confirmed | K34: Confirmed (dates published for Oct 2026 to Mar 2027) | L34: Not stated (online imaging service with hands on) | M34: Commercial CME course | N34: Vet abdominal ultrasound | O34: Beginner vets learn ultrasound here. Equipment supply to these courses would put CHISON probes in new users' hands. | P34: Training device supplier not stated. | Q34: Unverified. Exhibitor list for this edition is not published. | R34: Not applicable. | S34: Medium | T34: Low | U34: Small classes | V34: Not retrieved. | W34: Registration per session. | X34: Ask Skyvets which scanners are used. | Y34: https://sky-vets.com/seminar/
A35: 3 | B35: P2 | C35: Vet | D35: Japan | E35: JSVAS 113th Japanese Society of Veterinary Anesthesia and Surgery Meeting | F35: 46374 | G35: 46376 | H35: 46357 | I35: 18 to 20 Dec 2026 | J35: Confirmed | K35: Confirmed | L35: Congress Square Grand Green Osaka, Osaka | M35: Society scientific meeting (with the 31st Veterinary Endoscopic Surgery meeting) | N35: Veterinary anaesthesia and surgery | O35: Ultrasound guided blocks and intra operative scanning. Surgeons choose portable ultrasound for theatre. | P35: Expected, not verified: Fujifilm VET Systems (market leader, wireless echo), Canon Medtech Supply (vet ultrasound), Mediark. SonoScape and Mindray vet models are imported by Shoei Japan. Samsung: no Japan vet distributor found. | Q35: Unverified. Exhibitor list for this edition is not published. | R35: Shoei Japan (importer of SonoScape S6V, A6V, X5V, E2V and Mindray 6600vet), Mediark, Nittoku Medical, Frontier International (livestock ultrasound). Approach these as competitor dealers who may take a second brand. | S35: Medium | T35: Medium | U35: Several hundred (est.) | V35: Not published. Request the exhibitor guide from the organiser. | W35: Event is 8 weeks away. Ask the secretariat now. | X35: Visit or exhibit if a Kansai vet dealer partner is in place. | Y35: https://www.jsvas.net/conference/index.php
A36: 4 | B36: P3 | C36: Vet | D36: Japan | E36: Japanese Veterinary Cancer Society 35th Meeting | F36: 46417 | G36: 46418 | H36: 46388 | I36: 30 to 31 Jan 2027 | J36: Confirmed | K36: Confirmed | L36: Hotel New Otani Osaka, Osaka | M36: Society scientific meeting | N36: Veterinary oncology | O36: Oncology specialists use ultrasound for staging and guided biopsy. | P36: Expected, not verified: Fujifilm VET Systems (market leader, wireless echo), Canon Medtech Supply (vet ultrasound), Mediark. SonoScape and Mindray vet models are imported by Shoei Japan. Samsung: no Japan vet distributor found. | Q36: Unverified. Exhibitor list for this edition is not published. | R36: Shoei Japan (importer of SonoScape S6V, A6V, X5V, E2V and Mindray 6600vet), Mediark, Nittoku Medical, Frontier International (livestock ultrasound). Approach these as competitor dealers who may take a second brand. | S36: Medium | T36: Low | U36: Several hundred (est.) | V36: Not published. Request the exhibitor guide from the organiser. | W36: Not published. | X36: Optional. Attend if an Osaka dealer meeting is booked. | Y36: https://www.jvcs.jp/society/
A37: 5 | B37: P1 | C37: Vet | D37: Japan | E37: JCVIM 2027, 23rd Japanese College of Veterinary Internal Medicine Annual Meeting | F37: 46437 | G37: 46439 | H37: 46419 | I37: 19 to 21 Feb 2027 | J37: Confirmed | K37: Confirmed | L37: Pacifico Yokohama North, Yokohama | M37: Academic congress with company exhibition and luncheon seminars | N37: Small animal internal medicine | O37: Internal medicine specialists are heavy ultrasound users. A documented sponsorship path exists, which makes this the best vet booth event in Japan. | P37: Confirmed: Fujifilm VET Systems and Fujifilm Healthcare exhibited and ran seminars at JCVIM 2024, 2025 and 2026. Others not found. | Q37: Confirmed for Fujifilm (prior editions). | R37: Shoei Japan (importer of SonoScape S6V, A6V, X5V, E2V and Mindray 6600vet), Mediark, Nittoku Medical, Frontier International (livestock ultrasound). Approach these as competitor dealers who may take a second brand. | S37: High | T37: Medium | U37: About 1,500 to 2,000 (est.) | V37: Sponsorship tiers on smartconf.jp. Fees not retrieved. | W37: Sponsor recruitment opened 7 Jul 2026. Closing date not stated, so assume it is close. | X37: Open smartconf.jp/content/jcvim2027/sponsorship now and request the tier list. Decide in November. | Y37: https://www.jcvim.org/
A38: 6 | B38: P2 | C38: Vet | D38: Japan | E38: JVMA 44th Veterinary Academic Society Annual Meeting (Japan Veterinary Medical Association) | F38: 46445 | G38: 46446 | H38: 46419 | I38: 27 to 28 Feb 2027 | J38: Confirmed | K38: Confirmed per JVMA magazine | L38: Azabu University, Sagamihara, Kanagawa | M38: National veterinary society meeting | N38: Small animal, large animal and public health sessions | O38: Nationwide practitioner audience including livestock vets who use ultrasound for pregnancy checks. | P38: Expected, not verified: Fujifilm VET Systems (cattle wireless echo). Others unverified. | Q38: Likely. | R38: Shoei Japan (importer of SonoScape S6V, A6V, X5V, E2V and Mindray 6600vet), Mediark, Nittoku Medical, Frontier International (livestock ultrasound). Approach these as competitor dealers who may take a second brand. | S38: Medium | T38: Medium | U38: Thousands (est.) | V38: Not published. Request the exhibitor guide from the organiser. | W38: Not published. | X38: Check JVMA site for exhibitor guide in autumn. | Y38: https://jvma-vet.jp/society/
A39: 7 | B39: P3 | C39: Vet | D39: Japan | E39: JBVP Nagoya Regional Meeting (7th) | F39: 46446 | G39: 46446 | H39: 46419 | I39: 28 Feb 2027 | J39: Confirmed | K39: Confirmed per JBVP site (read through a search extract, my direct fetch was blocked) | L39: Wink Aichi (Aichi Industry and Labor Center), Nagoya | M39: Regional practitioner forum | N39: Small animal practice | O39: Chubu region vet practitioners and dealers. | P39: Expected, not verified: Fujifilm VET Systems (market leader, wireless echo), Canon Medtech Supply (vet ultrasound), Mediark. SonoScape and Mindray vet models are imported by Shoei Japan. Samsung: no Japan vet distributor found. | Q39: Unverified. Exhibitor list for this edition is not published. | R39: Shoei Japan (importer of SonoScape S6V, A6V, X5V, E2V and Mindray 6600vet), Mediark, Nittoku Medical, Frontier International (livestock ultrasound). Approach these as competitor dealers who may take a second brand. | S39: Low | T39: Medium | U39: Hundreds (est.) | V39: Not published. Request the exhibitor guide from the organiser. | W39: Not published. | X39: Visit only when the same week includes a Chubu dealer meeting. | Y39: https://www.jbvp.org/regional/nagoya.html
A40: 8 | B40: P3 | C40: Vet | D40: Japan | E40: JBVP Kyushu Regional Meeting (23rd) | F40: 46467 | G40: 46467 | H40: 46447 | I40: 21 Mar 2027 | J40: Confirmed | K40: Confirmed per JBVP site (read through a search extract, my direct fetch was blocked) | L40: Fukuoka International Congress Center, Fukuoka | M40: Regional practitioner forum | N40: Small animal practice | O40: Kyushu vets and dealers. | P40: Expected, not verified: Fujifilm VET Systems (market leader, wireless echo), Canon Medtech Supply (vet ultrasound), Mediark. SonoScape and Mindray vet models are imported by Shoei Japan. Samsung: no Japan vet distributor found. | Q40: Unverified. Exhibitor list for this edition is not published. | R40: Shoei Japan (importer of SonoScape S6V, A6V, X5V, E2V and Mindray 6600vet), Mediark, Nittoku Medical, Frontier International (livestock ultrasound). Approach these as competitor dealers who may take a second brand. | S40: Low | T40: Medium | U40: Hundreds (est.) | V40: Not published. Request the exhibitor guide from the organiser. | W40: Not published. | X40: Bundle with the JBVP Hokkaido date only if travel allows. | Y40: https://www.jbvp.org/regional/kyushu.html
A41: 9 | B41: P3 | C41: Vet | D41: Japan | E41: JBVP Hokkaido Regional Meeting (25th) | F41: 46474 | G41: 46474 | H41: 46447 | I41: 28 Mar 2027 | J41: Confirmed | K41: Confirmed per JBVP site (read through a search extract, my direct fetch was blocked) | L41: Sapporo Convention Center, Sapporo | M41: Regional practitioner forum | N41: Small animal and mixed animal practice | O41: Hokkaido has strong mixed animal practices that scan cattle and pets. | P41: Expected, not verified: Fujifilm VET Systems (market leader, wireless echo), Canon Medtech Supply (vet ultrasound), Mediark. SonoScape and Mindray vet models are imported by Shoei Japan. Samsung: no Japan vet distributor found. | Q41: Unverified. Exhibitor list for this edition is not published. | R41: Shoei Japan (importer of SonoScape S6V, A6V, X5V, E2V and Mindray 6600vet), Mediark, Nittoku Medical, Frontier International (livestock ultrasound). Approach these as competitor dealers who may take a second brand. | S41: Low | T41: Medium | U41: Hundreds (est.) | V41: Not published. Request the exhibitor guide from the organiser. | W41: Not published. | X41: Optional. | Y41: https://www.jbvp.org/regional/hokkaido.html
A42: 10 | B42: P3 | C42: Vet | D42: Japan | E42: JBVP Tohoku Regional Meeting (26th) | H42: 46447 | I42: March 2027 (not published) | J42: TBC | K42: TBC. Annual pattern: March (25th was 22 Mar 2026 at Sendai International Center) | L42: Sendai (2026 venue: Sendai International Center) | M42: Regional practitioner forum | N42: Small animal practice | O42: Tohoku region vets and dealers. | P42: Expected, not verified: Fujifilm VET Systems (market leader, wireless echo), Canon Medtech Supply (vet ultrasound), Mediark. SonoScape and Mindray vet models are imported by Shoei Japan. Samsung: no Japan vet distributor found. | Q42: Unverified. Exhibitor list for this edition is not published. | R42: Shoei Japan (importer of SonoScape S6V, A6V, X5V, E2V and Mindray 6600vet), Mediark, Nittoku Medical, Frontier International (livestock ultrasound). Approach these as competitor dealers who may take a second brand. | S42: Low | T42: Medium | U42: Hundreds (est.) | V42: Not published. Request the exhibitor guide from the organiser. | W42: Not published. | X42: Check jbvp.org in January. | Y42: https://www.jbvp.org/regional/tohoku.html
A43: 11 | B43: P3 | C43: Vet | D43: Japan | E43: JBVP Kyoto Regional Meeting (20th) | H43: 46447 | I43: March 2027 (not published) | J43: TBC | K43: TBC. Annual pattern: March (19th was 8 Mar 2026 at TKP Garden City Kyoto Tower Hotel) | L43: Kyoto | M43: Regional practitioner forum | N43: Small animal practice | O43: Kansai vets and dealers. | P43: Expected, not verified: Fujifilm VET Systems (market leader, wireless echo), Canon Medtech Supply (vet ultrasound), Mediark. SonoScape and Mindray vet models are imported by Shoei Japan. Samsung: no Japan vet distributor found. | Q43: Unverified. Exhibitor list for this edition is not published. | R43: Shoei Japan (importer of SonoScape S6V, A6V, X5V, E2V and Mindray 6600vet), Mediark, Nittoku Medical, Frontier International (livestock ultrasound). Approach these as competitor dealers who may take a second brand. | S43: Low | T43: Medium | U43: Hundreds (est.) | V43: Not published. Request the exhibitor guide from the organiser. | W43: Not published. | X43: Check jbvp.org in January. | Y43: https://www.jbvp.org/regional/kyoto.html
A44: 12 | B44: P3 | C44: Vet | D44: Japan | E44: Interpets Tokyo 2027 (16th) | F44: 46478 | G44: 46481 | H44: 46478 | I44: 1 to 4 Apr 2027 | J44: Confirmed | K44: Confirmed. Business day is 1 Apr, public from 2 Apr | L44: Tokyo Big Sight East Halls 1 to 4, 7, 8, Tokyo | M44: Pet industry trade and consumer show | N44: Pet products, services, animal health | O44: Pet industry show, not clinical. Vet clinic owners and pet product distributors walk the business day. Dealer sourcing only. | P44: Not documented. Vet equipment is a minor part of the floor. | Q44: Unverified. Exhibitor list for this edition is not published. | R44: Pet industry distributors. | S44: Low | T44: Medium | U44: Organiser forecast: 800 exhibitors, 69,000 visitors | V44: Not published. Mini booths sold out. | W44: Mini booth sales closed. Regular booths still open per organiser. | X44: Visit the business day only. Low priority. | Y44: https://interpets.jp.messefrankfurt.com/tokyo/en/facts-figures.html
A45: 13 | B45: P2 | C45: Vet | D45: Japan | E45: JSVC Spring Meeting 2027 (Japanese Society of Veterinary Cardiology) | H45: 46478 | I45: Spring 2027 (not published) | J45: TBC | K45: TBC. The society holds two meetings a year: spring near Tokyo, autumn in rotating cities | L45: Tokyo area | M45: Society scientific meeting | N45: Veterinary cardiology and echocardiography | O45: Cardiology specialists. Cardiac echo probes are a high value vet sale. | P45: Expected, not verified: Fujifilm VET Systems (market leader, wireless echo), Canon Medtech Supply (vet ultrasound), Mediark. SonoScape and Mindray vet models are imported by Shoei Japan. Samsung: no Japan vet distributor found. | Q45: Unverified. Exhibitor list for this edition is not published. | R45: Shoei Japan (importer of SonoScape S6V, A6V, X5V, E2V and Mindray 6600vet), Mediark, Nittoku Medical, Frontier International (livestock ultrasound). Approach these as competitor dealers who may take a second brand. | S45: High | T45: Low | U45: Hundreds (est.) | V45: Not published. Request the exhibitor guide from the organiser. | W45: Not published. | X45: Check jsvc.jp/meeting in January. | Y45: https://www.jsvc.jp/meeting/
A46: 14 | B46: P3 | C46: Vet | D46: Japan | E46: Interpets Osaka 2027 (5th) | F46: 46549 | G46: 46551 | H46: 46539 | I46: 11 to 13 Jun 2027 | J46: Confirmed | K46: Confirmed | L46: INTEX Osaka Halls 4, 5, 6A, 6B, Osaka | M46: Pet industry trade and consumer show | N46: Pet products and services | O46: Kansai pet industry. Same logic as Tokyo. | P46: Not documented. | Q46: Unverified. Exhibitor list for this edition is not published. | R46: Pet industry distributors. | S46: Low | T46: Low | U46: Not published | V46: Not published. Exhibitor recruitment open. | W46: Open now. | X46: Optional. | Y46: https://interpets-osaka.jp.messefrankfurt.com/osaka/en.html
A47: 15 | B47: P1 | C47: Vet | D47: Japan | E47: JSVDI 80th Japanese Society of Veterinary Diagnostic Imaging Meeting | H47: 46539 | I47: June 2027 (not published) | J47: TBC | K47: TBC. Annual pattern: June (78th was 13 to 14 Jun 2026, Tokyo University of Agriculture and Technology, Fuchu) | L47: Rotating venue (university campus or congress centre) | M47: Society scientific meeting | N47: Veterinary diagnostic imaging | O47: Second JSVDI meeting of 2027 and the best mid year chance to meet imaging KOLs. | P47: Expected, not verified: Fujifilm VET Systems (market leader, wireless echo), Canon Medtech Supply (vet ultrasound), Mediark. SonoScape and Mindray vet models are imported by Shoei Japan. Samsung: no Japan vet distributor found. | Q47: Likely. The 78th meeting sold exhibits. | R47: Shoei Japan (importer of SonoScape S6V, A6V, X5V, E2V and Mindray 6600vet), Mediark, Nittoku Medical, Frontier International (livestock ultrasound). Approach these as competitor dealers who may take a second brand. | S47: High | T47: Medium | U47: Several hundred (est.) | V47: Not published. Request the exhibitor guide from the organiser. | W47: Exhibit call for the 78th meeting appeared months ahead. | X47: Check jsvdi.com from January 2027. | Y47: https://jsvdi.com/category/conference/
A48: 16 | B48: P2 | C48: Vet | D48: Japan | E48: JSVAS 114th Japanese Society of Veterinary Anesthesia and Surgery Meeting | H48: 46539 | I48: June 2027 (not published) | J48: TBC | K48: TBC. Annual pattern: June (112th was 19 to 21 Jun 2026, Omiya Sonic City) | L48: Rotating city | M48: Society scientific meeting | N48: Veterinary anaesthesia and surgery | O48: Same audience as Dec 2026. | P48: Expected, not verified: Fujifilm VET Systems (market leader, wireless echo), Canon Medtech Supply (vet ultrasound), Mediark. SonoScape and Mindray vet models are imported by Shoei Japan. Samsung: no Japan vet distributor found. | Q48: Unverified. Exhibitor list for this edition is not published. | R48: Shoei Japan (importer of SonoScape S6V, A6V, X5V, E2V and Mindray 6600vet), Mediark, Nittoku Medical, Frontier International (livestock ultrasound). Approach these as competitor dealers who may take a second brand. | S48: Medium | T48: Medium | U48: Several hundred (est.) | V48: Not published. Request the exhibitor guide from the organiser. | W48: Not published. | X48: Check jsvas.net in 2027. | Y48: https://www.jsvas.net/conference/index.php
A49: 17 | B49: P3 | C49: Vet | D49: Japan | E49: Japanese Veterinary Cancer Society 36th Meeting | F49: 46571 | G49: 46572 | H49: 46569 | I49: 3 to 4 Jul 2027 | J49: Confirmed | K49: Confirmed per society page | L49: Hotel New Otani Tokyo, Tokyo | M49: Society scientific meeting | N49: Veterinary oncology | O49: Oncology staging with ultrasound. | P49: Expected, not verified: Fujifilm VET Systems (market leader, wireless echo), Canon Medtech Supply (vet ultrasound), Mediark. SonoScape and Mindray vet models are imported by Shoei Japan. Samsung: no Japan vet distributor found. | Q49: Unverified. Exhibitor list for this edition is not published. | R49: Shoei Japan (importer of SonoScape S6V, A6V, X5V, E2V and Mindray 6600vet), Mediark, Nittoku Medical, Frontier International (livestock ultrasound). Approach these as competitor dealers who may take a second brand. | S49: Medium | T49: Low | U49: Several hundred (est.) | V49: Not published. Request the exhibitor guide from the organiser. | W49: Not published. | X49: Optional. | Y49: https://www.jvcs.jp/society/
A50: 18 | B50: P2 | C50: Both | D50: Japan | E50: International Modern Hospital Show (IMHS) 2027 | H50: 46569 | I50: July 2027 (date not published) | J50: TBC | K50: TBC. Annual pattern: mid July (2026 was 8 to 10 Jul) | L50: Tokyo Big Sight West Halls, Tokyo | M50: Hospital trade show | N50: Hospital equipment (human). Vet dealers sometimes visit | O50: General medtech show. Vet distributors walk it, but vet content is minimal. | P50: Not documented. | Q50: Unverified. Exhibitor list for this edition is not published. | R50: Hospital equipment dealers. | S50: Low | T50: Medium | U50: 2026: 35,316 visitors | V50: Not published. | W50: Not published. | X50: See the Diagnostics tab row. | Y50: https://www.noma-hs.com/
A51: 19 | B51: P1 | C51: Vet | D51: Japan | E51: WJVF 18th (western Japan forum co hosted by JAHA and JBVP, full English name to be confirmed) | F51: 46599 | G51: 46600 | H51: 46569 | I51: 31 Jul to 1 Aug 2027 | J51: Confirmed | K51: Confirmed per JBVP site (read through a search extract, my direct fetch was blocked) | L51: Hotel New Otani Osaka, Osaka | M51: Practitioner congress with company exhibition and luncheon seminars | N51: Small animal practice, vet nurses | O51: The big western Japan practitioner meeting. 2024 attendance included 688 vets and 592 nurses and groomers. Practice owners who buy equipment attend. | P51: Expected, not verified: Fujifilm VET Systems exhibits at JBVP family events. Others unverified. | Q51: Likely. | R51: Shoei Japan (importer of SonoScape S6V, A6V, X5V, E2V and Mindray 6600vet), Mediark, Nittoku Medical, Frontier International (livestock ultrasound). Approach these as competitor dealers who may take a second brand. | S51: High | T51: High | U51: 2024: 688 vets, 592 vet nurses, groomers (JBVP report) | V51: Not published. Request the exhibitor guide from the organiser. | W51: Company exhibition and luncheon seminar calls ran about 6 months ahead for 2026 (QIX notice). | X51: Request the exhibitor guide in January 2027. Strong dealer and clinic lead source. | Y51: https://www.jbvp.org/wjvf/
A52: 20 | B52: P3 | C52: Vet | D52: Japan | E52: JSVS 170th Japanese Society of Veterinary Science Meeting | F52: 46645 | G52: 46648 | H52: 46631 | I52: 15 to 18 Sep 2027 | J52: Confirmed | K52: Confirmed per JSVS page | L52: Iwate University, Morioka | M52: Academic meeting | N52: Veterinary science (research) | O52: Academic research audience. Low buying power but useful for KOL links to universities. | P52: Mostly research suppliers. | Q52: Unverified. Exhibitor list for this edition is not published. | R52: Low. | S52: Medium | T52: Low | U52: Thousands (est.) | V52: Not published. Request the exhibitor guide from the organiser. | W52: Not published. | X52: Optional. | Y52: https://www.jsvetsci.jp/meeting/index.php
A53: 21 | B53: P1 | C53: Vet | D53: Japan | E53: JBVP 29th Annual Meeting 2027 (Japan Clinical Veterinary Forum) | F53: 46655 | G53: 46656 | H53: 46631 | I53: 25 to 26 Sep 2027 | J53: Confirmed | K53: Confirmed per JBVP site (read through a search extract, my direct fetch was blocked) | L53: Hotel New Otani Tokyo, Chiyoda, Tokyo | M53: Practitioner congress with company exhibition and luncheon seminars | N53: Small animal practice, specialties | O53: Flagship small animal practitioner event. Practice owners and dealers attend. Strongest vet event for distributor recruitment. | P53: Confirmed: Fujifilm VET Systems exhibition and luncheon seminar at JBVP 2025. Others unverified. | Q53: Confirmed for Fujifilm (2025). | R53: Shoei Japan (importer of SonoScape S6V, A6V, X5V, E2V and Mindray 6600vet), Mediark, Nittoku Medical, Frontier International (livestock ultrasound). Approach these as competitor dealers who may take a second brand. | S53: High | T53: High | U53: Thousands (est.) | V53: Not published. Request the exhibitor guide from the organiser. | W53: Company seminar and exhibition calls open about 6 months ahead (2026 notice by QIX). | X53: Request exhibitor guide in February 2027. Priority 1 for vet. | Y53: https://www.jbvp.org/forum/
A54: 22 | B54: P2 | C54: Both | D54: Japan | E54: Medical Japan Osaka 2027 | F54: 46659 | G54: 46661 | H54: 46631 | I54: 29 Sep to 1 Oct 2027 | J54: Confirmed | K54: Confirmed | L54: INTEX Osaka, Osaka | M54: Trade exhibition | N54: Medical devices (human). Vet distributors visit | O54: General medtech show where overseas OEMs find Japanese dealers. Some vet equipment dealers attend. | P54: Not documented. | Q54: Unverified. Exhibitor list for this edition is not published. | R54: Japanese dealers. | S54: Low | T54: High | U54: Several hundred exhibitors (est.) | V54: Not published. | W54: Booth sales open. | X54: See the Diagnostics tab row. | Y54: https://medical-jpn.jp/osaka/en-gb.html
A55: 23 | B55: P2 | C55: Vet | D55: Japan | E55: JSVC Autumn Meeting 2027 (Japanese Society of Veterinary Cardiology) | H55: 46661 | I55: Autumn 2027 (not published) | J55: TBC | K55: TBC. Autumn meeting in a rotating city | L55: Rotating city | M55: Society scientific meeting | N55: Veterinary cardiology | O55: Second cardiology meeting of the year. | P55: Expected, not verified: Fujifilm VET Systems (market leader, wireless echo), Canon Medtech Supply (vet ultrasound), Mediark. SonoScape and Mindray vet models are imported by Shoei Japan. Samsung: no Japan vet distributor found. | Q55: Unverified. Exhibitor list for this edition is not published. | R55: Shoei Japan (importer of SonoScape S6V, A6V, X5V, E2V and Mindray 6600vet), Mediark, Nittoku Medical, Frontier International (livestock ultrasound). Approach these as competitor dealers who may take a second brand. | S55: High | T55: Low | U55: Hundreds (est.) | V55: Not published. Request the exhibitor guide from the organiser. | W55: Not published. | X55: Check jsvc.jp. | Y55: https://www.jsvc.jp/meeting/

Sheet Competitor and Dealer Intel
A1: Competitor and local dealer intelligence. Only facts with a source are listed. Gaps are stated, not filled.
A2: Market | B2: Segment | C2: Company or Brand | D2: Role | E2: What was found | F2: Where it was seen | G2: Evidence strength | H2: So what for CHISON | I2: Source
A3: Japan | B3: Both | C3: Fujifilm (incl. Fujifilm VET Systems) | D3: Competitor, domestic leader (ex Hitachi ultrasound) | E3: Luncheon seminar at JSUM 2026. Booth guide for ITEM 2026. Exhibition and luncheon seminar at JCVIM 2024, 2025 and 2026 and JBVP 2025. Runs vet wireless echo webinars. | F3: JSUM, ITEM, JCVIM, JBVP | G3: Confirmed | H3: Fujifilm is the benchmark in both segments. Parity at JSUM or JCVIM means a luncheon seminar, not just a booth. | I3: https://www.fujifilm.com/jp/ja/healthcare/events/veterinary
A4: Japan | B4: Diagnostics | C4: Canon Medical | D4: Competitor | E4: Exhibited AI imaging at ITEM 2026 (JIRA report). Canon Medtech Supply sells vet ultrasound. | F4: ITEM 2026 | G4: Confirmed | H4: Expect Canon at JRC and ITEM 2027. | I4: https://www.yakuji.co.jp/?p=133219
A5: Japan | B5: Diagnostics | C5: Siemens Healthineers | D5: Competitor | E5: Lists ultrasound among ITEM 2026 exhibits. | F5: ITEM 2026 | G5: Confirmed | H5: Premium segment, not a direct rival for CHISON. | I5: https://www.siemens-healthineers.com/jp/news-and-events/conferences-events-new/item
A6: Japan | B6: Diagnostics | C6: GE HealthCare | D6: Competitor | E6: Event PDF for ITEM 2025. The label GEHC also appears in the JSUM99 programme listing (role not confirmed). | F6: ITEM 2025, JSUM 2026 | G6: Confirmed (ITEM). Partial (JSUM) | H6: Expect GE at JRC and ITEM 2027. | I6: https://www.gehealthcare.com/content/dam/gehc/sitecore-migrated-assets/files/japan/event/2025/20250411_item2025.pdf
A7: Japan | B7: Diagnostics | C7: Philips Japan | D7: Competitor | E7: Co hosted the 49th JSS meeting (Jul 2024) and had a device exhibition. | F7: JSS 49th | G7: Confirmed (2024) | H7: The sonographer society is a Philips stronghold. Expect it at JSS 52nd. | I7: https://www.documents.philips.com/assets/20240604/97c55c34c58241d1b73bb18500379783.pdf
A8: Japan | B8: Diagnostics | C8: Samsung Medison | D8: Competitor | E8: Entered Japan in 2017 through Hitachi (HS40, from 33 million yen). No 2025 or 2026 Japan launch found. | F8: n/a | G8: Confirmed (2017). Current status unverified | H8: Low direct threat in Japan today. Verify current channel. | I8: https://www.hitachi.com/ja-jp/press/articles/2017/10/1004/
A9: Japan | B9: Diagnostics | C9: Mindray and SonoScape (human) | D9: Competitor | E9: No Japanese distributor or event exhibit found in searches. | F9: n/a | G9: Gap | H9: Possible whitespace, but also a sign dealers may be hard to find. Check PMDA registrations and Japan_Distributor_List_Human_v1.xlsx. | I9: n/a
A10: Japan | B10: Vet | C10: Shoei Japan | D10: Competitor dealer | E10: Listed as Japan general importer for SonoScape vet (S6V, A6V, X5V, E2V), Mindray 6600vet and HUGER vet ultrasound. | F10: Company product page | G10: Confirmed (company page) | H10: The direct benchmark dealer. Approach only if you accept channel conflict risk. | I10: http://www.shoeijapan.co.jp/products/products-v.html
A11: Japan | B11: Vet | C11: Mediark | D11: Competitor dealer | E11: Sells portable vet echo and offers imaging support to animal hospitals. | F11: Company website | G11: Confirmed (website) | H11: Possible dealer for a second brand. | I11: https://vet.mediark.co.jp/vetecho
A12: Japan | B12: Vet | C12: Frontier International | D12: Dealer (livestock) | E12: Livestock ultrasound catalogue for pig and cattle farms. | F12: Company website | G12: Confirmed (website) | H12: Livestock dealer, relevant to large animal scanners. | I12: https://frontier-intl.co.jp/catalog/ultrasounddevice/
A13: South Korea | B13: Both | C13: Samsung Medison | D13: Competitor, home market leader | E13: KIMES 2026: One Platform, V4, EVO Q10. KSOG 111th congress page lists Samsung in the Gold tier (read from image file names). Feb 2026 MoU with KAHA for Samsung Sono VET Academy and KAHA STARTER ultrasound course. | F13: KIMES, KSOG, KAHA | G13: Confirmed | H13: Samsung has a signed training partnership with KAHA, so expect it to be strong at KAHA events. Presence at any specific event is not confirmed. For CHISON, KOL events and importers may be a better route than head to head booths. | I13: https://www.koreabiomed.com/news/articleView.html?idxno=30734
... A25: Singapore | B25: Both | C25: Mindray, SonoScape, Samsung, Philips, GE | D25: Competitors | E25: No event specific exhibitor list found for SGCR, SHBC or Medical Fair Asia 2026. The only ultrasound related exhibitor found at Medical Fair Asia 2026 was iTD (not a rival). | F25: n/a | G25: Gap | H25: Request exhibitor lists from SGCR WIRES and SHBC organisers. | I25: https://www.medicalfair-asia.com/exhibitor-list/
